Workbook

Sheet Summary
A1: HubSpot Newsletter Audit – Summary data
A2: Source: HubSpot Analyze export and Health tab, pulled 8 Oct 2026.
A4: All marketing emails, 1 Oct 2025 – 30 Sep 2026 (vs previous 365 days)
A5: Metric | B5: Value | C5: Change vs previous 365 days
A6: Emails sent | B6: 1028641 | C6: -0.2193
A7: Unique emails | B7: 1032 | C7: –
A8: Delivered | B8: 1011458 | C8: –
A9: Delivery rate | B9: 0.9833 | C9: -0.0077
A10: Open rate | B10: 0.2688 | C10: -0.1138
A11: Click rate | B11: 0.0326 | C11: -0.0158
A12: Click-through rate (clicks ÷ opens) | B12: 0.1213 | C12: 0.1106
A13: Reply rate | B13: 0.0001 | C13: -0.2829
A14: Hard bounce rate | B14: 0.0129 | C14: 0.9746
A15: Unsubscribe rate | B15: 0.0081 | C15: 0.7244
A16: Spam report rate | B16: 0.0001 | C16: 0.7813
A19: Email health, last 30 days (5 Sep – 5 Oct 2026)
A20: Metric | B20: PnP | C20: HubSpot benchmark | D20: HubSpot rating
A21: Email health score | B21: 3 / 10 | C21: – | D21: Needs work
A22: Opens | B22: 0.25 | C22: 0.195 | D22: Very good
A23: Click-throughs | B23: 0.075 | C23: 0.085 | D23: Okay
A24: Hard bounces | B24: 0.0254 | C24: 0.0025 | D24: Poor
A25: Unsubscribes | B25: 0.0104 | C25: 0.0035 | D25: Poor
A26: Spam reports | B26: 5 | C26: – | D26: –
A27: Emails sent | B27: 158769 | C27: – | D27: –
A30: Email health by month (HubSpot Health tab)
A31: Month | B31: Health score (/10) | C31: Opens | D31: Click-throughs | E31: Hard bounces | F31: Unsubscribes | G31: Emails sent
A32: Oct 2025 | B32: 5 | C32: 0.299 | D32: 0.112 | E32: 0.0107 | F32: 0.0043 | G32: 112000
A33: Nov 2025 | B33: 6 | C33: 0.347 | D33: 0.147 | E33: 0.0056 | F33: 0.0042 | G33: 55700
A34: Dec 2025 | B34: 5 | C34: 0.279 | D34: 0.11 | E34: 0.0051 | F34: 0.0055 | G34: 56400
A35: Jan 2026 | B35: 5 | C35: 0.268 | D35: 0.142 | E35: 0.0128 | F35: 0.0047 | G35: 58600
A36: Feb 2026 | B36: 3 | C36: 0.292 | D36: 0.135 | E36: 0.0186 | F36: 0.007 | G36: 61100
A37: Mar 2026 | B37: 4 | C37: 0.285 | D37: 0.151 | E37: 0.0095 | F37: 0.0077 | G37: 72400
A38: Apr 2026 | B38: 3 | C38: 0.23 | D38: 0.128 | E38: 0.0129 | F38: 0.0066 | G38: 112200
A39: May 2026 | B39: 6 | C39: 0.297 | D39: 0.146 | E39: 0.0039 | F39: 0.0057 | G39: 77000
A40: Jun 2026 | B40: 4 | C40: 0.222 | D40: 0.124 | E40: 0.0076 | F40: 0.0055 | G40: 87700
A41: Jul 2026 | B41: 4 | C41: 0.225 | D41: 0.138 | E41: 0.0077 | F41: 0.0055 | G41: 70700
A42: Aug 2026 | B42: 3 | C42: 0.273 | D42: 0.091 | E42: 0.0177 | F42: 0.0116 | G42: 105200
A43: Sep 2026 | B43: 3 | C43: 0.267 | D43: 0.068 | E43: 0.0317 | F43: 0.0115 | G43: 124000
A44: Red = above HubSpot benchmark (hard bounces 0.25%, unsubscribes 0.35%).
A46: Device type (1 Oct 2025 – 30 Sep 2026)
A47: Device | B47: Opens | C47: Clicks
A48: Desktop | B48: 186370 | C48: 42918
A49: Mobile | B49: 83437 | C49: 13767
A50: Other | B50: 320849 | C50: 0
A51: Unsubscribe reasons | B51: No data

Sheet Newsletters
A1: Recurring newsletters, 6 Aug – 30 Sep 2026
A2: Calculated from the 'Emails Aug-Sep' tab (duplicates excluded).
A4: Newsletter | B4: From name | C4: Subscription type | D4: Send dates | E4: Sends | F4: Avg. delivered | G4: Click rate | H4: Unsub rate | I4: Bounce rate
A5: Fintech & AI Fund Insights | B5: Brooke Ballinger | C5: Fintech & AI Fund Insights | D5: 09-23 | E5: =COUNTIFS('Emails Aug-Sep'!$E$5:$E$104,A5,'Emails Aug-Sep'!$N$5:$N$104,"No") -> 1 | F5: =IF(E5=0,0,SUMIFS('Emails Aug-Sep'!$F$5:$F$104,'Emails Aug-Sep'!$E$5:$E$104,A5,'Emails Aug-Sep'!$N$5:$N$104,"No")/E5) -> 8611 | G5: =IF(E5=0,0,SUMIFS('Emails Aug-Sep'!$I$5:$I$104,'Emails Aug-Sep'!$E$5:$E$104,A5,'Emails Aug-Sep'!$N$5:$N$104,"No")/SUMIFS('Emails Aug-Sep'!$F$5:$F$104,'Emails Aug-Sep'!$E$5:$E$104,A5,'Emails Aug-Sep'!$N$5:$N$104,"No")) -> 0.0069678318 | H5: =IF(E5=0,0,SUMIFS('Emails Aug-Sep'!$J$5:$J$104,'Emails Aug-Sep'!$E$5:$E$104,A5,'Emails Aug-Sep'!$N$5:$N$104,"No")/SUMIFS('Emails Aug-Sep'!$F$5:$F$104,'Emails Aug-Sep'!$E$5:$E$104,A5,'Emails Aug-Sep'!$N$5:$N$104,"No")) -> 0.014167925 | I5: =IF(E5=0,0,SUMIFS('Emails Aug-Sep'!$L$5:$L$104,'Emails Aug-Sep'!$E$5:$E$104,A5,'Emails Aug-Sep'!$N$5:$N$104,"No")/(SUMIFS('Emails Aug-Sep'!$F$5:$F$104,'Emails Aug-Sep'!$E$5:$E$104,A5,'Emails Aug-Sep'!$N$5:$N$104,"No")+SUMIFS('Emails Aug-Sep'!$L$5:$L$104,'Emails Aug-Sep'!$E$5:$E$104,A5,'Emails Aug-Sep'!$N$5:$N$104,"No"))) -> 0.012952774
A6: Italy Newsletter | B6: Tommaso Maschera | C6: Plug and Play Marketing Communications | D6: 08-06, 09-17 | E6: =COUNTIFS('Emails Aug-Sep'!$E$5:$E$104,A6,'Emails Aug-Sep'!$N$5:$N$104,"No") -> 2 | F6: =IF(E6=0,0,SUMIFS('Emails Aug-Sep'!$F$5:$F$104,'Emails Aug-Sep'!$E$5:$E$104,A6,'Emails Aug-Sep'!$N$5:$N$104,"No")/E6) -> 6624 | G6: =IF(E6=0,0,SUMIFS('Emails Aug-Sep'!$I$5:$I$104,'Emails Aug-Sep'!$E$5:$E$104,A6,'Emails Aug-Sep'!$N$5:$N$104,"No")/SUMIFS('Emails Aug-Sep'!$F$5:$F$104,'Emails Aug-Sep'!$E$5:$E$104,A6,'Emails Aug-Sep'!$N$5:$N$104,"No")) -> 0.012756643 | H6: =IF(E6=0,0,SUMIFS('Emails Aug-Sep'!$J$5:$J$104,'Emails Aug-Sep'!$E$5:$E$104,A6,'Emails Aug-Sep'!$N$5:$N$104,"No")/SUMIFS('Emails Aug-Sep'!$F$5:$F$104,'Emails Aug-Sep'!$E$5:$E$104,A6,'Emails Aug-Sep'!$N$5:$N$104,"No")) -> 0.0095863527 | I6: =IF(E6=0,0,SUMIFS('Emails Aug-Sep'!$L$5:$L$104,'Emails Aug-Sep'!$E$5:$E$104,A6,'Emails Aug-Sep'!$N$5:$N$104,"No")/(SUMIFS('Emails Aug-Sep'!$F$5:$F$104,'Emails Aug-Sep'!$E$5:$E$104,A6,'Emails Aug-Sep'!$N$5:$N$104,"No")+SUMIFS('Emails Aug-Sep'!$L$5:$L$104,'Emails Aug-Sep'!$E$5:$E$104,A6,'Emails Aug-Sep'!$N$5:$N$104,"No"))) -> 0.011490822
A7: UK Newsletter | B7: Kieran Borrett | C7: Plug and Play Marketing Communications | D7: 09-02, 09-30 | E7: =COUNTIFS('Emails Aug-Sep'!$E$5:$E$104,A7,'Emails Aug-Sep'!$N$5:$N$104,"No") -> 2 | F7: =IF(E7=0,0,SUMIFS('Emails Aug-Sep'!$F$5:$F$104,'Emails Aug-Sep'!$E$5:$E$104,A7,'Emails Aug-Sep'!$N$5:$N$104,"No")/E7) -> 6474.5 | G7: =IF(E7=0,0,SUMIFS('Emails Aug-Sep'!$I$5:$I$104,'Emails Aug-Sep'!$E$5:$E$104,A7,'Emails Aug-Sep'!$N$5:$N$104,"No")/SUMIFS('Emails Aug-Sep'!$F$5:$F$104,'Emails Aug-Sep'!$E$5:$E$104,A7,'Emails Aug-Sep'!$N$5:$N$104,"No")) -> 0.010502742 | H7: =IF(E7=0,0,SUMIFS('Emails Aug-Sep'!$J$5:$J$104,'Emails Aug-Sep'!$E$5:$E$104,A7,'Emails Aug-Sep'!$N$5:$N$104,"No")/SUMIFS('Emails Aug-Sep'!$F$5:$F$104,'Emails Aug-Sep'!$E$5:$E$104,A7,'Emails Aug-Sep'!$N$5:$N$104,"No")) -> 0.0098077072 | I7: =IF(E7=0,0,SUMIFS('Emails Aug-Sep'!$L$5:$L$104,'Emails Aug-Sep'!$E$5:$E$104,A7,'Emails Aug-Sep'!$N$5:$N$104,"No")/(SUMIFS('Emails Aug-Sep'!$F$5:$F$104,'Emails Aug-Sep'!$E$5:$E$104,A7,'Emails Aug-Sep'!$N$5:$N$104,"No")+SUMIFS('Emails Aug-Sep'!$L$5:$L$104,'Emails Aug-Sep'!$E$5:$E$104,A7,'Emails Aug-Sep'!$N$5:$N$104,"No"))) -> 0.0070546737
A8: Global Newsletter (GNL) | B8: Jacky from Plug and Play | C8: Plug and Play Global Newsletter | D8: 08-25, 08-25, 09-29 | E8: =COUNTIFS('Emails Aug-Sep'!$E$5:$E$104,A8,'Emails Aug-Sep'!$N$5:$N$104,"No") -> 3 | F8: =IF(E8=0,0,SUMIFS('Emails Aug-Sep'!$F$5:$F$104,'Emails Aug-Sep'!$E$5:$E$104,A8,'Emails Aug-Sep'!$N$5:$N$104,"No")/E8) -> 5748.3333 | G8: =IF(E8=0,0,SUMIFS('Emails Aug-Sep'!$I$5:$I$104,'Emails Aug-Sep'!$E$5:$E$104,A8,'Emails Aug-Sep'!$N$5:$N$104,"No")/SUMIFS('Emails Aug-Sep'!$F$5:$F$104,'Emails Aug-Sep'!$E$5:$E$104,A8,'Emails Aug-Sep'!$N$5:$N$104,"No")) -> 0.023543056 | H8: =IF(E8=0,0,SUMIFS('Emails Aug-Sep'!$J$5:$J$104,'Emails Aug-Sep'!$E$5:$E$104,A8,'Emails Aug-Sep'!$N$5:$N$104,"No")/SUMIFS('Emails Aug-Sep'!$F$5:$F$104,'Emails Aug-Sep'!$E$5:$E$104,A8,'Emails Aug-Sep'!$N$5:$N$104,"No")) -> 0.0053348797 | I8: =IF(E8=0,0,SUMIFS('Emails Aug-Sep'!$L$5:$L$104,'Emails Aug-Sep'!$E$5:$E$104,A8,'Emails Aug-Sep'!$N$5:$N$104,"No")/(SUMIFS('Emails Aug-Sep'!$F$5:$F$104,'Emails Aug-Sep'!$E$5:$E$104,A8,'Emails Aug-Sep'!$N$5:$N$104,"No")+SUMIFS('Emails Aug-Sep'!$L$5:$L$104,'Emails Aug-Sep'!$E$5:$E$104,A8,'Emails Aug-Sep'!$N$5:$N$104,"No"))) -> 0.0045026843
A9: Texas Newsletter | B9: Francis from Plug and Play | C9: Plug and Play Marketing Communications | D9: 08-26, 09-29 | E9: =COUNTIFS('Emails Aug-Sep'!$E$5:$E$104,A9,'Emails Aug-Sep'!$N$5:$N$104,"No") -> 2 | F9: =IF(E9=0,0,SUMIFS('Emails Aug-Sep'!$F$5:$F$104,'Emails Aug-Sep'!$E$5:$E$104,A9,'Emails Aug-Sep'!$N$5:$N$104,"No")/E9) -> 4746.5 | G9: =IF(E9=0,0,SUMIFS('Emails Aug-Sep'!$I$5:$I$104,'Emails Aug-Sep'!$E$5:$E$104,A9,'Emails Aug-Sep'!$N$5:$N$104,"No")/SUMIFS('Emails Aug-Sep'!$F$5:$F$104,'Emails Aug-Sep'!$E$5:$E$104,A9,'Emails Aug-Sep'!$N$5:$N$104,"No")) -> 0.028968714 | H9: =IF(E9=0,0,SUMIFS('Emails Aug-Sep'!$J$5:$J$104,'Emails Aug-Sep'!$E$5:$E$104,A9,'Emails Aug-Sep'!$N$5:$N$104,"No")/SUMIFS('Emails Aug-Sep'!$F$5:$F$104,'Emails Aug-Sep'!$E$5:$E$104,A9,'Emails Aug-Sep'!$N$5:$N$104,"No")) -> 0.0065311282 | I9: =IF(E9=0,0,SUMIFS('Emails Aug-Sep'!$L$5:$L$104,'Emails Aug-Sep'!$E$5:$E$104,A9,'Emails Aug-Sep'!$N$5:$N$104,"No")/(SUMIFS('Emails Aug-Sep'!$F$5:$F$104,'Emails Aug-Sep'!$E$5:$E$104,A9,'Emails Aug-Sep'!$N$5:$N$104,"No")+SUMIFS('Emails Aug-Sep'!$L$5:$L$104,'Emails Aug-Sep'!$E$5:$E$104,A9,'Emails Aug-Sep'!$N$5:$N$104,"No"))) -> 0.009391631
A10: Startup Autobahn Monthly | B10: STARTUP AUTOBAHN powered by Plug and Play | C10: Startup Autobahn Communications | D10: 09-07 | E10: =COUNTIFS('Emails Aug-Sep'!$E$5:$E$104,A10,'Emails Aug-Sep'!$N$5:$N$104,"No") -> 1 | F10: =IF(E10=0,0,SUMIFS('Emails Aug-Sep'!$F$5:$F$104,'Emails Aug-Sep'!$E$5:$E$104,A10,'Emails Aug-Sep'!$N$5:$N$104,"No")/E10) -> 4384 | G10: =IF(E10=0,0,SUMIFS('Emails Aug-Sep'!$I$5:$I$104,'Emails Aug-Sep'!$E$5:$E$104,A10,'Emails Aug-Sep'!$N$5:$N$104,"No")/SUMIFS('Emails Aug-Sep'!$F$5:$F$104,'Emails Aug-Sep'!$E$5:$E$104,A10,'Emails Aug-Sep'!$N$5:$N$104,"No")) -> 0.020985401 | H10: =IF(E10=0,0,SUMIFS('Emails Aug-Sep'!$J$5:$J$104,'Emails Aug-Sep'!$E$5:$E$104,A10,'Emails Aug-Sep'!$N$5:$N$104,"No")/SUMIFS('Emails Aug-Sep'!$F$5:$F$104,'Emails Aug-Sep'!$E$5:$E$104,A10,'Emails Aug-Sep'!$N$5:$N$104,"No")) -> 0.0034215328 | I10: =IF(E10=0,0,SUMIFS('Emails Aug-Sep'!$L$5:$L$104,'Emails Aug-Sep'!$E$5:$E$104,A10,'Emails Aug-Sep'!$N$5:$N$104,"No")/(SUMIFS('Emails Aug-Sep'!$F$5:$F$104,'Emails Aug-Sep'!$E$5:$E$104,A10,'Emails Aug-Sep'!$N$5:$N$104,"No")+SUMIFS('Emails Aug-Sep'!$L$5:$L$104,'Emails Aug-Sep'!$E$5:$E$104,A10,'Emails Aug-Sep'!$N$5:$N$104,"No"))) -> 0.010160307
A11: Central Asia & Caucasus Latest News | B11: Sofi from Plug and Play Central Asia and Caucasus | C11: Plug and Play Marketing Communications | D11: 09-04 | E11: =COUNTIFS('Emails Aug-Sep'!$E$5:$E$104,A11,'Emails Aug-Sep'!$N$5:$N$104,"No") -> 1 | F11: =IF(E11=0,0,SUMIFS('Emails Aug-Sep'!$F$5:$F$104,'Emails Aug-Sep'!$E$5:$E$104,A11,'Emails Aug-Sep'!$N$5:$N$104,"No")/E11) -> 3302 | G11: =IF(E11=0,0,SUMIFS('Emails Aug-Sep'!$I$5:$I$104,'Emails Aug-Sep'!$E$5:$E$104,A11,'Emails Aug-Sep'!$N$5:$N$104,"No")/SUMIFS('Emails Aug-Sep'!$F$5:$F$104,'Emails Aug-Sep'!$E$5:$E$104,A11,'Emails Aug-Sep'!$N$5:$N$104,"No")) -> 0.015142338 | H11: =IF(E11=0,0,SUMIFS('Emails Aug-Sep'!$J$5:$J$104,'Emails Aug-Sep'!$E$5:$E$104,A11,'Emails Aug-Sep'!$N$5:$N$104,"No")/SUMIFS('Emails Aug-Sep'!$F$5:$F$104,'Emails Aug-Sep'!$E$5:$E$104,A11,'Emails Aug-Sep'!$N$5:$N$104,"No")) -> 0.007571169 | I11: =IF(E11=0,0,SUMIFS('Emails Aug-Sep'!$L$5:$L$104,'Emails Aug-Sep'!$E$5:$E$104,A11,'Emails Aug-Sep'!$N$5:$N$104,"No")/(SUMIFS('Emails Aug-Sep'!$F$5:$F$104,'Emails Aug-Sep'!$E$5:$E$104,A11,'Emails Aug-Sep'!$N$5:$N$104,"No")+SUMIFS('Emails Aug-Sep'!$L$5:$L$104,'Emails Aug-Sep'!$E$5:$E$104,A11,'Emails Aug-Sep'!$N$5:$N$104,"No"))) -> 0.022209061
A12: APAC Newsletter | B12: Plug and Play APAC | C12: Plug and Play APAC | D12: 08-19, 09-23 | E12: =COUNTIFS('Emails Aug-Sep'!$E$5:$E$104,A12,'Emails Aug-Sep'!$N$5:$N$104,"No") -> 2 | F12: =IF(E12=0,0,SUMIFS('Emails Aug-Sep'!$F$5:$F$104,'Emails Aug-Sep'!$E$5:$E$104,A12,'Emails Aug-Sep'!$N$5:$N$104,"No")/E12) -> 2756 | G12: =IF(E12=0,0,SUMIFS('Emails Aug-Sep'!$I$5:$I$104,'Emails Aug-Sep'!$E$5:$E$104,A12,'Emails Aug-Sep'!$N$5:$N$104,"No")/SUMIFS('Emails Aug-Sep'!$F$5:$F$104,'Emails Aug-Sep'!$E$5:$E$104,A12,'Emails Aug-Sep'!$N$5:$N$104,"No")) -> 0.029571843 | H12: =IF(E12=0,0,SUMIFS('Emails Aug-Sep'!$J$5:$J$104,'Emails Aug-Sep'!$E$5:$E$104,A12,'Emails Aug-Sep'!$N$5:$N$104,"No")/SUMIFS('Emails Aug-Sep'!$F$5:$F$104,'Emails Aug-Sep'!$E$5:$E$104,A12,'Emails Aug-Sep'!$N$5:$N$104,"No")) -> 0.003628447 | I12: =IF(E12=0,0,SUMIFS('Emails Aug-Sep'!$L$5:$L$104,'Emails Aug-Sep'!$E$5:$E$104,A12,'Emails Aug-Sep'!$N$5:$N$104,"No")/(SUMIFS('Emails Aug-Sep'!$F$5:$F$104,'Emails Aug-Sep'!$E$5:$E$104,A12,'Emails Aug-Sep'!$N$5:$N$104,"No")+SUMIFS('Emails Aug-Sep'!$L$5:$L$104,'Emails Aug-Sep'!$E$5:$E$104,A12,'Emails Aug-Sep'!$N$5:$N$104,"No"))) -> 0.006309717
A13: Seattle Community Newsletter | B13: Emmanuel Chan | C13: Plug and Play Marketing Communications | D13: 09-01 | E13: =COUNTIFS('Emails Aug-Sep'!$E$5:$E$104,A13,'Emails Aug-Sep'!$N$5:$N$104,"No") -> 1 | F13: =IF(E13=0,0,SUMIFS('Emails Aug-Sep'!$F$5:$F$104,'Emails Aug-Sep'!$E$5:$E$104,A13,'Emails Aug-Sep'!$N$5:$N$104,"No")/E13) -> 1787 | G13: =IF(E13=0,0,SUMIFS('Emails Aug-Sep'!$I$5:$I$104,'Emails Aug-Sep'!$E$5:$E$104,A13,'Emails Aug-Sep'!$N$5:$N$104,"No")/SUMIFS('Emails Aug-Sep'!$F$5:$F$104,'Emails Aug-Sep'!$E$5:$E$104,A13,'Emails Aug-Sep'!$N$5:$N$104,"No")) -> 0.021824287 | H13: =IF(E13=0,0,SUMIFS('Emails Aug-Sep'!$J$5:$J$104,'Emails Aug-Sep'!$E$5:$E$104,A13,'Emails Aug-Sep'!$N$5:$N$104,"No")/SUMIFS('Emails Aug-Sep'!$F$5:$F$104,'Emails Aug-Sep'!$E$5:$E$104,A13,'Emails Aug-Sep'!$N$5:$N$104,"No")) -> 0.0055959709 | I13: =IF(E13=0,0,SUMIFS('Emails Aug-Sep'!$L$5:$L$104,'Emails Aug-Sep'!$E$5:$E$104,A13,'Emails Aug-Sep'!$N$5:$N$104,"No")/(SUMIFS('Emails Aug-Sep'!$F$5:$F$104,'Emails Aug-Sep'!$E$5:$E$104,A13,'Emails Aug-Sep'!$N$5:$N$104,"No")+SUMIFS('Emails Aug-Sep'!$L$5:$L$104,'Emails Aug-Sep'!$E$5:$E$104,A13,'Emails Aug-Sep'!$N$5:$N$104,"No"))) -> 0.0072222222
A14: Indiana Medtech + Lifetech Newsletter | B14: Plug and Play Indiana | C14: Plug and Play Marketing Communications | D14: 09-18 | E14: =COUNTIFS('Emails Aug-Sep'!$E$5:$E$104,A14,'Emails Aug-Sep'!$N$5:$N$104,"No") -> 1 | F14: =IF(E14=0,0,SUMIFS('Emails Aug-Sep'!$F$5:$F$104,'Emails Aug-Sep'!$E$5:$E$104,A14,'Emails Aug-Sep'!$N$5:$N$104,"No")/E14) -> 1430 | G14: =IF(E14=0,0,SUMIFS('Emails Aug-Sep'!$I$5:$I$104,'Emails Aug-Sep'!$E$5:$E$104,A14,'Emails Aug-Sep'!$N$5:$N$104,"No")/SUMIFS('Emails Aug-Sep'!$F$5:$F$104,'Emails Aug-Sep'!$E$5:$E$104,A14,'Emails Aug-Sep'!$N$5:$N$104,"No")) -> 0.013286713 | H14: =IF(E14=0,0,SUMIFS('Emails Aug-Sep'!$J$5:$J$104,'Emails Aug-Sep'!$E$5:$E$104,A14,'Emails Aug-Sep'!$N$5:$N$104,"No")/SUMIFS('Emails Aug-Sep'!$F$5:$F$104,'Emails Aug-Sep'!$E$5:$E$104,A14,'Emails Aug-Sep'!$N$5:$N$104,"No")) -> 0.0055944056 | I14: =IF(E14=0,0,SUMIFS('Emails Aug-Sep'!$L$5:$L$104,'Emails Aug-Sep'!$E$5:$E$104,A14,'Emails Aug-Sep'!$N$5:$N$104,"No")/(SUMIFS('Emails Aug-Sep'!$F$5:$F$104,'Emails Aug-Sep'!$E$5:$E$104,A14,'Emails Aug-Sep'!$N$5:$N$104,"No")+SUMIFS('Emails Aug-Sep'!$L$5:$L$104,'Emails Aug-Sep'!$E$5:$E$104,A14,'Emails Aug-Sep'!$N$5:$N$104,"No"))) -> 0.0069444444
A15: Türkiye Newsletter | B15: Zeynep from Plug and Play | C15: Plug and Play Marketing Communications | D15: 08-31 | E15: =COUNTIFS('Emails Aug-Sep'!$E$5:$E$104,A15,'Emails Aug-Sep'!$N$5:$N$104,"No") -> 1 | F15: =IF(E15=0,0,SUMIFS('Emails Aug-Sep'!$F$5:$F$104,'Emails Aug-Sep'!$E$5:$E$104,A15,'Emails Aug-Sep'!$N$5:$N$104,"No")/E15) -> 1420 | G15: =IF(E15=0,0,SUMIFS('Emails Aug-Sep'!$I$5:$I$104,'Emails Aug-Sep'!$E$5:$E$104,A15,'Emails Aug-Sep'!$N$5:$N$104,"No")/SUMIFS('Emails Aug-Sep'!$F$5:$F$104,'Emails Aug-Sep'!$E$5:$E$104,A15,'Emails Aug-Sep'!$N$5:$N$104,"No")) -> 0.019014085 | H15: =IF(E15=0,0,SUMIFS('Emails Aug-Sep'!$J$5:$J$104,'Emails Aug-Sep'!$E$5:$E$104,A15,'Emails Aug-Sep'!$N$5:$N$104,"No")/SUMIFS('Emails Aug-Sep'!$F$5:$F$104,'Emails Aug-Sep'!$E$5:$E$104,A15,'Emails Aug-Sep'!$N$5:$N$104,"No")) -> 0.0056338028 | I15: =IF(E15=0,0,SUMIFS('Emails Aug-Sep'!$L$5:$L$104,'Emails Aug-Sep'!$E$5:$E$104,A15,'Emails Aug-Sep'!$N$5:$N$104,"No")/(SUMIFS('Emails Aug-Sep'!$F$5:$F$104,'Emails Aug-Sep'!$E$5:$E$104,A15,'Emails Aug-Sep'!$N$5:$N$104,"No")+SUMIFS('Emails Aug-Sep'!$L$5:$L$104,'Emails Aug-Sep'!$E$5:$E$104,A15,'Emails Aug-Sep'!$N$5:$N$104,"No"))) -> 0.0076869322
A16: Japan Newsletter | B16: Plug and Play Japan | C16: Plug and Play Japan | D16: 08-19, 09-02, 09-16, 09-30 | E16: =COUNTIFS('Emails Aug-Sep'!$E$5:$E$104,A16,'Emails Aug-Sep'!$N$5:$N$104,"No") -> 4 | F16: =IF(E16=0,0,SUMIFS('Emails Aug-Sep'!$F$5:$F$104,'Emails Aug-Sep'!$E$5:$E$104,A16,'Emails Aug-Sep'!$N$5:$N$104,"No")/E16) -> 988.75 | G16: =IF(E16=0,0,SUMIFS('Emails Aug-Sep'!$I$5:$I$104,'Emails Aug-Sep'!$E$5:$E$104,A16,'Emails Aug-Sep'!$N$5:$N$104,"No")/SUMIFS('Emails Aug-Sep'!$F$5:$F$104,'Emails Aug-Sep'!$E$5:$E$104,A16,'Emails Aug-Sep'!$N$5:$N$104,"No")) -> 0.096333755 | H16: =IF(E16=0,0,SUMIFS('Emails Aug-Sep'!$J$5:$J$104,'Emails Aug-Sep'!$E$5:$E$104,A16,'Emails Aug-Sep'!$N$5:$N$104,"No")/SUMIFS('Emails Aug-Sep'!$F$5:$F$104,'Emails Aug-Sep'!$E$5:$E$104,A16,'Emails Aug-Sep'!$N$5:$N$104,"No")) -> 0.000505689 | I16: =IF(E16=0,0,SUMIFS('Emails Aug-Sep'!$L$5:$L$104,'Emails Aug-Sep'!$E$5:$E$104,A16,'Emails Aug-Sep'!$N$5:$N$104,"No")/(SUMIFS('Emails Aug-Sep'!$F$5:$F$104,'Emails Aug-Sep'!$E$5:$E$104,A16,'Emails Aug-Sep'!$N$5:$N$104,"No")+SUMIFS('Emails Aug-Sep'!$L$5:$L$104,'Emails Aug-Sep'!$E$5:$E$104,A16,'Emails Aug-Sep'!$N$5:$N$104,"No"))) -> 0.0020186727
... A26: Shamrock Foods Monthly Signal | B26: Plug and Play Supply Chain | C26: Plug and Play Marketing Communications | D26: 09-14 | E26: =COUNTIFS('Emails Aug-Sep'!$E$5:$E$104,A26,'Emails Aug-Sep'!$N$5:$N$104,"No") -> 1 | F26: =IF(E26=0,0,SUMIFS('Emails Aug-Sep'!$F$5:$F$104,'Emails Aug-Sep'!$E$5:$E$104,A26,'Emails Aug-Sep'!$N$5:$N$104,"No")/E26) -> 7 | G26: =IF(E26=0,0,SUMIFS('Emails Aug-Sep'!$I$5:$I$104,'Emails Aug-Sep'!$E$5:$E$104,A26,'Emails Aug-Sep'!$N$5:$N$104,"No")/SUMIFS('Emails Aug-Sep'!$F$5:$F$104,'Emails Aug-Sep'!$E$5:$E$104,A26,'Emails Aug-Sep'!$N$5:$N$104,"No")) -> 0 | H26: =IF(E26=0,0,SUMIFS('Emails Aug-Sep'!$J$5:$J$104,'Emails Aug-Sep'!$E$5:$E$104,A26,'Emails Aug-Sep'!$N$5:$N$104,"No")/SUMIFS('Emails Aug-Sep'!$F$5:$F$104,'Emails Aug-Sep'!$E$5:$E$104,A26,'Emails Aug-Sep'!$N$5:$N$104,"No")) -> 0 | I26: =IF(E26=0,0,SUMIFS('Emails Aug-Sep'!$L$5:$L$104,'Emails Aug-Sep'!$E$5:$E$104,A26,'Emails Aug-Sep'!$N$5:$N$104,"No")/(SUMIFS('Emails Aug-Sep'!$F$5:$F$104,'Emails Aug-Sep'!$E$5:$E$104,A26,'Emails Aug-Sep'!$N$5:$N$104,"No")+SUMIFS('Emails Aug-Sep'!$L$5:$L$104,'Emails Aug-Sep'!$E$5:$E$104,A26,'Emails Aug-Sep'!$N$5:$N$104,"No"))) -> 0
A27: Red = unsubscribe rate above HubSpot benchmark (0.35%). Send dates are MM-DD, 2026.
A29: All emails by number of recipients, 6 Aug – 30 Sep 2026
A30: Delivered per email | B30: Emails | C30: Delivered | D30: Click rate | E30: Unsub rate | F30: Bounce rate
A31: Fewer than 300 | B31: =COUNTIFS('Emails Aug-Sep'!$F$5:$F$104,">=0",'Emails Aug-Sep'!$F$5:$F$104,"<300",'Emails Aug-Sep'!$N$5:$N$104,"No") -> 47 | C31: =SUMIFS('Emails Aug-Sep'!$F$5:$F$104,'Emails Aug-Sep'!$F$5:$F$104,">=0",'Emails Aug-Sep'!$F$5:$F$104,"<300",'Emails Aug-Sep'!$N$5:$N$104,"No") -> 4300 | D31: =IF(C31=0,0,SUMIFS('Emails Aug-Sep'!$I$5:$I$104,'Emails Aug-Sep'!$F$5:$F$104,">=0",'Emails Aug-Sep'!$F$5:$F$104,"<300",'Emails Aug-Sep'!$N$5:$N$104,"No")/C31) -> 0.11930233 | E31: =IF(C31=0,0,SUMIFS('Emails Aug-Sep'!$J$5:$J$104,'Emails Aug-Sep'!$F$5:$F$104,">=0",'Emails Aug-Sep'!$F$5:$F$104,"<300",'Emails Aug-Sep'!$N$5:$N$104,"No")/C31) -> 0.0018604651 | F31: =IF(C31=0,0,SUMIFS('Emails Aug-Sep'!$L$5:$L$104,'Emails Aug-Sep'!$F$5:$F$104,">=0",'Emails Aug-Sep'!$F$5:$F$104,"<300",'Emails Aug-Sep'!$N$5:$N$104,"No")/(C31+SUMIFS('Emails Aug-Sep'!$L$5:$L$104,'Emails Aug-Sep'!$F$5:$F$104,">=0",'Emails Aug-Sep'!$F$5:$F$104,"<300",'Emails Aug-Sep'!$N$5:$N$104,"No"))) -> 0.0023201856
A32: 300 – 4,999 | B32: =COUNTIFS('Emails Aug-Sep'!$F$5:$F$104,">=300",'Emails Aug-Sep'!$F$5:$F$104,"<5000",'Emails Aug-Sep'!$N$5:$N$104,"No") -> 39 | C32: =SUMIFS('Emails Aug-Sep'!$F$5:$F$104,'Emails Aug-Sep'!$F$5:$F$104,">=300",'Emails Aug-Sep'!$F$5:$F$104,"<5000",'Emails Aug-Sep'!$N$5:$N$104,"No") -> 78299 | D32: =IF(C32=0,0,SUMIFS('Emails Aug-Sep'!$I$5:$I$104,'Emails Aug-Sep'!$F$5:$F$104,">=300",'Emails Aug-Sep'!$F$5:$F$104,"<5000",'Emails Aug-Sep'!$N$5:$N$104,"No")/C32) -> 0.025811313 | E32: =IF(C32=0,0,SUMIFS('Emails Aug-Sep'!$J$5:$J$104,'Emails Aug-Sep'!$F$5:$F$104,">=300",'Emails Aug-Sep'!$F$5:$F$104,"<5000",'Emails Aug-Sep'!$N$5:$N$104,"No")/C32) -> 0.0081737953 | F32: =IF(C32=0,0,SUMIFS('Emails Aug-Sep'!$L$5:$L$104,'Emails Aug-Sep'!$F$5:$F$104,">=300",'Emails Aug-Sep'!$F$5:$F$104,"<5000",'Emails Aug-Sep'!$N$5:$N$104,"No")/(C32+SUMIFS('Emails Aug-Sep'!$L$5:$L$104,'Emails Aug-Sep'!$F$5:$F$104,">=300",'Emails Aug-Sep'!$F$5:$F$104,"<5000",'Emails Aug-Sep'!$N$5:$N$104,"No"))) -> 0.011513552
A33: 5,000 or more | B33: =COUNTIFS('Emails Aug-Sep'!$F$5:$F$104,">=5000",'Emails Aug-Sep'!$F$5:$F$104,"<1000000000",'Emails Aug-Sep'!$N$5:$N$104,"No") -> 11 | C33: =SUMIFS('Emails Aug-Sep'!$F$5:$F$104,'Emails Aug-Sep'!$F$5:$F$104,">=5000",'Emails Aug-Sep'!$F$5:$F$104,"<1000000000",'Emails Aug-Sep'!$N$5:$N$104,"No") -> 131465 | D33: =IF(C33=0,0,SUMIFS('Emails Aug-Sep'!$I$5:$I$104,'Emails Aug-Sep'!$F$5:$F$104,">=5000",'Emails Aug-Sep'!$F$5:$F$104,"<1000000000",'Emails Aug-Sep'!$N$5:$N$104,"No")/C33) -> 0.014247138 | E33: =IF(C33=0,0,SUMIFS('Emails Aug-Sep'!$J$5:$J$104,'Emails Aug-Sep'!$F$5:$F$104,">=5000",'Emails Aug-Sep'!$F$5:$F$104,"<1000000000",'Emails Aug-Sep'!$N$5:$N$104,"No")/C33) -> 0.015593504 | F33: =IF(C33=0,0,SUMIFS('Emails Aug-Sep'!$L$5:$L$104,'Emails Aug-Sep'!$F$5:$F$104,">=5000",'Emails Aug-Sep'!$F$5:$F$104,"<1000000000",'Emails Aug-Sep'!$N$5:$N$104,"No")/(C33+SUMIFS('Emails Aug-Sep'!$L$5:$L$104,'Emails Aug-Sep'!$F$5:$F$104,">=5000",'Emails Aug-Sep'!$F$5:$F$104,"<1000000000",'Emails Aug-Sep'!$N$5:$N$104,"No"))) -> 0.041821243
A34: Total | B34: =SUM(B31:B33) -> 97 | C34: =SUM(C31:C33) -> 214064
A37: 3 emails with the most bounces, 6 Aug – 30 Sep 2026
A38: Email | B38: Send date | C38: Delivered | D38: Unsubscribes | E38: Bounces | F38: Share of all unsubscribes | G38: Share of all bounces
A39: JTP | JAP_Sansan List_Consent Mail_20260909 | B39: 2026-09-18 | C39: =SUMIFS('Emails Aug-Sep'!$F$5:$F$104,'Emails Aug-Sep'!$A$5:$A$104,A39,'Emails Aug-Sep'!$N$5:$N$104,"No") -> 38385 | D39: =SUMIFS('Emails Aug-Sep'!$J$5:$J$104,'Emails Aug-Sep'!$A$5:$A$104,A39,'Emails Aug-Sep'!$N$5:$N$104,"No") -> 735 | E39: =SUMIFS('Emails Aug-Sep'!$L$5:$L$104,'Emails Aug-Sep'!$A$5:$A$104,A39,'Emails Aug-Sep'!$N$5:$N$104,"No") -> 3576 | F39: =D39/SUMIFS('Emails Aug-Sep'!$J$5:$J$104,'Emails Aug-Sep'!$N$5:$N$104,"No") -> 0.27242402 | G39: =E39/SUMIFS('Emails Aug-Sep'!$L$5:$L$104,'Emails Aug-Sep'!$N$5:$N$104,"No") -> 0.53693694
A40: Plug and Play's 2026 Corporate Partnership Survey - Third Batch | B40: 2026-08-25 | C40: =SUMIFS('Emails Aug-Sep'!$F$5:$F$104,'Emails Aug-Sep'!$A$5:$A$104,A40,'Emails Aug-Sep'!$N$5:$N$104,"No") -> 13111 | D40: =SUMIFS('Emails Aug-Sep'!$J$5:$J$104,'Emails Aug-Sep'!$A$5:$A$104,A40,'Emails Aug-Sep'!$N$5:$N$104,"No") -> 252 | E40: =SUMIFS('Emails Aug-Sep'!$L$5:$L$104,'Emails Aug-Sep'!$A$5:$A$104,A40,'Emails Aug-Sep'!$N$5:$N$104,"No") -> 826 | F40: =D40/SUMIFS('Emails Aug-Sep'!$J$5:$J$104,'Emails Aug-Sep'!$N$5:$N$104,"No") -> 0.09340252 | G40: =E40/SUMIFS('Emails Aug-Sep'!$L$5:$L$104,'Emails Aug-Sep'!$N$5:$N$104,"No") -> 0.12402402
A41: FR_ALIBABA COCREATE STARUP EMAIL FINAL | B41: 2026-08-17 | C41: =SUMIFS('Emails Aug-Sep'!$F$5:$F$104,'Emails Aug-Sep'!$A$5:$A$104,A41,'Emails Aug-Sep'!$N$5:$N$104,"No") -> 18358 | D41: =SUMIFS('Emails Aug-Sep'!$J$5:$J$104,'Emails Aug-Sep'!$A$5:$A$104,A41,'Emails Aug-Sep'!$N$5:$N$104,"No") -> 417 | E41: =SUMIFS('Emails Aug-Sep'!$L$5:$L$104,'Emails Aug-Sep'!$A$5:$A$104,A41,'Emails Aug-Sep'!$N$5:$N$104,"No") -> 834 | F41: =D41/SUMIFS('Emails Aug-Sep'!$J$5:$J$104,'Emails Aug-Sep'!$N$5:$N$104,"No") -> 0.15455893 | G41: =E41/SUMIFS('Emails Aug-Sep'!$L$5:$L$104,'Emails Aug-Sep'!$N$5:$N$104,"No") -> 0.12522523
A42: These 3 emails combined | C42: =SUM(C39:C41) -> 69854 | D42: =SUM(D39:D41) -> 1404 | E42: =SUM(E39:E41) -> 5236 | F42: =D42/SUMIFS('Emails Aug-Sep'!$J$5:$J$104,'Emails Aug-Sep'!$N$5:$N$104,"No") -> 0.52038547 | G42: =E42/SUMIFS('Emails Aug-Sep'!$L$5:$L$104,'Emails Aug-Sep'!$N$5:$N$104,"No") -> 0.78618619

Sheet Locations
A1: Location newsletters and subscription types
A2: Sources: Emails Aug-Sep tab; Settings › Marketing › Email › Subscriptions; HubSpot teams list (8 Oct 2026).
A4: Location | B4: Newsletter | C4: Subscription type used | D4: Location's own subscription type | E4: Status of own type | F4: HubSpot team (users)
A5: UK | B5: UK Newsletter | C5: Plug and Play Marketing Communications | D5: Plug and Play UK Communications | E5: Archived | F5: London (3)
A6: Italy | B6: Italy Newsletter | C6: Plug and Play Marketing Communications | D6: Plug and Play Italy (2 types) | E6: Archived | F6: Italy (3), ITALY BD (2)
A7: Texas | B7: Texas Newsletter | C7: Plug and Play Marketing Communications | D7: Plug and Play Texas | E7: Archived | F7: –
A8: Seattle | B8: Seattle Community Newsletter | C8: Plug and Play Marketing Communications | D8: Plug and Play Seattle | E8: Archived | F8: –
A9: Indiana | B9: Indiana Medtech + Lifetech Newsletter | C9: Plug and Play Marketing Communications | D9: Plug and Play Indiana | E9: Archived | F9: –
A10: Türkiye | B10: Türkiye Newsletter | C10: Plug and Play Marketing Communications | D10: Plug and Play Istanbul Communications | E10: Archived | F10: Istanbul (1)
A11: Central Asia & Caucasus | B11: Central Asia & Caucasus Latest News | C11: Plug and Play Marketing Communications | D11: Plug and Play Central Asia & Caucasus | E11: Archived | F11: Kazakhstan (1)
A12: Cyprus | B12: Cyprus Latest News | C12: Plug and Play Marketing Communications | D12: None | E12: – | F12: –
A13: Japan | B13: Japan Newsletter | C13: Plug and Play Japan | D13: Plug and Play Japan | E13: Active | F13: Japan (32)
A14: APAC | B14: APAC Newsletter | C14: Plug and Play APAC | D14: Plug and Play APAC | E14: Active | F14: APAC (5)
A16: =COUNTIF(C5:C14,"Plug and Play Marketing Communications")&" of 10 location newsletters use 'Plug and Play Marketing Communications'." -> 8 of 10 location newsletters use 'Plug and Play Marketing Communications'.
A17: =COUNTIFS('Emails Aug-Sep'!$D$5:$D$104,"Plug and Play Marketing Communications",'Emails Aug-Sep'!$N$5:$N$104,"No")&" of "&COUNTIFS('Emails Aug-Sep'!$N$5:$N$104,"No")&" emails sent 6 Aug – 30 Sep 2026 used 'Plug and Play Marketing Communications'." -> 32 of 97 emails sent 6 Aug – 30 Sep 2026 used 'Plug and Play Marketing Communications'.

Sheet Contacts
A1: Contacts
A2: Source: HubSpot contact counts and Settings › Account & Billing › Usage, 8 Oct 2026.
A4: Measure | B4: Contacts | C4: % of marketing contacts
A5: All contacts | B5: 1198117 | C5: –
A6: Marketing contacts (Marketing contact status = Marketing contact) | B6: 590458 | C6: 1
A7: Marketing contact tier | B7: 630000 | C7: –
A8: Marketing contacts with no marketing email open or click in last 12 months (never opened/clicked included) | B8: 508812 | C8: =B8/$B$6 -> 0.86172429
A9: Marketing contacts who never opened a marketing email | B9: 433657 | C9: =B9/$B$6 -> 0.73444174
A10: Marketing contacts with known open/click dates, both older than 12 months | B10: 29115 | C10: =B10/$B$6 -> 0.04930918
A11: Contacts who clicked a marketing email in last 12 months | B11: 20539 | C11: –
A12: Contacts who clicked a marketing email in last 6 months | B12: 12055 | C12: –
A13: Contacts with a bounce recorded (marketing emails bounced or hard bounce reason known) | B13: 76830 | C13: –
A14: Contacts unsubscribed from all email | B14: 10148 | C14: –
A15: Contacts scheduled to become non-marketing before 31 Oct 2026 | B15: 454 | C15: –
A16: Marketing contacts who opened or clicked in last 12 months | B16: =B6-B8 -> 81646 | C16: =B16/B6 -> 0.13827571
A17: Marketing contacts left before the tier limit (and % of tier used) | B17: =B7-B6 -> 39542 | C17: =B6/B7 -> 0.93723492
A19: Next marketing contact update: 31 Oct 2026. Last billing date: 19 Sep 2026.

Sheet Subscription Types
A1: Subscription types (95: 14 active, 81 archived)
A2: Source: Settings › Marketing › Email › Subscriptions, 8 Oct 2026. All on the default business unit.
A4: Name | B4: Description | C4: Status
A5: Fintech & AI Fund Insights | B5: This newsletter is where we'll track what's actually happening across our fund, including partnerships going live, portfolio wins, and the shifts we're watching in fintech and AI. | C5: Active
A6: Internal Plug and Play Communications | B6: Internal updates and announcements for Plug and Play teams | C6: Active
A7: One to One | B7: One to One emails | C7: Active
A8: Plug and Play APAC | B8: The latest news, event updates, and more about Plug and Play APAC in your inbox | C8: Active
A9: Plug and Play Brand and Retail team | B9: News, insights and events from Plug and Play Brand and Retail | C9: Active
A10: Plug and Play Events | B10: The latest event updates from Plug and Play in your inbox | C10: Active
A11: Plug and Play Foundation | B11: Latest updates and news from the Plug and Play Foundation | C11: Active
A12: Plug and Play Global Newsletter | B12: The latest news, event updates, and more about Plug and Play in your inbox | C12: Active
A13: Plug and Play Information & Services | B13: Information about programs and services from Plug and Play | C13: Active
A14: Plug and Play Japan | B14: The latest news, event updates, and more about Plug and Play Japan in your inbox | C14: Active
A15: Plug and Play Los Angeles | B15: Los Angeles | C15: Active
... A99: University Pitch Session Americas | B99: 30 startups from different universities pitch every Wednesday | C99: Archived
A101: Subscription settings
A102: Unsubscribe feedback survey | B102: OFF
A103: Resubscription email | B103: OFF
A104: Don't send to unengaged contacts | B104: ON
A105: Compliance BCC | B105: OFF
A106: Active subscription types (count) | B106: =COUNTIF(C5:C99,"Active") -> 14
A107: Archived subscription types (count) | B107: =COUNTIF(C5:C99,"Archived") -> 81

Sheet Workflows
A1: Workflows with a 'Send email' action (309)
A2: Source: Automation › Workflows, 8 Oct 2026.
A4: Workflow | B4: Status | C4: Currently enrolled | D4: Last updated | E4: ON and last updated before 2024
A5: LNS - RFI - 2025 | B5: On | C5: 4742 | D5: 2026-09-03 | E5: =IF(AND(B5="On",D5<"2024-01-01"),"Yes","No") -> No
A6: IA - CDW - EAI - Report - The Ultimate AI Playbook | B6: On | C6: 12 | D6: 2026-03-09 | E6: =IF(AND(B6="On",D6<"2024-01-01"),"Yes","No") -> No
A7: GNL reactivation campaign | B7: On | C7: 7 | D7: 2026-04-09 | E7: =IF(AND(B7="On",D7<"2024-01-01"),"Yes","No") -> No
A8: IA - CDW - EGY - Report - Energizing AI: A Deep Dive Into the Data Center Energy Value Chain | B8: On | C8: 0 | D8: 2026-09-23 | E8: =IF(AND(B8="On",D8<"2024-01-01"),"Yes","No") -> No
A9: IA - CDW - AI Survey Report | B9: On | C9: 0 | D9: 2026-09-22 | E9: =IF(AND(B9="On",D9<"2024-01-01"),"Yes","No") -> No
A10: Send a follow-up email after form submission | B10: On | C10: 0 | D10: 2026-09-09 | E10: =IF(AND(B10="On",D10<"2024-01-01"),"Yes","No") -> No
A11: JAP \| JTP_Japan Summit Inquiry | B11: On | C11: 0 | D11: 2026-07-29 | E11: =IF(AND(B11="On",D11<"2024-01-01"),"Yes","No") -> No
A12: IA - CDW - EGY - Report - Secure Systems: Building Resilient Energy Infrastructure | B12: On | C12: 0 | D12: 2026-07-09 | E12: =IF(AND(B12="On",D12<"2024-01-01"),"Yes","No") -> No
A13: IA - CDW - Innovation Assessment Report | B13: On | C13: 0 | D13: 2026-07-06 | E13: =IF(AND(B13="On",D13<"2024-01-01"),"Yes","No") -> No
A14: IA - CDW - EAI - Report - The AI-Enabled Waste Recovery Opportunity | B14: On | C14: 0 | D14: 2026-07-02 | E14: =IF(AND(B14="On",D14<"2024-01-01"),"Yes","No") -> No
A15: JAP \| JTP_Resource Download Thanks Mail_Trend Report | B15: On | C15: 0 | D15: 2026-06-16 | E15: =IF(AND(B15="On",D15<"2024-01-01"),"Yes","No") -> No
A16: JAP \| JTP_Resource Download Thanks Mail_Company Report | B16: On | C16: 0 | D16: 2026-06-16 | E16: =IF(AND(B16="On",D16<"2024-01-01"),"Yes","No") -> No
... A313: LNS_Lead Nurturing_Lead to SQL | B313: Off | C313: 0 | D313: 2022-02-15 | E313: =IF(AND(B313="On",D313<"2024-01-01"),"Yes","No") -> No
A315: Total | B315: =COUNTA(A5:A313) -> 309
A316: ON | B316: =COUNTIF(B5:B313,"On") -> 251
A317: OFF | B317: =COUNTIF(B5:B313,"Off") -> 58
A318: ON and last updated before 2024 | B318: =COUNTIF(E5:E313,"Yes") -> 65
A319: ON with 'COVID' in the name | B319: =COUNTIFS(A5:A313,"*COVID*",B5:B313,"On") -> 5

Sheet Teams
A1: HubSpot teams (62)
A2: Source: HubSpot teams list, 8 Oct 2026. None of the 1,042 emails sent 1 Oct 2025 – 30 Sep 2026 has a team assigned.
A4: Team | B4: Primary users | C4: Secondary users | D4: Parent team
A5: Abu Dhabi | B5: 3 | C5: 0
A6: AgTech | B6: 0 | C6: 0
A7: Alberta | B7: 3 | C7: 0
A8: Amsterdam | B8: 1 | C8: 0
A9: APAC | B9: 5 | C9: 0
A10: Arizona | B10: 4 | C10: 1 | D10: Supply Chain
A11: Barcelona | B11: 2 | C11: 1
A12: Basel | B12: 0 | C12: 0
A13: Borja's team - VLC | B13: 6 | C13: 0
A14: Brazil | B14: 0 | C14: 0
A15: Building Ops SV | B15: 0 | C15: 2
A16: Cleveland Team | B16: 2 | C16: 0
A17: Corporate Overall | B17: 2 | C17: 0
A18: Egypt | B18: 1 | C18: 0
A19: EMEA Fund | B19: 3 | C19: 1
A20: Energy | B20: 2 | C20: 1
A21: Fintech | B21: 6 | C21: 0
A22: Food | B22: 2 | C22: 0
... A31: Italy | B31: 3 | C31: 0
A32: ITALY BD | B32: 2 | C32: 0 | D32: Italy
A33: Japan | B33: 32 | C33: 0
A34: Kazakhstan | B34: 1 | C34: 0
A35: LA | B35: 2 | C35: 1
A36: LATAM | B36: 0 | C36: 0
A37: London | B37: 3 | C37: 0
A38: Maritime | B38: 0 | C38: 0
A39: Marketing | B39: 15 | C39: 3
A40: Materials | B40: 1 | C40: 0
A41: Media | B41: 0 | C41: 1
A42: Media & Advertising | B42: 0 | C42: 1 | D42: LA
A43: Mobility/IoT | B43: 8 | C43: 0
A44: munich | B44: 1 | C44: 0
A45: Nordics | B45: 0 | C45: 0
A46: Operations | B46: 3 | C46: 0
A47: Paris | B47: 0 | C47: 0
A48: Real Estate | B48: 2 | C48: 0
A49: Retail | B49: 4 | C49: 0
A50: Sanam's Test Team | B50: 2 | C50: 0
A51: Saudi | B51: 1 | C51: 0
A52: Savannah | B52: 0 | C52: 0
A53: Silicon Valley | B53: 1 | C53: 1
A54: Smart Cities | B54: 5 | C54: 1
... A64: Travel | B64: 1 | C64: 0
A65: Travel EU/Vienna | B65: 5 | C65: 0 | D65: Travel
A66: Ventures | B66: 1 | C66: 0
A67: Total | B67: =SUM(B5:B66) -> 170 | C67: =SUM(C5:C66) -> 14 | D67: =COUNTA(A5:A66)&" teams" -> 62 teams

Sheet Emails Aug-Sep
A1: Sent emails, 6 Aug – 30 Sep 2026 (latest 100 records)
A2: Source: HubSpot › Marketing › Email › Manage, 8 Oct 2026. Rows marked Duplicate = Yes have identical stats to another row and are excluded from totals.
A4: Email name | B4: Send date | C4: From name | D4: Subscription type | E4: Newsletter | F4: Delivered | G4: Open rate | H4: Click rate | I4: Clicks (calc.) | J4: Unsubscribes | K4: Unsub rate | L4: Bounces (hard + soft) | M4: Bounce rate | N4: Duplicate
A5: 2026 travel nov summit outreach (rest) | B5: 2026-09-30 | C5: Brandon Lee | D5: Plug and Play Travel and Hospitality Silicon Valley | F5: 576 | G5: 0.311 | H5: 0.028 | I5: =ROUND(F5*H5,0) -> 16 | J5: 3 | K5: =IF(F5=0,0,J5/F5) -> 0.0052083333 | L5: 32 | M5: =IF(F5+L5=0,0,L5/(F5+L5)) -> 0.052631579 | N5: No
A6: September_Internal_Newsletter | B6: 2026-09-30 | C6: Sanam Amidi | D6: Internal Plug and Play Communications | E6: Internal Newsletter | F6: 618 | G6: 0.12 | H6: 0.06 | I6: =ROUND(F6*H6,0) -> 37 | J6: 0 | K6: =IF(F6=0,0,J6/F6) -> 0 | L6: 1 | M6: =IF(F6+L6=0,0,L6/(F6+L6)) -> 0.0016155089 | N6: No
A7: Physical AI | B7: 2026-09-30 | C7: Rick Hernandez | D7: Plug and Play Events | F7: 124 | G7: 0.452 | H7: 0.008 | I7: =ROUND(F7*H7,0) -> 1 | J7: 0 | K7: =IF(F7=0,0,J7/F7) -> 0 | L7: 0 | M7: =IF(F7+L7=0,0,L7/(F7+L7)) -> 0 | N7: No
A8: UK September 2026 Newsletter | B8: 2026-09-30 | C8: Kieran Borrett | D8: Plug and Play Marketing Communications | E8: UK Newsletter | F8: 6415 | G8: 0.261 | H8: 0.009 | I8: =ROUND(F8*H8,0) -> 58 | J8: 56 | K8: =IF(F8=0,0,J8/F8) -> 0.0087295401 | L8: 38 | M8: =IF(F8+L8=0,0,L8/(F8+L8)) -> 0.0058887339 | N8: No
A9: JAP_Newsletter_Sept - 2026 - 30 | B9: 2026-09-30 | C9: Plug and Play Japan | D9: Plug and Play Japan | E9: Japan Newsletter | F9: 1108 | G9: 0.428 | H9: 0.057 | I9: =ROUND(F9*H9,0) -> 63 | J9: 0 | K9: =IF(F9=0,0,J9/F9) -> 0 | L9: 1 | M9: =IF(F9+L9=0,0,L9/(F9+L9)) -> 0.00090171326 | N9: No
A10: Tirana Expo Invitation (2) 2026 | B10: 2026-09-30 | C10: Plug and Play Tirana | D10: Plug and Play Events | F10: 958 | G10: 0.31 | H10: 0.082 | I10: =ROUND(F10*H10,0) -> 79 | J10: 4 | K10: =IF(F10=0,0,J10/F10) -> 0.0041753653 | L10: 16 | M10: =IF(F10+L10=0,0,L10/(F10+L10)) -> 0.016427105 | N10: No
A11: October Events | B11: 2026-09-30 | C11: Rick Hernandez | D11: Plug and Play Events | F11: 124 | G11: 0.653 | H11: 0.016 | I11: =ROUND(F11*H11,0) -> 2 | J11: 0 | K11: =IF(F11=0,0,J11/F11) -> 0 | L11: 0 | M11: =IF(F11+L11=0,0,L11/(F11+L11)) -> 0 | N11: No
A12: GNL_September 2026 | B12: 2026-09-29 | C12: Jacky from Plug and Play | D12: Plug and Play Global Newsletter | E12: Global Newsletter (GNL) | F12: 7029 | G12: 0.178 | H12: 0.03 | I12: =ROUND(F12*H12,0) -> 211 | J12: 29 | K12: =IF(F12=0,0,J12/F12) -> 0.0041257647 | L12: 34 | M12: =IF(F12+L12=0,0,L12/(F12+L12)) -> 0.0048138185 | N12: No
A13: TEXAS September Newsletter | B13: 2026-09-29 | C13: Francis from Plug and Play | D13: Plug and Play Marketing Communications | E13: Texas Newsletter | F13: 4698 | G13: 0.245 | H13: 0.026 | I13: =ROUND(F13*H13,0) -> 122 | J13: 28 | K13: =IF(F13=0,0,J13/F13) -> 0.005959983 | L13: 38 | M13: =IF(F13+L13=0,0,L13/(F13+L13)) -> 0.0080236486 | N13: No
A14: BRAM Newsletter #2 - RetailClub Notes/ September 2026 | B14: 2026-09-29 | C14: Plug and Play Brand and Retail | D14: Plug and Play Brand and Retail team | E14: Brand & Retail (BRAM) Newsletter | F14: 114 | G14: 0.254 | H14: 0.026 | I14: =ROUND(F14*H14,0) -> 3 | J14: 0 | K14: =IF(F14=0,0,J14/F14) -> 0 | L14: 0 | M14: =IF(F14+L14=0,0,L14/(F14+L14)) -> 0 | N14: No
A15: 🚀 Plug and Play Cyprus_Expo News | B15: 2026-09-29 | C15: Victoria from Plug and Play Cyprus | D15: Plug and Play Marketing Communications | F15: 3663 | G15: 0.292 | H15: 0.016 | I15: =ROUND(F15*H15,0) -> 59 | J15: 33 | K15: =IF(F15=0,0,J15/F15) -> 0.009009009 | L15: 65 | M15: =IF(F15+L15=0,0,L15/(F15+L15)) -> 0.017435622 | N15: No
A16: THF Launch_General (registered) (Sept 28) | B16: 2026-09-28 | C16: Plug and Play Finland | D16: Plug and Play Events | F16: 79 | G16: 0.544 | H16: 0 | I16: =ROUND(F16*H16,0) -> 0 | J16: 0 | K16: =IF(F16=0,0,J16/F16) -> 0 | L16: 0 | M16: =IF(F16+L16=0,0,L16/(F16+L16)) -> 0 | N16: No
A17: Live Pitch Feedback Event: Mobility & Advanced Hardware | B17: 2026-09-25 | C17: Rick Hernandez | D17: Plug and Play Events | F17: 124 | G17: 0.556 | H17: 0.065 | I17: =ROUND(F17*H17,0) -> 8 | J17: 0 | K17: =IF(F17=0,0,J17/F17) -> 0 | L17: 0 | M17: =IF(F17+L17=0,0,L17/(F17+L17)) -> 0 | N17: No
A18: New email | B18: 2026-09-24 | C18: roza amrollah | D18: Plug and Play Events | F18: 70 | G18: 0.486 | H18: 0.043 | I18: =ROUND(F18*H18,0) -> 3 | J18: 0 | K18: =IF(F18=0,0,J18/F18) -> 0 | L18: 0 | M18: =IF(F18+L18=0,0,L18/(F18+L18)) -> 0 | N18: No
A19: Summit for Tenants | B19: 2026-09-24 | C19: Rick Hernandez | D19: Plug and Play Events | F19: 125 | G19: 0.664 | H19: 0.192 | I19: =ROUND(F19*H19,0) -> 24 | J19: 0 | K19: =IF(F19=0,0,J19/F19) -> 0 | L19: 0 | M19: =IF(F19+L19=0,0,L19/(F19+L19)) -> 0 | N19: No
A20: Fintech & AI Insights - Edition 2 - September 23, 2026 | B20: 2026-09-23 | C20: Brooke Ballinger | D20: Fintech & AI Fund Insights | E20: Fintech & AI Fund Insights | F20: 8611 | G20: 0.359 | H20: 0.007 | I20: =ROUND(F20*H20,0) -> 60 | J20: 122 | K20: =IF(F20=0,0,J20/F20) -> 0.014167925 | L20: 113 | M20: =IF(F20+L20=0,0,L20/(F20+L20)) -> 0.012952774 | N20: No
A21: ME Innovation Day, Email 2 | B21: 2026-09-23 | C21: Ava Milana | D21: Plug and Play Marketing Communications | F21: 4295 | G21: 0.276 | H21: 0.02 | I21: =ROUND(F21*H21,0) -> 86 | J21: 26 | K21: =IF(F21=0,0,J21/F21) -> 0.0060535506 | L21: 44 | M21: =IF(F21+L21=0,0,L21/(F21+L21)) -> 0.010140585 | N21: No
A22: Alignment 2026 | B22: 2026-09-23 | C22: Rick Hernandez | D22: Plug and Play Events | F22: 126 | G22: 0.5 | H22: 0.056 | I22: =ROUND(F22*H22,0) -> 7 | J22: 0 | K22: =IF(F22=0,0,J22/F22) -> 0 | L22: 0 | M22: =IF(F22+L22=0,0,L22/(F22+L22)) -> 0 | N22: No
A23: APAC_Newsletter_September_2026 | B23: 2026-09-23 | C23: Plug and Play APAC | D23: Plug and Play APAC | E23: APAC Newsletter | F23: 2789 | G23: 0.321 | H23: 0.034 | I23: =ROUND(F23*H23,0) -> 95 | J23: 10 | K23: =IF(F23=0,0,J23/F23) -> 0.0035855145 | L23: 17 | M23: =IF(F23+L23=0,0,L23/(F23+L23)) -> 0.0060584462 | N23: No
A24: THF Launch_General (registered) (Sept 22) | B24: 2026-09-22 | C24: Plug and Play Finland | D24: Plug and Play Events | F24: 79 | G24: 0.544 | H24: 0.215 | I24: =ROUND(F24*H24,0) -> 17 | J24: 0 | K24: =IF(F24=0,0,J24/F24) -> 0 | L24: 0 | M24: =IF(F24+L24=0,0,L24/(F24+L24)) -> 0 | N24: No
A25: SMB Tech Connect | B25: 2026-09-22 | C25: Rick Hernandez | D25: Plug and Play Events | F25: 126 | G25: 0.563 | H25: 0.016 | I25: =ROUND(F25*H25,0) -> 2 | J25: 0 | K25: =IF(F25=0,0,J25/F25) -> 0 | L25: 0 | M25: =IF(F25+L25=0,0,L25/(F25+L25)) -> 0 | N25: No
A26: Indiana Medtech + Lifetech Newsletter September 2026 | B26: 2026-09-18 | C26: Plug and Play Indiana | D26: Plug and Play Marketing Communications | E26: Indiana Medtech + Lifetech Newsletter | F26: 1430 | G26: 0.414 | H26: 0.013 | I26: =ROUND(F26*H26,0) -> 19 | J26: 8 | K26: =IF(F26=0,0,J26/F26) -> 0.0055944056 | L26: 10 | M26: =IF(F26+L26=0,0,L26/(F26+L26)) -> 0.0069444444 | N26: No
A27: Indiana Medtech + Lifetech Newsletter September 2026 | B27: 2026-09-18 | C27: Plug and Play Indiana | D27: Plug and Play Marketing Communications | E27: Indiana Medtech + Lifetech Newsletter | F27: 1430 | G27: 0.414 | H27: 0.013 | I27: =ROUND(F27*H27,0) -> 19 | J27: 8 | K27: =IF(F27=0,0,J27/F27) -> 0.0055944056 | L27: 10 | M27: =IF(F27+L27=0,0,L27/(F27+L27)) -> 0.0069444444 | N27: Yes
A28: JTP | JAP_Sansan List_Consent Mail_20260909 | B28: 2026-09-18 | C28: Plug and Play Japan | D28: Plug and Play Japan | F28: 38385 | G28: 0.229 | H28: 0.003 | I28: =ROUND(F28*H28,0) -> 115 | J28: 735 | K28: =IF(F28=0,0,J28/F28) -> 0.019148105 | L28: 3576 | M28: =IF(F28+L28=0,0,L28/(F28+L28)) -> 0.085221992 | N28: No
A29: 2026 travel nov summit outreach | B29: 2026-09-18 | C29: Brandon Lee | D29: Plug and Play Travel and Hospitality Silicon Valley | F29: 1545 | G29: 0.35 | H29: 0.015 | I29: =ROUND(F29*H29,0) -> 23 | J29: 25 | K29: =IF(F29=0,0,J29/F29) -> 0.01618123 | L29: 48 | M29: =IF(F29+L29=0,0,L29/(F29+L29)) -> 0.030131827 | N29: No
A30: Indiana Lifetech & Medtech Alumni - Invitation to SV Summit November 2026 | B30: 2026-09-17 | C30: Eileen Alberding | D30: Plug and Play Events | F30: 108 | G30: 0.472 | H30: 0.028 | I30: =ROUND(F30*H30,0) -> 3 | J30: 0 | K30: =IF(F30=0,0,J30/F30) -> 0 | L30: 1 | M30: =IF(F30+L30=0,0,L30/(F30+L30)) -> 0.0091743119 | N30: No
A31: Indiana Lifetech & Medtech Mentors - Invitation to SV Summit November 2026 (Clone) | B31: 2026-09-17 | C31: Eileen Alberding | D31: Plug and Play Events | F31: 72 | G31: 0.653 | H31: 0.208 | I31: =ROUND(F31*H31,0) -> 15 | J31: 0 | K31: =IF(F31=0,0,J31/F31) -> 0 | L31: 0 | M31: =IF(F31+L31=0,0,L31/(F31+L31)) -> 0 | N31: No
A32: ITA26_Newsletter September | B32: 2026-09-17 | C32: Tommaso Maschera | D32: Plug and Play Marketing Communications | E32: Italy Newsletter | F32: 7259 | G32: 0.263 | H32: 0.01 | I32: =ROUND(F32*H32,0) -> 73 | J32: 62 | K32: =IF(F32=0,0,J32/F32) -> 0.0085411214 | L32: 100 | M32: =IF(F32+L32=0,0,L32/(F32+L32)) -> 0.013588803 | N32: No
A33: JAP_Newsletter - Sept - 2026 - 16 | B33: 2026-09-16 | C33: Plug and Play Japan | D33: Plug and Play Japan | E33: Japan Newsletter | F33: 887 | G33: 0.263 | H33: 0.061 | I33: =ROUND(F33*H33,0) -> 54 | J33: 2 | K33: =IF(F33=0,0,J33/F33) -> 0.0022547914 | L33: 1 | M33: =IF(F33+L33=0,0,L33/(F33+L33)) -> 0.0011261261 | N33: No
A34: KOCCA SG Biz Matching -1 | B34: 2026-09-16 | C34: Tae Rin Ha | D34: Plug and Play APAC | F34: 44 | G34: 0.455 | H34: 0.114 | I34: =ROUND(F34*H34,0) -> 5 | J34: 0 | K34: =IF(F34=0,0,J34/F34) -> 0 | L34: 0 | M34: =IF(F34+L34=0,0,L34/(F34+L34)) -> 0 | N34: No
A35: THF_Selected (FORM - follow up) | B35: 2026-09-16 | C35: Plug and Play Finland | D35: Plug and Play Marketing Communications | F35: 9 | G35: 0.889 | H35: 0.556 | I35: =ROUND(F35*H35,0) -> 5 | J35: 0 | K35: =IF(F35=0,0,J35/F35) -> 0 | L35: 0 | M35: =IF(F35+L35=0,0,L35/(F35+L35)) -> 0 | N35: No
A36: THF Launch_General (NOT registered) (Sept 15) | B36: 2026-09-15 | C36: Plug and Play Finland | D36: Plug and Play Events | F36: 90 | G36: 0.333 | H36: 0.089 | I36: =ROUND(F36*H36,0) -> 8 | J36: 0 | K36: =IF(F36=0,0,J36/F36) -> 0 | L36: 1 | M36: =IF(F36+L36=0,0,L36/(F36+L36)) -> 0.010989011 | N36: No
A37: THF Launch_General (registered) (Sept 15) | B37: 2026-09-15 | C37: Plug and Play Finland | D37: Plug and Play Events | F37: 73 | G37: 0.466 | H37: 0.11 | I37: =ROUND(F37*H37,0) -> 8 | J37: 0 | K37: =IF(F37=0,0,J37/F37) -> 0 | L37: 0 | M37: =IF(F37+L37=0,0,L37/(F37+L37)) -> 0 | N37: No
A38: THF_Selected (FORM) | B38: 2026-09-15 | C38: Plug and Play Finland | D38: Plug and Play Marketing Communications | F38: 9 | G38: 0.889 | H38: 0.778 | I38: =ROUND(F38*H38,0) -> 7 | J38: 0 | K38: =IF(F38=0,0,J38/F38) -> 0 | L38: 0 | M38: =IF(F38+L38=0,0,L38/(F38+L38)) -> 0 | N38: No
A39: Reminder: Founders Lunch | B39: 2026-09-15 | C39: Rick Hernandez | D39: Plug and Play Events | F39: 123 | G39: 0.504 | H39: 0.057 | I39: =ROUND(F39*H39,0) -> 7 | J39: 0 | K39: =IF(F39=0,0,J39/F39) -> 0 | L39: 0 | M39: =IF(F39+L39=0,0,L39/(F39+L39)) -> 0 | N39: No
A40: Shamrock Foods - Monthly Signal August 31 (v1) | B40: 2026-09-14 | C40: Plug and Play Supply Chain | D40: Plug and Play Marketing Communications | E40: Shamrock Foods Monthly Signal | F40: 7 | G40: 0.857 | H40: 0 | I40: =ROUND(F40*H40,0) -> 0 | J40: 0 | K40: =IF(F40=0,0,J40/F40) -> 0 | L40: 0 | M40: =IF(F40+L40=0,0,L40/(F40+L40)) -> 0 | N40: No
A41: Selection Day & Batch Kickoff Thank you email | General Mills | B41: 2026-09-14 | C41: Tabitha Mills | D41: Plug and Play Global Newsletter | F41: 177 | G41: 0.508 | H41: 0.186 | I41: =ROUND(F41*H41,0) -> 33 | J41: 0 | K41: =IF(F41=0,0,J41/F41) -> 0 | L41: 1 | M41: =IF(F41+L41=0,0,L41/(F41+L41)) -> 0.0056179775 | N41: No
A42: Career, Rewired for the AI Age | B42: 2026-09-14 | C42: Rick Hernandez | D42: Plug and Play Events | F42: 123 | G42: 0.528 | H42: 0.049 | I42: =ROUND(F42*H42,0) -> 6 | J42: 0 | K42: =IF(F42=0,0,J42/F42) -> 0 | L42: 0 | M42: =IF(F42+L42=0,0,L42/(F42+L42)) -> 0 | N42: No
A43: THF_Selected | B43: 2026-09-14 | C43: Plug and Play Finland | D43: Plug and Play Marketing Communications | F43: 8 | G43: 0.875 | H43: 0 | I43: =ROUND(F43*H43,0) -> 0 | J43: 0 | K43: =IF(F43=0,0,J43/F43) -> 0 | L43: 0 | M43: =IF(F43+L43=0,0,L43/(F43+L43)) -> 0 | N43: No
A44: THF_Not Selected | B44: 2026-09-14 | C44: Plug and Play Finland | D44: Plug and Play Events | F44: 12 | G44: 0.917 | H44: 0.167 | I44: =ROUND(F44*H44,0) -> 2 | J44: 0 | K44: =IF(F44=0,0,J44/F44) -> 0 | L44: 0 | M44: =IF(F44+L44=0,0,L44/(F44+L44)) -> 0 | N44: No
A45: THF_Not Shortlisted | B45: 2026-09-14 | C45: Plug and Play Finland | D45: Plug and Play Events | F45: 81 | G45: 0.704 | H45: 0.099 | I45: =ROUND(F45*H45,0) -> 8 | J45: 1 | K45: =IF(F45=0,0,J45/F45) -> 0.012345679 | L45: 1 | M45: =IF(F45+L45=0,0,L45/(F45+L45)) -> 0.012195122 | N45: No
A46: CLONE Revised BRAM Newsletter #1 / September 2026 - Version A | B46: 2026-09-11 | C46: Plug and Play Brand and Retail | D46: Plug and Play Brand and Retail team | E46: Brand & Retail (BRAM) Newsletter | F46: 148 | G46: 0.277 | H46: 0.027 | I46: =ROUND(F46*H46,0) -> 4 | J46: 1 | K46: =IF(F46=0,0,J46/F46) -> 0.0067567568 | L46: 0 | M46: =IF(F46+L46=0,0,L46/(F46+L46)) -> 0 | N46: No
A47: Revised BRAM Newsletter #1 / September 2026 | B47: 2026-09-11 | C47: Plug and Play Brand and Retail | D47: Plug and Play Information & Services | E47: Brand & Retail (BRAM) Newsletter | F47: 117 | G47: 0.274 | H47: 0.043 | I47: =ROUND(F47*H47,0) -> 5 | J47: 1 | K47: =IF(F47=0,0,J47/F47) -> 0.0085470085 | L47: 0 | M47: =IF(F47+L47=0,0,L47/(F47+L47)) -> 0 | N47: No
A48: Revised BRAM Newsletter #1 / September 2026 | B48: 2026-09-11 | C48: Plug and Play Brand and Retail | D48: Plug and Play Information & Services | E48: Brand & Retail (BRAM) Newsletter | F48: 117 | G48: 0.274 | H48: 0.043 | I48: =ROUND(F48*H48,0) -> 5 | J48: 1 | K48: =IF(F48=0,0,J48/F48) -> 0.0085470085 | L48: 0 | M48: =IF(F48+L48=0,0,L48/(F48+L48)) -> 0 | N48: Yes
A49: Pitch Deck Teardown | B49: 2026-09-10 | C49: Rick Hernandez | D49: Plug and Play Events | F49: 123 | G49: 0.48 | H49: 0.057 | I49: =ROUND(F49*H49,0) -> 7 | J49: 0 | K49: =IF(F49=0,0,J49/F49) -> 0 | L49: 0 | M49: =IF(F49+L49=0,0,L49/(F49+L49)) -> 0 | N49: No
A50: Youth Social | B50: 2026-09-09 | C50: Rick Hernandez | D50: Plug and Play Events | F50: 124 | G50: 0.581 | H50: 0.056 | I50: =ROUND(F50*H50,0) -> 7 | J50: 0 | K50: =IF(F50=0,0,J50/F50) -> 0 | L50: 0 | M50: =IF(F50+L50=0,0,L50/(F50+L50)) -> 0 | N50: No
A51: San Jose office Event | B51: 2026-09-08 | C51: Rick Hernandez | D51: Plug and Play Events | F51: 124 | G51: 0.685 | H51: 0.065 | I51: =ROUND(F51*H51,0) -> 8 | J51: 0 | K51: =IF(F51=0,0,J51/F51) -> 0 | L51: 0 | M51: =IF(F51+L51=0,0,L51/(F51+L51)) -> 0 | N51: No
A52: Thank you - Medtech Expo attendees September 2026 | B52: 2026-09-08 | C52: Plug and Play Warsaw - Medtech | D52: Plug and Play Marketing Communications | F52: 101 | G52: 0.545 | H52: 0.109 | I52: =ROUND(F52*H52,0) -> 11 | J52: 0 | K52: =IF(F52=0,0,J52/F52) -> 0 | L52: 0 | M52: =IF(F52+L52=0,0,L52/(F52+L52)) -> 0 | N52: No
A53: SLAM Innovation Brief 3 September 2026 | B53: 2026-09-08 | C53: Plug and Play Supply Chain | D53: Plug and Play Information & Services | E53: Supply Chain (SLAM) Innovation Brief | F53: 54 | G53: 0.259 | H53: 0.093 | I53: =ROUND(F53*H53,0) -> 5 | J53: 0 | K53: =IF(F53=0,0,J53/F53) -> 0 | L53: 0 | M53: =IF(F53+L53=0,0,L53/(F53+L53)) -> 0 | N53: No
A54: FR_ALIBABA COCREATE TIER 1 FINALISTS | B54: 2026-09-08 | C54: Philipp Hödl | D54: Plug and Play Marketing Communications | F54: 27 | G54: 0.852 | H54: 0.778 | I54: =ROUND(F54*H54,0) -> 21 | J54: 0 | K54: =IF(F54=0,0,J54/F54) -> 0 | L54: 0 | M54: =IF(F54+L54=0,0,L54/(F54+L54)) -> 0 | N54: No
A55: FR_ALIBABA COCREATE FINALISTS-GENERAL | B55: 2026-09-08 | C55: Philipp Hödl | D55: Plug and Play Marketing Communications | F55: 173 | G55: 0.717 | H55: 0.607 | I55: =ROUND(F55*H55,0) -> 105 | J55: 1 | K55: =IF(F55=0,0,J55/F55) -> 0.0057803468 | L55: 0 | M55: =IF(F55+L55=0,0,L55/(F55+L55)) -> 0 | N55: No
A56: Your Monthly Dose of Tech Inspiration 🍁 Autumn is here! | B56: 2026-09-07 | C56: STARTUP AUTOBAHN powered by Plug and Play | D56: Startup Autobahn Communications | E56: Startup Autobahn Monthly | F56: 4384 | G56: 0.224 | H56: 0.021 | I56: =ROUND(F56*H56,0) -> 92 | J56: 15 | K56: =IF(F56=0,0,J56/F56) -> 0.0034215328 | L56: 45 | M56: =IF(F56+L56=0,0,L56/(F56+L56)) -> 0.010160307 | N56: No
A57: GoSentrix | B57: 2026-09-04 | C57: Rick Hernandez | D57: Plug and Play Events | F57: 125 | G57: 0.552 | H57: 0.04 | I57: =ROUND(F57*H57,0) -> 5 | J57: 0 | K57: =IF(F57=0,0,J57/F57) -> 0 | L57: 0 | M57: =IF(F57+L57=0,0,L57/(F57+L57)) -> 0 | N57: No
A58: 🚀 Plug and Play Cyprus_Latest News_09/26 | B58: 2026-09-04 | C58: Victoria from Plug and Play Cyprus | D58: Plug and Play Marketing Communications | E58: Cyprus Latest News | F58: 309 | G58: 0.379 | H58: 0.104 | I58: =ROUND(F58*H58,0) -> 32 | J58: 6 | K58: =IF(F58=0,0,J58/F58) -> 0.019417476 | L58: 26 | M58: =IF(F58+L58=0,0,L58/(F58+L58)) -> 0.07761194 | N58: No
A59: PNPCA_Latest News_ August_2026 | B59: 2026-09-04 | C59: Sofi from Plug and Play Central Asia and Caucasus | D59: Plug and Play Marketing Communications | E59: Central Asia & Caucasus Latest News | F59: 3302 | G59: 0.255 | H59: 0.015 | I59: =ROUND(F59*H59,0) -> 50 | J59: 25 | K59: =IF(F59=0,0,J59/F59) -> 0.007571169 | L59: 75 | M59: =IF(F59+L59=0,0,L59/(F59+L59)) -> 0.022209061 | N59: No
A60: Minnesota Sustainability 2026 H2 Mentor Newsletter | B60: 2026-09-03 | C60: Tabitha Mills | D60: Plug and Play Global Newsletter | E60: Mentor Newsletters (Minnesota Sustainability & NMP) | F60: 26 | G60: 0.654 | H60: 0.462 | I60: =ROUND(F60*H60,0) -> 12 | J60: 0 | K60: =IF(F60=0,0,J60/F60) -> 0 | L60: 0 | M60: =IF(F60+L60=0,0,L60/(F60+L60)) -> 0 | N60: No
A61: NMP 2026 H2 Mentor Newsletter | B61: 2026-09-03 | C61: Tabitha Mills | D61: Plug and Play Global Newsletter | E61: Mentor Newsletters (Minnesota Sustainability & NMP) | F61: 22 | G61: 0.682 | H61: 0.455 | I61: =ROUND(F61*H61,0) -> 10 | J61: 0 | K61: =IF(F61=0,0,J61/F61) -> 0 | L61: 0 | M61: =IF(F61+L61=0,0,L61/(F61+L61)) -> 0 | N61: No
A62: UK - Mobilise Monthly Update (August) | B62: 2026-09-03 | C62: Adam McGuinness | D62: Plug and Play Events | E62: UK Mobilise Monthly Update | F62: 31 | G62: 0.613 | H62: 0.065 | I62: =ROUND(F62*H62,0) -> 2 | J62: 0 | K62: =IF(F62=0,0,J62/F62) -> 0 | L62: 0 | M62: =IF(F62+L62=0,0,L62/(F62+L62)) -> 0 | N62: No
A63: 2026 Batch 22 Kickoff Newsletter | B63: 2026-09-02 | C63: Brandon Lee | D63: Plug and Play Global Newsletter | F63: 59 | G63: 0.407 | H63: 0.119 | I63: =ROUND(F63*H63,0) -> 7 | J63: 0 | K63: =IF(F63=0,0,J63/F63) -> 0 | L63: 0 | M63: =IF(F63+L63=0,0,L63/(F63+L63)) -> 0 | N63: No
A64: Finovate Fall Blast (Final) | B64: 2026-09-02 | C64: Jacky from Plug and Play | D64: Plug and Play Global Newsletter | F64: 1330 | G64: 0.261 | H64: 0.026 | I64: =ROUND(F64*H64,0) -> 35 | J64: 11 | K64: =IF(F64=0,0,J64/F64) -> 0.0082706767 | L64: 7 | M64: =IF(F64+L64=0,0,L64/(F64+L64)) -> 0.0052356021 | N64: No
A65: YOU ARE INVITED: Innovation Connect | B65: 2026-09-02 | C65: Rick Hernandez | D65: Plug and Play Events | F65: 125 | G65: 0.592 | H65: 0.128 | I65: =ROUND(F65*H65,0) -> 16 | J65: 0 | K65: =IF(F65=0,0,J65/F65) -> 0 | L65: 0 | M65: =IF(F65+L65=0,0,L65/(F65+L65)) -> 0 | N65: No
A66: FR_ALIBABA COCREATE UNI EMAIL FOLLOW UP | B66: 2026-09-02 | C66: Katya Rozhkova | D66: Plug and Play Marketing Communications | F66: 1346 | G66: 0.245 | H66: 0.025 | I66: =ROUND(F66*H66,0) -> 34 | J66: 11 | K66: =IF(F66=0,0,J66/F66) -> 0.0081723626 | L66: 6 | M66: =IF(F66+L66=0,0,L66/(F66+L66)) -> 0.0044378698 | N66: No
A67: FR_ALIBABA COCREATE VC EMAIL FOLLOW UP | B67: 2026-09-02 | C67: Philipp Hödl | D67: Plug and Play Marketing Communications | F67: 3448 | G67: 0.226 | H67: 0.01 | I67: =ROUND(F67*H67,0) -> 34 | J67: 58 | K67: =IF(F67=0,0,J67/F67) -> 0.016821346 | L67: 62 | M67: =IF(F67+L67=0,0,L67/(F67+L67)) -> 0.017663818 | N67: No
A68: UK August 2026 Newsletter | B68: 2026-09-02 | C68: Kieran Borrett | D68: Plug and Play Marketing Communications | E68: UK Newsletter | F68: 6534 | G68: 0.266 | H68: 0.012 | I68: =ROUND(F68*H68,0) -> 78 | J68: 71 | K68: =IF(F68=0,0,J68/F68) -> 0.010866238 | L68: 54 | M68: =IF(F68+L68=0,0,L68/(F68+L68)) -> 0.0081967213 | N68: No
A69: JAP_Newsletter_Sept - 2026 - 2 | B69: 2026-09-02 | C69: Plug and Play Japan | D69: Plug and Play Japan | E69: Japan Newsletter | F69: 982 | G69: 0.379 | H69: 0.065 | I69: =ROUND(F69*H69,0) -> 64 | J69: 0 | K69: =IF(F69=0,0,J69/F69) -> 0 | L69: 4 | M69: =IF(F69+L69=0,0,L69/(F69+L69)) -> 0.0040567951 | N69: No
A70: Seattle Community Newsletter (Aug 2026) | B70: 2026-09-01 | C70: Emmanuel Chan | D70: Plug and Play Marketing Communications | E70: Seattle Community Newsletter | F70: 1787 | G70: 0.276 | H70: 0.022 | I70: =ROUND(F70*H70,0) -> 39 | J70: 10 | K70: =IF(F70=0,0,J70/F70) -> 0.0055959709 | L70: 13 | M70: =IF(F70+L70=0,0,L70/(F70+L70)) -> 0.0072222222 | N70: No
A71: Finovate Fall Blast | B71: 2026-09-01 | C71: Jacky from Plug and Play | D71: Plug and Play Global Newsletter | F71: 618 | G71: 0.259 | H71: 0.042 | I71: =ROUND(F71*H71,0) -> 26 | J71: 9 | K71: =IF(F71=0,0,J71/F71) -> 0.014563107 | L71: 5 | M71: =IF(F71+L71=0,0,L71/(F71+L71)) -> 0.0080256822 | N71: No
A72: August_Internal_Newsletter | B72: 2026-08-31 | C72: Sanam Amidi | D72: Internal Plug and Play Communications | E72: Internal Newsletter | F72: 664 | G72: 0.721 | H72: 0.081 | I72: =ROUND(F72*H72,0) -> 54 | J72: 0 | K72: =IF(F72=0,0,J72/F72) -> 0 | L72: 3 | M72: =IF(F72+L72=0,0,L72/(F72+L72)) -> 0.0044977511 | N72: No
A73: Plug and Play's 2026 Corporate Partnership Survey - Final Email | B73: 2026-08-31 | C73: Jacky Tsang | D73: Plug and Play Marketing Communications | F73: 12799 | G73: 0.266 | H73: 0.007 | I73: =ROUND(F73*H73,0) -> 90 | J73: 203 | K73: =IF(F73=0,0,J73/F73) -> 0.015860614 | L73: 86 | M73: =IF(F73+L73=0,0,L73/(F73+L73)) -> 0.0066744276 | N73: No
A74: Plug and Play Türkiye August 2026 Newsletter | B74: 2026-08-31 | C74: Zeynep from Plug and Play | D74: Plug and Play Marketing Communications | E74: Türkiye Newsletter | F74: 1420 | G74: 0.268 | H74: 0.019 | I74: =ROUND(F74*H74,0) -> 27 | J74: 8 | K74: =IF(F74=0,0,J74/F74) -> 0.0056338028 | L74: 11 | M74: =IF(F74+L74=0,0,L74/(F74+L74)) -> 0.0076869322 | N74: No
A75: September Events (Clone) | B75: 2026-08-28 | C75: Rick Hernandez | D75: Plug and Play Events | F75: 126 | G75: 0.722 | H75: 0.063 | I75: =ROUND(F75*H75,0) -> 8 | J75: 1 | K75: =IF(F75=0,0,J75/F75) -> 0.0079365079 | L75: 1 | M75: =IF(F75+L75=0,0,L75/(F75+L75)) -> 0.0078740157 | N75: No
A76: PNPCA_ISAA grant announcement | B76: 2026-08-28 | C76: Alfredo from Plug and Play | D76: Plug and Play Marketing Communications | F76: 1254 | G76: 0.33 | H76: 0.017 | I76: =ROUND(F76*H76,0) -> 21 | J76: 16 | K76: =IF(F76=0,0,J76/F76) -> 0.012759171 | L76: 7 | M76: =IF(F76+L76=0,0,L76/(F76+L76)) -> 0.0055511499 | N76: No
A77: ME Innovation Day, Email 1 | B77: 2026-08-27 | C77: Ava Milana | D77: Plug and Play Events | F77: 2814 | G77: 0.284 | H77: 0.002 | I77: =ROUND(F77*H77,0) -> 6 | J77: 21 | K77: =IF(F77=0,0,J77/F77) -> 0.0074626866 | L77: 21 | M77: =IF(F77+L77=0,0,L77/(F77+L77)) -> 0.0074074074 | N77: No
A78: THF Launch_VIP (VC session) 2 invitation | B78: 2026-08-27 | C78: Christian Johansson | D78: Plug and Play Events | F78: 42 | G78: 0.405 | H78: 0.095 | I78: =ROUND(F78*H78,0) -> 4 | J78: 0 | K78: =IF(F78=0,0,J78/F78) -> 0 | L78: 0 | M78: =IF(F78+L78=0,0,L78/(F78+L78)) -> 0 | N78: No
A79: THF Launch_Soft launch attendees - 2nd invite | B79: 2026-08-27 | C79: Plug and Play Finland | D79: Plug and Play Events | F79: 101 | G79: 0.337 | H79: 0.139 | I79: =ROUND(F79*H79,0) -> 14 | J79: 1 | K79: =IF(F79=0,0,J79/F79) -> 0.0099009901 | L79: 0 | M79: =IF(F79+L79=0,0,L79/(F79+L79)) -> 0 | N79: No
A80: ICT Week 2026 invitations - Uzbekistan | B80: 2026-08-27 | C80: Alfredo Gómez | D80: Plug and Play Events | F80: 4273 | G80: 0.308 | H80: 0.03 | I80: =ROUND(F80*H80,0) -> 128 | J80: 72 | K80: =IF(F80=0,0,J80/F80) -> 0.016849988 | L80: 87 | M80: =IF(F80+L80=0,0,L80/(F80+L80)) -> 0.019954128 | N80: No
A81: ICT Week 2026 invitations - Uzbekistan | B81: 2026-08-27 | C81: Alfredo Gómez | D81: Plug and Play Events | F81: 4273 | G81: 0.308 | H81: 0.03 | I81: =ROUND(F81*H81,0) -> 128 | J81: 72 | K81: =IF(F81=0,0,J81/F81) -> 0.016849988 | L81: 87 | M81: =IF(F81+L81=0,0,L81/(F81+L81)) -> 0.019954128 | N81: Yes
A82: TEXAS August Newsletter | B82: 2026-08-26 | C82: Francis from Plug and Play | D82: Plug and Play Marketing Communications | E82: Texas Newsletter | F82: 4795 | G82: 0.269 | H82: 0.032 | I82: =ROUND(F82*H82,0) -> 153 | J82: 34 | K82: =IF(F82=0,0,J82/F82) -> 0.0070907195 | L82: 52 | M82: =IF(F82+L82=0,0,L82/(F82+L82)) -> 0.010728286 | N82: No
A83: AgAH Alumni/Mentor 2026 Q3 Newsletter | B83: 2026-08-26 | C83: Anne Gunden | D83: Plug and Play Marketing Communications | E83: AgTech & Animal Health Alumni/Mentor Newsletter | F83: 219 | G83: 0.443 | H83: 0.018 | I83: =ROUND(F83*H83,0) -> 4 | J83: 0 | K83: =IF(F83=0,0,J83/F83) -> 0 | L83: 2 | M83: =IF(F83+L83=0,0,L83/(F83+L83)) -> 0.0090497738 | N83: No
A84: MedTech Warsaw Expo B5 Save the Date - Expo Only - Last Call 1 week | B84: 2026-08-26 | C84: Plug and Play Warsaw - Medtech | D84: Plug and Play Marketing Communications | F84: 936 | G84: 0.339 | H84: 0.029 | I84: =ROUND(F84*H84,0) -> 27 | J84: 2 | K84: =IF(F84=0,0,J84/F84) -> 0.0021367521 | L84: 3 | M84: =IF(F84+L84=0,0,L84/(F84+L84)) -> 0.0031948882 | N84: No
A85: GNL_August 2026 | B85: 2026-08-25 | C85: Jacky from Plug and Play | D85: Plug and Play Global Newsletter | E85: Global Newsletter (GNL) | F85: 3241 | G85: 0.142 | H85: 0.019 | I85: =ROUND(F85*H85,0) -> 62 | J85: 25 | K85: =IF(F85=0,0,J85/F85) -> 0.0077136686 | L85: 21 | M85: =IF(F85+L85=0,0,L85/(F85+L85)) -> 0.0064377682 | N85: No
A86: Plug and Play's 2026 Corporate Partnership Survey - Third Batch | B86: 2026-08-25 | C86: Jacky Tsang | D86: Plug and Play Marketing Communications | F86: 13111 | G86: 0.324 | H86: 0.013 | I86: =ROUND(F86*H86,0) -> 170 | J86: 252 | K86: =IF(F86=0,0,J86/F86) -> 0.019220502 | L86: 826 | M86: =IF(F86+L86=0,0,L86/(F86+L86)) -> 0.0592667 | N86: No
A87: GNL_August 2026 | B87: 2026-08-25 | C87: Jacky from Plug and Play | D87: Plug and Play Global Newsletter | E87: Global Newsletter (GNL) | F87: 6975 | G87: 0.165 | H87: 0.019 | I87: =ROUND(F87*H87,0) -> 133 | J87: 38 | K87: =IF(F87=0,0,J87/F87) -> 0.0054480287 | L87: 23 | M87: =IF(F87+L87=0,0,L87/(F87+L87)) -> 0.0032866533 | N87: No
A88: Plug and Play's 2026 Corporate Partnership Survey - Email #4 | B88: 2026-08-24 | C88: Jacky Tsang | D88: Plug and Play Marketing Communications | F88: 3260 | G88: 0.316 | H88: 0.006 | I88: =ROUND(F88*H88,0) -> 20 | J88: 37 | K88: =IF(F88=0,0,J88/F88) -> 0.011349693 | L88: 27 | M88: =IF(F88+L88=0,0,L88/(F88+L88)) -> 0.0082141771 | N88: No
A89: Toastmasters | B89: 2026-08-20 | C89: Rick Hernandez | D89: Plug and Play Events | F89: 127 | G89: 0.512 | H89: 0.039 | I89: =ROUND(F89*H89,0) -> 5 | J89: 1 | K89: =IF(F89=0,0,J89/F89) -> 0.0078740157 | L89: 0 | M89: =IF(F89+L89=0,0,L89/(F89+L89)) -> 0 | N89: No
A90: Paris Motor Show 2026 | B90: 2026-08-20 | C90: Ava Milana | D90: Plug and Play Events | F90: 485 | G90: 0.26 | H90: 0.031 | I90: =ROUND(F90*H90,0) -> 15 | J90: 5 | K90: =IF(F90=0,0,J90/F90) -> 0.010309278 | L90: 5 | M90: =IF(F90+L90=0,0,L90/(F90+L90)) -> 0.010204082 | N90: No
A91: Cedar Park 1 Week Out Email Aug 2026 Expo 8.19.26 | B91: 2026-08-19 | C91: Kevin Farjallah | D91: Plug and Play Events | F91: 1138 | G91: 0.293 | H91: 0.03 | I91: =ROUND(F91*H91,0) -> 34 | J91: 12 | K91: =IF(F91=0,0,J91/F91) -> 0.010544815 | L91: 4 | M91: =IF(F91+L91=0,0,L91/(F91+L91)) -> 0.003502627 | N91: No
A92: MedTech Warsaw Expo B5 Save the Date - Expo Only (Speaker Announcement! 2 weeks | B92: 2026-08-19 | C92: Plug and Play Warsaw - Medtech | D92: Plug and Play Marketing Communications | F92: 957 | G92: 0.323 | H92: 0.041 | I92: =ROUND(F92*H92,0) -> 39 | J92: 1 | K92: =IF(F92=0,0,J92/F92) -> 0.0010449321 | L92: 6 | M92: =IF(F92+L92=0,0,L92/(F92+L92)) -> 0.0062305296 | N92: No
A93: APAC_Newsletter_August_2026 | B93: 2026-08-19 | C93: Plug and Play APAC | D93: Plug and Play APAC | E93: APAC Newsletter | F93: 2723 | G93: 0.312 | H93: 0.025 | I93: =ROUND(F93*H93,0) -> 68 | J93: 10 | K93: =IF(F93=0,0,J93/F93) -> 0.0036724201 | L93: 18 | M93: =IF(F93+L93=0,0,L93/(F93+L93)) -> 0.0065669464 | N93: No
A94: JAP_Newsletter - Aug - 2026 - 19 | B94: 2026-08-19 | C94: Plug and Play Japan | D94: Plug and Play Japan | E94: Japan Newsletter | F94: 978 | G94: 0.507 | H94: 0.204 | I94: =ROUND(F94*H94,0) -> 200 | J94: 0 | K94: =IF(F94=0,0,J94/F94) -> 0 | L94: 2 | M94: =IF(F94+L94=0,0,L94/(F94+L94)) -> 0.0020408163 | N94: No
A95: PNP Foundation Newsletter (July 2026) | B95: 2026-08-18 | C95: Dominique Reese | D95: Plug and Play Foundation | E95: Foundation Newsletter | F95: 805 | G95: 0.277 | H95: 0.007 | I95: =ROUND(F95*H95,0) -> 6 | J95: 8 | K95: =IF(F95=0,0,J95/F95) -> 0.0099378882 | L95: 33 | M95: =IF(F95+L95=0,0,L95/(F95+L95)) -> 0.039379475 | N95: No
A96: Plug and Play's 2026 Corporate Partnership Survey - Email #3 | B96: 2026-08-18 | C96: Jacky Tsang | D96: Plug and Play Marketing Communications | F96: 3313 | G96: 0.273 | H96: 0.009 | I96: =ROUND(F96*H96,0) -> 30 | J96: 37 | K96: =IF(F96=0,0,J96/F96) -> 0.011168126 | L96: 27 | M96: =IF(F96+L96=0,0,L96/(F96+L96)) -> 0.0080838323 | N96: No
A97: FR_ALIBABA COCREATE STARUP EMAIL FINAL | B97: 2026-08-17 | C97: Alba Brotons | D97: Plug and Play Marketing Communications | F97: 18358 | G97: 0.268 | H97: 0.043 | I97: =ROUND(F97*H97,0) -> 789 | J97: 417 | K97: =IF(F97=0,0,J97/F97) -> 0.022714893 | L97: 834 | M97: =IF(F97+L97=0,0,L97/(F97+L97)) -> 0.043455607 | N97: No
A98: Plug and Play Cedar Park Aug 26 Expo 8.11.26 (Clone) | B98: 2026-08-13 | C98: Kevin Farjallah | D98: Plug and Play Events | F98: 1168 | G98: 0.209 | H98: 0.015 | I98: =ROUND(F98*H98,0) -> 18 | J98: 17 | K98: =IF(F98=0,0,J98/F98) -> 0.014554795 | L98: 25 | M98: =IF(F98+L98=0,0,L98/(F98+L98)) -> 0.020955574 | N98: No
A99: THF Launch_VIP (VC session+lunch) invitation | B99: 2026-08-13 | C99: Christian Johansson | D99: Plug and Play Events | F99: 54 | G99: 0.481 | H99: 0.167 | I99: =ROUND(F99*H99,0) -> 9 | J99: 0 | K99: =IF(F99=0,0,J99/F99) -> 0 | L99: 1 | M99: =IF(F99+L99=0,0,L99/(F99+L99)) -> 0.018181818 | N99: No
A100: THF Launch_Soft launch attendees invitation 1 | B100: 2026-08-13 | C100: Plug and Play Finland | D100: Plug and Play Events | F100: 147 | G100: 0.605 | H100: 0.354 | I100: =ROUND(F100*H100,0) -> 52 | J100: 0 | K100: =IF(F100=0,0,J100/F100) -> 0 | L100: 2 | M100: =IF(F100+L100=0,0,L100/(F100+L100)) -> 0.013422819 | N100: No
A101: APAC_Cambodia Community Series 3_ThankYou | B101: 2026-08-13 | C101: Plug and Play APAC | D101: Plug and Play APAC | F101: 78 | G101: 0.462 | H101: 0.231 | I101: =ROUND(F101*H101,0) -> 18 | J101: 1 | K101: =IF(F101=0,0,J101/F101) -> 0.012820513 | L101: 0 | M101: =IF(F101+L101=0,0,L101/(F101+L101)) -> 0 | N101: No
...

Sheet Sources
A1: Sources and definitions
A3: Data pulled | B3: 8 Oct 2026, read-only, HubSpot portal 3340630. Nothing in HubSpot was changed.
A4: Analyze export | B4: Marketing › Email › Analyze, 1 Oct 2025 – 30 Sep 2026, compared with previous 365 days.
A5: Health tab | B5: Marketing › Email › Health. Last 30 days = 5 Sep – 5 Oct 2026. Benchmarks are HubSpot's.
A6: Emails | B6: Latest 100 email records sent (6 Aug – 30 Sep 2026) out of 1,042 sent 1 Oct 2025 – 30 Sep 2026. 3 duplicate records excluded. Workflow (automated) emails not included.
A7: Click rate | B7: Unique clicks ÷ delivered.
A8: Unsub rate | B8: Unsubscribes ÷ delivered.
A9: Bounce rate (per email) | B9: All bounces (hard + soft) ÷ (delivered + bounces). Account-level bounce figures are hard bounces only.
A10: Newsletter | B10: Recurring newsletters grouped by email name (e.g. 'UK August 2026 Newsletter' and 'UK September 2026 Newsletter' = UK Newsletter).
A11: Contacts | B11: Contact counts from HubSpot contact search; marketing contacts and tier from Settings › Account & Billing › Usage.
