Workbook

Sheet Dashboard
B1: ="Paid Media Spend "&Settings!$C$12&" – Year Overview" -> Paid Media Spend 2026 – Year Overview | P1: Helper cells for formatting – don't edit
B2: ="Platform data up to "&TEXT(Settings!$C$5,"d mmm yyyy")&" · amounts in "&Settings!$C$6&" · Google converted from EUR at "&TEXT(Settings!$B$41,"0.0000")&" · Meta, Google Ads and ChatGPT Ads" -> Platform data up to 30 Sep 2026 · amounts in USD · Google converted from EUR at 1.1177 · Meta, Google Ads and ChatGPT Ads | P2: =Calc!C9 -> 0.74794521
B3: ="Budget: "&Settings!$C$9 -> Budget: Confirmed by Tereza on 13 Oct 2026: $300k for 2026 (originally $350k). We can go up to $320k, ideally not more. | P3: =Calc!C42-Calc!C27 -> 3058.3922
B5: ="BUDGET "&Settings!$C$12 -> BUDGET 2026 | D5: ="SPENT SO FAR" -> SPENT SO FAR | F5: ="LEFT IN THE BUDGET" -> LEFT IN THE BUDGET | H5: ="LEFT UP TO THE MAXIMUM" -> LEFT UP TO THE MAXIMUM | J5: ="CURRENT PACE PER WEEK" -> CURRENT PACE PER WEEK | L5: ="FORECAST YEAR-END" -> FORECAST YEAR-END
B6: =IF(Settings!$C$6="USD","$","€")&TEXT(Calc!C27,"#,##0") -> $300,000 | D6: =IF(Settings!$C$6="USD","$","€")&TEXT(Calc!C30,"#,##0") -> $278,601 | F6: =IF(Calc!C31<0,"–"&IF(Settings!$C$6="USD","$","€")&TEXT(-Calc!C31,"#,##0"),IF(Settings!$C$6="USD","$","€")&TEXT(Calc!C31,"#,##0")) -> $21,399 | H6: =IF(Calc!C32<0,"–"&IF(Settings!$C$6="USD","$","€")&TEXT(-Calc!C32,"#,##0"),IF(Settings!$C$6="USD","$","€")&TEXT(Calc!C32,"#,##0")) -> $41,399 | J6: =IF(Settings!$C$6="USD","$","€")&TEXT(Calc!C39,"#,##0") -> $1,861 | L6: =IF(Settings!$C$6="USD","$","€")&TEXT(Calc!C42,"#,##0") -> $303,058
B7: ="Maximum "&IF(Settings!$C$6="USD","$","€")&TEXT(Calc!C28,"#,##0")&" · originally "&IF(Settings!$C$6="USD","$","€")&TEXT(Calc!C29,"#,##0") -> Maximum $320,000 · originally $350,000 | D7: =TEXT(Calc!C33,"0%")&" of budget · "&TEXT(Calc!C9,"0%")&" of the year gone" -> 93% of budget · 75% of the year gone | F7: =IF(Calc!C31<0,"Budget already used up","≈ "&IF(Settings!$C$6="USD","$","€")&TEXT(Calc!C43,"#,##0")&" a week until "&TEXT(Calc!C5,"d mmm")) -> ≈ $1,628 a week until 31 Dec | H7: =IF(Calc!C32<0,"Maximum already passed","≈ "&IF(Settings!$C$6="USD","$","€")&TEXT(Calc!C44,"#,##0")&" a week until "&TEXT(Calc!C5,"d mmm")) -> ≈ $3,150 a week until 31 Dec | J7: =IF(Calc!C37>0,"Platforms, last 3 full weeks","Agency reports, last 3 weeks (after the cuts)") -> Agency reports, last 3 weeks (after the cuts) | L7: =IF(Calc!C42>Calc!C27,"▲ "&IF(Settings!$C$6="USD","$","€")&TEXT(Calc!C42-Calc!C27,"#,##0")&" over budget","▼ "&IF(Settings!$C$6="USD","$","€")&TEXT(Calc!C27-Calc!C42,"#,##0")&" under budget")&" · "&IF(Calc!C42>Calc!C28,"over","within")&" the maximum" -> ▲ $3,058 over budget · within the maximum
B9: BUDGET CHECK
B10: Measure | D10: Amount | E10: Spent so far | F10: Left | G10: % used | H10: ="Progress (year gone: "&TEXT(Calc!C9,"0%")&")" -> Progress (year gone: 75%) | K10: Status at the current pace
B11: Budget | D11: =Calc!C27 -> 300000 | E11: =Calc!C30 -> 278601.38 | F11: =Calc!C31 -> 21398.616 | G11: =Calc!C33 -> 0.92867128 | H11: =REPT("█",ROUND(MIN(G11,1)*26,0))&REPT("░",26-ROUND(MIN(G11,1)*26,0)) -> ████████████████████████░░ | K11: =IF(Calc!C30>=Calc!C27,"▲ Budget used up",IF(Calc!C42>Calc!C27,"▲ Ends ≈ "&IF(Settings!$C$6="USD","$","€")&TEXT(Calc!C42-Calc!C27,"#,##0")&" over budget","● Ends within budget")) -> ▲ Ends ≈ $3,058 over budget
B12: Maximum (ideally not more) | D12: =Calc!C28 -> 320000 | E12: =Calc!C30 -> 278601.38 | F12: =Calc!C32 -> 41398.616 | G12: =Calc!C34 -> 0.87062933 | H12: =REPT("█",ROUND(MIN(G12,1)*26,0))&REPT("░",26-ROUND(MIN(G12,1)*26,0)) -> ███████████████████████░░░ | K12: =IF(Calc!C30>=Calc!C28,"▲ Maximum passed",IF(Calc!C42>Calc!C28,"▲ Ends ≈ "&IF(Settings!$C$6="USD","$","€")&TEXT(Calc!C42-Calc!C28,"#,##0")&" over the maximum","● Ends ≈ "&IF(Settings!$C$6="USD","$","€")&TEXT(Calc!C28-Calc!C42,"#,##0")&" under the maximum")) -> ● Ends ≈ $16,942 under the maximum
B13: ="By "&TEXT(Calc!C3,"d mmm")&", "&IF(Settings!$C$6="USD","$","€")&TEXT(Calc!C30,"#,##0")&" was spent: "&IF(Settings!$C$6="USD","$","€")&TEXT(ABS(Calc!C36),"#,##0")&IF(Calc!C36>=0," more"," less")&" than an even pace through the year ("&IF(Settings!$C$6="USD","$","€")&TEXT(Calc!C35,"#,##0")&"). Current pace from "&Calc!C40&"." -> By 30 Sep, $278,601 was spent: $54,218 more than an even pace through the year ($224,384). Current pace from the agency reports for W/C 21 Sep – 5 Oct (after the September cuts).
B15: SPEND BY CHANNEL
B16: Channel | D16: ="Spent ("&Settings!$C$6&")" -> Spent (USD) | E16: Share | F16: Last full month | G16: Last 3 full months | H16: Last full week | I16: Counts toward budget? | J16: Billing currency | K16: Note
B17: Meta | D17: =Calc!D20 -> 178067.03 | E17: =Calc!I20 -> 0.63914625 | F17: =Calc!E20 -> 11062.98 | G17: =Calc!F20 -> 40663.58 | H17: =IF(Calc!G20=0,"–",Calc!G20) -> – | I17: =Settings!C22 -> Yes | J17: =Settings!B22 -> USD | K17: =IF(Settings!E22="","",Settings!E22) -> Includes FR_Alibaba (run by PnP's internal team) – confirm it belongs in this budget.
B18: Google Ads | D18: =Calc!D21 -> 100277.78 | E18: =Calc!I21 -> 0.3599328 | F18: =Calc!E21 -> 6854.2282 | G18: =Calc!F21 -> 32249.009 | H18: =IF(Calc!G21=0,"–",Calc!G21) -> – | I18: =Settings!C23 -> Yes | J18: =Settings!B23 -> EUR | K18: =IF(Settings!E23="","",Settings!E23)
B19: ChatGPT Ads | D19: =Calc!D22 -> 256.57921 | E19: =Calc!I22 -> 0.00092095455 | F19: =Calc!E22 -> 256.57921 | G19: =Calc!F22 -> 256.57921 | H19: =IF(Calc!G22=0,"–",Calc!G22) -> – | I19: =Settings!C24 -> Yes | J19: =Settings!B24 -> EUR | K19: =IF(Settings!E24="","",Settings!E24) -> To confirm with Tereza.
B20: LinkedIn Ads | D20: =Calc!D23 -> 0 | E20: =Calc!I23 -> 0 | F20: =Calc!E23 -> 0 | G20: =Calc!F23 -> 0 | H20: =IF(Calc!G23=0,"–",Calc!G23) -> – | I20: =Settings!C25 -> Yes | J20: =Settings!B25 -> USD | K20: =IF(Settings!E25="","",Settings!E25) -> No spend in 2026. Billing currency to check.
B21: Total – all channels | D21: =Calc!D25 -> 278601.38 | E21: =IF(Calc!D25=0,"",1) -> 1 | F21: =Calc!E25 -> 18173.787 | G21: =Calc!F25 -> 73169.168 | H21: =IF(Calc!G25=0,"–",Calc!G25) -> –
B22: 'Last full week' needs daily platform rows: it shows – until the daily exports are pasted.
B24: SPEND BY MONTH AND CHANNEL vs. PLAN | H24: SPEND SO FAR vs. PLAN AND MAXIMUM (CUMULATIVE)
B42: QUARTER BY QUARTER
B43: Quarter | D43: Meta | E43: Google Ads | F43: ChatGPT Ads | G43: LinkedIn Ads | H43: Total – all channels | I43: Counts toward budget | J43: Plan | K43: Status
B44: ="Q1 ("&TEXT(Monthly!A5,"mmm")&"–"&TEXT(Monthly!A7,"mmm")&")" -> Q1 (Jan–Mar) | D44: =SUM(Monthly!C5:C7) -> 75432.1 | E44: =SUM(Monthly!D5:D7) -> 32036.49 | F44: =SUM(Monthly!E5:E7) -> 0 | G44: =SUM(Monthly!F5:F7) -> 0 | H44: =SUM(D44:G44) -> 107468.59 | I44: =SUM(Monthly!H5:H7) -> 107468.59 | J44: =SUM(Monthly!I5:I7) -> 73972.603 | K44: =IF(Settings!$C$5>=EOMONTH(Monthly!A7,0),IF(Settings!$C$5<EOMONTH(Monthly!A10,0),"Complete · last quarter","Complete"),IF(Settings!$C$5>=Monthly!A5,"In progress","Not started")) -> Complete
B45: ="Q2 ("&TEXT(Monthly!A8,"mmm")&"–"&TEXT(Monthly!A10,"mmm")&")" -> Q2 (Apr–Jun) | D45: =SUM(Monthly!C8:C10) -> 61971.35 | E45: =SUM(Monthly!D8:D10) -> 35992.276 | F45: =SUM(Monthly!E8:E10) -> 0 | G45: =SUM(Monthly!F8:F10) -> 0 | H45: =SUM(D45:G45) -> 97963.626 | I45: =SUM(Monthly!H8:H10) -> 97963.626 | J45: =SUM(Monthly!I8:I10) -> 74794.521 | K45: =IF(Settings!$C$5>=EOMONTH(Monthly!A10,0),IF(Settings!$C$5<EOMONTH(Monthly!A13,0),"Complete · last quarter","Complete"),IF(Settings!$C$5>=Monthly!A8,"In progress","Not started")) -> Complete
B46: ="Q3 ("&TEXT(Monthly!A11,"mmm")&"–"&TEXT(Monthly!A13,"mmm")&")" -> Q3 (Jul–Sep) | D46: =SUM(Monthly!C11:C13) -> 40663.58 | E46: =SUM(Monthly!D11:D13) -> 32249.009 | F46: =SUM(Monthly!E11:E13) -> 256.57921 | G46: =SUM(Monthly!F11:F13) -> 0 | H46: =SUM(D46:G46) -> 73169.168 | I46: =SUM(Monthly!H11:H13) -> 73169.168 | J46: =SUM(Monthly!I11:I13) -> 75616.438 | K46: =IF(Settings!$C$5>=EOMONTH(Monthly!A13,0),IF(Settings!$C$5<EOMONTH(Monthly!A16,0),"Complete · last quarter","Complete"),IF(Settings!$C$5>=Monthly!A11,"In progress","Not started")) -> Complete · last quarter
B47: ="Q4 ("&TEXT(Monthly!A14,"mmm")&"–"&TEXT(Monthly!A16,"mmm")&")" -> Q4 (Oct–Dec) | D47: =SUM(Monthly!C14:C16) -> 0 | E47: =SUM(Monthly!D14:D16) -> 0 | F47: =SUM(Monthly!E14:E16) -> 0 | G47: =SUM(Monthly!F14:F16) -> 0 | H47: =SUM(D47:G47) -> 0 | I47: =SUM(Monthly!H14:H16) -> 0 | J47: =SUM(Monthly!I14:I16) -> 75616.438 | K47: =IF(Settings!$C$5>=EOMONTH(Monthly!A16,0),"Complete",IF(Settings!$C$5>=Monthly!A14,"In progress","Not started")) -> Not started
B48: Total | D48: =SUM(D44:D47) -> 178067.03 | E48: =SUM(E44:E47) -> 100277.78 | F48: =SUM(F44:F47) -> 256.57921 | G48: =SUM(G44:G47) -> 0 | H48: =SUM(H44:H47) -> 278601.38 | I48: =SUM(I44:I47) -> 278601.38 | J48: =SUM(J44:J47) -> 300000
B50: YEAR-END OUTLOOK (budget channels)
B51: If we spend from now on at… | F51: ="Per week ("&Settings!$C$6&")" -> Per week (USD) | G51: Year-end total | H51: vs. budget | I51: vs. maximum | J51: What it means
B52: ="…the current pace" -> …the current pace | F52: =Calc!C39 -> 1860.8593 | G52: =Calc!C42 -> 303058.39 | H52: =G52-Calc!$C$27 -> 3058.3922 | I52: =G52-Calc!$C$28 -> -16941.608 | J52: ="Source: "&Calc!C40 -> Source: the agency reports for W/C 21 Sep – 5 Oct (after the September cuts)
B53: ="…a pace that lands exactly on the budget" -> …a pace that lands exactly on the budget | F53: =MAX(0,Calc!C43) -> 1628.1555 | G53: =Calc!C27 -> 300000 | H53: =G53-Calc!$C$27 -> 0 | I53: =G53-Calc!$C$28 -> -20000 | J53: =IF(Calc!C31<=0,"The budget is already used up",IF(Calc!C39=0,"",IF(Calc!C43<Calc!C39,TEXT(1-Calc!C43/Calc!C39,"0%")&" less per week than the current pace",TEXT(Calc!C43/Calc!C39-1,"0%")&" more per week than the current pace"))) -> 13% less per week than the current pace
B54: ="…a pace that uses the maximum" -> …a pace that uses the maximum | F54: =MAX(0,Calc!C44) -> 3149.8947 | G54: =Calc!C28 -> 320000 | H54: =G54-Calc!$C$27 -> 20000 | I54: =G54-Calc!$C$28 -> 0 | J54: =IF(Calc!C32<=0,"The maximum is already passed",IF(Calc!C39=0,"",IF(Calc!C44<Calc!C39,TEXT(1-Calc!C44/Calc!C39,"0%")&" less per week than the current pace",TEXT(Calc!C44/Calc!C39-1,"0%")&" more per week than the current pace"))) -> 69% more per week than the current pace
B55: ="…last month's pace ("&TEXT(Calc!C11,"mmmm")&", before the cuts)" -> …last month's pace (September, before the cuts) | F55: =Calc!C45/Calc!C17*7 -> 4240.5504 | G55: =Calc!C47 -> 334334.33 | H55: =G55-Calc!$C$27 -> 34334.332 | I55: =G55-Calc!$C$28 -> 14334.332 | J55: ="For reference" -> For reference
B57: WHERE THE MONEY WENT – BY REGION | H57: TOP MARKETS (year to date)
B73: Region and market come from the location code in each campaign name – see the 'By location & type' and 'Campaigns' tabs. Sources, exchange rate and how to update: 'How to update' tab.

Sheet Weekly
A1: Weekly spend
A2: ="Weeks run Monday to Sunday · amounts in "&Settings!$C$6&" · from the daily platform exports. Yellow columns are typed by you." -> Weeks run Monday to Sunday · amounts in USD · from the daily platform exports. Yellow columns are typed by you.
A3: Data up to: | C3: =Settings!$C$5 -> 46295 | D3: Last full week ends: | F3: =Calc!C13 -> 46292 | H3: Spend before October fills in once the daily platform exports are pasted. Until then, the agency's weekly figures are on the 'Agency reports' tab and their notes are in column R.
A4: Week | B4: Starts (Mon) | C4: Ends (Sun) | D4: Meta | E4: Google Ads | F4: ChatGPT Ads | G4: LinkedIn Ads | H4: Total – all channels | I4: Counts toward budget | J4: Plan (budget spread evenly by day) | K4: Over (+) / under (−) plan | L4: Meta conversions | M4: Meta cost per conversion | N4: Google conversions | O4: Google cost per conversion | P4: MQLs – paid social (HubSpot, optional) | Q4: MQLs – paid search (HubSpot, optional) | R4: Notes – what happened this week | S4: Chart label
A5: 1 | B5: =Settings!$C$13+7*(A5-1) -> 46020 | C5: =B5+6 -> 46026 | D5: =SUMIFS('Meta data'!$I$3:$I$20000,'Meta data'!$A$3:$A$20000,">="&$B5,'Meta data'!$A$3:$A$20000,"<="&$C5,'Meta data'!$G$3:$G$20000,"<>Month total") -> 0 | E5: =SUMIFS('Google data'!$I$3:$I$20000,'Google data'!$A$3:$A$20000,">="&$B5,'Google data'!$A$3:$A$20000,"<="&$C5,'Google data'!$G$3:$G$20000,"<>Month total") -> 0 | F5: =SUMIFS('ChatGPT data'!$I$3:$I$20000,'ChatGPT data'!$A$3:$A$20000,">="&$B5,'ChatGPT data'!$A$3:$A$20000,"<="&$C5,'ChatGPT data'!$G$3:$G$20000,"<>Month total") -> 0 | G5: =SUMIFS('LinkedIn data'!$I$3:$I$20000,'LinkedIn data'!$A$3:$A$20000,">="&$B5,'LinkedIn data'!$A$3:$A$20000,"<="&$C5,'LinkedIn data'!$G$3:$G$20000,"<>Month total") -> 0 | H5: =SUM(D5:G5) -> 0 | I5: =D5*(Settings!$C$22="Yes")+E5*(Settings!$C$23="Yes")+F5*(Settings!$C$24="Yes")+G5*(Settings!$C$25="Yes") -> 0 | J5: =Settings!$D$16*MAX(0,MIN(C5,Settings!$C$11)-MAX(B5,Settings!$C$10)+1)/(Settings!$C$11-Settings!$C$10+1) -> 3287.6712 | K5: =IF(OR(C5>$C$3,I5=0),"",I5-J5) | L5: =SUMIFS('Meta data'!$F$3:$F$20000,'Meta data'!$A$3:$A$20000,">="&$B5,'Meta data'!$A$3:$A$20000,"<="&$C5,'Meta data'!$G$3:$G$20000,"<>Month total") -> 0 | M5: =IF(L5=0,"",D5/L5) | N5: =SUMIFS('Google data'!$F$3:$F$20000,'Google data'!$A$3:$A$20000,">="&$B5,'Google data'!$A$3:$A$20000,"<="&$C5,'Google data'!$G$3:$G$20000,"<>Month total") -> 0 | O5: =IF(N5=0,"",E5/N5) | R5: Agency: Paused the Health ad set on Meta EMEA. Next: prepare the location strategy, launch a Meta retargeting campaign for job-application (JTP) conversions, build a PMax asset group from the Quantum ad. | S5: =TEXT(B5,"d mmm") -> 29 Dec
A6: 2 | B6: =Settings!$C$13+7*(A6-1) -> 46027 | C6: =B6+6 -> 46033 | D6: =SUMIFS('Meta data'!$I$3:$I$20000,'Meta data'!$A$3:$A$20000,">="&$B6,'Meta data'!$A$3:$A$20000,"<="&$C6,'Meta data'!$G$3:$G$20000,"<>Month total") -> 0 | E6: =SUMIFS('Google data'!$I$3:$I$20000,'Google data'!$A$3:$A$20000,">="&$B6,'Google data'!$A$3:$A$20000,"<="&$C6,'Google data'!$G$3:$G$20000,"<>Month total") -> 0 | F6: =SUMIFS('ChatGPT data'!$I$3:$I$20000,'ChatGPT data'!$A$3:$A$20000,">="&$B6,'ChatGPT data'!$A$3:$A$20000,"<="&$C6,'ChatGPT data'!$G$3:$G$20000,"<>Month total") -> 0 | G6: =SUMIFS('LinkedIn data'!$I$3:$I$20000,'LinkedIn data'!$A$3:$A$20000,">="&$B6,'LinkedIn data'!$A$3:$A$20000,"<="&$C6,'LinkedIn data'!$G$3:$G$20000,"<>Month total") -> 0 | H6: =SUM(D6:G6) -> 0 | I6: =D6*(Settings!$C$22="Yes")+E6*(Settings!$C$23="Yes")+F6*(Settings!$C$24="Yes")+G6*(Settings!$C$25="Yes") -> 0 | J6: =Settings!$D$16*MAX(0,MIN(C6,Settings!$C$11)-MAX(B6,Settings!$C$10)+1)/(Settings!$C$11-Settings!$C$10+1) -> 5753.4247 | K6: =IF(OR(C6>$C$3,I6=0),"",I6-J6) | L6: =SUMIFS('Meta data'!$F$3:$F$20000,'Meta data'!$A$3:$A$20000,">="&$B6,'Meta data'!$A$3:$A$20000,"<="&$C6,'Meta data'!$G$3:$G$20000,"<>Month total") -> 0 | M6: =IF(L6=0,"",D6/L6) | N6: =SUMIFS('Google data'!$F$3:$F$20000,'Google data'!$A$3:$A$20000,">="&$B6,'Google data'!$A$3:$A$20000,"<="&$C6,'Google data'!$G$3:$G$20000,"<>Month total") -> 0 | O6: =IF(N6=0,"",E6/N6) | R6: Agency: Added Meta JTP retargeting campaigns, which pushed CPL up. Google EMEA non-brand dropped while PMax and Brand rose. Plan: agree and start the new geo structure. | S6: =TEXT(B6,"d mmm") -> 5 Jan
A7: 3 | B7: =Settings!$C$13+7*(A7-1) -> 46034 | C7: =B7+6 -> 46040 | D7: =SUMIFS('Meta data'!$I$3:$I$20000,'Meta data'!$A$3:$A$20000,">="&$B7,'Meta data'!$A$3:$A$20000,"<="&$C7,'Meta data'!$G$3:$G$20000,"<>Month total") -> 0 | E7: =SUMIFS('Google data'!$I$3:$I$20000,'Google data'!$A$3:$A$20000,">="&$B7,'Google data'!$A$3:$A$20000,"<="&$C7,'Google data'!$G$3:$G$20000,"<>Month total") -> 0 | F7: =SUMIFS('ChatGPT data'!$I$3:$I$20000,'ChatGPT data'!$A$3:$A$20000,">="&$B7,'ChatGPT data'!$A$3:$A$20000,"<="&$C7,'ChatGPT data'!$G$3:$G$20000,"<>Month total") -> 0 | G7: =SUMIFS('LinkedIn data'!$I$3:$I$20000,'LinkedIn data'!$A$3:$A$20000,">="&$B7,'LinkedIn data'!$A$3:$A$20000,"<="&$C7,'LinkedIn data'!$G$3:$G$20000,"<>Month total") -> 0 | H7: =SUM(D7:G7) -> 0 | I7: =D7*(Settings!$C$22="Yes")+E7*(Settings!$C$23="Yes")+F7*(Settings!$C$24="Yes")+G7*(Settings!$C$25="Yes") -> 0 | J7: =Settings!$D$16*MAX(0,MIN(C7,Settings!$C$11)-MAX(B7,Settings!$C$10)+1)/(Settings!$C$11-Settings!$C$10+1) -> 5753.4247 | K7: =IF(OR(C7>$C$3,I7=0),"",I7-J7) | L7: =SUMIFS('Meta data'!$F$3:$F$20000,'Meta data'!$A$3:$A$20000,">="&$B7,'Meta data'!$A$3:$A$20000,"<="&$C7,'Meta data'!$G$3:$G$20000,"<>Month total") -> 0 | M7: =IF(L7=0,"",D7/L7) | N7: =SUMIFS('Google data'!$F$3:$F$20000,'Google data'!$A$3:$A$20000,">="&$B7,'Google data'!$A$3:$A$20000,"<="&$C7,'Google data'!$G$3:$G$20000,"<>Month total") -> 0 | O7: =IF(N7=0,"",E7/N7) | R7: Agency: New Google structure live; EMEA location campaigns had no leads yet. Meta being restructured for the geo strategy. Paused the Health push in USCA. | S7: =TEXT(B7,"d mmm") -> 12 Jan
A8: 4 | B8: =Settings!$C$13+7*(A8-1) -> 46041 | C8: =B8+6 -> 46047 | D8: =SUMIFS('Meta data'!$I$3:$I$20000,'Meta data'!$A$3:$A$20000,">="&$B8,'Meta data'!$A$3:$A$20000,"<="&$C8,'Meta data'!$G$3:$G$20000,"<>Month total") -> 0 | E8: =SUMIFS('Google data'!$I$3:$I$20000,'Google data'!$A$3:$A$20000,">="&$B8,'Google data'!$A$3:$A$20000,"<="&$C8,'Google data'!$G$3:$G$20000,"<>Month total") -> 0 | F8: =SUMIFS('ChatGPT data'!$I$3:$I$20000,'ChatGPT data'!$A$3:$A$20000,">="&$B8,'ChatGPT data'!$A$3:$A$20000,"<="&$C8,'ChatGPT data'!$G$3:$G$20000,"<>Month total") -> 0 | G8: =SUMIFS('LinkedIn data'!$I$3:$I$20000,'LinkedIn data'!$A$3:$A$20000,">="&$B8,'LinkedIn data'!$A$3:$A$20000,"<="&$C8,'LinkedIn data'!$G$3:$G$20000,"<>Month total") -> 0 | H8: =SUM(D8:G8) -> 0 | I8: =D8*(Settings!$C$22="Yes")+E8*(Settings!$C$23="Yes")+F8*(Settings!$C$24="Yes")+G8*(Settings!$C$25="Yes") -> 0 | J8: =Settings!$D$16*MAX(0,MIN(C8,Settings!$C$11)-MAX(B8,Settings!$C$10)+1)/(Settings!$C$11-Settings!$C$10+1) -> 5753.4247 | K8: =IF(OR(C8>$C$3,I8=0),"",I8-J8) | L8: =SUMIFS('Meta data'!$F$3:$F$20000,'Meta data'!$A$3:$A$20000,">="&$B8,'Meta data'!$A$3:$A$20000,"<="&$C8,'Meta data'!$G$3:$G$20000,"<>Month total") -> 0 | M8: =IF(L8=0,"",D8/L8) | N8: =SUMIFS('Google data'!$F$3:$F$20000,'Google data'!$A$3:$A$20000,">="&$B8,'Google data'!$A$3:$A$20000,"<="&$C8,'Google data'!$G$3:$G$20000,"<>Month total") -> 0 | O8: =IF(N8=0,"",E8/N8) | R8: Agency: Spend down 15% WoW due to the new structure. Splitting California out of USCA hurt Meta. Google pushed new locations: more spend, no extra leads. | S8: =TEXT(B8,"d mmm") -> 19 Jan
A9: 5 | B9: =Settings!$C$13+7*(A9-1) -> 46048 | C9: =B9+6 -> 46054 | D9: =SUMIFS('Meta data'!$I$3:$I$20000,'Meta data'!$A$3:$A$20000,">="&$B9,'Meta data'!$A$3:$A$20000,"<="&$C9,'Meta data'!$G$3:$G$20000,"<>Month total") -> 0 | E9: =SUMIFS('Google data'!$I$3:$I$20000,'Google data'!$A$3:$A$20000,">="&$B9,'Google data'!$A$3:$A$20000,"<="&$C9,'Google data'!$G$3:$G$20000,"<>Month total") -> 0 | F9: =SUMIFS('ChatGPT data'!$I$3:$I$20000,'ChatGPT data'!$A$3:$A$20000,">="&$B9,'ChatGPT data'!$A$3:$A$20000,"<="&$C9,'ChatGPT data'!$G$3:$G$20000,"<>Month total") -> 0 | G9: =SUMIFS('LinkedIn data'!$I$3:$I$20000,'LinkedIn data'!$A$3:$A$20000,">="&$B9,'LinkedIn data'!$A$3:$A$20000,"<="&$C9,'LinkedIn data'!$G$3:$G$20000,"<>Month total") -> 0 | H9: =SUM(D9:G9) -> 0 | I9: =D9*(Settings!$C$22="Yes")+E9*(Settings!$C$23="Yes")+F9*(Settings!$C$24="Yes")+G9*(Settings!$C$25="Yes") -> 0 | J9: =Settings!$D$16*MAX(0,MIN(C9,Settings!$C$11)-MAX(B9,Settings!$C$10)+1)/(Settings!$C$11-Settings!$C$10+1) -> 5753.4247 | K9: =IF(OR(C9>$C$3,I9=0),"",I9-J9) | L9: =SUMIFS('Meta data'!$F$3:$F$20000,'Meta data'!$A$3:$A$20000,">="&$B9,'Meta data'!$A$3:$A$20000,"<="&$C9,'Meta data'!$G$3:$G$20000,"<>Month total") -> 0 | M9: =IF(L9=0,"",D9/L9) | N9: =SUMIFS('Google data'!$F$3:$F$20000,'Google data'!$A$3:$A$20000,">="&$B9,'Google data'!$A$3:$A$20000,"<="&$C9,'Google data'!$G$3:$G$20000,"<>Month total") -> 0 | O9: =IF(N9=0,"",E9/N9) | R9: Agency: Google CPL rose as spend moved from PMax to Search. NY, NJ, AZ, IN and Washington had no leads. Quantum was the top Meta ad. | S9: =TEXT(B9,"d mmm") -> 26 Jan
A10: 6 | B10: =Settings!$C$13+7*(A10-1) -> 46055 | C10: =B10+6 -> 46061 | D10: =SUMIFS('Meta data'!$I$3:$I$20000,'Meta data'!$A$3:$A$20000,">="&$B10,'Meta data'!$A$3:$A$20000,"<="&$C10,'Meta data'!$G$3:$G$20000,"<>Month total") -> 0 | E10: =SUMIFS('Google data'!$I$3:$I$20000,'Google data'!$A$3:$A$20000,">="&$B10,'Google data'!$A$3:$A$20000,"<="&$C10,'Google data'!$G$3:$G$20000,"<>Month total") -> 0 | F10: =SUMIFS('ChatGPT data'!$I$3:$I$20000,'ChatGPT data'!$A$3:$A$20000,">="&$B10,'ChatGPT data'!$A$3:$A$20000,"<="&$C10,'ChatGPT data'!$G$3:$G$20000,"<>Month total") -> 0 | G10: =SUMIFS('LinkedIn data'!$I$3:$I$20000,'LinkedIn data'!$A$3:$A$20000,">="&$B10,'LinkedIn data'!$A$3:$A$20000,"<="&$C10,'LinkedIn data'!$G$3:$G$20000,"<>Month total") -> 0 | H10: =SUM(D10:G10) -> 0 | I10: =D10*(Settings!$C$22="Yes")+E10*(Settings!$C$23="Yes")+F10*(Settings!$C$24="Yes")+G10*(Settings!$C$25="Yes") -> 0 | J10: =Settings!$D$16*MAX(0,MIN(C10,Settings!$C$11)-MAX(B10,Settings!$C$10)+1)/(Settings!$C$11-Settings!$C$10+1) -> 5753.4247 | K10: =IF(OR(C10>$C$3,I10=0),"",I10-J10) | L10: =SUMIFS('Meta data'!$F$3:$F$20000,'Meta data'!$A$3:$A$20000,">="&$B10,'Meta data'!$A$3:$A$20000,"<="&$C10,'Meta data'!$G$3:$G$20000,"<>Month total") -> 0 | M10: =IF(L10=0,"",D10/L10) | N10: =SUMIFS('Google data'!$F$3:$F$20000,'Google data'!$A$3:$A$20000,">="&$B10,'Google data'!$A$3:$A$20000,"<="&$C10,'Google data'!$G$3:$G$20000,"<>Month total") -> 0 | O10: =IF(N10=0,"",E10/N10) | R10: Agency: Google clicks up 188% but CR fell; US campaigns underperformed. Meta Spanish Grid ads lowered CPL. Plan: increase spend in all regions. | S10: =TEXT(B10,"d mmm") -> 2 Feb
A11: 7 | B11: =Settings!$C$13+7*(A11-1) -> 46062 | C11: =B11+6 -> 46068 | D11: =SUMIFS('Meta data'!$I$3:$I$20000,'Meta data'!$A$3:$A$20000,">="&$B11,'Meta data'!$A$3:$A$20000,"<="&$C11,'Meta data'!$G$3:$G$20000,"<>Month total") -> 0 | E11: =SUMIFS('Google data'!$I$3:$I$20000,'Google data'!$A$3:$A$20000,">="&$B11,'Google data'!$A$3:$A$20000,"<="&$C11,'Google data'!$G$3:$G$20000,"<>Month total") -> 0 | F11: =SUMIFS('ChatGPT data'!$I$3:$I$20000,'ChatGPT data'!$A$3:$A$20000,">="&$B11,'ChatGPT data'!$A$3:$A$20000,"<="&$C11,'ChatGPT data'!$G$3:$G$20000,"<>Month total") -> 0 | G11: =SUMIFS('LinkedIn data'!$I$3:$I$20000,'LinkedIn data'!$A$3:$A$20000,">="&$B11,'LinkedIn data'!$A$3:$A$20000,"<="&$C11,'LinkedIn data'!$G$3:$G$20000,"<>Month total") -> 0 | H11: =SUM(D11:G11) -> 0 | I11: =D11*(Settings!$C$22="Yes")+E11*(Settings!$C$23="Yes")+F11*(Settings!$C$24="Yes")+G11*(Settings!$C$25="Yes") -> 0 | J11: =Settings!$D$16*MAX(0,MIN(C11,Settings!$C$11)-MAX(B11,Settings!$C$10)+1)/(Settings!$C$11-Settings!$C$10+1) -> 5753.4247 | K11: =IF(OR(C11>$C$3,I11=0),"",I11-J11) | L11: =SUMIFS('Meta data'!$F$3:$F$20000,'Meta data'!$A$3:$A$20000,">="&$B11,'Meta data'!$A$3:$A$20000,"<="&$C11,'Meta data'!$G$3:$G$20000,"<>Month total") -> 0 | M11: =IF(L11=0,"",D11/L11) | N11: =SUMIFS('Google data'!$F$3:$F$20000,'Google data'!$A$3:$A$20000,">="&$B11,'Google data'!$A$3:$A$20000,"<="&$C11,'Google data'!$G$3:$G$20000,"<>Month total") -> 0 | O11: =IF(N11=0,"",E11/N11) | R11: Agency: Meta location campaigns launched Thursday; spend jumped. Broader Google keywords added; some locations underspending (may move to Max Clicks). | S11: =TEXT(B11,"d mmm") -> 9 Feb
A12: 8 | B12: =Settings!$C$13+7*(A12-1) -> 46069 | C12: =B12+6 -> 46075 | D12: =SUMIFS('Meta data'!$I$3:$I$20000,'Meta data'!$A$3:$A$20000,">="&$B12,'Meta data'!$A$3:$A$20000,"<="&$C12,'Meta data'!$G$3:$G$20000,"<>Month total") -> 0 | E12: =SUMIFS('Google data'!$I$3:$I$20000,'Google data'!$A$3:$A$20000,">="&$B12,'Google data'!$A$3:$A$20000,"<="&$C12,'Google data'!$G$3:$G$20000,"<>Month total") -> 0 | F12: =SUMIFS('ChatGPT data'!$I$3:$I$20000,'ChatGPT data'!$A$3:$A$20000,">="&$B12,'ChatGPT data'!$A$3:$A$20000,"<="&$C12,'ChatGPT data'!$G$3:$G$20000,"<>Month total") -> 0 | G12: =SUMIFS('LinkedIn data'!$I$3:$I$20000,'LinkedIn data'!$A$3:$A$20000,">="&$B12,'LinkedIn data'!$A$3:$A$20000,"<="&$C12,'LinkedIn data'!$G$3:$G$20000,"<>Month total") -> 0 | H12: =SUM(D12:G12) -> 0 | I12: =D12*(Settings!$C$22="Yes")+E12*(Settings!$C$23="Yes")+F12*(Settings!$C$24="Yes")+G12*(Settings!$C$25="Yes") -> 0 | J12: =Settings!$D$16*MAX(0,MIN(C12,Settings!$C$11)-MAX(B12,Settings!$C$10)+1)/(Settings!$C$11-Settings!$C$10+1) -> 5753.4247 | K12: =IF(OR(C12>$C$3,I12=0),"",I12-J12) | L12: =SUMIFS('Meta data'!$F$3:$F$20000,'Meta data'!$A$3:$A$20000,">="&$B12,'Meta data'!$A$3:$A$20000,"<="&$C12,'Meta data'!$G$3:$G$20000,"<>Month total") -> 0 | M12: =IF(L12=0,"",D12/L12) | N12: =SUMIFS('Google data'!$F$3:$F$20000,'Google data'!$A$3:$A$20000,">="&$B12,'Google data'!$A$3:$A$20000,"<="&$C12,'Google data'!$G$3:$G$20000,"<>Month total") -> 0 | O12: =IF(N12=0,"",E12/N12) | R12: Agency: Both Google Global search campaigns budget-limited; agency asks to move budget "even if out of plan". Indiana the worst Meta location. | S12: =TEXT(B12,"d mmm") -> 16 Feb
A13: 9 | B13: =Settings!$C$13+7*(A13-1) -> 46076 | C13: =B13+6 -> 46082 | D13: =SUMIFS('Meta data'!$I$3:$I$20000,'Meta data'!$A$3:$A$20000,">="&$B13,'Meta data'!$A$3:$A$20000,"<="&$C13,'Meta data'!$G$3:$G$20000,"<>Month total") -> 0 | E13: =SUMIFS('Google data'!$I$3:$I$20000,'Google data'!$A$3:$A$20000,">="&$B13,'Google data'!$A$3:$A$20000,"<="&$C13,'Google data'!$G$3:$G$20000,"<>Month total") -> 0 | F13: =SUMIFS('ChatGPT data'!$I$3:$I$20000,'ChatGPT data'!$A$3:$A$20000,">="&$B13,'ChatGPT data'!$A$3:$A$20000,"<="&$C13,'ChatGPT data'!$G$3:$G$20000,"<>Month total") -> 0 | G13: =SUMIFS('LinkedIn data'!$I$3:$I$20000,'LinkedIn data'!$A$3:$A$20000,">="&$B13,'LinkedIn data'!$A$3:$A$20000,"<="&$C13,'LinkedIn data'!$G$3:$G$20000,"<>Month total") -> 0 | H13: =SUM(D13:G13) -> 0 | I13: =D13*(Settings!$C$22="Yes")+E13*(Settings!$C$23="Yes")+F13*(Settings!$C$24="Yes")+G13*(Settings!$C$25="Yes") -> 0 | J13: =Settings!$D$16*MAX(0,MIN(C13,Settings!$C$11)-MAX(B13,Settings!$C$10)+1)/(Settings!$C$11-Settings!$C$10+1) -> 5753.4247 | K13: =IF(OR(C13>$C$3,I13=0),"",I13-J13) | L13: =SUMIFS('Meta data'!$F$3:$F$20000,'Meta data'!$A$3:$A$20000,">="&$B13,'Meta data'!$A$3:$A$20000,"<="&$C13,'Meta data'!$G$3:$G$20000,"<>Month total") -> 0 | M13: =IF(L13=0,"",D13/L13) | N13: =SUMIFS('Google data'!$F$3:$F$20000,'Google data'!$A$3:$A$20000,">="&$B13,'Google data'!$A$3:$A$20000,"<="&$C13,'Google data'!$G$3:$G$20000,"<>Month total") -> 0 | O13: =IF(N13=0,"",E13/N13) | R13: Agency: Google YouTube campaigns ended. Search improved but Global still budget-limited. Meta CPM rose across campaigns. | S13: =TEXT(B13,"d mmm") -> 23 Feb
A14: 10 | B14: =Settings!$C$13+7*(A14-1) -> 46083 | C14: =B14+6 -> 46089 | D14: =SUMIFS('Meta data'!$I$3:$I$20000,'Meta data'!$A$3:$A$20000,">="&$B14,'Meta data'!$A$3:$A$20000,"<="&$C14,'Meta data'!$G$3:$G$20000,"<>Month total") -> 0 | E14: =SUMIFS('Google data'!$I$3:$I$20000,'Google data'!$A$3:$A$20000,">="&$B14,'Google data'!$A$3:$A$20000,"<="&$C14,'Google data'!$G$3:$G$20000,"<>Month total") -> 0 | F14: =SUMIFS('ChatGPT data'!$I$3:$I$20000,'ChatGPT data'!$A$3:$A$20000,">="&$B14,'ChatGPT data'!$A$3:$A$20000,"<="&$C14,'ChatGPT data'!$G$3:$G$20000,"<>Month total") -> 0 | G14: =SUMIFS('LinkedIn data'!$I$3:$I$20000,'LinkedIn data'!$A$3:$A$20000,">="&$B14,'LinkedIn data'!$A$3:$A$20000,"<="&$C14,'LinkedIn data'!$G$3:$G$20000,"<>Month total") -> 0 | H14: =SUM(D14:G14) -> 0 | I14: =D14*(Settings!$C$22="Yes")+E14*(Settings!$C$23="Yes")+F14*(Settings!$C$24="Yes")+G14*(Settings!$C$25="Yes") -> 0 | J14: =Settings!$D$16*MAX(0,MIN(C14,Settings!$C$11)-MAX(B14,Settings!$C$10)+1)/(Settings!$C$11-Settings!$C$10+1) -> 5753.4247 | K14: =IF(OR(C14>$C$3,I14=0),"",I14-J14) | L14: =SUMIFS('Meta data'!$F$3:$F$20000,'Meta data'!$A$3:$A$20000,">="&$B14,'Meta data'!$A$3:$A$20000,"<="&$C14,'Meta data'!$G$3:$G$20000,"<>Month total") -> 0 | M14: =IF(L14=0,"",D14/L14) | N14: =SUMIFS('Google data'!$F$3:$F$20000,'Google data'!$A$3:$A$20000,">="&$B14,'Google data'!$A$3:$A$20000,"<="&$C14,'Google data'!$G$3:$G$20000,"<>Month total") -> 0 | O14: =IF(N14=0,"",E14/N14) | R14: Agency: Tightened Google targets in some locations; added broad keywords in UK, France, Texas. Agency asks to use HubSpot as Google's conversion source. | S14: =TEXT(B14,"d mmm") -> 2 Mar
A15: 11 | B15: =Settings!$C$13+7*(A15-1) -> 46090 | C15: =B15+6 -> 46096 | D15: =SUMIFS('Meta data'!$I$3:$I$20000,'Meta data'!$A$3:$A$20000,">="&$B15,'Meta data'!$A$3:$A$20000,"<="&$C15,'Meta data'!$G$3:$G$20000,"<>Month total") -> 0 | E15: =SUMIFS('Google data'!$I$3:$I$20000,'Google data'!$A$3:$A$20000,">="&$B15,'Google data'!$A$3:$A$20000,"<="&$C15,'Google data'!$G$3:$G$20000,"<>Month total") -> 0 | F15: =SUMIFS('ChatGPT data'!$I$3:$I$20000,'ChatGPT data'!$A$3:$A$20000,">="&$B15,'ChatGPT data'!$A$3:$A$20000,"<="&$C15,'ChatGPT data'!$G$3:$G$20000,"<>Month total") -> 0 | G15: =SUMIFS('LinkedIn data'!$I$3:$I$20000,'LinkedIn data'!$A$3:$A$20000,">="&$B15,'LinkedIn data'!$A$3:$A$20000,"<="&$C15,'LinkedIn data'!$G$3:$G$20000,"<>Month total") -> 0 | H15: =SUM(D15:G15) -> 0 | I15: =D15*(Settings!$C$22="Yes")+E15*(Settings!$C$23="Yes")+F15*(Settings!$C$24="Yes")+G15*(Settings!$C$25="Yes") -> 0 | J15: =Settings!$D$16*MAX(0,MIN(C15,Settings!$C$11)-MAX(B15,Settings!$C$10)+1)/(Settings!$C$11-Settings!$C$10+1) -> 5753.4247 | K15: =IF(OR(C15>$C$3,I15=0),"",I15-J15) | L15: =SUMIFS('Meta data'!$F$3:$F$20000,'Meta data'!$A$3:$A$20000,">="&$B15,'Meta data'!$A$3:$A$20000,"<="&$C15,'Meta data'!$G$3:$G$20000,"<>Month total") -> 0 | M15: =IF(L15=0,"",D15/L15) | N15: =SUMIFS('Google data'!$F$3:$F$20000,'Google data'!$A$3:$A$20000,">="&$B15,'Google data'!$A$3:$A$20000,"<="&$C15,'Google data'!$G$3:$G$20000,"<>Month total") -> 0 | O15: =IF(N15=0,"",E15/N15) | R15: Agency: Google spend raised after better in-platform results. Large Google vs HubSpot gap flagged. NY, NJ and AZ Meta campaigns worsening. | S15: =TEXT(B15,"d mmm") -> 9 Mar
A16: 12 | B16: =Settings!$C$13+7*(A16-1) -> 46097 | C16: =B16+6 -> 46103 | D16: =SUMIFS('Meta data'!$I$3:$I$20000,'Meta data'!$A$3:$A$20000,">="&$B16,'Meta data'!$A$3:$A$20000,"<="&$C16,'Meta data'!$G$3:$G$20000,"<>Month total") -> 0 | E16: =SUMIFS('Google data'!$I$3:$I$20000,'Google data'!$A$3:$A$20000,">="&$B16,'Google data'!$A$3:$A$20000,"<="&$C16,'Google data'!$G$3:$G$20000,"<>Month total") -> 0 | F16: =SUMIFS('ChatGPT data'!$I$3:$I$20000,'ChatGPT data'!$A$3:$A$20000,">="&$B16,'ChatGPT data'!$A$3:$A$20000,"<="&$C16,'ChatGPT data'!$G$3:$G$20000,"<>Month total") -> 0 | G16: =SUMIFS('LinkedIn data'!$I$3:$I$20000,'LinkedIn data'!$A$3:$A$20000,">="&$B16,'LinkedIn data'!$A$3:$A$20000,"<="&$C16,'LinkedIn data'!$G$3:$G$20000,"<>Month total") -> 0 | H16: =SUM(D16:G16) -> 0 | I16: =D16*(Settings!$C$22="Yes")+E16*(Settings!$C$23="Yes")+F16*(Settings!$C$24="Yes")+G16*(Settings!$C$25="Yes") -> 0 | J16: =Settings!$D$16*MAX(0,MIN(C16,Settings!$C$11)-MAX(B16,Settings!$C$10)+1)/(Settings!$C$11-Settings!$C$10+1) -> 5753.4247 | K16: =IF(OR(C16>$C$3,I16=0),"",I16-J16) | L16: =SUMIFS('Meta data'!$F$3:$F$20000,'Meta data'!$A$3:$A$20000,">="&$B16,'Meta data'!$A$3:$A$20000,"<="&$C16,'Meta data'!$G$3:$G$20000,"<>Month total") -> 0 | M16: =IF(L16=0,"",D16/L16) | N16: =SUMIFS('Google data'!$F$3:$F$20000,'Google data'!$A$3:$A$20000,">="&$B16,'Google data'!$A$3:$A$20000,"<="&$C16,'Google data'!$G$3:$G$20000,"<>Month total") -> 0 | O16: =IF(N16=0,"",E16/N16) | R16: Agency: Google Global EMEA at 0 leads despite a 60% spend cut; under review. Demand Gen running in Texas and Florida. Meta "All" campaigns refresh planned. | S16: =TEXT(B16,"d mmm") -> 16 Mar
... A45: 41 | B45: =Settings!$C$13+7*(A45-1) -> 46300 | C45: =B45+6 -> 46306 | D45: =SUMIFS('Meta data'!$I$3:$I$20000,'Meta data'!$A$3:$A$20000,">="&$B45,'Meta data'!$A$3:$A$20000,"<="&$C45,'Meta data'!$G$3:$G$20000,"<>Month total") -> 0 | E45: =SUMIFS('Google data'!$I$3:$I$20000,'Google data'!$A$3:$A$20000,">="&$B45,'Google data'!$A$3:$A$20000,"<="&$C45,'Google data'!$G$3:$G$20000,"<>Month total") -> 0 | F45: =SUMIFS('ChatGPT data'!$I$3:$I$20000,'ChatGPT data'!$A$3:$A$20000,">="&$B45,'ChatGPT data'!$A$3:$A$20000,"<="&$C45,'ChatGPT data'!$G$3:$G$20000,"<>Month total") -> 0 | G45: =SUMIFS('LinkedIn data'!$I$3:$I$20000,'LinkedIn data'!$A$3:$A$20000,">="&$B45,'LinkedIn data'!$A$3:$A$20000,"<="&$C45,'LinkedIn data'!$G$3:$G$20000,"<>Month total") -> 0 | H45: =SUM(D45:G45) -> 0 | I45: =D45*(Settings!$C$22="Yes")+E45*(Settings!$C$23="Yes")+F45*(Settings!$C$24="Yes")+G45*(Settings!$C$25="Yes") -> 0 | J45: =Settings!$D$16*MAX(0,MIN(C45,Settings!$C$11)-MAX(B45,Settings!$C$10)+1)/(Settings!$C$11-Settings!$C$10+1) -> 5753.4247 | K45: =IF(OR(C45>$C$3,I45=0),"",I45-J45) | L45: =SUMIFS('Meta data'!$F$3:$F$20000,'Meta data'!$A$3:$A$20000,">="&$B45,'Meta data'!$A$3:$A$20000,"<="&$C45,'Meta data'!$G$3:$G$20000,"<>Month total") -> 0 | M45: =IF(L45=0,"",D45/L45) | N45: =SUMIFS('Google data'!$F$3:$F$20000,'Google data'!$A$3:$A$20000,">="&$B45,'Google data'!$A$3:$A$20000,"<="&$C45,'Google data'!$G$3:$G$20000,"<>Month total") -> 0 | O45: =IF(N45=0,"",E45/N45) | R45: Agency: Google CPL fell to €27.75. Plan: check channel vs HubSpot discrepancy, pause PP-266, judge case-study statics launched 8 Oct. | S45: =TEXT(B45,"d mmm") -> 5 Oct
A46: 42 | B46: =Settings!$C$13+7*(A46-1) -> 46307 | C46: =B46+6 -> 46313 | D46: =SUMIFS('Meta data'!$I$3:$I$20000,'Meta data'!$A$3:$A$20000,">="&$B46,'Meta data'!$A$3:$A$20000,"<="&$C46,'Meta data'!$G$3:$G$20000,"<>Month total") -> 0 | E46: =SUMIFS('Google data'!$I$3:$I$20000,'Google data'!$A$3:$A$20000,">="&$B46,'Google data'!$A$3:$A$20000,"<="&$C46,'Google data'!$G$3:$G$20000,"<>Month total") -> 0 | F46: =SUMIFS('ChatGPT data'!$I$3:$I$20000,'ChatGPT data'!$A$3:$A$20000,">="&$B46,'ChatGPT data'!$A$3:$A$20000,"<="&$C46,'ChatGPT data'!$G$3:$G$20000,"<>Month total") -> 0 | G46: =SUMIFS('LinkedIn data'!$I$3:$I$20000,'LinkedIn data'!$A$3:$A$20000,">="&$B46,'LinkedIn data'!$A$3:$A$20000,"<="&$C46,'LinkedIn data'!$G$3:$G$20000,"<>Month total") -> 0 | H46: =SUM(D46:G46) -> 0 | I46: =D46*(Settings!$C$22="Yes")+E46*(Settings!$C$23="Yes")+F46*(Settings!$C$24="Yes")+G46*(Settings!$C$25="Yes") -> 0 | J46: =Settings!$D$16*MAX(0,MIN(C46,Settings!$C$11)-MAX(B46,Settings!$C$10)+1)/(Settings!$C$11-Settings!$C$10+1) -> 5753.4247 | K46: =IF(OR(C46>$C$3,I46=0),"",I46-J46) | L46: =SUMIFS('Meta data'!$F$3:$F$20000,'Meta data'!$A$3:$A$20000,">="&$B46,'Meta data'!$A$3:$A$20000,"<="&$C46,'Meta data'!$G$3:$G$20000,"<>Month total") -> 0 | M46: =IF(L46=0,"",D46/L46) | N46: =SUMIFS('Google data'!$F$3:$F$20000,'Google data'!$A$3:$A$20000,">="&$B46,'Google data'!$A$3:$A$20000,"<="&$C46,'Google data'!$G$3:$G$20000,"<>Month total") -> 0 | O46: =IF(N46=0,"",E46/N46) | S46: =TEXT(B46,"d mmm") -> 12 Oct
A47: 43 | B47: =Settings!$C$13+7*(A47-1) -> 46314 | C47: =B47+6 -> 46320 | D47: =SUMIFS('Meta data'!$I$3:$I$20000,'Meta data'!$A$3:$A$20000,">="&$B47,'Meta data'!$A$3:$A$20000,"<="&$C47,'Meta data'!$G$3:$G$20000,"<>Month total") -> 0 | E47: =SUMIFS('Google data'!$I$3:$I$20000,'Google data'!$A$3:$A$20000,">="&$B47,'Google data'!$A$3:$A$20000,"<="&$C47,'Google data'!$G$3:$G$20000,"<>Month total") -> 0 | F47: =SUMIFS('ChatGPT data'!$I$3:$I$20000,'ChatGPT data'!$A$3:$A$20000,">="&$B47,'ChatGPT data'!$A$3:$A$20000,"<="&$C47,'ChatGPT data'!$G$3:$G$20000,"<>Month total") -> 0 | G47: =SUMIFS('LinkedIn data'!$I$3:$I$20000,'LinkedIn data'!$A$3:$A$20000,">="&$B47,'LinkedIn data'!$A$3:$A$20000,"<="&$C47,'LinkedIn data'!$G$3:$G$20000,"<>Month total") -> 0 | H47: =SUM(D47:G47) -> 0 | I47: =D47*(Settings!$C$22="Yes")+E47*(Settings!$C$23="Yes")+F47*(Settings!$C$24="Yes")+G47*(Settings!$C$25="Yes") -> 0 | J47: =Settings!$D$16*MAX(0,MIN(C47,Settings!$C$11)-MAX(B47,Settings!$C$10)+1)/(Settings!$C$11-Settings!$C$10+1) -> 5753.4247 | K47: =IF(OR(C47>$C$3,I47=0),"",I47-J47) | L47: =SUMIFS('Meta data'!$F$3:$F$20000,'Meta data'!$A$3:$A$20000,">="&$B47,'Meta data'!$A$3:$A$20000,"<="&$C47,'Meta data'!$G$3:$G$20000,"<>Month total") -> 0 | M47: =IF(L47=0,"",D47/L47) | N47: =SUMIFS('Google data'!$F$3:$F$20000,'Google data'!$A$3:$A$20000,">="&$B47,'Google data'!$A$3:$A$20000,"<="&$C47,'Google data'!$G$3:$G$20000,"<>Month total") -> 0 | O47: =IF(N47=0,"",E47/N47) | S47: =TEXT(B47,"d mmm") -> 19 Oct
A48: 44 | B48: =Settings!$C$13+7*(A48-1) -> 46321 | C48: =B48+6 -> 46327 | D48: =SUMIFS('Meta data'!$I$3:$I$20000,'Meta data'!$A$3:$A$20000,">="&$B48,'Meta data'!$A$3:$A$20000,"<="&$C48,'Meta data'!$G$3:$G$20000,"<>Month total") -> 0 | E48: =SUMIFS('Google data'!$I$3:$I$20000,'Google data'!$A$3:$A$20000,">="&$B48,'Google data'!$A$3:$A$20000,"<="&$C48,'Google data'!$G$3:$G$20000,"<>Month total") -> 0 | F48: =SUMIFS('ChatGPT data'!$I$3:$I$20000,'ChatGPT data'!$A$3:$A$20000,">="&$B48,'ChatGPT data'!$A$3:$A$20000,"<="&$C48,'ChatGPT data'!$G$3:$G$20000,"<>Month total") -> 0 | G48: =SUMIFS('LinkedIn data'!$I$3:$I$20000,'LinkedIn data'!$A$3:$A$20000,">="&$B48,'LinkedIn data'!$A$3:$A$20000,"<="&$C48,'LinkedIn data'!$G$3:$G$20000,"<>Month total") -> 0 | H48: =SUM(D48:G48) -> 0 | I48: =D48*(Settings!$C$22="Yes")+E48*(Settings!$C$23="Yes")+F48*(Settings!$C$24="Yes")+G48*(Settings!$C$25="Yes") -> 0 | J48: =Settings!$D$16*MAX(0,MIN(C48,Settings!$C$11)-MAX(B48,Settings!$C$10)+1)/(Settings!$C$11-Settings!$C$10+1) -> 5753.4247 | K48: =IF(OR(C48>$C$3,I48=0),"",I48-J48) | L48: =SUMIFS('Meta data'!$F$3:$F$20000,'Meta data'!$A$3:$A$20000,">="&$B48,'Meta data'!$A$3:$A$20000,"<="&$C48,'Meta data'!$G$3:$G$20000,"<>Month total") -> 0 | M48: =IF(L48=0,"",D48/L48) | N48: =SUMIFS('Google data'!$F$3:$F$20000,'Google data'!$A$3:$A$20000,">="&$B48,'Google data'!$A$3:$A$20000,"<="&$C48,'Google data'!$G$3:$G$20000,"<>Month total") -> 0 | O48: =IF(N48=0,"",E48/N48) | S48: =TEXT(B48,"d mmm") -> 26 Oct
A49: 45 | B49: =Settings!$C$13+7*(A49-1) -> 46328 | C49: =B49+6 -> 46334 | D49: =SUMIFS('Meta data'!$I$3:$I$20000,'Meta data'!$A$3:$A$20000,">="&$B49,'Meta data'!$A$3:$A$20000,"<="&$C49,'Meta data'!$G$3:$G$20000,"<>Month total") -> 0 | E49: =SUMIFS('Google data'!$I$3:$I$20000,'Google data'!$A$3:$A$20000,">="&$B49,'Google data'!$A$3:$A$20000,"<="&$C49,'Google data'!$G$3:$G$20000,"<>Month total") -> 0 | F49: =SUMIFS('ChatGPT data'!$I$3:$I$20000,'ChatGPT data'!$A$3:$A$20000,">="&$B49,'ChatGPT data'!$A$3:$A$20000,"<="&$C49,'ChatGPT data'!$G$3:$G$20000,"<>Month total") -> 0 | G49: =SUMIFS('LinkedIn data'!$I$3:$I$20000,'LinkedIn data'!$A$3:$A$20000,">="&$B49,'LinkedIn data'!$A$3:$A$20000,"<="&$C49,'LinkedIn data'!$G$3:$G$20000,"<>Month total") -> 0 | H49: =SUM(D49:G49) -> 0 | I49: =D49*(Settings!$C$22="Yes")+E49*(Settings!$C$23="Yes")+F49*(Settings!$C$24="Yes")+G49*(Settings!$C$25="Yes") -> 0 | J49: =Settings!$D$16*MAX(0,MIN(C49,Settings!$C$11)-MAX(B49,Settings!$C$10)+1)/(Settings!$C$11-Settings!$C$10+1) -> 5753.4247 | K49: =IF(OR(C49>$C$3,I49=0),"",I49-J49) | L49: =SUMIFS('Meta data'!$F$3:$F$20000,'Meta data'!$A$3:$A$20000,">="&$B49,'Meta data'!$A$3:$A$20000,"<="&$C49,'Meta data'!$G$3:$G$20000,"<>Month total") -> 0 | M49: =IF(L49=0,"",D49/L49) | N49: =SUMIFS('Google data'!$F$3:$F$20000,'Google data'!$A$3:$A$20000,">="&$B49,'Google data'!$A$3:$A$20000,"<="&$C49,'Google data'!$G$3:$G$20000,"<>Month total") -> 0 | O49: =IF(N49=0,"",E49/N49) | S49: =TEXT(B49,"d mmm") -> 2 Nov
A50: 46 | B50: =Settings!$C$13+7*(A50-1) -> 46335 | C50: =B50+6 -> 46341 | D50: =SUMIFS('Meta data'!$I$3:$I$20000,'Meta data'!$A$3:$A$20000,">="&$B50,'Meta data'!$A$3:$A$20000,"<="&$C50,'Meta data'!$G$3:$G$20000,"<>Month total") -> 0 | E50: =SUMIFS('Google data'!$I$3:$I$20000,'Google data'!$A$3:$A$20000,">="&$B50,'Google data'!$A$3:$A$20000,"<="&$C50,'Google data'!$G$3:$G$20000,"<>Month total") -> 0 | F50: =SUMIFS('ChatGPT data'!$I$3:$I$20000,'ChatGPT data'!$A$3:$A$20000,">="&$B50,'ChatGPT data'!$A$3:$A$20000,"<="&$C50,'ChatGPT data'!$G$3:$G$20000,"<>Month total") -> 0 | G50: =SUMIFS('LinkedIn data'!$I$3:$I$20000,'LinkedIn data'!$A$3:$A$20000,">="&$B50,'LinkedIn data'!$A$3:$A$20000,"<="&$C50,'LinkedIn data'!$G$3:$G$20000,"<>Month total") -> 0 | H50: =SUM(D50:G50) -> 0 | I50: =D50*(Settings!$C$22="Yes")+E50*(Settings!$C$23="Yes")+F50*(Settings!$C$24="Yes")+G50*(Settings!$C$25="Yes") -> 0 | J50: =Settings!$D$16*MAX(0,MIN(C50,Settings!$C$11)-MAX(B50,Settings!$C$10)+1)/(Settings!$C$11-Settings!$C$10+1) -> 5753.4247 | K50: =IF(OR(C50>$C$3,I50=0),"",I50-J50) | L50: =SUMIFS('Meta data'!$F$3:$F$20000,'Meta data'!$A$3:$A$20000,">="&$B50,'Meta data'!$A$3:$A$20000,"<="&$C50,'Meta data'!$G$3:$G$20000,"<>Month total") -> 0 | M50: =IF(L50=0,"",D50/L50) | N50: =SUMIFS('Google data'!$F$3:$F$20000,'Google data'!$A$3:$A$20000,">="&$B50,'Google data'!$A$3:$A$20000,"<="&$C50,'Google data'!$G$3:$G$20000,"<>Month total") -> 0 | O50: =IF(N50=0,"",E50/N50) | S50: =TEXT(B50,"d mmm") -> 9 Nov
A51: 47 | B51: =Settings!$C$13+7*(A51-1) -> 46342 | C51: =B51+6 -> 46348 | D51: =SUMIFS('Meta data'!$I$3:$I$20000,'Meta data'!$A$3:$A$20000,">="&$B51,'Meta data'!$A$3:$A$20000,"<="&$C51,'Meta data'!$G$3:$G$20000,"<>Month total") -> 0 | E51: =SUMIFS('Google data'!$I$3:$I$20000,'Google data'!$A$3:$A$20000,">="&$B51,'Google data'!$A$3:$A$20000,"<="&$C51,'Google data'!$G$3:$G$20000,"<>Month total") -> 0 | F51: =SUMIFS('ChatGPT data'!$I$3:$I$20000,'ChatGPT data'!$A$3:$A$20000,">="&$B51,'ChatGPT data'!$A$3:$A$20000,"<="&$C51,'ChatGPT data'!$G$3:$G$20000,"<>Month total") -> 0 | G51: =SUMIFS('LinkedIn data'!$I$3:$I$20000,'LinkedIn data'!$A$3:$A$20000,">="&$B51,'LinkedIn data'!$A$3:$A$20000,"<="&$C51,'LinkedIn data'!$G$3:$G$20000,"<>Month total") -> 0 | H51: =SUM(D51:G51) -> 0 | I51: =D51*(Settings!$C$22="Yes")+E51*(Settings!$C$23="Yes")+F51*(Settings!$C$24="Yes")+G51*(Settings!$C$25="Yes") -> 0 | J51: =Settings!$D$16*MAX(0,MIN(C51,Settings!$C$11)-MAX(B51,Settings!$C$10)+1)/(Settings!$C$11-Settings!$C$10+1) -> 5753.4247 | K51: =IF(OR(C51>$C$3,I51=0),"",I51-J51) | L51: =SUMIFS('Meta data'!$F$3:$F$20000,'Meta data'!$A$3:$A$20000,">="&$B51,'Meta data'!$A$3:$A$20000,"<="&$C51,'Meta data'!$G$3:$G$20000,"<>Month total") -> 0 | M51: =IF(L51=0,"",D51/L51) | N51: =SUMIFS('Google data'!$F$3:$F$20000,'Google data'!$A$3:$A$20000,">="&$B51,'Google data'!$A$3:$A$20000,"<="&$C51,'Google data'!$G$3:$G$20000,"<>Month total") -> 0 | O51: =IF(N51=0,"",E51/N51) | S51: =TEXT(B51,"d mmm") -> 16 Nov
A52: 48 | B52: =Settings!$C$13+7*(A52-1) -> 46349 | C52: =B52+6 -> 46355 | D52: =SUMIFS('Meta data'!$I$3:$I$20000,'Meta data'!$A$3:$A$20000,">="&$B52,'Meta data'!$A$3:$A$20000,"<="&$C52,'Meta data'!$G$3:$G$20000,"<>Month total") -> 0 | E52: =SUMIFS('Google data'!$I$3:$I$20000,'Google data'!$A$3:$A$20000,">="&$B52,'Google data'!$A$3:$A$20000,"<="&$C52,'Google data'!$G$3:$G$20000,"<>Month total") -> 0 | F52: =SUMIFS('ChatGPT data'!$I$3:$I$20000,'ChatGPT data'!$A$3:$A$20000,">="&$B52,'ChatGPT data'!$A$3:$A$20000,"<="&$C52,'ChatGPT data'!$G$3:$G$20000,"<>Month total") -> 0 | G52: =SUMIFS('LinkedIn data'!$I$3:$I$20000,'LinkedIn data'!$A$3:$A$20000,">="&$B52,'LinkedIn data'!$A$3:$A$20000,"<="&$C52,'LinkedIn data'!$G$3:$G$20000,"<>Month total") -> 0 | H52: =SUM(D52:G52) -> 0 | I52: =D52*(Settings!$C$22="Yes")+E52*(Settings!$C$23="Yes")+F52*(Settings!$C$24="Yes")+G52*(Settings!$C$25="Yes") -> 0 | J52: =Settings!$D$16*MAX(0,MIN(C52,Settings!$C$11)-MAX(B52,Settings!$C$10)+1)/(Settings!$C$11-Settings!$C$10+1) -> 5753.4247 | K52: =IF(OR(C52>$C$3,I52=0),"",I52-J52) | L52: =SUMIFS('Meta data'!$F$3:$F$20000,'Meta data'!$A$3:$A$20000,">="&$B52,'Meta data'!$A$3:$A$20000,"<="&$C52,'Meta data'!$G$3:$G$20000,"<>Month total") -> 0 | M52: =IF(L52=0,"",D52/L52) | N52: =SUMIFS('Google data'!$F$3:$F$20000,'Google data'!$A$3:$A$20000,">="&$B52,'Google data'!$A$3:$A$20000,"<="&$C52,'Google data'!$G$3:$G$20000,"<>Month total") -> 0 | O52: =IF(N52=0,"",E52/N52) | S52: =TEXT(B52,"d mmm") -> 23 Nov
A53: 49 | B53: =Settings!$C$13+7*(A53-1) -> 46356 | C53: =B53+6 -> 46362 | D53: =SUMIFS('Meta data'!$I$3:$I$20000,'Meta data'!$A$3:$A$20000,">="&$B53,'Meta data'!$A$3:$A$20000,"<="&$C53,'Meta data'!$G$3:$G$20000,"<>Month total") -> 0 | E53: =SUMIFS('Google data'!$I$3:$I$20000,'Google data'!$A$3:$A$20000,">="&$B53,'Google data'!$A$3:$A$20000,"<="&$C53,'Google data'!$G$3:$G$20000,"<>Month total") -> 0 | F53: =SUMIFS('ChatGPT data'!$I$3:$I$20000,'ChatGPT data'!$A$3:$A$20000,">="&$B53,'ChatGPT data'!$A$3:$A$20000,"<="&$C53,'ChatGPT data'!$G$3:$G$20000,"<>Month total") -> 0 | G53: =SUMIFS('LinkedIn data'!$I$3:$I$20000,'LinkedIn data'!$A$3:$A$20000,">="&$B53,'LinkedIn data'!$A$3:$A$20000,"<="&$C53,'LinkedIn data'!$G$3:$G$20000,"<>Month total") -> 0 | H53: =SUM(D53:G53) -> 0 | I53: =D53*(Settings!$C$22="Yes")+E53*(Settings!$C$23="Yes")+F53*(Settings!$C$24="Yes")+G53*(Settings!$C$25="Yes") -> 0 | J53: =Settings!$D$16*MAX(0,MIN(C53,Settings!$C$11)-MAX(B53,Settings!$C$10)+1)/(Settings!$C$11-Settings!$C$10+1) -> 5753.4247 | K53: =IF(OR(C53>$C$3,I53=0),"",I53-J53) | L53: =SUMIFS('Meta data'!$F$3:$F$20000,'Meta data'!$A$3:$A$20000,">="&$B53,'Meta data'!$A$3:$A$20000,"<="&$C53,'Meta data'!$G$3:$G$20000,"<>Month total") -> 0 | M53: =IF(L53=0,"",D53/L53) | N53: =SUMIFS('Google data'!$F$3:$F$20000,'Google data'!$A$3:$A$20000,">="&$B53,'Google data'!$A$3:$A$20000,"<="&$C53,'Google data'!$G$3:$G$20000,"<>Month total") -> 0 | O53: =IF(N53=0,"",E53/N53) | S53: =TEXT(B53,"d mmm") -> 30 Nov
A54: 50 | B54: =Settings!$C$13+7*(A54-1) -> 46363 | C54: =B54+6 -> 46369 | D54: =SUMIFS('Meta data'!$I$3:$I$20000,'Meta data'!$A$3:$A$20000,">="&$B54,'Meta data'!$A$3:$A$20000,"<="&$C54,'Meta data'!$G$3:$G$20000,"<>Month total") -> 0 | E54: =SUMIFS('Google data'!$I$3:$I$20000,'Google data'!$A$3:$A$20000,">="&$B54,'Google data'!$A$3:$A$20000,"<="&$C54,'Google data'!$G$3:$G$20000,"<>Month total") -> 0 | F54: =SUMIFS('ChatGPT data'!$I$3:$I$20000,'ChatGPT data'!$A$3:$A$20000,">="&$B54,'ChatGPT data'!$A$3:$A$20000,"<="&$C54,'ChatGPT data'!$G$3:$G$20000,"<>Month total") -> 0 | G54: =SUMIFS('LinkedIn data'!$I$3:$I$20000,'LinkedIn data'!$A$3:$A$20000,">="&$B54,'LinkedIn data'!$A$3:$A$20000,"<="&$C54,'LinkedIn data'!$G$3:$G$20000,"<>Month total") -> 0 | H54: =SUM(D54:G54) -> 0 | I54: =D54*(Settings!$C$22="Yes")+E54*(Settings!$C$23="Yes")+F54*(Settings!$C$24="Yes")+G54*(Settings!$C$25="Yes") -> 0 | J54: =Settings!$D$16*MAX(0,MIN(C54,Settings!$C$11)-MAX(B54,Settings!$C$10)+1)/(Settings!$C$11-Settings!$C$10+1) -> 5753.4247 | K54: =IF(OR(C54>$C$3,I54=0),"",I54-J54) | L54: =SUMIFS('Meta data'!$F$3:$F$20000,'Meta data'!$A$3:$A$20000,">="&$B54,'Meta data'!$A$3:$A$20000,"<="&$C54,'Meta data'!$G$3:$G$20000,"<>Month total") -> 0 | M54: =IF(L54=0,"",D54/L54) | N54: =SUMIFS('Google data'!$F$3:$F$20000,'Google data'!$A$3:$A$20000,">="&$B54,'Google data'!$A$3:$A$20000,"<="&$C54,'Google data'!$G$3:$G$20000,"<>Month total") -> 0 | O54: =IF(N54=0,"",E54/N54) | S54: =TEXT(B54,"d mmm") -> 7 Dec
A55: 51 | B55: =Settings!$C$13+7*(A55-1) -> 46370 | C55: =B55+6 -> 46376 | D55: =SUMIFS('Meta data'!$I$3:$I$20000,'Meta data'!$A$3:$A$20000,">="&$B55,'Meta data'!$A$3:$A$20000,"<="&$C55,'Meta data'!$G$3:$G$20000,"<>Month total") -> 0 | E55: =SUMIFS('Google data'!$I$3:$I$20000,'Google data'!$A$3:$A$20000,">="&$B55,'Google data'!$A$3:$A$20000,"<="&$C55,'Google data'!$G$3:$G$20000,"<>Month total") -> 0 | F55: =SUMIFS('ChatGPT data'!$I$3:$I$20000,'ChatGPT data'!$A$3:$A$20000,">="&$B55,'ChatGPT data'!$A$3:$A$20000,"<="&$C55,'ChatGPT data'!$G$3:$G$20000,"<>Month total") -> 0 | G55: =SUMIFS('LinkedIn data'!$I$3:$I$20000,'LinkedIn data'!$A$3:$A$20000,">="&$B55,'LinkedIn data'!$A$3:$A$20000,"<="&$C55,'LinkedIn data'!$G$3:$G$20000,"<>Month total") -> 0 | H55: =SUM(D55:G55) -> 0 | I55: =D55*(Settings!$C$22="Yes")+E55*(Settings!$C$23="Yes")+F55*(Settings!$C$24="Yes")+G55*(Settings!$C$25="Yes") -> 0 | J55: =Settings!$D$16*MAX(0,MIN(C55,Settings!$C$11)-MAX(B55,Settings!$C$10)+1)/(Settings!$C$11-Settings!$C$10+1) -> 5753.4247 | K55: =IF(OR(C55>$C$3,I55=0),"",I55-J55) | L55: =SUMIFS('Meta data'!$F$3:$F$20000,'Meta data'!$A$3:$A$20000,">="&$B55,'Meta data'!$A$3:$A$20000,"<="&$C55,'Meta data'!$G$3:$G$20000,"<>Month total") -> 0 | M55: =IF(L55=0,"",D55/L55) | N55: =SUMIFS('Google data'!$F$3:$F$20000,'Google data'!$A$3:$A$20000,">="&$B55,'Google data'!$A$3:$A$20000,"<="&$C55,'Google data'!$G$3:$G$20000,"<>Month total") -> 0 | O55: =IF(N55=0,"",E55/N55) | S55: =TEXT(B55,"d mmm") -> 14 Dec
A56: 52 | B56: =Settings!$C$13+7*(A56-1) -> 46377 | C56: =B56+6 -> 46383 | D56: =SUMIFS('Meta data'!$I$3:$I$20000,'Meta data'!$A$3:$A$20000,">="&$B56,'Meta data'!$A$3:$A$20000,"<="&$C56,'Meta data'!$G$3:$G$20000,"<>Month total") -> 0 | E56: =SUMIFS('Google data'!$I$3:$I$20000,'Google data'!$A$3:$A$20000,">="&$B56,'Google data'!$A$3:$A$20000,"<="&$C56,'Google data'!$G$3:$G$20000,"<>Month total") -> 0 | F56: =SUMIFS('ChatGPT data'!$I$3:$I$20000,'ChatGPT data'!$A$3:$A$20000,">="&$B56,'ChatGPT data'!$A$3:$A$20000,"<="&$C56,'ChatGPT data'!$G$3:$G$20000,"<>Month total") -> 0 | G56: =SUMIFS('LinkedIn data'!$I$3:$I$20000,'LinkedIn data'!$A$3:$A$20000,">="&$B56,'LinkedIn data'!$A$3:$A$20000,"<="&$C56,'LinkedIn data'!$G$3:$G$20000,"<>Month total") -> 0 | H56: =SUM(D56:G56) -> 0 | I56: =D56*(Settings!$C$22="Yes")+E56*(Settings!$C$23="Yes")+F56*(Settings!$C$24="Yes")+G56*(Settings!$C$25="Yes") -> 0 | J56: =Settings!$D$16*MAX(0,MIN(C56,Settings!$C$11)-MAX(B56,Settings!$C$10)+1)/(Settings!$C$11-Settings!$C$10+1) -> 5753.4247 | K56: =IF(OR(C56>$C$3,I56=0),"",I56-J56) | L56: =SUMIFS('Meta data'!$F$3:$F$20000,'Meta data'!$A$3:$A$20000,">="&$B56,'Meta data'!$A$3:$A$20000,"<="&$C56,'Meta data'!$G$3:$G$20000,"<>Month total") -> 0 | M56: =IF(L56=0,"",D56/L56) | N56: =SUMIFS('Google data'!$F$3:$F$20000,'Google data'!$A$3:$A$20000,">="&$B56,'Google data'!$A$3:$A$20000,"<="&$C56,'Google data'!$G$3:$G$20000,"<>Month total") -> 0 | O56: =IF(N56=0,"",E56/N56) | S56: =TEXT(B56,"d mmm") -> 21 Dec
A57: 53 | B57: =Settings!$C$13+7*(A57-1) -> 46384 | C57: =B57+6 -> 46390 | D57: =SUMIFS('Meta data'!$I$3:$I$20000,'Meta data'!$A$3:$A$20000,">="&$B57,'Meta data'!$A$3:$A$20000,"<="&$C57,'Meta data'!$G$3:$G$20000,"<>Month total") -> 0 | E57: =SUMIFS('Google data'!$I$3:$I$20000,'Google data'!$A$3:$A$20000,">="&$B57,'Google data'!$A$3:$A$20000,"<="&$C57,'Google data'!$G$3:$G$20000,"<>Month total") -> 0 | F57: =SUMIFS('ChatGPT data'!$I$3:$I$20000,'ChatGPT data'!$A$3:$A$20000,">="&$B57,'ChatGPT data'!$A$3:$A$20000,"<="&$C57,'ChatGPT data'!$G$3:$G$20000,"<>Month total") -> 0 | G57: =SUMIFS('LinkedIn data'!$I$3:$I$20000,'LinkedIn data'!$A$3:$A$20000,">="&$B57,'LinkedIn data'!$A$3:$A$20000,"<="&$C57,'LinkedIn data'!$G$3:$G$20000,"<>Month total") -> 0 | H57: =SUM(D57:G57) -> 0 | I57: =D57*(Settings!$C$22="Yes")+E57*(Settings!$C$23="Yes")+F57*(Settings!$C$24="Yes")+G57*(Settings!$C$25="Yes") -> 0 | J57: =Settings!$D$16*MAX(0,MIN(C57,Settings!$C$11)-MAX(B57,Settings!$C$10)+1)/(Settings!$C$11-Settings!$C$10+1) -> 3287.6712 | K57: =IF(OR(C57>$C$3,I57=0),"",I57-J57) | L57: =SUMIFS('Meta data'!$F$3:$F$20000,'Meta data'!$A$3:$A$20000,">="&$B57,'Meta data'!$A$3:$A$20000,"<="&$C57,'Meta data'!$G$3:$G$20000,"<>Month total") -> 0 | M57: =IF(L57=0,"",D57/L57) | N57: =SUMIFS('Google data'!$F$3:$F$20000,'Google data'!$A$3:$A$20000,">="&$B57,'Google data'!$A$3:$A$20000,"<="&$C57,'Google data'!$G$3:$G$20000,"<>Month total") -> 0 | O57: =IF(N57=0,"",E57/N57) | S57: =TEXT(B57,"d mmm") -> 28 Dec
A59: Week 1 includes the last days of the previous year. Over/under plan is shown for complete weeks with data. Notes marked 'Agency:' are summarised from the agency's weekly reports.
A61: WEEKLY SPEND BY CHANNEL (platform data)

Sheet Monthly
A1: Monthly spend
A2: ="Amounts in "&Settings!$C$6&" · Google converted from EUR with the Settings rates · platform data up to "&TEXT(Settings!$C$5,"d mmm yyyy") -> Amounts in USD · Google converted from EUR with the Settings rates · platform data up to 30 Sep 2026 | T2: Data up to | U2: =Settings!$C$5 -> 46295
A4: Month | B4: Quarter | C4: Meta | D4: Google Ads | E4: ChatGPT Ads | F4: LinkedIn Ads | G4: Total – all channels | H4: Counts toward budget | I4: Plan (budget spread evenly by day) | J4: Over (+) / under (−) plan | K4: Cumulative spend (budget channels) | L4: Cumulative plan | M4: Maximum | N4: % of budget used | O4: Status | P4: Meta as billed (USD) | Q4: Google as billed (EUR) | R4: EUR → USD rate used | S4: Chart label
A5: =DATE(Settings!$C$12,1,1) -> 46023 | B5: ="Q"&ROUNDUP(MONTH(A5)/3,0) -> Q1 | C5: =SUMIFS('Meta data'!$I$3:$I$20000,'Meta data'!$A$3:$A$20000,">="&$A5,'Meta data'!$A$3:$A$20000,"<="&EOMONTH($A5,0)) -> 8092.51 | D5: =SUMIFS('Google data'!$I$3:$I$20000,'Google data'!$A$3:$A$20000,">="&$A5,'Google data'!$A$3:$A$20000,"<="&EOMONTH($A5,0)) -> 10838.862 | E5: =SUMIFS('ChatGPT data'!$I$3:$I$20000,'ChatGPT data'!$A$3:$A$20000,">="&$A5,'ChatGPT data'!$A$3:$A$20000,"<="&EOMONTH($A5,0)) -> 0 | F5: =SUMIFS('LinkedIn data'!$I$3:$I$20000,'LinkedIn data'!$A$3:$A$20000,">="&$A5,'LinkedIn data'!$A$3:$A$20000,"<="&EOMONTH($A5,0)) -> 0 | G5: =SUM(C5:F5) -> 18931.372 | H5: =C5*(Settings!$C$22="Yes")+D5*(Settings!$C$23="Yes")+E5*(Settings!$C$24="Yes")+F5*(Settings!$C$25="Yes") -> 18931.372 | I5: =Settings!$D$16*MAX(0,MIN(EOMONTH($A5,0),Settings!$C$11)-MAX($A5,Settings!$C$10)+1)/(Settings!$C$11-Settings!$C$10+1) -> 25479.452 | J5: =IF(EOMONTH($A5,0)>Settings!$C$5,"",H5-I5) -> -6548.0798 | K5: =IF($A5>Settings!$C$5,"",SUM($H$5:H5)) -> 18931.372 | L5: =SUM($I$5:I5) -> 25479.452 | M5: =Settings!$D$17 -> 320000 | N5: =IF(OR(K5="",Settings!$D$16=0),"",K5/Settings!$D$16) -> 0.063104574 | O5: =IF(EOMONTH($A5,0)<=Settings!$C$5,"Complete",IF($A5<=Settings!$C$5,"In progress","Not started")) -> Complete | P5: =SUMIFS('Meta data'!$C$3:$C$20000,'Meta data'!$A$3:$A$20000,">="&$A5,'Meta data'!$A$3:$A$20000,"<="&EOMONTH($A5,0)) -> 8092.51 | Q5: =SUMIFS('Google data'!$C$3:$C$20000,'Google data'!$A$3:$A$20000,">="&$A5,'Google data'!$A$3:$A$20000,"<="&EOMONTH($A5,0)) -> 9697.47 | R5: =INDEX(Settings!$B$29:$B$40,MONTH(A5)) -> 1.1177 | S5: =TEXT(A5,"mmm") -> Jan
A6: =DATE(Settings!$C$12,2,1) -> 46054 | B6: ="Q"&ROUNDUP(MONTH(A6)/3,0) -> Q1 | C6: =SUMIFS('Meta data'!$I$3:$I$20000,'Meta data'!$A$3:$A$20000,">="&$A6,'Meta data'!$A$3:$A$20000,"<="&EOMONTH($A6,0)) -> 28952.75 | D6: =SUMIFS('Google data'!$I$3:$I$20000,'Google data'!$A$3:$A$20000,">="&$A6,'Google data'!$A$3:$A$20000,"<="&EOMONTH($A6,0)) -> 11084.41 | E6: =SUMIFS('ChatGPT data'!$I$3:$I$20000,'ChatGPT data'!$A$3:$A$20000,">="&$A6,'ChatGPT data'!$A$3:$A$20000,"<="&EOMONTH($A6,0)) -> 0 | F6: =SUMIFS('LinkedIn data'!$I$3:$I$20000,'LinkedIn data'!$A$3:$A$20000,">="&$A6,'LinkedIn data'!$A$3:$A$20000,"<="&EOMONTH($A6,0)) -> 0 | G6: =SUM(C6:F6) -> 40037.16 | H6: =C6*(Settings!$C$22="Yes")+D6*(Settings!$C$23="Yes")+E6*(Settings!$C$24="Yes")+F6*(Settings!$C$25="Yes") -> 40037.16 | I6: =Settings!$D$16*MAX(0,MIN(EOMONTH($A6,0),Settings!$C$11)-MAX($A6,Settings!$C$10)+1)/(Settings!$C$11-Settings!$C$10+1) -> 23013.699 | J6: =IF(EOMONTH($A6,0)>Settings!$C$5,"",H6-I6) -> 17023.461 | K6: =IF($A6>Settings!$C$5,"",SUM($H$5:H6)) -> 58968.532 | L6: =SUM($I$5:I6) -> 48493.151 | M6: =Settings!$D$17 -> 320000 | N6: =IF(OR(K6="",Settings!$D$16=0),"",K6/Settings!$D$16) -> 0.19656177 | O6: =IF(EOMONTH($A6,0)<=Settings!$C$5,"Complete",IF($A6<=Settings!$C$5,"In progress","Not started")) -> Complete | P6: =SUMIFS('Meta data'!$C$3:$C$20000,'Meta data'!$A$3:$A$20000,">="&$A6,'Meta data'!$A$3:$A$20000,"<="&EOMONTH($A6,0)) -> 28952.75 | Q6: =SUMIFS('Google data'!$C$3:$C$20000,'Google data'!$A$3:$A$20000,">="&$A6,'Google data'!$A$3:$A$20000,"<="&EOMONTH($A6,0)) -> 9917.16 | R6: =INDEX(Settings!$B$29:$B$40,MONTH(A6)) -> 1.1177 | S6: =TEXT(A6,"mmm") -> Feb
A7: =DATE(Settings!$C$12,3,1) -> 46082 | B7: ="Q"&ROUNDUP(MONTH(A7)/3,0) -> Q1 | C7: =SUMIFS('Meta data'!$I$3:$I$20000,'Meta data'!$A$3:$A$20000,">="&$A7,'Meta data'!$A$3:$A$20000,"<="&EOMONTH($A7,0)) -> 38386.84 | D7: =SUMIFS('Google data'!$I$3:$I$20000,'Google data'!$A$3:$A$20000,">="&$A7,'Google data'!$A$3:$A$20000,"<="&EOMONTH($A7,0)) -> 10113.218 | E7: =SUMIFS('ChatGPT data'!$I$3:$I$20000,'ChatGPT data'!$A$3:$A$20000,">="&$A7,'ChatGPT data'!$A$3:$A$20000,"<="&EOMONTH($A7,0)) -> 0 | F7: =SUMIFS('LinkedIn data'!$I$3:$I$20000,'LinkedIn data'!$A$3:$A$20000,">="&$A7,'LinkedIn data'!$A$3:$A$20000,"<="&EOMONTH($A7,0)) -> 0 | G7: =SUM(C7:F7) -> 48500.058 | H7: =C7*(Settings!$C$22="Yes")+D7*(Settings!$C$23="Yes")+E7*(Settings!$C$24="Yes")+F7*(Settings!$C$25="Yes") -> 48500.058 | I7: =Settings!$D$16*MAX(0,MIN(EOMONTH($A7,0),Settings!$C$11)-MAX($A7,Settings!$C$10)+1)/(Settings!$C$11-Settings!$C$10+1) -> 25479.452 | J7: =IF(EOMONTH($A7,0)>Settings!$C$5,"",H7-I7) -> 23020.606 | K7: =IF($A7>Settings!$C$5,"",SUM($H$5:H7)) -> 107468.59 | L7: =SUM($I$5:I7) -> 73972.603 | M7: =Settings!$D$17 -> 320000 | N7: =IF(OR(K7="",Settings!$D$16=0),"",K7/Settings!$D$16) -> 0.35822863 | O7: =IF(EOMONTH($A7,0)<=Settings!$C$5,"Complete",IF($A7<=Settings!$C$5,"In progress","Not started")) -> Complete | P7: =SUMIFS('Meta data'!$C$3:$C$20000,'Meta data'!$A$3:$A$20000,">="&$A7,'Meta data'!$A$3:$A$20000,"<="&EOMONTH($A7,0)) -> 38386.84 | Q7: =SUMIFS('Google data'!$C$3:$C$20000,'Google data'!$A$3:$A$20000,">="&$A7,'Google data'!$A$3:$A$20000,"<="&EOMONTH($A7,0)) -> 9048.24 | R7: =INDEX(Settings!$B$29:$B$40,MONTH(A7)) -> 1.1177 | S7: =TEXT(A7,"mmm") -> Mar
A8: =DATE(Settings!$C$12,4,1) -> 46113 | B8: ="Q"&ROUNDUP(MONTH(A8)/3,0) -> Q2 | C8: =SUMIFS('Meta data'!$I$3:$I$20000,'Meta data'!$A$3:$A$20000,">="&$A8,'Meta data'!$A$3:$A$20000,"<="&EOMONTH($A8,0)) -> 22241.56 | D8: =SUMIFS('Google data'!$I$3:$I$20000,'Google data'!$A$3:$A$20000,">="&$A8,'Google data'!$A$3:$A$20000,"<="&EOMONTH($A8,0)) -> 9972.2647 | E8: =SUMIFS('ChatGPT data'!$I$3:$I$20000,'ChatGPT data'!$A$3:$A$20000,">="&$A8,'ChatGPT data'!$A$3:$A$20000,"<="&EOMONTH($A8,0)) -> 0 | F8: =SUMIFS('LinkedIn data'!$I$3:$I$20000,'LinkedIn data'!$A$3:$A$20000,">="&$A8,'LinkedIn data'!$A$3:$A$20000,"<="&EOMONTH($A8,0)) -> 0 | G8: =SUM(C8:F8) -> 32213.825 | H8: =C8*(Settings!$C$22="Yes")+D8*(Settings!$C$23="Yes")+E8*(Settings!$C$24="Yes")+F8*(Settings!$C$25="Yes") -> 32213.825 | I8: =Settings!$D$16*MAX(0,MIN(EOMONTH($A8,0),Settings!$C$11)-MAX($A8,Settings!$C$10)+1)/(Settings!$C$11-Settings!$C$10+1) -> 24657.534 | J8: =IF(EOMONTH($A8,0)>Settings!$C$5,"",H8-I8) -> 7556.2905 | K8: =IF($A8>Settings!$C$5,"",SUM($H$5:H8)) -> 139682.41 | L8: =SUM($I$5:I8) -> 98630.137 | M8: =Settings!$D$17 -> 320000 | N8: =IF(OR(K8="",Settings!$D$16=0),"",K8/Settings!$D$16) -> 0.46560805 | O8: =IF(EOMONTH($A8,0)<=Settings!$C$5,"Complete",IF($A8<=Settings!$C$5,"In progress","Not started")) -> Complete | P8: =SUMIFS('Meta data'!$C$3:$C$20000,'Meta data'!$A$3:$A$20000,">="&$A8,'Meta data'!$A$3:$A$20000,"<="&EOMONTH($A8,0)) -> 22241.56 | Q8: =SUMIFS('Google data'!$C$3:$C$20000,'Google data'!$A$3:$A$20000,">="&$A8,'Google data'!$A$3:$A$20000,"<="&EOMONTH($A8,0)) -> 8922.13 | R8: =INDEX(Settings!$B$29:$B$40,MONTH(A8)) -> 1.1177 | S8: =TEXT(A8,"mmm") -> Apr
A9: =DATE(Settings!$C$12,5,1) -> 46143 | B9: ="Q"&ROUNDUP(MONTH(A9)/3,0) -> Q2 | C9: =SUMIFS('Meta data'!$I$3:$I$20000,'Meta data'!$A$3:$A$20000,">="&$A9,'Meta data'!$A$3:$A$20000,"<="&EOMONTH($A9,0)) -> 22276.5 | D9: =SUMIFS('Google data'!$I$3:$I$20000,'Google data'!$A$3:$A$20000,">="&$A9,'Google data'!$A$3:$A$20000,"<="&EOMONTH($A9,0)) -> 12063.638 | E9: =SUMIFS('ChatGPT data'!$I$3:$I$20000,'ChatGPT data'!$A$3:$A$20000,">="&$A9,'ChatGPT data'!$A$3:$A$20000,"<="&EOMONTH($A9,0)) -> 0 | F9: =SUMIFS('LinkedIn data'!$I$3:$I$20000,'LinkedIn data'!$A$3:$A$20000,">="&$A9,'LinkedIn data'!$A$3:$A$20000,"<="&EOMONTH($A9,0)) -> 0 | G9: =SUM(C9:F9) -> 34340.138 | H9: =C9*(Settings!$C$22="Yes")+D9*(Settings!$C$23="Yes")+E9*(Settings!$C$24="Yes")+F9*(Settings!$C$25="Yes") -> 34340.138 | I9: =Settings!$D$16*MAX(0,MIN(EOMONTH($A9,0),Settings!$C$11)-MAX($A9,Settings!$C$10)+1)/(Settings!$C$11-Settings!$C$10+1) -> 25479.452 | J9: =IF(EOMONTH($A9,0)>Settings!$C$5,"",H9-I9) -> 8860.6858 | K9: =IF($A9>Settings!$C$5,"",SUM($H$5:H9)) -> 174022.55 | L9: =SUM($I$5:I9) -> 124109.59 | M9: =Settings!$D$17 -> 320000 | N9: =IF(OR(K9="",Settings!$D$16=0),"",K9/Settings!$D$16) -> 0.58007517 | O9: =IF(EOMONTH($A9,0)<=Settings!$C$5,"Complete",IF($A9<=Settings!$C$5,"In progress","Not started")) -> Complete | P9: =SUMIFS('Meta data'!$C$3:$C$20000,'Meta data'!$A$3:$A$20000,">="&$A9,'Meta data'!$A$3:$A$20000,"<="&EOMONTH($A9,0)) -> 22276.5 | Q9: =SUMIFS('Google data'!$C$3:$C$20000,'Google data'!$A$3:$A$20000,">="&$A9,'Google data'!$A$3:$A$20000,"<="&EOMONTH($A9,0)) -> 10793.27 | R9: =INDEX(Settings!$B$29:$B$40,MONTH(A9)) -> 1.1177 | S9: =TEXT(A9,"mmm") -> May
A10: =DATE(Settings!$C$12,6,1) -> 46174 | B10: ="Q"&ROUNDUP(MONTH(A10)/3,0) -> Q2 | C10: =SUMIFS('Meta data'!$I$3:$I$20000,'Meta data'!$A$3:$A$20000,">="&$A10,'Meta data'!$A$3:$A$20000,"<="&EOMONTH($A10,0)) -> 17453.29 | D10: =SUMIFS('Google data'!$I$3:$I$20000,'Google data'!$A$3:$A$20000,">="&$A10,'Google data'!$A$3:$A$20000,"<="&EOMONTH($A10,0)) -> 13956.373 | E10: =SUMIFS('ChatGPT data'!$I$3:$I$20000,'ChatGPT data'!$A$3:$A$20000,">="&$A10,'ChatGPT data'!$A$3:$A$20000,"<="&EOMONTH($A10,0)) -> 0 | F10: =SUMIFS('LinkedIn data'!$I$3:$I$20000,'LinkedIn data'!$A$3:$A$20000,">="&$A10,'LinkedIn data'!$A$3:$A$20000,"<="&EOMONTH($A10,0)) -> 0 | G10: =SUM(C10:F10) -> 31409.663 | H10: =C10*(Settings!$C$22="Yes")+D10*(Settings!$C$23="Yes")+E10*(Settings!$C$24="Yes")+F10*(Settings!$C$25="Yes") -> 31409.663 | I10: =Settings!$D$16*MAX(0,MIN(EOMONTH($A10,0),Settings!$C$11)-MAX($A10,Settings!$C$10)+1)/(Settings!$C$11-Settings!$C$10+1) -> 24657.534 | J10: =IF(EOMONTH($A10,0)>Settings!$C$5,"",H10-I10) -> 6752.1292 | K10: =IF($A10>Settings!$C$5,"",SUM($H$5:H10)) -> 205432.22 | L10: =SUM($I$5:I10) -> 148767.12 | M10: =Settings!$D$17 -> 320000 | N10: =IF(OR(K10="",Settings!$D$16=0),"",K10/Settings!$D$16) -> 0.68477405 | O10: =IF(EOMONTH($A10,0)<=Settings!$C$5,"Complete",IF($A10<=Settings!$C$5,"In progress","Not started")) -> Complete | P10: =SUMIFS('Meta data'!$C$3:$C$20000,'Meta data'!$A$3:$A$20000,">="&$A10,'Meta data'!$A$3:$A$20000,"<="&EOMONTH($A10,0)) -> 17453.29 | Q10: =SUMIFS('Google data'!$C$3:$C$20000,'Google data'!$A$3:$A$20000,">="&$A10,'Google data'!$A$3:$A$20000,"<="&EOMONTH($A10,0)) -> 12486.69 | R10: =INDEX(Settings!$B$29:$B$40,MONTH(A10)) -> 1.1177 | S10: =TEXT(A10,"mmm") -> Jun
A11: =DATE(Settings!$C$12,7,1) -> 46204 | B11: ="Q"&ROUNDUP(MONTH(A11)/3,0) -> Q3 | C11: =SUMIFS('Meta data'!$I$3:$I$20000,'Meta data'!$A$3:$A$20000,">="&$A11,'Meta data'!$A$3:$A$20000,"<="&EOMONTH($A11,0)) -> 18956.66 | D11: =SUMIFS('Google data'!$I$3:$I$20000,'Google data'!$A$3:$A$20000,">="&$A11,'Google data'!$A$3:$A$20000,"<="&EOMONTH($A11,0)) -> 13148.198 | E11: =SUMIFS('ChatGPT data'!$I$3:$I$20000,'ChatGPT data'!$A$3:$A$20000,">="&$A11,'ChatGPT data'!$A$3:$A$20000,"<="&EOMONTH($A11,0)) -> 0 | F11: =SUMIFS('LinkedIn data'!$I$3:$I$20000,'LinkedIn data'!$A$3:$A$20000,">="&$A11,'LinkedIn data'!$A$3:$A$20000,"<="&EOMONTH($A11,0)) -> 0 | G11: =SUM(C11:F11) -> 32104.858 | H11: =C11*(Settings!$C$22="Yes")+D11*(Settings!$C$23="Yes")+E11*(Settings!$C$24="Yes")+F11*(Settings!$C$25="Yes") -> 32104.858 | I11: =Settings!$D$16*MAX(0,MIN(EOMONTH($A11,0),Settings!$C$11)-MAX($A11,Settings!$C$10)+1)/(Settings!$C$11-Settings!$C$10+1) -> 25479.452 | J11: =IF(EOMONTH($A11,0)>Settings!$C$5,"",H11-I11) -> 6625.406 | K11: =IF($A11>Settings!$C$5,"",SUM($H$5:H11)) -> 237537.07 | L11: =SUM($I$5:I11) -> 174246.58 | M11: =Settings!$D$17 -> 320000 | N11: =IF(OR(K11="",Settings!$D$16=0),"",K11/Settings!$D$16) -> 0.79179025 | O11: =IF(EOMONTH($A11,0)<=Settings!$C$5,"Complete",IF($A11<=Settings!$C$5,"In progress","Not started")) -> Complete | P11: =SUMIFS('Meta data'!$C$3:$C$20000,'Meta data'!$A$3:$A$20000,">="&$A11,'Meta data'!$A$3:$A$20000,"<="&EOMONTH($A11,0)) -> 18956.66 | Q11: =SUMIFS('Google data'!$C$3:$C$20000,'Google data'!$A$3:$A$20000,">="&$A11,'Google data'!$A$3:$A$20000,"<="&EOMONTH($A11,0)) -> 11763.62 | R11: =INDEX(Settings!$B$29:$B$40,MONTH(A11)) -> 1.1177 | S11: =TEXT(A11,"mmm") -> Jul
A12: =DATE(Settings!$C$12,8,1) -> 46235 | B12: ="Q"&ROUNDUP(MONTH(A12)/3,0) -> Q3 | C12: =SUMIFS('Meta data'!$I$3:$I$20000,'Meta data'!$A$3:$A$20000,">="&$A12,'Meta data'!$A$3:$A$20000,"<="&EOMONTH($A12,0)) -> 10643.94 | D12: =SUMIFS('Google data'!$I$3:$I$20000,'Google data'!$A$3:$A$20000,">="&$A12,'Google data'!$A$3:$A$20000,"<="&EOMONTH($A12,0)) -> 12246.583 | E12: =SUMIFS('ChatGPT data'!$I$3:$I$20000,'ChatGPT data'!$A$3:$A$20000,">="&$A12,'ChatGPT data'!$A$3:$A$20000,"<="&EOMONTH($A12,0)) -> 0 | F12: =SUMIFS('LinkedIn data'!$I$3:$I$20000,'LinkedIn data'!$A$3:$A$20000,">="&$A12,'LinkedIn data'!$A$3:$A$20000,"<="&EOMONTH($A12,0)) -> 0 | G12: =SUM(C12:F12) -> 22890.523 | H12: =C12*(Settings!$C$22="Yes")+D12*(Settings!$C$23="Yes")+E12*(Settings!$C$24="Yes")+F12*(Settings!$C$25="Yes") -> 22890.523 | I12: =Settings!$D$16*MAX(0,MIN(EOMONTH($A12,0),Settings!$C$11)-MAX($A12,Settings!$C$10)+1)/(Settings!$C$11-Settings!$C$10+1) -> 25479.452 | J12: =IF(EOMONTH($A12,0)>Settings!$C$5,"",H12-I12) -> -2588.929 | K12: =IF($A12>Settings!$C$5,"",SUM($H$5:H12)) -> 260427.6 | L12: =SUM($I$5:I12) -> 199726.03 | M12: =Settings!$D$17 -> 320000 | N12: =IF(OR(K12="",Settings!$D$16=0),"",K12/Settings!$D$16) -> 0.86809199 | O12: =IF(EOMONTH($A12,0)<=Settings!$C$5,"Complete",IF($A12<=Settings!$C$5,"In progress","Not started")) -> Complete | P12: =SUMIFS('Meta data'!$C$3:$C$20000,'Meta data'!$A$3:$A$20000,">="&$A12,'Meta data'!$A$3:$A$20000,"<="&EOMONTH($A12,0)) -> 10643.94 | Q12: =SUMIFS('Google data'!$C$3:$C$20000,'Google data'!$A$3:$A$20000,">="&$A12,'Google data'!$A$3:$A$20000,"<="&EOMONTH($A12,0)) -> 10956.95 | R12: =INDEX(Settings!$B$29:$B$40,MONTH(A12)) -> 1.1177 | S12: =TEXT(A12,"mmm") -> Aug
A13: =DATE(Settings!$C$12,9,1) -> 46266 | B13: ="Q"&ROUNDUP(MONTH(A13)/3,0) -> Q3 | C13: =SUMIFS('Meta data'!$I$3:$I$20000,'Meta data'!$A$3:$A$20000,">="&$A13,'Meta data'!$A$3:$A$20000,"<="&EOMONTH($A13,0)) -> 11062.98 | D13: =SUMIFS('Google data'!$I$3:$I$20000,'Google data'!$A$3:$A$20000,">="&$A13,'Google data'!$A$3:$A$20000,"<="&EOMONTH($A13,0)) -> 6854.2282 | E13: =SUMIFS('ChatGPT data'!$I$3:$I$20000,'ChatGPT data'!$A$3:$A$20000,">="&$A13,'ChatGPT data'!$A$3:$A$20000,"<="&EOMONTH($A13,0)) -> 256.57921 | F13: =SUMIFS('LinkedIn data'!$I$3:$I$20000,'LinkedIn data'!$A$3:$A$20000,">="&$A13,'LinkedIn data'!$A$3:$A$20000,"<="&EOMONTH($A13,0)) -> 0 | G13: =SUM(C13:F13) -> 18173.787 | H13: =C13*(Settings!$C$22="Yes")+D13*(Settings!$C$23="Yes")+E13*(Settings!$C$24="Yes")+F13*(Settings!$C$25="Yes") -> 18173.787 | I13: =Settings!$D$16*MAX(0,MIN(EOMONTH($A13,0),Settings!$C$11)-MAX($A13,Settings!$C$10)+1)/(Settings!$C$11-Settings!$C$10+1) -> 24657.534 | J13: =IF(EOMONTH($A13,0)>Settings!$C$5,"",H13-I13) -> -6483.7468 | K13: =IF($A13>Settings!$C$5,"",SUM($H$5:H13)) -> 278601.38 | L13: =SUM($I$5:I13) -> 224383.56 | M13: =Settings!$D$17 -> 320000 | N13: =IF(OR(K13="",Settings!$D$16=0),"",K13/Settings!$D$16) -> 0.92867128 | O13: =IF(EOMONTH($A13,0)<=Settings!$C$5,"Complete",IF($A13<=Settings!$C$5,"In progress","Not started")) -> Complete | P13: =SUMIFS('Meta data'!$C$3:$C$20000,'Meta data'!$A$3:$A$20000,">="&$A13,'Meta data'!$A$3:$A$20000,"<="&EOMONTH($A13,0)) -> 11062.98 | Q13: =SUMIFS('Google data'!$C$3:$C$20000,'Google data'!$A$3:$A$20000,">="&$A13,'Google data'!$A$3:$A$20000,"<="&EOMONTH($A13,0)) -> 6132.44 | R13: =INDEX(Settings!$B$29:$B$40,MONTH(A13)) -> 1.1177 | S13: =TEXT(A13,"mmm") -> Sep
A14: =DATE(Settings!$C$12,10,1) -> 46296 | B14: ="Q"&ROUNDUP(MONTH(A14)/3,0) -> Q4 | C14: =SUMIFS('Meta data'!$I$3:$I$20000,'Meta data'!$A$3:$A$20000,">="&$A14,'Meta data'!$A$3:$A$20000,"<="&EOMONTH($A14,0)) -> 0 | D14: =SUMIFS('Google data'!$I$3:$I$20000,'Google data'!$A$3:$A$20000,">="&$A14,'Google data'!$A$3:$A$20000,"<="&EOMONTH($A14,0)) -> 0 | E14: =SUMIFS('ChatGPT data'!$I$3:$I$20000,'ChatGPT data'!$A$3:$A$20000,">="&$A14,'ChatGPT data'!$A$3:$A$20000,"<="&EOMONTH($A14,0)) -> 0 | F14: =SUMIFS('LinkedIn data'!$I$3:$I$20000,'LinkedIn data'!$A$3:$A$20000,">="&$A14,'LinkedIn data'!$A$3:$A$20000,"<="&EOMONTH($A14,0)) -> 0 | G14: =SUM(C14:F14) -> 0 | H14: =C14*(Settings!$C$22="Yes")+D14*(Settings!$C$23="Yes")+E14*(Settings!$C$24="Yes")+F14*(Settings!$C$25="Yes") -> 0 | I14: =Settings!$D$16*MAX(0,MIN(EOMONTH($A14,0),Settings!$C$11)-MAX($A14,Settings!$C$10)+1)/(Settings!$C$11-Settings!$C$10+1) -> 25479.452 | J14: =IF(EOMONTH($A14,0)>Settings!$C$5,"",H14-I14) | K14: =IF($A14>Settings!$C$5,"",SUM($H$5:H14)) | L14: =SUM($I$5:I14) -> 249863.01 | M14: =Settings!$D$17 -> 320000 | N14: =IF(OR(K14="",Settings!$D$16=0),"",K14/Settings!$D$16) | O14: =IF(EOMONTH($A14,0)<=Settings!$C$5,"Complete",IF($A14<=Settings!$C$5,"In progress","Not started")) -> Not started | P14: =SUMIFS('Meta data'!$C$3:$C$20000,'Meta data'!$A$3:$A$20000,">="&$A14,'Meta data'!$A$3:$A$20000,"<="&EOMONTH($A14,0)) -> 0 | Q14: =SUMIFS('Google data'!$C$3:$C$20000,'Google data'!$A$3:$A$20000,">="&$A14,'Google data'!$A$3:$A$20000,"<="&EOMONTH($A14,0)) -> 0 | R14: =INDEX(Settings!$B$29:$B$40,MONTH(A14)) -> 1.1177 | S14: =TEXT(A14,"mmm") -> Oct
A15: =DATE(Settings!$C$12,11,1) -> 46327 | B15: ="Q"&ROUNDUP(MONTH(A15)/3,0) -> Q4 | C15: =SUMIFS('Meta data'!$I$3:$I$20000,'Meta data'!$A$3:$A$20000,">="&$A15,'Meta data'!$A$3:$A$20000,"<="&EOMONTH($A15,0)) -> 0 | D15: =SUMIFS('Google data'!$I$3:$I$20000,'Google data'!$A$3:$A$20000,">="&$A15,'Google data'!$A$3:$A$20000,"<="&EOMONTH($A15,0)) -> 0 | E15: =SUMIFS('ChatGPT data'!$I$3:$I$20000,'ChatGPT data'!$A$3:$A$20000,">="&$A15,'ChatGPT data'!$A$3:$A$20000,"<="&EOMONTH($A15,0)) -> 0 | F15: =SUMIFS('LinkedIn data'!$I$3:$I$20000,'LinkedIn data'!$A$3:$A$20000,">="&$A15,'LinkedIn data'!$A$3:$A$20000,"<="&EOMONTH($A15,0)) -> 0 | G15: =SUM(C15:F15) -> 0 | H15: =C15*(Settings!$C$22="Yes")+D15*(Settings!$C$23="Yes")+E15*(Settings!$C$24="Yes")+F15*(Settings!$C$25="Yes") -> 0 | I15: =Settings!$D$16*MAX(0,MIN(EOMONTH($A15,0),Settings!$C$11)-MAX($A15,Settings!$C$10)+1)/(Settings!$C$11-Settings!$C$10+1) -> 24657.534 | J15: =IF(EOMONTH($A15,0)>Settings!$C$5,"",H15-I15) | K15: =IF($A15>Settings!$C$5,"",SUM($H$5:H15)) | L15: =SUM($I$5:I15) -> 274520.55 | M15: =Settings!$D$17 -> 320000 | N15: =IF(OR(K15="",Settings!$D$16=0),"",K15/Settings!$D$16) | O15: =IF(EOMONTH($A15,0)<=Settings!$C$5,"Complete",IF($A15<=Settings!$C$5,"In progress","Not started")) -> Not started | P15: =SUMIFS('Meta data'!$C$3:$C$20000,'Meta data'!$A$3:$A$20000,">="&$A15,'Meta data'!$A$3:$A$20000,"<="&EOMONTH($A15,0)) -> 0 | Q15: =SUMIFS('Google data'!$C$3:$C$20000,'Google data'!$A$3:$A$20000,">="&$A15,'Google data'!$A$3:$A$20000,"<="&EOMONTH($A15,0)) -> 0 | R15: =INDEX(Settings!$B$29:$B$40,MONTH(A15)) -> 1.1177 | S15: =TEXT(A15,"mmm") -> Nov
A16: =DATE(Settings!$C$12,12,1) -> 46357 | B16: ="Q"&ROUNDUP(MONTH(A16)/3,0) -> Q4 | C16: =SUMIFS('Meta data'!$I$3:$I$20000,'Meta data'!$A$3:$A$20000,">="&$A16,'Meta data'!$A$3:$A$20000,"<="&EOMONTH($A16,0)) -> 0 | D16: =SUMIFS('Google data'!$I$3:$I$20000,'Google data'!$A$3:$A$20000,">="&$A16,'Google data'!$A$3:$A$20000,"<="&EOMONTH($A16,0)) -> 0 | E16: =SUMIFS('ChatGPT data'!$I$3:$I$20000,'ChatGPT data'!$A$3:$A$20000,">="&$A16,'ChatGPT data'!$A$3:$A$20000,"<="&EOMONTH($A16,0)) -> 0 | F16: =SUMIFS('LinkedIn data'!$I$3:$I$20000,'LinkedIn data'!$A$3:$A$20000,">="&$A16,'LinkedIn data'!$A$3:$A$20000,"<="&EOMONTH($A16,0)) -> 0 | G16: =SUM(C16:F16) -> 0 | H16: =C16*(Settings!$C$22="Yes")+D16*(Settings!$C$23="Yes")+E16*(Settings!$C$24="Yes")+F16*(Settings!$C$25="Yes") -> 0 | I16: =Settings!$D$16*MAX(0,MIN(EOMONTH($A16,0),Settings!$C$11)-MAX($A16,Settings!$C$10)+1)/(Settings!$C$11-Settings!$C$10+1) -> 25479.452 | J16: =IF(EOMONTH($A16,0)>Settings!$C$5,"",H16-I16) | K16: =IF($A16>Settings!$C$5,"",SUM($H$5:H16)) | L16: =SUM($I$5:I16) -> 300000 | M16: =Settings!$D$17 -> 320000 | N16: =IF(OR(K16="",Settings!$D$16=0),"",K16/Settings!$D$16) | O16: =IF(EOMONTH($A16,0)<=Settings!$C$5,"Complete",IF($A16<=Settings!$C$5,"In progress","Not started")) -> Not started | P16: =SUMIFS('Meta data'!$C$3:$C$20000,'Meta data'!$A$3:$A$20000,">="&$A16,'Meta data'!$A$3:$A$20000,"<="&EOMONTH($A16,0)) -> 0 | Q16: =SUMIFS('Google data'!$C$3:$C$20000,'Google data'!$A$3:$A$20000,">="&$A16,'Google data'!$A$3:$A$20000,"<="&EOMONTH($A16,0)) -> 0 | R16: =INDEX(Settings!$B$29:$B$40,MONTH(A16)) -> 1.1177 | S16: =TEXT(A16,"mmm") -> Dec
A17: Total | C17: =SUM(C5:C16) -> 178067.03 | D17: =SUM(D5:D16) -> 100277.78 | E17: =SUM(E5:E16) -> 256.57921 | F17: =SUM(F5:F16) -> 0 | G17: =SUM(G5:G16) -> 278601.38 | H17: =SUM(H5:H16) -> 278601.38 | I17: =SUM(I5:I16) -> 300000 | J17: =SUM(J5:J16) -> 54217.823 | P17: =SUM(P5:P16) -> 178067.03 | Q17: =SUM(Q5:Q16) -> 89717.97
A18: Over/under plan is shown for complete months only. The plan spreads the annual budget evenly over the days of the year.
A21: CLICKS, CONVERSIONS AND COSTS – as reported by each platform
B22: Meta | F22: Google Ads | J22: ChatGPT Ads
A23: Month | B23: Clicks | C23: Conversions | D23: Cost per click | E23: Cost per conversion | F23: Clicks | G23: Conversions | H23: Cost per click | I23: Cost per conversion | J23: Clicks | K23: Conversions | L23: Cost per click | M23: Cost per conversion
A24: =A5 -> 46023 | B24: =SUMIFS('Meta data'!$E$3:$E$20000,'Meta data'!$A$3:$A$20000,">="&$A24,'Meta data'!$A$3:$A$20000,"<="&EOMONTH($A24,0)) -> 7240 | C24: =SUMIFS('Meta data'!$F$3:$F$20000,'Meta data'!$A$3:$A$20000,">="&$A24,'Meta data'!$A$3:$A$20000,"<="&EOMONTH($A24,0)) -> 719 | D24: =IF(B24=0,"",C5/B24) -> 1.11775 | E24: =IF(C24=0,"",C5/C24) -> 11.255229 | F24: =SUMIFS('Google data'!$E$3:$E$20000,'Google data'!$A$3:$A$20000,">="&$A24,'Google data'!$A$3:$A$20000,"<="&EOMONTH($A24,0)) -> 49631 | G24: =SUMIFS('Google data'!$F$3:$F$20000,'Google data'!$A$3:$A$20000,">="&$A24,'Google data'!$A$3:$A$20000,"<="&EOMONTH($A24,0)) -> 224.08 | H24: =IF(F24=0,"",D5/F24) -> 0.21838895 | I24: =IF(G24=0,"",D5/G24) -> 48.370503 | J24: =SUMIFS('ChatGPT data'!$E$3:$E$20000,'ChatGPT data'!$A$3:$A$20000,">="&$A24,'ChatGPT data'!$A$3:$A$20000,"<="&EOMONTH($A24,0)) -> 0 | K24: =SUMIFS('ChatGPT data'!$F$3:$F$20000,'ChatGPT data'!$A$3:$A$20000,">="&$A24,'ChatGPT data'!$A$3:$A$20000,"<="&EOMONTH($A24,0)) -> 0 | L24: =IF(J24=0,"",E5/J24) | M24: =IF(K24=0,"",E5/K24)
A25: =A6 -> 46054 | B25: =SUMIFS('Meta data'!$E$3:$E$20000,'Meta data'!$A$3:$A$20000,">="&$A25,'Meta data'!$A$3:$A$20000,"<="&EOMONTH($A25,0)) -> 22402 | C25: =SUMIFS('Meta data'!$F$3:$F$20000,'Meta data'!$A$3:$A$20000,">="&$A25,'Meta data'!$A$3:$A$20000,"<="&EOMONTH($A25,0)) -> 1557 | D25: =IF(B25=0,"",C6/B25) -> 1.2924181 | E25: =IF(C25=0,"",C6/C25) -> 18.595215 | F25: =SUMIFS('Google data'!$E$3:$E$20000,'Google data'!$A$3:$A$20000,">="&$A25,'Google data'!$A$3:$A$20000,"<="&EOMONTH($A25,0)) -> 9835 | G25: =SUMIFS('Google data'!$F$3:$F$20000,'Google data'!$A$3:$A$20000,">="&$A25,'Google data'!$A$3:$A$20000,"<="&EOMONTH($A25,0)) -> 151.23 | H25: =IF(F25=0,"",D6/F25) -> 1.1270371 | I25: =IF(G25=0,"",D6/G25) -> 73.295046 | J25: =SUMIFS('ChatGPT data'!$E$3:$E$20000,'ChatGPT data'!$A$3:$A$20000,">="&$A25,'ChatGPT data'!$A$3:$A$20000,"<="&EOMONTH($A25,0)) -> 0 | K25: =SUMIFS('ChatGPT data'!$F$3:$F$20000,'ChatGPT data'!$A$3:$A$20000,">="&$A25,'ChatGPT data'!$A$3:$A$20000,"<="&EOMONTH($A25,0)) -> 0 | L25: =IF(J25=0,"",E6/J25) | M25: =IF(K25=0,"",E6/K25)
A26: =A7 -> 46082 | B26: =SUMIFS('Meta data'!$E$3:$E$20000,'Meta data'!$A$3:$A$20000,">="&$A26,'Meta data'!$A$3:$A$20000,"<="&EOMONTH($A26,0)) -> 18722 | C26: =SUMIFS('Meta data'!$F$3:$F$20000,'Meta data'!$A$3:$A$20000,">="&$A26,'Meta data'!$A$3:$A$20000,"<="&EOMONTH($A26,0)) -> 1516 | D26: =IF(B26=0,"",C7/B26) -> 2.05036 | E26: =IF(C26=0,"",C7/C26) -> 25.321135 | F26: =SUMIFS('Google data'!$E$3:$E$20000,'Google data'!$A$3:$A$20000,">="&$A26,'Google data'!$A$3:$A$20000,"<="&EOMONTH($A26,0)) -> 3244 | G26: =SUMIFS('Google data'!$F$3:$F$20000,'Google data'!$A$3:$A$20000,">="&$A26,'Google data'!$A$3:$A$20000,"<="&EOMONTH($A26,0)) -> 150.25 | H26: =IF(F26=0,"",D7/F26) -> 3.1175147 | I26: =IF(G26=0,"",D7/G26) -> 67.30927 | J26: =SUMIFS('ChatGPT data'!$E$3:$E$20000,'ChatGPT data'!$A$3:$A$20000,">="&$A26,'ChatGPT data'!$A$3:$A$20000,"<="&EOMONTH($A26,0)) -> 0 | K26: =SUMIFS('ChatGPT data'!$F$3:$F$20000,'ChatGPT data'!$A$3:$A$20000,">="&$A26,'ChatGPT data'!$A$3:$A$20000,"<="&EOMONTH($A26,0)) -> 0 | L26: =IF(J26=0,"",E7/J26) | M26: =IF(K26=0,"",E7/K26)
A27: =A8 -> 46113 | B27: =SUMIFS('Meta data'!$E$3:$E$20000,'Meta data'!$A$3:$A$20000,">="&$A27,'Meta data'!$A$3:$A$20000,"<="&EOMONTH($A27,0)) -> 11067 | C27: =SUMIFS('Meta data'!$F$3:$F$20000,'Meta data'!$A$3:$A$20000,">="&$A27,'Meta data'!$A$3:$A$20000,"<="&EOMONTH($A27,0)) -> 876 | D27: =IF(B27=0,"",C8/B27) -> 2.009719 | E27: =IF(C27=0,"",C8/C27) -> 25.389909 | F27: =SUMIFS('Google data'!$E$3:$E$20000,'Google data'!$A$3:$A$20000,">="&$A27,'Google data'!$A$3:$A$20000,"<="&EOMONTH($A27,0)) -> 2903 | G27: =SUMIFS('Google data'!$F$3:$F$20000,'Google data'!$A$3:$A$20000,">="&$A27,'Google data'!$A$3:$A$20000,"<="&EOMONTH($A27,0)) -> 118.59 | H27: =IF(F27=0,"",D8/F27) -> 3.4351584 | I27: =IF(G27=0,"",D8/G27) -> 84.090266 | J27: =SUMIFS('ChatGPT data'!$E$3:$E$20000,'ChatGPT data'!$A$3:$A$20000,">="&$A27,'ChatGPT data'!$A$3:$A$20000,"<="&EOMONTH($A27,0)) -> 0 | K27: =SUMIFS('ChatGPT data'!$F$3:$F$20000,'ChatGPT data'!$A$3:$A$20000,">="&$A27,'ChatGPT data'!$A$3:$A$20000,"<="&EOMONTH($A27,0)) -> 0 | L27: =IF(J27=0,"",E8/J27) | M27: =IF(K27=0,"",E8/K27)
A28: =A9 -> 46143 | B28: =SUMIFS('Meta data'!$E$3:$E$20000,'Meta data'!$A$3:$A$20000,">="&$A28,'Meta data'!$A$3:$A$20000,"<="&EOMONTH($A28,0)) -> 8317 | C28: =SUMIFS('Meta data'!$F$3:$F$20000,'Meta data'!$A$3:$A$20000,">="&$A28,'Meta data'!$A$3:$A$20000,"<="&EOMONTH($A28,0)) -> 632 | D28: =IF(B28=0,"",C9/B28) -> 2.6784297 | E28: =IF(C28=0,"",C9/C28) -> 35.247627 | F28: =SUMIFS('Google data'!$E$3:$E$20000,'Google data'!$A$3:$A$20000,">="&$A28,'Google data'!$A$3:$A$20000,"<="&EOMONTH($A28,0)) -> 2889 | G28: =SUMIFS('Google data'!$F$3:$F$20000,'Google data'!$A$3:$A$20000,">="&$A28,'Google data'!$A$3:$A$20000,"<="&EOMONTH($A28,0)) -> 142.1 | H28: =IF(F28=0,"",D9/F28) -> 4.175714 | I28: =IF(G28=0,"",D9/G28) -> 84.895411 | J28: =SUMIFS('ChatGPT data'!$E$3:$E$20000,'ChatGPT data'!$A$3:$A$20000,">="&$A28,'ChatGPT data'!$A$3:$A$20000,"<="&EOMONTH($A28,0)) -> 0 | K28: =SUMIFS('ChatGPT data'!$F$3:$F$20000,'ChatGPT data'!$A$3:$A$20000,">="&$A28,'ChatGPT data'!$A$3:$A$20000,"<="&EOMONTH($A28,0)) -> 0 | L28: =IF(J28=0,"",E9/J28) | M28: =IF(K28=0,"",E9/K28)
A29: =A10 -> 46174 | B29: =SUMIFS('Meta data'!$E$3:$E$20000,'Meta data'!$A$3:$A$20000,">="&$A29,'Meta data'!$A$3:$A$20000,"<="&EOMONTH($A29,0)) -> 6676 | C29: =SUMIFS('Meta data'!$F$3:$F$20000,'Meta data'!$A$3:$A$20000,">="&$A29,'Meta data'!$A$3:$A$20000,"<="&EOMONTH($A29,0)) -> 485 | D29: =IF(B29=0,"",C10/B29) -> 2.6143334 | E29: =IF(C29=0,"",C10/C29) -> 35.986165 | F29: =SUMIFS('Google data'!$E$3:$E$20000,'Google data'!$A$3:$A$20000,">="&$A29,'Google data'!$A$3:$A$20000,"<="&EOMONTH($A29,0)) -> 4356 | G29: =SUMIFS('Google data'!$F$3:$F$20000,'Google data'!$A$3:$A$20000,">="&$A29,'Google data'!$A$3:$A$20000,"<="&EOMONTH($A29,0)) -> 156.86 | H29: =IF(F29=0,"",D10/F29) -> 3.2039425 | I29: =IF(G29=0,"",D10/G29) -> 88.973438 | J29: =SUMIFS('ChatGPT data'!$E$3:$E$20000,'ChatGPT data'!$A$3:$A$20000,">="&$A29,'ChatGPT data'!$A$3:$A$20000,"<="&EOMONTH($A29,0)) -> 0 | K29: =SUMIFS('ChatGPT data'!$F$3:$F$20000,'ChatGPT data'!$A$3:$A$20000,">="&$A29,'ChatGPT data'!$A$3:$A$20000,"<="&EOMONTH($A29,0)) -> 0 | L29: =IF(J29=0,"",E10/J29) | M29: =IF(K29=0,"",E10/K29)
A30: =A11 -> 46204 | B30: =SUMIFS('Meta data'!$E$3:$E$20000,'Meta data'!$A$3:$A$20000,">="&$A30,'Meta data'!$A$3:$A$20000,"<="&EOMONTH($A30,0)) -> 11374 | C30: =SUMIFS('Meta data'!$F$3:$F$20000,'Meta data'!$A$3:$A$20000,">="&$A30,'Meta data'!$A$3:$A$20000,"<="&EOMONTH($A30,0)) -> 284 | D30: =IF(B30=0,"",C11/B30) -> 1.6666661 | E30: =IF(C30=0,"",C11/C30) -> 66.748803 | F30: =SUMIFS('Google data'!$E$3:$E$20000,'Google data'!$A$3:$A$20000,">="&$A30,'Google data'!$A$3:$A$20000,"<="&EOMONTH($A30,0)) -> 4963 | G30: =SUMIFS('Google data'!$F$3:$F$20000,'Google data'!$A$3:$A$20000,">="&$A30,'Google data'!$A$3:$A$20000,"<="&EOMONTH($A30,0)) -> 68.56 | H30: =IF(F30=0,"",D11/F30) -> 2.649244 | I30: =IF(G30=0,"",D11/G30) -> 191.77652 | J30: =SUMIFS('ChatGPT data'!$E$3:$E$20000,'ChatGPT data'!$A$3:$A$20000,">="&$A30,'ChatGPT data'!$A$3:$A$20000,"<="&EOMONTH($A30,0)) -> 0 | K30: =SUMIFS('ChatGPT data'!$F$3:$F$20000,'ChatGPT data'!$A$3:$A$20000,">="&$A30,'ChatGPT data'!$A$3:$A$20000,"<="&EOMONTH($A30,0)) -> 0 | L30: =IF(J30=0,"",E11/J30) | M30: =IF(K30=0,"",E11/K30)
A31: =A12 -> 46235 | B31: =SUMIFS('Meta data'!$E$3:$E$20000,'Meta data'!$A$3:$A$20000,">="&$A31,'Meta data'!$A$3:$A$20000,"<="&EOMONTH($A31,0)) -> 15505 | C31: =SUMIFS('Meta data'!$F$3:$F$20000,'Meta data'!$A$3:$A$20000,">="&$A31,'Meta data'!$A$3:$A$20000,"<="&EOMONTH($A31,0)) -> 489 | D31: =IF(B31=0,"",C12/B31) -> 0.68648436 | E31: =IF(C31=0,"",C12/C31) -> 21.766748 | F31: =SUMIFS('Google data'!$E$3:$E$20000,'Google data'!$A$3:$A$20000,">="&$A31,'Google data'!$A$3:$A$20000,"<="&EOMONTH($A31,0)) -> 8114 | G31: =SUMIFS('Google data'!$F$3:$F$20000,'Google data'!$A$3:$A$20000,">="&$A31,'Google data'!$A$3:$A$20000,"<="&EOMONTH($A31,0)) -> 272.85 | H31: =IF(F31=0,"",D12/F31) -> 1.5093151 | I31: =IF(G31=0,"",D12/G31) -> 44.88394 | J31: =SUMIFS('ChatGPT data'!$E$3:$E$20000,'ChatGPT data'!$A$3:$A$20000,">="&$A31,'ChatGPT data'!$A$3:$A$20000,"<="&EOMONTH($A31,0)) -> 0 | K31: =SUMIFS('ChatGPT data'!$F$3:$F$20000,'ChatGPT data'!$A$3:$A$20000,">="&$A31,'ChatGPT data'!$A$3:$A$20000,"<="&EOMONTH($A31,0)) -> 0 | L31: =IF(J31=0,"",E12/J31) | M31: =IF(K31=0,"",E12/K31)
A32: =A13 -> 46266 | B32: =SUMIFS('Meta data'!$E$3:$E$20000,'Meta data'!$A$3:$A$20000,">="&$A32,'Meta data'!$A$3:$A$20000,"<="&EOMONTH($A32,0)) -> 89293 | C32: =SUMIFS('Meta data'!$F$3:$F$20000,'Meta data'!$A$3:$A$20000,">="&$A32,'Meta data'!$A$3:$A$20000,"<="&EOMONTH($A32,0)) -> 655 | D32: =IF(B32=0,"",C13/B32) -> 0.12389527 | E32: =IF(C32=0,"",C13/C32) -> 16.890046 | F32: =SUMIFS('Google data'!$E$3:$E$20000,'Google data'!$A$3:$A$20000,">="&$A32,'Google data'!$A$3:$A$20000,"<="&EOMONTH($A32,0)) -> 3923 | G32: =SUMIFS('Google data'!$F$3:$F$20000,'Google data'!$A$3:$A$20000,">="&$A32,'Google data'!$A$3:$A$20000,"<="&EOMONTH($A32,0)) -> 165.47 | H32: =IF(F32=0,"",D13/F32) -> 1.7471905 | I32: =IF(G32=0,"",D13/G32) -> 41.422785 | J32: =SUMIFS('ChatGPT data'!$E$3:$E$20000,'ChatGPT data'!$A$3:$A$20000,">="&$A32,'ChatGPT data'!$A$3:$A$20000,"<="&EOMONTH($A32,0)) -> 43 | K32: =SUMIFS('ChatGPT data'!$F$3:$F$20000,'ChatGPT data'!$A$3:$A$20000,">="&$A32,'ChatGPT data'!$A$3:$A$20000,"<="&EOMONTH($A32,0)) -> 0 | L32: =IF(J32=0,"",E13/J32) -> 5.9669584 | M32: =IF(K32=0,"",E13/K32)
A33: =A14 -> 46296 | B33: =SUMIFS('Meta data'!$E$3:$E$20000,'Meta data'!$A$3:$A$20000,">="&$A33,'Meta data'!$A$3:$A$20000,"<="&EOMONTH($A33,0)) -> 0 | C33: =SUMIFS('Meta data'!$F$3:$F$20000,'Meta data'!$A$3:$A$20000,">="&$A33,'Meta data'!$A$3:$A$20000,"<="&EOMONTH($A33,0)) -> 0 | D33: =IF(B33=0,"",C14/B33) | E33: =IF(C33=0,"",C14/C33) | F33: =SUMIFS('Google data'!$E$3:$E$20000,'Google data'!$A$3:$A$20000,">="&$A33,'Google data'!$A$3:$A$20000,"<="&EOMONTH($A33,0)) -> 0 | G33: =SUMIFS('Google data'!$F$3:$F$20000,'Google data'!$A$3:$A$20000,">="&$A33,'Google data'!$A$3:$A$20000,"<="&EOMONTH($A33,0)) -> 0 | H33: =IF(F33=0,"",D14/F33) | I33: =IF(G33=0,"",D14/G33) | J33: =SUMIFS('ChatGPT data'!$E$3:$E$20000,'ChatGPT data'!$A$3:$A$20000,">="&$A33,'ChatGPT data'!$A$3:$A$20000,"<="&EOMONTH($A33,0)) -> 0 | K33: =SUMIFS('ChatGPT data'!$F$3:$F$20000,'ChatGPT data'!$A$3:$A$20000,">="&$A33,'ChatGPT data'!$A$3:$A$20000,"<="&EOMONTH($A33,0)) -> 0 | L33: =IF(J33=0,"",E14/J33) | M33: =IF(K33=0,"",E14/K33)
A34: =A15 -> 46327 | B34: =SUMIFS('Meta data'!$E$3:$E$20000,'Meta data'!$A$3:$A$20000,">="&$A34,'Meta data'!$A$3:$A$20000,"<="&EOMONTH($A34,0)) -> 0 | C34: =SUMIFS('Meta data'!$F$3:$F$20000,'Meta data'!$A$3:$A$20000,">="&$A34,'Meta data'!$A$3:$A$20000,"<="&EOMONTH($A34,0)) -> 0 | D34: =IF(B34=0,"",C15/B34) | E34: =IF(C34=0,"",C15/C34) | F34: =SUMIFS('Google data'!$E$3:$E$20000,'Google data'!$A$3:$A$20000,">="&$A34,'Google data'!$A$3:$A$20000,"<="&EOMONTH($A34,0)) -> 0 | G34: =SUMIFS('Google data'!$F$3:$F$20000,'Google data'!$A$3:$A$20000,">="&$A34,'Google data'!$A$3:$A$20000,"<="&EOMONTH($A34,0)) -> 0 | H34: =IF(F34=0,"",D15/F34) | I34: =IF(G34=0,"",D15/G34) | J34: =SUMIFS('ChatGPT data'!$E$3:$E$20000,'ChatGPT data'!$A$3:$A$20000,">="&$A34,'ChatGPT data'!$A$3:$A$20000,"<="&EOMONTH($A34,0)) -> 0 | K34: =SUMIFS('ChatGPT data'!$F$3:$F$20000,'ChatGPT data'!$A$3:$A$20000,">="&$A34,'ChatGPT data'!$A$3:$A$20000,"<="&EOMONTH($A34,0)) -> 0 | L34: =IF(J34=0,"",E15/J34) | M34: =IF(K34=0,"",E15/K34)
A35: =A16 -> 46357 | B35: =SUMIFS('Meta data'!$E$3:$E$20000,'Meta data'!$A$3:$A$20000,">="&$A35,'Meta data'!$A$3:$A$20000,"<="&EOMONTH($A35,0)) -> 0 | C35: =SUMIFS('Meta data'!$F$3:$F$20000,'Meta data'!$A$3:$A$20000,">="&$A35,'Meta data'!$A$3:$A$20000,"<="&EOMONTH($A35,0)) -> 0 | D35: =IF(B35=0,"",C16/B35) | E35: =IF(C35=0,"",C16/C35) | F35: =SUMIFS('Google data'!$E$3:$E$20000,'Google data'!$A$3:$A$20000,">="&$A35,'Google data'!$A$3:$A$20000,"<="&EOMONTH($A35,0)) -> 0 | G35: =SUMIFS('Google data'!$F$3:$F$20000,'Google data'!$A$3:$A$20000,">="&$A35,'Google data'!$A$3:$A$20000,"<="&EOMONTH($A35,0)) -> 0 | H35: =IF(F35=0,"",D16/F35) | I35: =IF(G35=0,"",D16/G35) | J35: =SUMIFS('ChatGPT data'!$E$3:$E$20000,'ChatGPT data'!$A$3:$A$20000,">="&$A35,'ChatGPT data'!$A$3:$A$20000,"<="&EOMONTH($A35,0)) -> 0 | K35: =SUMIFS('ChatGPT data'!$F$3:$F$20000,'ChatGPT data'!$A$3:$A$20000,">="&$A35,'ChatGPT data'!$A$3:$A$20000,"<="&EOMONTH($A35,0)) -> 0 | L35: =IF(J35=0,"",E16/J35) | M35: =IF(K35=0,"",E16/K35)
A36: Total | B36: =SUM(B24:B35) -> 190596 | C36: =SUM(C24:C35) -> 7213 | D36: =IF(B36=0,"",C17/B36) -> 0.93426426 | E36: =IF(C36=0,"",C17/C36) -> 24.686958 | F36: =SUM(F24:F35) -> 89858 | G36: =SUM(G24:G35) -> 1449.99 | H36: =IF(F36=0,"",D17/F36) -> 1.1159582 | I36: =IF(G36=0,"",D17/G36) -> 69.157563 | J36: =SUM(J24:J35) -> 43 | K36: =SUM(K24:K35) -> 0 | L36: =IF(J36=0,"",E17/J36) -> 5.9669584 | M36: =IF(K36=0,"",E17/K36)
A37: Conversions use each platform's own definition: Meta = 'Website registrations completed'; Google Ads = 'Conversions' (its primary conversion actions, which the agency changed during the year). Compare each channel with itself, not with each other.

Sheet By location & type
A1: Spend by region, market and campaign type
A2: ="Amounts in "&Settings!$C$6&" · location and type come from the Campaigns tab (based on the campaign names) · platform data up to "&TEXT(Settings!$C$5,"d mmm yyyy") -> Amounts in USD · location and type come from the Campaigns tab (based on the campaign names) · platform data up to 30 Sep 2026
A4: BY REGION
A5: Region | B5: =TEXT(Campaigns!F3,"mmm") -> Jan | C5: =TEXT(Campaigns!G3,"mmm") -> Feb | D5: =TEXT(Campaigns!H3,"mmm") -> Mar | E5: =TEXT(Campaigns!I3,"mmm") -> Apr | F5: =TEXT(Campaigns!J3,"mmm") -> May | G5: =TEXT(Campaigns!K3,"mmm") -> Jun | H5: =TEXT(Campaigns!L3,"mmm") -> Jul | I5: =TEXT(Campaigns!M3,"mmm") -> Aug | ... M5: =TEXT(Campaigns!Q3,"mmm") -> Dec | N5: Total | O5: Share | P5: Share of spend
A6: EMEA | B6: =SUMIFS(Campaigns!F$7:F$300,Campaigns!D$7:D$300,$A6) -> 7126.4538 | C6: =SUMIFS(Campaigns!G$7:G$300,Campaigns!D$7:D$300,$A6) -> 25908.553 | D6: =SUMIFS(Campaigns!H$7:H$300,Campaigns!D$7:D$300,$A6) -> 35880.04 | E6: =SUMIFS(Campaigns!I$7:I$300,Campaigns!D$7:D$300,$A6) -> 14545.649 | F6: =SUMIFS(Campaigns!J$7:J$300,Campaigns!D$7:D$300,$A6) -> 13085.623 | G6: =SUMIFS(Campaigns!K$7:K$300,Campaigns!D$7:D$300,$A6) -> 12652.039 | H6: =SUMIFS(Campaigns!L$7:L$300,Campaigns!D$7:D$300,$A6) -> 14192.077 | I6: =SUMIFS(Campaigns!M$7:M$300,Campaigns!D$7:D$300,$A6) -> 7742.1805 | J6: =SUMIFS(Campaigns!N$7:N$300,Campaigns!D$7:D$300,$A6) -> 8054.0146 | K6: =SUMIFS(Campaigns!O$7:O$300,Campaigns!D$7:D$300,$A6) -> 0 | L6: =SUMIFS(Campaigns!P$7:P$300,Campaigns!D$7:D$300,$A6) -> 0 | M6: =SUMIFS(Campaigns!Q$7:Q$300,Campaigns!D$7:D$300,$A6) -> 0 | N6: =SUM(B6:M6) -> 139186.63 | O6: =IF($N$11=0,"",N6/$N$11) -> 0.49959059 | P6: =IF(O6="","",REPT("█",ROUND(O6*40,0))) -> ████████████████████
A7: Americas | B7: =SUMIFS(Campaigns!F$7:F$300,Campaigns!D$7:D$300,$A7) -> 9759.7084 | C7: =SUMIFS(Campaigns!G$7:G$300,Campaigns!D$7:D$300,$A7) -> 13572.107 | D7: =SUMIFS(Campaigns!H$7:H$300,Campaigns!D$7:D$300,$A7) -> 11985.847 | E7: =SUMIFS(Campaigns!I$7:I$300,Campaigns!D$7:D$300,$A7) -> 17089.086 | F7: =SUMIFS(Campaigns!J$7:J$300,Campaigns!D$7:D$300,$A7) -> 20692.675 | G7: =SUMIFS(Campaigns!K$7:K$300,Campaigns!D$7:D$300,$A7) -> 17745.405 | H7: =SUMIFS(Campaigns!L$7:L$300,Campaigns!D$7:D$300,$A7) -> 14865.251 | I7: =SUMIFS(Campaigns!M$7:M$300,Campaigns!D$7:D$300,$A7) -> 12429.063 | J7: =SUMIFS(Campaigns!N$7:N$300,Campaigns!D$7:D$300,$A7) -> 7912.1415 | K7: =SUMIFS(Campaigns!O$7:O$300,Campaigns!D$7:D$300,$A7) -> 0 | L7: =SUMIFS(Campaigns!P$7:P$300,Campaigns!D$7:D$300,$A7) -> 0 | M7: =SUMIFS(Campaigns!Q$7:Q$300,Campaigns!D$7:D$300,$A7) -> 0 | N7: =SUM(B7:M7) -> 126051.28 | O7: =IF($N$11=0,"",N7/$N$11) -> 0.45244313 | P7: =IF(O7="","",REPT("█",ROUND(O7*40,0))) -> ██████████████████
A8: Global | B8: =SUMIFS(Campaigns!F$7:F$300,Campaigns!D$7:D$300,$A8) -> 2045.21 | C8: =SUMIFS(Campaigns!G$7:G$300,Campaigns!D$7:D$300,$A8) -> 556.5 | D8: =SUMIFS(Campaigns!H$7:H$300,Campaigns!D$7:D$300,$A8) -> 634.17 | E8: =SUMIFS(Campaigns!I$7:I$300,Campaigns!D$7:D$300,$A8) -> 579.09 | F8: =SUMIFS(Campaigns!J$7:J$300,Campaigns!D$7:D$300,$A8) -> 561.84 | G8: =SUMIFS(Campaigns!K$7:K$300,Campaigns!D$7:D$300,$A8) -> 1012.22 | H8: =SUMIFS(Campaigns!L$7:L$300,Campaigns!D$7:D$300,$A8) -> 3047.53 | I8: =SUMIFS(Campaigns!M$7:M$300,Campaigns!D$7:D$300,$A8) -> 2719.28 | J8: =SUMIFS(Campaigns!N$7:N$300,Campaigns!D$7:D$300,$A8) -> 1951.0521 | K8: =SUMIFS(Campaigns!O$7:O$300,Campaigns!D$7:D$300,$A8) -> 0 | L8: =SUMIFS(Campaigns!P$7:P$300,Campaigns!D$7:D$300,$A8) -> 0 | M8: =SUMIFS(Campaigns!Q$7:Q$300,Campaigns!D$7:D$300,$A8) -> 0 | N8: =SUM(B8:M8) -> 13106.892 | O8: =IF($N$11=0,"",N8/$N$11) -> 0.047045323 | P8: =IF(O8="","",REPT("█",ROUND(O8*40,0))) -> ██
A9: Not specified | B9: =SUMIFS(Campaigns!F$7:F$300,Campaigns!D$7:D$300,$A9) -> 0 | C9: =SUMIFS(Campaigns!G$7:G$300,Campaigns!D$7:D$300,$A9) -> 0 | D9: =SUMIFS(Campaigns!H$7:H$300,Campaigns!D$7:D$300,$A9) -> 0 | E9: =SUMIFS(Campaigns!I$7:I$300,Campaigns!D$7:D$300,$A9) -> 0 | F9: =SUMIFS(Campaigns!J$7:J$300,Campaigns!D$7:D$300,$A9) -> 0 | G9: =SUMIFS(Campaigns!K$7:K$300,Campaigns!D$7:D$300,$A9) -> 0 | H9: =SUMIFS(Campaigns!L$7:L$300,Campaigns!D$7:D$300,$A9) -> 0 | I9: =SUMIFS(Campaigns!M$7:M$300,Campaigns!D$7:D$300,$A9) -> 0 | J9: =SUMIFS(Campaigns!N$7:N$300,Campaigns!D$7:D$300,$A9) -> 256.57921 | K9: =SUMIFS(Campaigns!O$7:O$300,Campaigns!D$7:D$300,$A9) -> 0 | L9: =SUMIFS(Campaigns!P$7:P$300,Campaigns!D$7:D$300,$A9) -> 0 | M9: =SUMIFS(Campaigns!Q$7:Q$300,Campaigns!D$7:D$300,$A9) -> 0 | N9: =SUM(B9:M9) -> 256.57921 | O9: =IF($N$11=0,"",N9/$N$11) -> 0.00092095455 | P9: =IF(O9="","",REPT("█",ROUND(O9*40,0)))
A10: Other / not listed above | B10: =Campaigns!F$6-SUM(B6:B9) -> 0 | C10: =Campaigns!G$6-SUM(C6:C9) -> 0 | D10: =Campaigns!H$6-SUM(D6:D9) -> 0 | E10: =Campaigns!I$6-SUM(E6:E9) -> 0 | F10: =Campaigns!J$6-SUM(F6:F9) -> 0 | G10: =Campaigns!K$6-SUM(G6:G9) -> 0 | H10: =Campaigns!L$6-SUM(H6:H9) -> 0 | I10: =Campaigns!M$6-SUM(I6:I9) -> 0 | ... M10: =Campaigns!Q$6-SUM(M6:M9) -> 0 | N10: =SUM(B10:M10) -> 0 | O10: =IF($N$11=0,"",N10/$N$11) -> 0 | P10: =IF(O10="","",REPT("█",ROUND(O10*40,0)))
A11: Total | B11: =SUM(B6:B10) -> 18931.372 | C11: =SUM(C6:C10) -> 40037.16 | D11: =SUM(D6:D10) -> 48500.058 | E11: =SUM(E6:E10) -> 32213.825 | F11: =SUM(F6:F10) -> 34340.138 | G11: =SUM(G6:G10) -> 31409.663 | H11: =SUM(H6:H10) -> 32104.858 | I11: =SUM(I6:I10) -> 22890.523 | ... M11: =SUM(M6:M10) -> 0 | N11: =SUM(B11:M11) -> 278601.38 | O11: =IF($N$11=0,"",N11/$N$11) -> 1
A14: BY MARKET
A15: Market | B15: Region | C15: =TEXT(Campaigns!F3,"mmm") -> Jan | D15: =TEXT(Campaigns!G3,"mmm") -> Feb | E15: =TEXT(Campaigns!H3,"mmm") -> Mar | F15: =TEXT(Campaigns!I3,"mmm") -> Apr | G15: =TEXT(Campaigns!J3,"mmm") -> May | H15: =TEXT(Campaigns!K3,"mmm") -> Jun | I15: =TEXT(Campaigns!L3,"mmm") -> Jul | J15: =TEXT(Campaigns!M3,"mmm") -> Aug | ... N15: =TEXT(Campaigns!Q3,"mmm") -> Dec | O15: Total | P15: Share | Q15: Share of spend
A16: EMEA – multi-country | B16: EMEA | C16: =SUMIFS(Campaigns!F$7:F$300,Campaigns!C$7:C$300,$A16) -> 5954.7466 | D16: =SUMIFS(Campaigns!G$7:G$300,Campaigns!C$7:C$300,$A16) -> 23854.656 | E16: =SUMIFS(Campaigns!H$7:H$300,Campaigns!C$7:C$300,$A16) -> 33746.742 | F16: =SUMIFS(Campaigns!I$7:I$300,Campaigns!C$7:C$300,$A16) -> 12417.615 | G16: =SUMIFS(Campaigns!J$7:J$300,Campaigns!C$7:C$300,$A16) -> 10916.637 | H16: =SUMIFS(Campaigns!K$7:K$300,Campaigns!C$7:C$300,$A16) -> 10700.713 | I16: =SUMIFS(Campaigns!L$7:L$300,Campaigns!C$7:C$300,$A16) -> 10124.509 | J16: =SUMIFS(Campaigns!M$7:M$300,Campaigns!C$7:C$300,$A16) -> 5240.3499 | K16: =SUMIFS(Campaigns!N$7:N$300,Campaigns!C$7:C$300,$A16) -> 3416.8046 | L16: =SUMIFS(Campaigns!O$7:O$300,Campaigns!C$7:C$300,$A16) -> 0 | M16: =SUMIFS(Campaigns!P$7:P$300,Campaigns!C$7:C$300,$A16) -> 0 | N16: =SUMIFS(Campaigns!Q$7:Q$300,Campaigns!C$7:C$300,$A16) -> 0 | O16: =SUM(C16:N16) -> 116372.77 | P16: =IF($O$35=0,"",O16/$O$35) -> 0.4177035 | Q16: =IF(P16="","",REPT("█",ROUND(P16*40,0))) -> █████████████████
A17: California | B17: Americas | C17: =SUMIFS(Campaigns!F$7:F$300,Campaigns!C$7:C$300,$A17) -> 1545.2517 | D17: =SUMIFS(Campaigns!G$7:G$300,Campaigns!C$7:C$300,$A17) -> 3357.031 | E17: =SUMIFS(Campaigns!H$7:H$300,Campaigns!C$7:C$300,$A17) -> 4056.5979 | F17: =SUMIFS(Campaigns!I$7:I$300,Campaigns!C$7:C$300,$A17) -> 4268.259 | G17: =SUMIFS(Campaigns!J$7:J$300,Campaigns!C$7:C$300,$A17) -> 4599.5137 | H17: =SUMIFS(Campaigns!K$7:K$300,Campaigns!C$7:C$300,$A17) -> 4415.7939 | I17: =SUMIFS(Campaigns!L$7:L$300,Campaigns!C$7:C$300,$A17) -> 3550.6472 | J17: =SUMIFS(Campaigns!M$7:M$300,Campaigns!C$7:C$300,$A17) -> 1859.1361 | K17: =SUMIFS(Campaigns!N$7:N$300,Campaigns!C$7:C$300,$A17) -> 1096.2385 | L17: =SUMIFS(Campaigns!O$7:O$300,Campaigns!C$7:C$300,$A17) -> 0 | M17: =SUMIFS(Campaigns!P$7:P$300,Campaigns!C$7:C$300,$A17) -> 0 | N17: =SUMIFS(Campaigns!Q$7:Q$300,Campaigns!C$7:C$300,$A17) -> 0 | O17: =SUM(C17:N17) -> 28748.469 | P17: =IF($O$35=0,"",O17/$O$35) -> 0.10318854 | Q17: =IF(P17="","",REPT("█",ROUND(P17*40,0))) -> ████
A18: US & Canada | B18: Americas | C18: =SUMIFS(Campaigns!F$7:F$300,Campaigns!C$7:C$300,$A18) -> 2773.2808 | D18: =SUMIFS(Campaigns!G$7:G$300,Campaigns!C$7:C$300,$A18) -> 2786.7732 | E18: =SUMIFS(Campaigns!H$7:H$300,Campaigns!C$7:C$300,$A18) -> 2200.97 | F18: =SUMIFS(Campaigns!I$7:I$300,Campaigns!C$7:C$300,$A18) -> 2116.08 | G18: =SUMIFS(Campaigns!J$7:J$300,Campaigns!C$7:C$300,$A18) -> 2121.95 | H18: =SUMIFS(Campaigns!K$7:K$300,Campaigns!C$7:C$300,$A18) -> 2619.6597 | I18: =SUMIFS(Campaigns!L$7:L$300,Campaigns!C$7:C$300,$A18) -> 2480.5113 | J18: =SUMIFS(Campaigns!M$7:M$300,Campaigns!C$7:C$300,$A18) -> 5222.7142 | K18: =SUMIFS(Campaigns!N$7:N$300,Campaigns!C$7:C$300,$A18) -> 4339.2658 | L18: =SUMIFS(Campaigns!O$7:O$300,Campaigns!C$7:C$300,$A18) -> 0 | M18: =SUMIFS(Campaigns!P$7:P$300,Campaigns!C$7:C$300,$A18) -> 0 | N18: =SUMIFS(Campaigns!Q$7:Q$300,Campaigns!C$7:C$300,$A18) -> 0 | O18: =SUM(C18:N18) -> 26661.205 | P18: =IF($O$35=0,"",O18/$O$35) -> 0.095696599 | Q18: =IF(P18="","",REPT("█",ROUND(P18*40,0))) -> ████
A19: US East Coast | B19: Americas | C19: =SUMIFS(Campaigns!F$7:F$300,Campaigns!C$7:C$300,$A19) -> 71.253375 | D19: =SUMIFS(Campaigns!G$7:G$300,Campaigns!C$7:C$300,$A19) -> 339.03194 | E19: =SUMIFS(Campaigns!H$7:H$300,Campaigns!C$7:C$300,$A19) -> 165.46431 | F19: =SUMIFS(Campaigns!I$7:I$300,Campaigns!C$7:C$300,$A19) -> 5434.0872 | G19: =SUMIFS(Campaigns!J$7:J$300,Campaigns!C$7:C$300,$A19) -> 8466.192 | H19: =SUMIFS(Campaigns!K$7:K$300,Campaigns!C$7:C$300,$A19) -> 5154.6401 | I19: =SUMIFS(Campaigns!L$7:L$300,Campaigns!C$7:C$300,$A19) -> 3328.5728 | J19: =SUMIFS(Campaigns!M$7:M$300,Campaigns!C$7:C$300,$A19) -> 2222.0621 | K19: =SUMIFS(Campaigns!N$7:N$300,Campaigns!C$7:C$300,$A19) -> 1178.52 | L19: =SUMIFS(Campaigns!O$7:O$300,Campaigns!C$7:C$300,$A19) -> 0 | M19: =SUMIFS(Campaigns!P$7:P$300,Campaigns!C$7:C$300,$A19) -> 0 | N19: =SUMIFS(Campaigns!Q$7:Q$300,Campaigns!C$7:C$300,$A19) -> 0 | O19: =SUM(C19:N19) -> 26359.824 | P19: =IF($O$35=0,"",O19/$O$35) -> 0.094614834 | Q19: =IF(P19="","",REPT("█",ROUND(P19*40,0))) -> ████
A20: US – national | B20: Americas | C20: =SUMIFS(Campaigns!F$7:F$300,Campaigns!C$7:C$300,$A20) -> 3455.8278 | D20: =SUMIFS(Campaigns!G$7:G$300,Campaigns!C$7:C$300,$A20) -> 3458.3108 | E20: =SUMIFS(Campaigns!H$7:H$300,Campaigns!C$7:C$300,$A20) -> 951.00622 | F20: =SUMIFS(Campaigns!I$7:I$300,Campaigns!C$7:C$300,$A20) -> 780.8364 | G20: =SUMIFS(Campaigns!J$7:J$300,Campaigns!C$7:C$300,$A20) -> 1889.9972 | H20: =SUMIFS(Campaigns!K$7:K$300,Campaigns!C$7:C$300,$A20) -> 2786.1467 | I20: =SUMIFS(Campaigns!L$7:L$300,Campaigns!C$7:C$300,$A20) -> 2436.5301 | J20: =SUMIFS(Campaigns!M$7:M$300,Campaigns!C$7:C$300,$A20) -> 1359.0673 | K20: =SUMIFS(Campaigns!N$7:N$300,Campaigns!C$7:C$300,$A20) -> 561.38718 | L20: =SUMIFS(Campaigns!O$7:O$300,Campaigns!C$7:C$300,$A20) -> 0 | M20: =SUMIFS(Campaigns!P$7:P$300,Campaigns!C$7:C$300,$A20) -> 0 | N20: =SUMIFS(Campaigns!Q$7:Q$300,Campaigns!C$7:C$300,$A20) -> 0 | O20: =SUM(C20:N20) -> 17679.11 | P20: =IF($O$35=0,"",O20/$O$35) -> 0.063456647 | Q20: =IF(P20="","",REPT("█",ROUND(P20*40,0))) -> ███
A21: Worldwide | B21: Global | C21: =SUMIFS(Campaigns!F$7:F$300,Campaigns!C$7:C$300,$A21) -> 2045.21 | D21: =SUMIFS(Campaigns!G$7:G$300,Campaigns!C$7:C$300,$A21) -> 556.5 | E21: =SUMIFS(Campaigns!H$7:H$300,Campaigns!C$7:C$300,$A21) -> 634.17 | F21: =SUMIFS(Campaigns!I$7:I$300,Campaigns!C$7:C$300,$A21) -> 579.09 | G21: =SUMIFS(Campaigns!J$7:J$300,Campaigns!C$7:C$300,$A21) -> 561.84 | H21: =SUMIFS(Campaigns!K$7:K$300,Campaigns!C$7:C$300,$A21) -> 1012.22 | I21: =SUMIFS(Campaigns!L$7:L$300,Campaigns!C$7:C$300,$A21) -> 3047.53 | J21: =SUMIFS(Campaigns!M$7:M$300,Campaigns!C$7:C$300,$A21) -> 2719.28 | K21: =SUMIFS(Campaigns!N$7:N$300,Campaigns!C$7:C$300,$A21) -> 1951.0521 | L21: =SUMIFS(Campaigns!O$7:O$300,Campaigns!C$7:C$300,$A21) -> 0 | M21: =SUMIFS(Campaigns!P$7:P$300,Campaigns!C$7:C$300,$A21) -> 0 | N21: =SUMIFS(Campaigns!Q$7:Q$300,Campaigns!C$7:C$300,$A21) -> 0 | O21: =SUM(C21:N21) -> 13106.892 | P21: =IF($O$35=0,"",O21/$O$35) -> 0.047045323 | Q21: =IF(P21="","",REPT("█",ROUND(P21*40,0))) -> ██
A22: US South & Central | B22: Americas | C22: =SUMIFS(Campaigns!F$7:F$300,Campaigns!C$7:C$300,$A22) -> 134.49284 | D22: =SUMIFS(Campaigns!G$7:G$300,Campaigns!C$7:C$300,$A22) -> 336.01415 | E22: =SUMIFS(Campaigns!H$7:H$300,Campaigns!C$7:C$300,$A22) -> 339.64668 | F22: =SUMIFS(Campaigns!I$7:I$300,Campaigns!C$7:C$300,$A22) -> 329.94504 | G22: =SUMIFS(Campaigns!J$7:J$300,Campaigns!C$7:C$300,$A22) -> 689.35265 | H22: =SUMIFS(Campaigns!K$7:K$300,Campaigns!C$7:C$300,$A22) -> 2769.1645 | I22: =SUMIFS(Campaigns!L$7:L$300,Campaigns!C$7:C$300,$A22) -> 3068.9892 | J22: =SUMIFS(Campaigns!M$7:M$300,Campaigns!C$7:C$300,$A22) -> 1766.0829 | K22: =SUMIFS(Campaigns!N$7:N$300,Campaigns!C$7:C$300,$A22) -> 736.73 | L22: =SUMIFS(Campaigns!O$7:O$300,Campaigns!C$7:C$300,$A22) -> 0 | M22: =SUMIFS(Campaigns!P$7:P$300,Campaigns!C$7:C$300,$A22) -> 0 | N22: =SUMIFS(Campaigns!Q$7:Q$300,Campaigns!C$7:C$300,$A22) -> 0 | O22: =SUM(C22:N22) -> 10170.418 | P22: =IF($O$35=0,"",O22/$O$35) -> 0.036505267 | Q22: =IF(P22="","",REPT("█",ROUND(P22*40,0))) -> █
A23: France | B23: EMEA | C23: =SUMIFS(Campaigns!F$7:F$300,Campaigns!C$7:C$300,$A23) -> 422.4906 | D23: =SUMIFS(Campaigns!G$7:G$300,Campaigns!C$7:C$300,$A23) -> 712.93612 | E23: =SUMIFS(Campaigns!H$7:H$300,Campaigns!C$7:C$300,$A23) -> 707.3588 | F23: =SUMIFS(Campaigns!I$7:I$300,Campaigns!C$7:C$300,$A23) -> 714.10971 | G23: =SUMIFS(Campaigns!J$7:J$300,Campaigns!C$7:C$300,$A23) -> 710.60013 | H23: =SUMIFS(Campaigns!K$7:K$300,Campaigns!C$7:C$300,$A23) -> 727.768 | I23: =SUMIFS(Campaigns!L$7:L$300,Campaigns!C$7:C$300,$A23) -> 676.72264 | J23: =SUMIFS(Campaigns!M$7:M$300,Campaigns!C$7:C$300,$A23) -> 263.50895 | K23: =SUMIFS(Campaigns!N$7:N$300,Campaigns!C$7:C$300,$A23) -> 3692.72 | L23: =SUMIFS(Campaigns!O$7:O$300,Campaigns!C$7:C$300,$A23) -> 0 | M23: =SUMIFS(Campaigns!P$7:P$300,Campaigns!C$7:C$300,$A23) -> 0 | N23: =SUMIFS(Campaigns!Q$7:Q$300,Campaigns!C$7:C$300,$A23) -> 0 | O23: =SUM(C23:N23) -> 8628.215 | P23: =IF($O$35=0,"",O23/$O$35) -> 0.030969749 | Q23: =IF(P23="","",REPT("█",ROUND(P23*40,0))) -> █
A24: UK | B24: EMEA | C24: =SUMIFS(Campaigns!F$7:F$300,Campaigns!C$7:C$300,$A24) -> 416.54444 | D24: =SUMIFS(Campaigns!G$7:G$300,Campaigns!C$7:C$300,$A24) -> 706.97878 | E24: =SUMIFS(Campaigns!H$7:H$300,Campaigns!C$7:C$300,$A24) -> 713.48379 | F24: =SUMIFS(Campaigns!I$7:I$300,Campaigns!C$7:C$300,$A24) -> 713.69616 | G24: =SUMIFS(Campaigns!J$7:J$300,Campaigns!C$7:C$300,$A24) -> 713.6291 | H24: =SUMIFS(Campaigns!K$7:K$300,Campaigns!C$7:C$300,$A24) -> 715.66331 | I24: =SUMIFS(Campaigns!L$7:L$300,Campaigns!C$7:C$300,$A24) -> 684.36771 | J24: =SUMIFS(Campaigns!M$7:M$300,Campaigns!C$7:C$300,$A24) -> 267.70033 | K24: =SUMIFS(Campaigns!N$7:N$300,Campaigns!C$7:C$300,$A24) -> 0 | L24: =SUMIFS(Campaigns!O$7:O$300,Campaigns!C$7:C$300,$A24) -> 0 | M24: =SUMIFS(Campaigns!P$7:P$300,Campaigns!C$7:C$300,$A24) -> 0 | N24: =SUMIFS(Campaigns!Q$7:Q$300,Campaigns!C$7:C$300,$A24) -> 0 | O24: =SUM(C24:N24) -> 4932.0636 | P24: =IF($O$35=0,"",O24/$O$35) -> 0.01770294 | Q24: =IF(P24="","",REPT("█",ROUND(P24*40,0))) -> █
A25: Florida | B25: Americas | C25: =SUMIFS(Campaigns!F$7:F$300,Campaigns!C$7:C$300,$A25) -> 483.12583 | D25: =SUMIFS(Campaigns!G$7:G$300,Campaigns!C$7:C$300,$A25) -> 820.34709 | E25: =SUMIFS(Campaigns!H$7:H$300,Campaigns!C$7:C$300,$A25) -> 1207.1495 | F25: =SUMIFS(Campaigns!I$7:I$300,Campaigns!C$7:C$300,$A25) -> 1230.0288 | G25: =SUMIFS(Campaigns!J$7:J$300,Campaigns!C$7:C$300,$A25) -> 708.55474 | H25: =SUMIFS(Campaigns!K$7:K$300,Campaigns!C$7:C$300,$A25) -> 0 | I25: =SUMIFS(Campaigns!L$7:L$300,Campaigns!C$7:C$300,$A25) -> 0 | J25: =SUMIFS(Campaigns!M$7:M$300,Campaigns!C$7:C$300,$A25) -> 0 | K25: =SUMIFS(Campaigns!N$7:N$300,Campaigns!C$7:C$300,$A25) -> 0 | L25: =SUMIFS(Campaigns!O$7:O$300,Campaigns!C$7:C$300,$A25) -> 0 | M25: =SUMIFS(Campaigns!P$7:P$300,Campaigns!C$7:C$300,$A25) -> 0 | N25: =SUMIFS(Campaigns!Q$7:Q$300,Campaigns!C$7:C$300,$A25) -> 0 | O25: =SUM(C25:N25) -> 4449.206 | P25: =IF($O$35=0,"",O25/$O$35) -> 0.015969792 | Q25: =IF(P25="","",REPT("█",ROUND(P25*40,0))) -> █
A26: Middle East | B26: EMEA | C26: =SUMIFS(Campaigns!F$7:F$300,Campaigns!C$7:C$300,$A26) -> 79.602594 | D26: =SUMIFS(Campaigns!G$7:G$300,Campaigns!C$7:C$300,$A26) -> 180.11736 | E26: =SUMIFS(Campaigns!H$7:H$300,Campaigns!C$7:C$300,$A26) -> 270.63988 | F26: =SUMIFS(Campaigns!I$7:I$300,Campaigns!C$7:C$300,$A26) -> 264.85019 | G26: =SUMIFS(Campaigns!J$7:J$300,Campaigns!C$7:C$300,$A26) -> 274.39535 | H26: =SUMIFS(Campaigns!K$7:K$300,Campaigns!C$7:C$300,$A26) -> 274.10475 | I26: =SUMIFS(Campaigns!L$7:L$300,Campaigns!C$7:C$300,$A26) -> 1332.5729 | J26: =SUMIFS(Campaigns!M$7:M$300,Campaigns!C$7:C$300,$A26) -> 1024.1 | K26: =SUMIFS(Campaigns!N$7:N$300,Campaigns!C$7:C$300,$A26) -> 463.94 | L26: =SUMIFS(Campaigns!O$7:O$300,Campaigns!C$7:C$300,$A26) -> 0 | M26: =SUMIFS(Campaigns!P$7:P$300,Campaigns!C$7:C$300,$A26) -> 0 | N26: =SUMIFS(Campaigns!Q$7:Q$300,Campaigns!C$7:C$300,$A26) -> 0 | O26: =SUM(C26:N26) -> 4164.323 | P26: =IF($O$35=0,"",O26/$O$35) -> 0.014947244 | Q26: =IF(P26="","",REPT("█",ROUND(P26*40,0))) -> █
A27: Texas | B27: Americas | C27: =SUMIFS(Campaigns!F$7:F$300,Campaigns!C$7:C$300,$A27) -> 384.32115 | D27: =SUMIFS(Campaigns!G$7:G$300,Campaigns!C$7:C$300,$A27) -> 682.85882 | E27: =SUMIFS(Campaigns!H$7:H$300,Campaigns!C$7:C$300,$A27) -> 1217.3206 | F27: =SUMIFS(Campaigns!I$7:I$300,Campaigns!C$7:C$300,$A27) -> 1112.6592 | G27: =SUMIFS(Campaigns!J$7:J$300,Campaigns!C$7:C$300,$A27) -> 650.54611 | H27: =SUMIFS(Campaigns!K$7:K$300,Campaigns!C$7:C$300,$A27) -> 0 | I27: =SUMIFS(Campaigns!L$7:L$300,Campaigns!C$7:C$300,$A27) -> 0 | J27: =SUMIFS(Campaigns!M$7:M$300,Campaigns!C$7:C$300,$A27) -> 0 | K27: =SUMIFS(Campaigns!N$7:N$300,Campaigns!C$7:C$300,$A27) -> 0 | L27: =SUMIFS(Campaigns!O$7:O$300,Campaigns!C$7:C$300,$A27) -> 0 | M27: =SUMIFS(Campaigns!P$7:P$300,Campaigns!C$7:C$300,$A27) -> 0 | N27: =SUMIFS(Campaigns!Q$7:Q$300,Campaigns!C$7:C$300,$A27) -> 0 | O27: =SUM(C27:N27) -> 4047.7058 | P27: =IF($O$35=0,"",O27/$O$35) -> 0.014528664 | Q27: =IF(P27="","",REPT("█",ROUND(P27*40,0))) -> █
... A33: Not specified | B33: Not specified | C33: =SUMIFS(Campaigns!F$7:F$300,Campaigns!C$7:C$300,$A33) -> 0 | D33: =SUMIFS(Campaigns!G$7:G$300,Campaigns!C$7:C$300,$A33) -> 0 | E33: =SUMIFS(Campaigns!H$7:H$300,Campaigns!C$7:C$300,$A33) -> 0 | F33: =SUMIFS(Campaigns!I$7:I$300,Campaigns!C$7:C$300,$A33) -> 0 | G33: =SUMIFS(Campaigns!J$7:J$300,Campaigns!C$7:C$300,$A33) -> 0 | H33: =SUMIFS(Campaigns!K$7:K$300,Campaigns!C$7:C$300,$A33) -> 0 | I33: =SUMIFS(Campaigns!L$7:L$300,Campaigns!C$7:C$300,$A33) -> 0 | J33: =SUMIFS(Campaigns!M$7:M$300,Campaigns!C$7:C$300,$A33) -> 0 | K33: =SUMIFS(Campaigns!N$7:N$300,Campaigns!C$7:C$300,$A33) -> 256.57921 | L33: =SUMIFS(Campaigns!O$7:O$300,Campaigns!C$7:C$300,$A33) -> 0 | M33: =SUMIFS(Campaigns!P$7:P$300,Campaigns!C$7:C$300,$A33) -> 0 | N33: =SUMIFS(Campaigns!Q$7:Q$300,Campaigns!C$7:C$300,$A33) -> 0 | O33: =SUM(C33:N33) -> 256.57921 | P33: =IF($O$35=0,"",O33/$O$35) -> 0.00092095455 | Q33: =IF(P33="","",REPT("█",ROUND(P33*40,0)))
A34: Other / not listed above | C34: =Campaigns!F$6-SUM(C16:C33) -> 0 | D34: =Campaigns!G$6-SUM(D16:D33) -> 0 | E34: =Campaigns!H$6-SUM(E16:E33) -> 0 | F34: =Campaigns!I$6-SUM(F16:F33) -> 0 | G34: =Campaigns!J$6-SUM(G16:G33) -> 0 | H34: =Campaigns!K$6-SUM(H16:H33) -> 0 | I34: =Campaigns!L$6-SUM(I16:I33) -> 0 | J34: =Campaigns!M$6-SUM(J16:J33) -> 0 | ... N34: =Campaigns!Q$6-SUM(N16:N33) -> 0 | O34: =SUM(C34:N34) -> 0 | P34: =IF($O$35=0,"",O34/$O$35) -> 0 | Q34: =IF(P34="","",REPT("█",ROUND(P34*40,0)))
A35: Total | C35: =SUM(C16:C34) -> 18931.372 | D35: =SUM(D16:D34) -> 40037.16 | E35: =SUM(E16:E34) -> 48500.058 | F35: =SUM(F16:F34) -> 32213.825 | G35: =SUM(G16:G34) -> 34340.138 | H35: =SUM(H16:H34) -> 31409.663 | I35: =SUM(I16:I34) -> 32104.858 | J35: =SUM(J16:J34) -> 22890.523 | ... N35: =SUM(N16:N34) -> 0 | O35: =SUM(C35:N35) -> 278601.38 | P35: =IF($O$35=0,"",O35/$O$35) -> 1
A38: BY CAMPAIGN TYPE
A39: Campaign type | B39: =TEXT(Campaigns!F3,"mmm") -> Jan | C39: =TEXT(Campaigns!G3,"mmm") -> Feb | D39: =TEXT(Campaigns!H3,"mmm") -> Mar | E39: =TEXT(Campaigns!I3,"mmm") -> Apr | F39: =TEXT(Campaigns!J3,"mmm") -> May | G39: =TEXT(Campaigns!K3,"mmm") -> Jun | H39: =TEXT(Campaigns!L3,"mmm") -> Jul | I39: =TEXT(Campaigns!M3,"mmm") -> Aug | ... M39: =TEXT(Campaigns!Q3,"mmm") -> Dec | N39: Total | O39: Share | P39: Share of spend
A40: Meta – lead ads, prospecting | B40: =SUMIFS(Campaigns!F$7:F$300,Campaigns!E$7:E$300,$A40) -> 5559.84 | C40: =SUMIFS(Campaigns!G$7:G$300,Campaigns!E$7:E$300,$A40) -> 25551.01 | D40: =SUMIFS(Campaigns!H$7:H$300,Campaigns!E$7:E$300,$A40) -> 37132.55 | E40: =SUMIFS(Campaigns!I$7:I$300,Campaigns!E$7:E$300,$A40) -> 21058.9 | F40: =SUMIFS(Campaigns!J$7:J$300,Campaigns!E$7:E$300,$A40) -> 21102.96 | G40: =SUMIFS(Campaigns!K$7:K$300,Campaigns!E$7:E$300,$A40) -> 16111.65 | H40: =SUMIFS(Campaigns!L$7:L$300,Campaigns!E$7:E$300,$A40) -> 15788.51 | I40: =SUMIFS(Campaigns!M$7:M$300,Campaigns!E$7:E$300,$A40) -> 7617.86 | J40: =SUMIFS(Campaigns!N$7:N$300,Campaigns!E$7:E$300,$A40) -> 5230.09 | K40: =SUMIFS(Campaigns!O$7:O$300,Campaigns!E$7:E$300,$A40) -> 0 | L40: =SUMIFS(Campaigns!P$7:P$300,Campaigns!E$7:E$300,$A40) -> 0 | M40: =SUMIFS(Campaigns!Q$7:Q$300,Campaigns!E$7:E$300,$A40) -> 0 | N40: =SUM(B40:M40) -> 155153.37 | O40: =IF($N$52=0,"",N40/$N$52) -> 0.55690093 | P40: =IF(O40="","",REPT("█",ROUND(O40*40,0))) -> ██████████████████████
A41: Google – Search, non-brand | B41: =SUMIFS(Campaigns!F$7:F$300,Campaigns!E$7:E$300,$A41) -> 6756.2394 | C41: =SUMIFS(Campaigns!G$7:G$300,Campaigns!E$7:E$300,$A41) -> 8956.2754 | D41: =SUMIFS(Campaigns!H$7:H$300,Campaigns!E$7:E$300,$A41) -> 8669.8424 | E41: =SUMIFS(Campaigns!I$7:I$300,Campaigns!E$7:E$300,$A41) -> 8938.3698 | F41: =SUMIFS(Campaigns!J$7:J$300,Campaigns!E$7:E$300,$A41) -> 11559.008 | G41: =SUMIFS(Campaigns!K$7:K$300,Campaigns!E$7:E$300,$A41) -> 11230.784 | H41: =SUMIFS(Campaigns!L$7:L$300,Campaigns!E$7:E$300,$A41) -> 10783.849 | I41: =SUMIFS(Campaigns!M$7:M$300,Campaigns!E$7:E$300,$A41) -> 9481.8403 | J41: =SUMIFS(Campaigns!N$7:N$300,Campaigns!E$7:E$300,$A41) -> 4492.5952 | K41: =SUMIFS(Campaigns!O$7:O$300,Campaigns!E$7:E$300,$A41) -> 0 | L41: =SUMIFS(Campaigns!P$7:P$300,Campaigns!E$7:E$300,$A41) -> 0 | M41: =SUMIFS(Campaigns!Q$7:Q$300,Campaigns!E$7:E$300,$A41) -> 0 | N41: =SUM(B41:M41) -> 80868.803 | O41: =IF($N$52=0,"",N41/$N$52) -> 0.29026705 | P41: =IF(O41="","",REPT("█",ROUND(O41*40,0))) -> ████████████
A42: Meta – lead ads, retargeting | B42: =SUMIFS(Campaigns!F$7:F$300,Campaigns!E$7:E$300,$A42) -> 969.5 | C42: =SUMIFS(Campaigns!G$7:G$300,Campaigns!E$7:E$300,$A42) -> 1114.79 | D42: =SUMIFS(Campaigns!H$7:H$300,Campaigns!E$7:E$300,$A42) -> 1254.29 | E42: =SUMIFS(Campaigns!I$7:I$300,Campaigns!E$7:E$300,$A42) -> 1182.66 | F42: =SUMIFS(Campaigns!J$7:J$300,Campaigns!E$7:E$300,$A42) -> 1173.54 | G42: =SUMIFS(Campaigns!K$7:K$300,Campaigns!E$7:E$300,$A42) -> 1341.64 | H42: =SUMIFS(Campaigns!L$7:L$300,Campaigns!E$7:E$300,$A42) -> 3047.53 | I42: =SUMIFS(Campaigns!M$7:M$300,Campaigns!E$7:E$300,$A42) -> 2719.28 | J42: =SUMIFS(Campaigns!N$7:N$300,Campaigns!E$7:E$300,$A42) -> 1895.1 | K42: =SUMIFS(Campaigns!O$7:O$300,Campaigns!E$7:E$300,$A42) -> 0 | L42: =SUMIFS(Campaigns!P$7:P$300,Campaigns!E$7:E$300,$A42) -> 0 | M42: =SUMIFS(Campaigns!Q$7:Q$300,Campaigns!E$7:E$300,$A42) -> 0 | N42: =SUM(B42:M42) -> 14698.33 | O42: =IF($N$52=0,"",N42/$N$52) -> 0.052757563 | P42: =IF(O42="","",REPT("█",ROUND(O42*40,0))) -> ██
A43: Google – YouTube video | B43: =SUMIFS(Campaigns!F$7:F$300,Campaigns!E$7:E$300,$A43) -> 0 | C43: =SUMIFS(Campaigns!G$7:G$300,Campaigns!E$7:E$300,$A43) -> 1679.8249 | D43: =SUMIFS(Campaigns!H$7:H$300,Campaigns!E$7:E$300,$A43) -> 399.51069 | E43: =SUMIFS(Campaigns!I$7:I$300,Campaigns!E$7:E$300,$A43) -> 717.86518 | F43: =SUMIFS(Campaigns!J$7:J$300,Campaigns!E$7:E$300,$A43) -> 335.31 | G43: =SUMIFS(Campaigns!K$7:K$300,Campaigns!E$7:E$300,$A43) -> 2040.4396 | H43: =SUMIFS(Campaigns!L$7:L$300,Campaigns!E$7:E$300,$A43) -> 1520.3961 | I43: =SUMIFS(Campaigns!M$7:M$300,Campaigns!E$7:E$300,$A43) -> 1360.3862 | J43: =SUMIFS(Campaigns!N$7:N$300,Campaigns!E$7:E$300,$A43) -> 1185.8573 | K43: =SUMIFS(Campaigns!O$7:O$300,Campaigns!E$7:E$300,$A43) -> 0 | L43: =SUMIFS(Campaigns!P$7:P$300,Campaigns!E$7:E$300,$A43) -> 0 | M43: =SUMIFS(Campaigns!Q$7:Q$300,Campaigns!E$7:E$300,$A43) -> 0 | N43: =SUM(B43:M43) -> 9239.59 | O43: =IF($N$52=0,"",N43/$N$52) -> 0.033164193 | P43: =IF(O43="","",REPT("█",ROUND(O43*40,0))) -> █
A44: Google – Performance Max | B44: =SUMIFS(Campaigns!F$7:F$300,Campaigns!E$7:E$300,$A44) -> 1070.2872 | C44: =SUMIFS(Campaigns!G$7:G$300,Campaigns!E$7:E$300,$A44) -> 377.13433 | D44: =SUMIFS(Campaigns!H$7:H$300,Campaigns!E$7:E$300,$A44) -> 267.74503 | E44: =SUMIFS(Campaigns!I$7:I$300,Campaigns!E$7:E$300,$A44) -> 146.04986 | F44: =SUMIFS(Campaigns!J$7:J$300,Campaigns!E$7:E$300,$A44) -> 0 | G44: =SUMIFS(Campaigns!K$7:K$300,Campaigns!E$7:E$300,$A44) -> 514.68967 | H44: =SUMIFS(Campaigns!L$7:L$300,Campaigns!E$7:E$300,$A44) -> 674.05134 | I44: =SUMIFS(Campaigns!M$7:M$300,Campaigns!E$7:E$300,$A44) -> 1356.3066 | J44: =SUMIFS(Campaigns!N$7:N$300,Campaigns!E$7:E$300,$A44) -> 1046.5472 | K44: =SUMIFS(Campaigns!O$7:O$300,Campaigns!E$7:E$300,$A44) -> 0 | L44: =SUMIFS(Campaigns!P$7:P$300,Campaigns!E$7:E$300,$A44) -> 0 | M44: =SUMIFS(Campaigns!Q$7:Q$300,Campaigns!E$7:E$300,$A44) -> 0 | N44: =SUM(B44:M44) -> 5452.8112 | O44: =IF($N$52=0,"",N44/$N$52) -> 0.019572089 | P44: =IF(O44="","",REPT("█",ROUND(O44*40,0))) -> █
A45: Meta – traffic | B45: =SUMIFS(Campaigns!F$7:F$300,Campaigns!E$7:E$300,$A45) -> 0 | C45: =SUMIFS(Campaigns!G$7:G$300,Campaigns!E$7:E$300,$A45) -> 0 | D45: =SUMIFS(Campaigns!H$7:H$300,Campaigns!E$7:E$300,$A45) -> 0 | E45: =SUMIFS(Campaigns!I$7:I$300,Campaigns!E$7:E$300,$A45) -> 0 | F45: =SUMIFS(Campaigns!J$7:J$300,Campaigns!E$7:E$300,$A45) -> 0 | G45: =SUMIFS(Campaigns!K$7:K$300,Campaigns!E$7:E$300,$A45) -> 0 | H45: =SUMIFS(Campaigns!L$7:L$300,Campaigns!E$7:E$300,$A45) -> 120.62 | I45: =SUMIFS(Campaigns!M$7:M$300,Campaigns!E$7:E$300,$A45) -> 306.8 | J45: =SUMIFS(Campaigns!N$7:N$300,Campaigns!E$7:E$300,$A45) -> 3937.79 | K45: =SUMIFS(Campaigns!O$7:O$300,Campaigns!E$7:E$300,$A45) -> 0 | L45: =SUMIFS(Campaigns!P$7:P$300,Campaigns!E$7:E$300,$A45) -> 0 | M45: =SUMIFS(Campaigns!Q$7:Q$300,Campaigns!E$7:E$300,$A45) -> 0 | N45: =SUM(B45:M45) -> 4365.21 | O45: =IF($N$52=0,"",N45/$N$52) -> 0.0156683 | P45: =IF(O45="","",REPT("█",ROUND(O45*40,0))) -> █
A46: Meta – other | B46: =SUMIFS(Campaigns!F$7:F$300,Campaigns!E$7:E$300,$A46) -> 1563.17 | C46: =SUMIFS(Campaigns!G$7:G$300,Campaigns!E$7:E$300,$A46) -> 2286.95 | D46: =SUMIFS(Campaigns!H$7:H$300,Campaigns!E$7:E$300,$A46) -> 0 | E46: =SUMIFS(Campaigns!I$7:I$300,Campaigns!E$7:E$300,$A46) -> 0 | F46: =SUMIFS(Campaigns!J$7:J$300,Campaigns!E$7:E$300,$A46) -> 0 | G46: =SUMIFS(Campaigns!K$7:K$300,Campaigns!E$7:E$300,$A46) -> 0 | H46: =SUMIFS(Campaigns!L$7:L$300,Campaigns!E$7:E$300,$A46) -> 0 | I46: =SUMIFS(Campaigns!M$7:M$300,Campaigns!E$7:E$300,$A46) -> 0 | J46: =SUMIFS(Campaigns!N$7:N$300,Campaigns!E$7:E$300,$A46) -> 0 | K46: =SUMIFS(Campaigns!O$7:O$300,Campaigns!E$7:E$300,$A46) -> 0 | L46: =SUMIFS(Campaigns!P$7:P$300,Campaigns!E$7:E$300,$A46) -> 0 | M46: =SUMIFS(Campaigns!Q$7:Q$300,Campaigns!E$7:E$300,$A46) -> 0 | N46: =SUM(B46:M46) -> 3850.12 | O46: =IF($N$52=0,"",N46/$N$52) -> 0.013819458 | P46: =IF(O46="","",REPT("█",ROUND(O46*40,0))) -> █
A47: Google – Demand Gen / YouTube reach | B47: =SUMIFS(Campaigns!F$7:F$300,Campaigns!E$7:E$300,$A47) -> 1963.0947 | C47: =SUMIFS(Campaigns!G$7:G$300,Campaigns!E$7:E$300,$A47) -> 0 | D47: =SUMIFS(Campaigns!H$7:H$300,Campaigns!E$7:E$300,$A47) -> 638.96674 | E47: =SUMIFS(Campaigns!I$7:I$300,Campaigns!E$7:E$300,$A47) -> 0 | F47: =SUMIFS(Campaigns!J$7:J$300,Campaigns!E$7:E$300,$A47) -> 0 | G47: =SUMIFS(Campaigns!K$7:K$300,Campaigns!E$7:E$300,$A47) -> 0 | H47: =SUMIFS(Campaigns!L$7:L$300,Campaigns!E$7:E$300,$A47) -> 0 | I47: =SUMIFS(Campaigns!M$7:M$300,Campaigns!E$7:E$300,$A47) -> 0 | J47: =SUMIFS(Campaigns!N$7:N$300,Campaigns!E$7:E$300,$A47) -> 0 | K47: =SUMIFS(Campaigns!O$7:O$300,Campaigns!E$7:E$300,$A47) -> 0 | L47: =SUMIFS(Campaigns!P$7:P$300,Campaigns!E$7:E$300,$A47) -> 0 | M47: =SUMIFS(Campaigns!Q$7:Q$300,Campaigns!E$7:E$300,$A47) -> 0 | N47: =SUM(B47:M47) -> 2602.0615 | O47: =IF($N$52=0,"",N47/$N$52) -> 0.0093397292 | P47: =IF(O47="","",REPT("█",ROUND(O47*40,0)))
A48: Google – Search, coworking | B48: =SUMIFS(Campaigns!F$7:F$300,Campaigns!E$7:E$300,$A48) -> 96.770466 | C48: =SUMIFS(Campaigns!G$7:G$300,Campaigns!E$7:E$300,$A48) -> 71.175136 | D48: =SUMIFS(Campaigns!H$7:H$300,Campaigns!E$7:E$300,$A48) -> 137.15297 | E48: =SUMIFS(Campaigns!I$7:I$300,Campaigns!E$7:E$300,$A48) -> 169.97982 | F48: =SUMIFS(Campaigns!J$7:J$300,Campaigns!E$7:E$300,$A48) -> 169.32037 | G48: =SUMIFS(Campaigns!K$7:K$300,Campaigns!E$7:E$300,$A48) -> 170.46043 | H48: =SUMIFS(Campaigns!L$7:L$300,Campaigns!E$7:E$300,$A48) -> 169.90158 | I48: =SUMIFS(Campaigns!M$7:M$300,Campaigns!E$7:E$300,$A48) -> 48.049923 | J48: =SUMIFS(Campaigns!N$7:N$300,Campaigns!E$7:E$300,$A48) -> 129.22847 | K48: =SUMIFS(Campaigns!O$7:O$300,Campaigns!E$7:E$300,$A48) -> 0 | L48: =SUMIFS(Campaigns!P$7:P$300,Campaigns!E$7:E$300,$A48) -> 0 | M48: =SUMIFS(Campaigns!Q$7:Q$300,Campaigns!E$7:E$300,$A48) -> 0 | N48: =SUM(B48:M48) -> 1162.0392 | O48: =IF($N$52=0,"",N48/$N$52) -> 0.0041709741 | P48: =IF(O48="","",REPT("█",ROUND(O48*40,0)))
A49: Google – Search, brand | B49: =SUMIFS(Campaigns!F$7:F$300,Campaigns!E$7:E$300,$A49) -> 952.47041 | C49: =SUMIFS(Campaigns!G$7:G$300,Campaigns!E$7:E$300,$A49) -> 0 | D49: =SUMIFS(Campaigns!H$7:H$300,Campaigns!E$7:E$300,$A49) -> 0 | E49: =SUMIFS(Campaigns!I$7:I$300,Campaigns!E$7:E$300,$A49) -> 0 | F49: =SUMIFS(Campaigns!J$7:J$300,Campaigns!E$7:E$300,$A49) -> 0 | G49: =SUMIFS(Campaigns!K$7:K$300,Campaigns!E$7:E$300,$A49) -> 0 | H49: =SUMIFS(Campaigns!L$7:L$300,Campaigns!E$7:E$300,$A49) -> 0 | I49: =SUMIFS(Campaigns!M$7:M$300,Campaigns!E$7:E$300,$A49) -> 0 | J49: =SUMIFS(Campaigns!N$7:N$300,Campaigns!E$7:E$300,$A49) -> 0 | K49: =SUMIFS(Campaigns!O$7:O$300,Campaigns!E$7:E$300,$A49) -> 0 | L49: =SUMIFS(Campaigns!P$7:P$300,Campaigns!E$7:E$300,$A49) -> 0 | M49: =SUMIFS(Campaigns!Q$7:Q$300,Campaigns!E$7:E$300,$A49) -> 0 | N49: =SUM(B49:M49) -> 952.47041 | O49: =IF($N$52=0,"",N49/$N$52) -> 0.0034187569 | P49: =IF(O49="","",REPT("█",ROUND(O49*40,0)))
A50: ChatGPT – test | B50: =SUMIFS(Campaigns!F$7:F$300,Campaigns!E$7:E$300,$A50) -> 0 | C50: =SUMIFS(Campaigns!G$7:G$300,Campaigns!E$7:E$300,$A50) -> 0 | D50: =SUMIFS(Campaigns!H$7:H$300,Campaigns!E$7:E$300,$A50) -> 0 | E50: =SUMIFS(Campaigns!I$7:I$300,Campaigns!E$7:E$300,$A50) -> 0 | F50: =SUMIFS(Campaigns!J$7:J$300,Campaigns!E$7:E$300,$A50) -> 0 | G50: =SUMIFS(Campaigns!K$7:K$300,Campaigns!E$7:E$300,$A50) -> 0 | H50: =SUMIFS(Campaigns!L$7:L$300,Campaigns!E$7:E$300,$A50) -> 0 | I50: =SUMIFS(Campaigns!M$7:M$300,Campaigns!E$7:E$300,$A50) -> 0 | J50: =SUMIFS(Campaigns!N$7:N$300,Campaigns!E$7:E$300,$A50) -> 256.57921 | K50: =SUMIFS(Campaigns!O$7:O$300,Campaigns!E$7:E$300,$A50) -> 0 | L50: =SUMIFS(Campaigns!P$7:P$300,Campaigns!E$7:E$300,$A50) -> 0 | M50: =SUMIFS(Campaigns!Q$7:Q$300,Campaigns!E$7:E$300,$A50) -> 0 | N50: =SUM(B50:M50) -> 256.57921 | O50: =IF($N$52=0,"",N50/$N$52) -> 0.00092095455 | P50: =IF(O50="","",REPT("█",ROUND(O50*40,0)))
A51: Other / not listed above | B51: =Campaigns!F$6-SUM(B40:B50) -> 0 | C51: =Campaigns!G$6-SUM(C40:C50) -> 0 | D51: =Campaigns!H$6-SUM(D40:D50) -> 0 | E51: =Campaigns!I$6-SUM(E40:E50) -> 0 | F51: =Campaigns!J$6-SUM(F40:F50) -> 0 | G51: =Campaigns!K$6-SUM(G40:G50) -> 0 | H51: =Campaigns!L$6-SUM(H40:H50) -> 0 | I51: =Campaigns!M$6-SUM(I40:I50) -> 0 | ... M51: =Campaigns!Q$6-SUM(M40:M50) -> 0 | N51: =SUM(B51:M51) -> 0 | O51: =IF($N$52=0,"",N51/$N$52) -> 0 | P51: =IF(O51="","",REPT("█",ROUND(O51*40,0)))
A52: Total | B52: =SUM(B40:B51) -> 18931.372 | C52: =SUM(C40:C51) -> 40037.16 | D52: =SUM(D40:D51) -> 48500.058 | E52: =SUM(E40:E51) -> 32213.825 | F52: =SUM(F40:F51) -> 34340.138 | G52: =SUM(G40:G51) -> 31409.663 | H52: =SUM(H40:H51) -> 32104.858 | I52: =SUM(I40:I51) -> 22890.523 | ... M52: =SUM(M40:M51) -> 0 | N52: =SUM(B52:M52) -> 278601.38 | O52: =IF($N$52=0,"",N52/$N$52) -> 1

Sheet Campaigns
A1: Campaigns – market, region, type and spend by month
A2: Every campaign in the data tabs needs a row here. Yellow = type it in when a new campaign starts. Market and region come from the location code in the campaign name.
A3: Check – spend in the data tabs that is missing from this list: | D3: =Calc!C46-R6 -> 0 | E3: =IF(ABS(D3)<0.5,"✓ all listed","⚠ add the campaigns flagged in the data tabs") -> ✓ all listed | F3: =DATE(Settings!$C$12,1,1) -> 46023 | G3: =DATE(Settings!$C$12,2,1) -> 46054 | H3: =DATE(Settings!$C$12,3,1) -> 46082 | I3: =DATE(Settings!$C$12,4,1) -> 46113 | J3: =DATE(Settings!$C$12,5,1) -> 46143 | K3: =DATE(Settings!$C$12,6,1) -> 46174 | L3: =DATE(Settings!$C$12,7,1) -> 46204 | M3: =DATE(Settings!$C$12,8,1) -> 46235 | N3: =DATE(Settings!$C$12,9,1) -> 46266 | O3: =DATE(Settings!$C$12,10,1) -> 46296 | P3: =DATE(Settings!$C$12,11,1) -> 46327 | Q3: =DATE(Settings!$C$12,12,1) -> 46357
F4: =EOMONTH(F3,0) -> 46053 | G4: =EOMONTH(G3,0) -> 46081 | H4: =EOMONTH(H3,0) -> 46112 | I4: =EOMONTH(I3,0) -> 46142 | J4: =EOMONTH(J3,0) -> 46173 | K4: =EOMONTH(K3,0) -> 46203 | L4: =EOMONTH(L3,0) -> 46234 | M4: =EOMONTH(M3,0) -> 46265 | ... Q4: =EOMONTH(Q3,0) -> 46387
A5: Campaign | B5: Channel | C5: Market | D5: Region | E5: Type | F5: =TEXT(F3,"mmm") -> Jan | G5: =TEXT(G3,"mmm") -> Feb | H5: =TEXT(H3,"mmm") -> Mar | I5: =TEXT(I3,"mmm") -> Apr | J5: =TEXT(J3,"mmm") -> May | K5: =TEXT(K3,"mmm") -> Jun | L5: =TEXT(L3,"mmm") -> Jul | M5: =TEXT(M3,"mmm") -> Aug | ... Q5: =TEXT(Q3,"mmm") -> Dec | R5: ="Total ("&Settings!$C$6&")" -> Total (USD) | S5: Clicks | T5: Conversions | U5: Cost per conversion
A6: Total – all campaigns listed | F6: =SUM(F7:F300) -> 18931.372 | G6: =SUM(G7:G300) -> 40037.16 | H6: =SUM(H7:H300) -> 48500.058 | I6: =SUM(I7:I300) -> 32213.825 | J6: =SUM(J7:J300) -> 34340.138 | K6: =SUM(K7:K300) -> 31409.663 | L6: =SUM(L7:L300) -> 32104.858 | M6: =SUM(M7:M300) -> 22890.523 | ... T6: =SUM(T7:T300) -> 8662.99 | U6: =IF(T6=0,"",R6/T6) -> 32.159957
A7: Geo:EMEA_Objective:lead_Type:prospecting_Budget:abo_Date:20260210 | B7: Meta | C7: EMEA – multi-country | D7: EMEA | E7: Meta – lead ads, prospecting | F7: =IF($A7="","",IF($B7="Meta",SUMIFS('Meta data'!$I$3:$I$20000,'Meta data'!$A$3:$A$20000,">="&F$3,'Meta data'!$A$3:$A$20000,"<="&F$4,'Meta data'!$B$3:$B$20000,$A7),IF($B7="Google Ads",SUMIFS('Google data'!$I$3:$I$20000,'Google data'!$A$3:$A$20000,">="&F$3,'Google data'!$A$3:$A$20000,"<="&F$4,'Google data'!$B$3:$B$20000,$A7),IF($B7="ChatGPT Ads",SUMIFS('ChatGPT data'!$I$3:$I$20000,'ChatGPT data'!$A$3:$A$20000,">="&F$3,'ChatGPT data'!$A$3:$A$20000,"<="&F$4,'ChatGPT data'!$B$3:$B$20000,$A7),IF($B7="LinkedIn Ads",SUMIFS('LinkedIn data'!$I$3:$I$20000,'LinkedIn data'!$A$3:$A$20000,">="&F$3,'LinkedIn data'!$A$3:$A$20000,"<="&F$4,'LinkedIn data'!$B$3:$B$20000,$A7),0))))) -> 0 | G7: =IF($A7="","",IF($B7="Meta",SUMIFS('Meta data'!$I$3:$I$20000,'Meta data'!$A$3:$A$20000,">="&G$3,'Meta data'!$A$3:$A$20000,"<="&G$4,'Meta data'!$B$3:$B$20000,$A7),IF($B7="Google Ads",SUMIFS('Google data'!$I$3:$I$20000,'Google data'!$A$3:$A$20000,">="&G$3,'Google data'!$A$3:$A$20000,"<="&G$4,'Google data'!$B$3:$B$20000,$A7),IF($B7="ChatGPT Ads",SUMIFS('ChatGPT data'!$I$3:$I$20000,'ChatGPT data'!$A$3:$A$20000,">="&G$3,'ChatGPT data'!$A$3:$A$20000,"<="&G$4,'ChatGPT data'!$B$3:$B$20000,$A7),IF($B7="LinkedIn Ads",SUMIFS('LinkedIn data'!$I$3:$I$20000,'LinkedIn data'!$A$3:$A$20000,">="&G$3,'LinkedIn data'!$A$3:$A$20000,"<="&G$4,'LinkedIn data'!$B$3:$B$20000,$A7),0))))) -> 18574.2 | H7: =IF($A7="","",IF($B7="Meta",SUMIFS('Meta data'!$I$3:$I$20000,'Meta data'!$A$3:$A$20000,">="&H$3,'Meta data'!$A$3:$A$20000,"<="&H$4,'Meta data'!$B$3:$B$20000,$A7),IF($B7="Google Ads",SUMIFS('Google data'!$I$3:$I$20000,'Google data'!$A$3:$A$20000,">="&H$3,'Google data'!$A$3:$A$20000,"<="&H$4,'Google data'!$B$3:$B$20000,$A7),IF($B7="ChatGPT Ads",SUMIFS('ChatGPT data'!$I$3:$I$20000,'ChatGPT data'!$A$3:$A$20000,">="&H$3,'ChatGPT data'!$A$3:$A$20000,"<="&H$4,'ChatGPT data'!$B$3:$B$20000,$A7),IF($B7="LinkedIn Ads",SUMIFS('LinkedIn data'!$I$3:$I$20000,'LinkedIn data'!$A$3:$A$20000,">="&H$3,'LinkedIn data'!$A$3:$A$20000,"<="&H$4,'LinkedIn data'!$B$3:$B$20000,$A7),0))))) -> 29346.15 | I7: =IF($A7="","",IF($B7="Meta",SUMIFS('Meta data'!$I$3:$I$20000,'Meta data'!$A$3:$A$20000,">="&I$3,'Meta data'!$A$3:$A$20000,"<="&I$4,'Meta data'!$B$3:$B$20000,$A7),IF($B7="Google Ads",SUMIFS('Google data'!$I$3:$I$20000,'Google data'!$A$3:$A$20000,">="&I$3,'Google data'!$A$3:$A$20000,"<="&I$4,'Google data'!$B$3:$B$20000,$A7),IF($B7="ChatGPT Ads",SUMIFS('ChatGPT data'!$I$3:$I$20000,'ChatGPT data'!$A$3:$A$20000,">="&I$3,'ChatGPT data'!$A$3:$A$20000,"<="&I$4,'ChatGPT data'!$B$3:$B$20000,$A7),IF($B7="LinkedIn Ads",SUMIFS('LinkedIn data'!$I$3:$I$20000,'LinkedIn data'!$A$3:$A$20000,">="&I$3,'LinkedIn data'!$A$3:$A$20000,"<="&I$4,'LinkedIn data'!$B$3:$B$20000,$A7),0))))) -> 8224.89 | J7: =IF($A7="","",IF($B7="Meta",SUMIFS('Meta data'!$I$3:$I$20000,'Meta data'!$A$3:$A$20000,">="&J$3,'Meta data'!$A$3:$A$20000,"<="&J$4,'Meta data'!$B$3:$B$20000,$A7),IF($B7="Google Ads",SUMIFS('Google data'!$I$3:$I$20000,'Google data'!$A$3:$A$20000,">="&J$3,'Google data'!$A$3:$A$20000,"<="&J$4,'Google data'!$B$3:$B$20000,$A7),IF($B7="ChatGPT Ads",SUMIFS('ChatGPT data'!$I$3:$I$20000,'ChatGPT data'!$A$3:$A$20000,">="&J$3,'ChatGPT data'!$A$3:$A$20000,"<="&J$4,'ChatGPT data'!$B$3:$B$20000,$A7),IF($B7="LinkedIn Ads",SUMIFS('LinkedIn data'!$I$3:$I$20000,'LinkedIn data'!$A$3:$A$20000,">="&J$3,'LinkedIn data'!$A$3:$A$20000,"<="&J$4,'LinkedIn data'!$B$3:$B$20000,$A7),0))))) -> 5591.42 | K7: =IF($A7="","",IF($B7="Meta",SUMIFS('Meta data'!$I$3:$I$20000,'Meta data'!$A$3:$A$20000,">="&K$3,'Meta data'!$A$3:$A$20000,"<="&K$4,'Meta data'!$B$3:$B$20000,$A7),IF($B7="Google Ads",SUMIFS('Google data'!$I$3:$I$20000,'Google data'!$A$3:$A$20000,">="&K$3,'Google data'!$A$3:$A$20000,"<="&K$4,'Google data'!$B$3:$B$20000,$A7),IF($B7="ChatGPT Ads",SUMIFS('ChatGPT data'!$I$3:$I$20000,'ChatGPT data'!$A$3:$A$20000,">="&K$3,'ChatGPT data'!$A$3:$A$20000,"<="&K$4,'ChatGPT data'!$B$3:$B$20000,$A7),IF($B7="LinkedIn Ads",SUMIFS('LinkedIn data'!$I$3:$I$20000,'LinkedIn data'!$A$3:$A$20000,">="&K$3,'LinkedIn data'!$A$3:$A$20000,"<="&K$4,'LinkedIn data'!$B$3:$B$20000,$A7),0))))) -> 4885.67 | L7: =IF($A7="","",IF($B7="Meta",SUMIFS('Meta data'!$I$3:$I$20000,'Meta data'!$A$3:$A$20000,">="&L$3,'Meta data'!$A$3:$A$20000,"<="&L$4,'Meta data'!$B$3:$B$20000,$A7),IF($B7="Google Ads",SUMIFS('Google data'!$I$3:$I$20000,'Google data'!$A$3:$A$20000,">="&L$3,'Google data'!$A$3:$A$20000,"<="&L$4,'Google data'!$B$3:$B$20000,$A7),IF($B7="ChatGPT Ads",SUMIFS('ChatGPT data'!$I$3:$I$20000,'ChatGPT data'!$A$3:$A$20000,">="&L$3,'ChatGPT data'!$A$3:$A$20000,"<="&L$4,'ChatGPT data'!$B$3:$B$20000,$A7),IF($B7="LinkedIn Ads",SUMIFS('LinkedIn data'!$I$3:$I$20000,'LinkedIn data'!$A$3:$A$20000,">="&L$3,'LinkedIn data'!$A$3:$A$20000,"<="&L$4,'LinkedIn data'!$B$3:$B$20000,$A7),0))))) -> 5011.85 | M7: =IF($A7="","",IF($B7="Meta",SUMIFS('Meta data'!$I$3:$I$20000,'Meta data'!$A$3:$A$20000,">="&M$3,'Meta data'!$A$3:$A$20000,"<="&M$4,'Meta data'!$B$3:$B$20000,$A7),IF($B7="Google Ads",SUMIFS('Google data'!$I$3:$I$20000,'Google data'!$A$3:$A$20000,">="&M$3,'Google data'!$A$3:$A$20000,"<="&M$4,'Google data'!$B$3:$B$20000,$A7),IF($B7="ChatGPT Ads",SUMIFS('ChatGPT data'!$I$3:$I$20000,'ChatGPT data'!$A$3:$A$20000,">="&M$3,'ChatGPT data'!$A$3:$A$20000,"<="&M$4,'ChatGPT data'!$B$3:$B$20000,$A7),IF($B7="LinkedIn Ads",SUMIFS('LinkedIn data'!$I$3:$I$20000,'LinkedIn data'!$A$3:$A$20000,">="&M$3,'LinkedIn data'!$A$3:$A$20000,"<="&M$4,'LinkedIn data'!$B$3:$B$20000,$A7),0))))) -> 0 | ... Q7: =IF($A7="","",IF($B7="Meta",SUMIFS('Meta data'!$I$3:$I$20000,'Meta data'!$A$3:$A$20000,">="&Q$3,'Meta data'!$A$3:$A$20000,"<="&Q$4,'Meta data'!$B$3:$B$20000,$A7),IF($B7="Google Ads",SUMIFS('Google data'!$I$3:$I$20000,'Google data'!$A$3:$A$20000,">="&Q$3,'Google data'!$A$3:$A$20000,"<="&Q$4,'Google data'!$B$3:$B$20000,$A7),IF($B7="ChatGPT Ads",SUMIFS('ChatGPT data'!$I$3:$I$20000,'ChatGPT data'!$A$3:$A$20000,">="&Q$3,'ChatGPT data'!$A$3:$A$20000,"<="&Q$4,'ChatGPT data'!$B$3:$B$20000,$A7),IF($B7="LinkedIn Ads",SUMIFS('LinkedIn data'!$I$3:$I$20000,'LinkedIn data'!$A$3:$A$20000,">="&Q$3,'LinkedIn data'!$A$3:$A$20000,"<="&Q$4,'LinkedIn data'!$B$3:$B$20000,$A7),0))))) -> 0 | R7: =IF($A7="","",SUM(F7:Q7)) -> 71634.18 | S7: =IF($A7="","",IF($B7="Meta",SUMIFS('Meta data'!$E$3:$E$20000,'Meta data'!$B$3:$B$20000,$A7),IF($B7="Google Ads",SUMIFS('Google data'!$E$3:$E$20000,'Google data'!$B$3:$B$20000,$A7),IF($B7="ChatGPT Ads",SUMIFS('ChatGPT data'!$E$3:$E$20000,'ChatGPT data'!$B$3:$B$20000,$A7),IF($B7="LinkedIn Ads",SUMIFS('LinkedIn data'!$E$3:$E$20000,'LinkedIn data'!$B$3:$B$20000,$A7),0))))) -> 38303 | T7: =IF($A7="","",IF($B7="Meta",SUMIFS('Meta data'!$F$3:$F$20000,'Meta data'!$B$3:$B$20000,$A7),IF($B7="Google Ads",SUMIFS('Google data'!$F$3:$F$20000,'Google data'!$B$3:$B$20000,$A7),IF($B7="ChatGPT Ads",SUMIFS('ChatGPT data'!$F$3:$F$20000,'ChatGPT data'!$B$3:$B$20000,$A7),IF($B7="LinkedIn Ads",SUMIFS('LinkedIn data'!$F$3:$F$20000,'LinkedIn data'!$B$3:$B$20000,$A7),0))))) -> 2238 | U7: =IF(OR($A7="",T7=0),"",R7/T7) -> 32.008123
A8: Geo:EMEA_Objective:lead_Type:prospecting-test_Budget:cbo_Date:20251010 | B8: Meta | C8: EMEA – multi-country | D8: EMEA | E8: Meta – lead ads, prospecting | F8: =IF($A8="","",IF($B8="Meta",SUMIFS('Meta data'!$I$3:$I$20000,'Meta data'!$A$3:$A$20000,">="&F$3,'Meta data'!$A$3:$A$20000,"<="&F$4,'Meta data'!$B$3:$B$20000,$A8),IF($B8="Google Ads",SUMIFS('Google data'!$I$3:$I$20000,'Google data'!$A$3:$A$20000,">="&F$3,'Google data'!$A$3:$A$20000,"<="&F$4,'Google data'!$B$3:$B$20000,$A8),IF($B8="ChatGPT Ads",SUMIFS('ChatGPT data'!$I$3:$I$20000,'ChatGPT data'!$A$3:$A$20000,">="&F$3,'ChatGPT data'!$A$3:$A$20000,"<="&F$4,'ChatGPT data'!$B$3:$B$20000,$A8),IF($B8="LinkedIn Ads",SUMIFS('LinkedIn data'!$I$3:$I$20000,'LinkedIn data'!$A$3:$A$20000,">="&F$3,'LinkedIn data'!$A$3:$A$20000,"<="&F$4,'LinkedIn data'!$B$3:$B$20000,$A8),0))))) -> 2782.56 | G8: =IF($A8="","",IF($B8="Meta",SUMIFS('Meta data'!$I$3:$I$20000,'Meta data'!$A$3:$A$20000,">="&G$3,'Meta data'!$A$3:$A$20000,"<="&G$4,'Meta data'!$B$3:$B$20000,$A8),IF($B8="Google Ads",SUMIFS('Google data'!$I$3:$I$20000,'Google data'!$A$3:$A$20000,">="&G$3,'Google data'!$A$3:$A$20000,"<="&G$4,'Google data'!$B$3:$B$20000,$A8),IF($B8="ChatGPT Ads",SUMIFS('ChatGPT data'!$I$3:$I$20000,'ChatGPT data'!$A$3:$A$20000,">="&G$3,'ChatGPT data'!$A$3:$A$20000,"<="&G$4,'ChatGPT data'!$B$3:$B$20000,$A8),IF($B8="LinkedIn Ads",SUMIFS('LinkedIn data'!$I$3:$I$20000,'LinkedIn data'!$A$3:$A$20000,">="&G$3,'LinkedIn data'!$A$3:$A$20000,"<="&G$4,'LinkedIn data'!$B$3:$B$20000,$A8),0))))) -> 2511.78 | H8: =IF($A8="","",IF($B8="Meta",SUMIFS('Meta data'!$I$3:$I$20000,'Meta data'!$A$3:$A$20000,">="&H$3,'Meta data'!$A$3:$A$20000,"<="&H$4,'Meta data'!$B$3:$B$20000,$A8),IF($B8="Google Ads",SUMIFS('Google data'!$I$3:$I$20000,'Google data'!$A$3:$A$20000,">="&H$3,'Google data'!$A$3:$A$20000,"<="&H$4,'Google data'!$B$3:$B$20000,$A8),IF($B8="ChatGPT Ads",SUMIFS('ChatGPT data'!$I$3:$I$20000,'ChatGPT data'!$A$3:$A$20000,">="&H$3,'ChatGPT data'!$A$3:$A$20000,"<="&H$4,'ChatGPT data'!$B$3:$B$20000,$A8),IF($B8="LinkedIn Ads",SUMIFS('LinkedIn data'!$I$3:$I$20000,'LinkedIn data'!$A$3:$A$20000,">="&H$3,'LinkedIn data'!$A$3:$A$20000,"<="&H$4,'LinkedIn data'!$B$3:$B$20000,$A8),0))))) -> 2776.42 | I8: =IF($A8="","",IF($B8="Meta",SUMIFS('Meta data'!$I$3:$I$20000,'Meta data'!$A$3:$A$20000,">="&I$3,'Meta data'!$A$3:$A$20000,"<="&I$4,'Meta data'!$B$3:$B$20000,$A8),IF($B8="Google Ads",SUMIFS('Google data'!$I$3:$I$20000,'Google data'!$A$3:$A$20000,">="&I$3,'Google data'!$A$3:$A$20000,"<="&I$4,'Google data'!$B$3:$B$20000,$A8),IF($B8="ChatGPT Ads",SUMIFS('ChatGPT data'!$I$3:$I$20000,'ChatGPT data'!$A$3:$A$20000,">="&I$3,'ChatGPT data'!$A$3:$A$20000,"<="&I$4,'ChatGPT data'!$B$3:$B$20000,$A8),IF($B8="LinkedIn Ads",SUMIFS('LinkedIn data'!$I$3:$I$20000,'LinkedIn data'!$A$3:$A$20000,">="&I$3,'LinkedIn data'!$A$3:$A$20000,"<="&I$4,'LinkedIn data'!$B$3:$B$20000,$A8),0))))) -> 2711.28 | J8: =IF($A8="","",IF($B8="Meta",SUMIFS('Meta data'!$I$3:$I$20000,'Meta data'!$A$3:$A$20000,">="&J$3,'Meta data'!$A$3:$A$20000,"<="&J$4,'Meta data'!$B$3:$B$20000,$A8),IF($B8="Google Ads",SUMIFS('Google data'!$I$3:$I$20000,'Google data'!$A$3:$A$20000,">="&J$3,'Google data'!$A$3:$A$20000,"<="&J$4,'Google data'!$B$3:$B$20000,$A8),IF($B8="ChatGPT Ads",SUMIFS('ChatGPT data'!$I$3:$I$20000,'ChatGPT data'!$A$3:$A$20000,">="&J$3,'ChatGPT data'!$A$3:$A$20000,"<="&J$4,'ChatGPT data'!$B$3:$B$20000,$A8),IF($B8="LinkedIn Ads",SUMIFS('LinkedIn data'!$I$3:$I$20000,'LinkedIn data'!$A$3:$A$20000,">="&J$3,'LinkedIn data'!$A$3:$A$20000,"<="&J$4,'LinkedIn data'!$B$3:$B$20000,$A8),0))))) -> 2778.32 | K8: =IF($A8="","",IF($B8="Meta",SUMIFS('Meta data'!$I$3:$I$20000,'Meta data'!$A$3:$A$20000,">="&K$3,'Meta data'!$A$3:$A$20000,"<="&K$4,'Meta data'!$B$3:$B$20000,$A8),IF($B8="Google Ads",SUMIFS('Google data'!$I$3:$I$20000,'Google data'!$A$3:$A$20000,">="&K$3,'Google data'!$A$3:$A$20000,"<="&K$4,'Google data'!$B$3:$B$20000,$A8),IF($B8="ChatGPT Ads",SUMIFS('ChatGPT data'!$I$3:$I$20000,'ChatGPT data'!$A$3:$A$20000,">="&K$3,'ChatGPT data'!$A$3:$A$20000,"<="&K$4,'ChatGPT data'!$B$3:$B$20000,$A8),IF($B8="LinkedIn Ads",SUMIFS('LinkedIn data'!$I$3:$I$20000,'LinkedIn data'!$A$3:$A$20000,">="&K$3,'LinkedIn data'!$A$3:$A$20000,"<="&K$4,'LinkedIn data'!$B$3:$B$20000,$A8),0))))) -> 2697.04 | L8: =IF($A8="","",IF($B8="Meta",SUMIFS('Meta data'!$I$3:$I$20000,'Meta data'!$A$3:$A$20000,">="&L$3,'Meta data'!$A$3:$A$20000,"<="&L$4,'Meta data'!$B$3:$B$20000,$A8),IF($B8="Google Ads",SUMIFS('Google data'!$I$3:$I$20000,'Google data'!$A$3:$A$20000,">="&L$3,'Google data'!$A$3:$A$20000,"<="&L$4,'Google data'!$B$3:$B$20000,$A8),IF($B8="ChatGPT Ads",SUMIFS('ChatGPT data'!$I$3:$I$20000,'ChatGPT data'!$A$3:$A$20000,">="&L$3,'ChatGPT data'!$A$3:$A$20000,"<="&L$4,'ChatGPT data'!$B$3:$B$20000,$A8),IF($B8="LinkedIn Ads",SUMIFS('LinkedIn data'!$I$3:$I$20000,'LinkedIn data'!$A$3:$A$20000,">="&L$3,'LinkedIn data'!$A$3:$A$20000,"<="&L$4,'LinkedIn data'!$B$3:$B$20000,$A8),0))))) -> 1743.28 | M8: =IF($A8="","",IF($B8="Meta",SUMIFS('Meta data'!$I$3:$I$20000,'Meta data'!$A$3:$A$20000,">="&M$3,'Meta data'!$A$3:$A$20000,"<="&M$4,'Meta data'!$B$3:$B$20000,$A8),IF($B8="Google Ads",SUMIFS('Google data'!$I$3:$I$20000,'Google data'!$A$3:$A$20000,">="&M$3,'Google data'!$A$3:$A$20000,"<="&M$4,'Google data'!$B$3:$B$20000,$A8),IF($B8="ChatGPT Ads",SUMIFS('ChatGPT data'!$I$3:$I$20000,'ChatGPT data'!$A$3:$A$20000,">="&M$3,'ChatGPT data'!$A$3:$A$20000,"<="&M$4,'ChatGPT data'!$B$3:$B$20000,$A8),IF($B8="LinkedIn Ads",SUMIFS('LinkedIn data'!$I$3:$I$20000,'LinkedIn data'!$A$3:$A$20000,">="&M$3,'LinkedIn data'!$A$3:$A$20000,"<="&M$4,'LinkedIn data'!$B$3:$B$20000,$A8),0))))) -> 0 | ... Q8: =IF($A8="","",IF($B8="Meta",SUMIFS('Meta data'!$I$3:$I$20000,'Meta data'!$A$3:$A$20000,">="&Q$3,'Meta data'!$A$3:$A$20000,"<="&Q$4,'Meta data'!$B$3:$B$20000,$A8),IF($B8="Google Ads",SUMIFS('Google data'!$I$3:$I$20000,'Google data'!$A$3:$A$20000,">="&Q$3,'Google data'!$A$3:$A$20000,"<="&Q$4,'Google data'!$B$3:$B$20000,$A8),IF($B8="ChatGPT Ads",SUMIFS('ChatGPT data'!$I$3:$I$20000,'ChatGPT data'!$A$3:$A$20000,">="&Q$3,'ChatGPT data'!$A$3:$A$20000,"<="&Q$4,'ChatGPT data'!$B$3:$B$20000,$A8),IF($B8="LinkedIn Ads",SUMIFS('LinkedIn data'!$I$3:$I$20000,'LinkedIn data'!$A$3:$A$20000,">="&Q$3,'LinkedIn data'!$A$3:$A$20000,"<="&Q$4,'LinkedIn data'!$B$3:$B$20000,$A8),0))))) -> 0 | R8: =IF($A8="","",SUM(F8:Q8)) -> 18000.68 | S8: =IF($A8="","",IF($B8="Meta",SUMIFS('Meta data'!$E$3:$E$20000,'Meta data'!$B$3:$B$20000,$A8),IF($B8="Google Ads",SUMIFS('Google data'!$E$3:$E$20000,'Google data'!$B$3:$B$20000,$A8),IF($B8="ChatGPT Ads",SUMIFS('ChatGPT data'!$E$3:$E$20000,'ChatGPT data'!$B$3:$B$20000,$A8),IF($B8="LinkedIn Ads",SUMIFS('LinkedIn data'!$E$3:$E$20000,'LinkedIn data'!$B$3:$B$20000,$A8),0))))) -> 18383 | T8: =IF($A8="","",IF($B8="Meta",SUMIFS('Meta data'!$F$3:$F$20000,'Meta data'!$B$3:$B$20000,$A8),IF($B8="Google Ads",SUMIFS('Google data'!$F$3:$F$20000,'Google data'!$B$3:$B$20000,$A8),IF($B8="ChatGPT Ads",SUMIFS('ChatGPT data'!$F$3:$F$20000,'ChatGPT data'!$B$3:$B$20000,$A8),IF($B8="LinkedIn Ads",SUMIFS('LinkedIn data'!$F$3:$F$20000,'LinkedIn data'!$B$3:$B$20000,$A8),0))))) -> 1505 | U8: =IF(OR($A8="",T8=0),"",R8/T8) -> 11.960585
A9: Geo:US-EastCoast_Objective:lead_Type:prospecting_Budget:cbo_Date:20260409 | B9: Meta | C9: US East Coast | D9: Americas | E9: Meta – lead ads, prospecting | F9: =IF($A9="","",IF($B9="Meta",SUMIFS('Meta data'!$I$3:$I$20000,'Meta data'!$A$3:$A$20000,">="&F$3,'Meta data'!$A$3:$A$20000,"<="&F$4,'Meta data'!$B$3:$B$20000,$A9),IF($B9="Google Ads",SUMIFS('Google data'!$I$3:$I$20000,'Google data'!$A$3:$A$20000,">="&F$3,'Google data'!$A$3:$A$20000,"<="&F$4,'Google data'!$B$3:$B$20000,$A9),IF($B9="ChatGPT Ads",SUMIFS('ChatGPT data'!$I$3:$I$20000,'ChatGPT data'!$A$3:$A$20000,">="&F$3,'ChatGPT data'!$A$3:$A$20000,"<="&F$4,'ChatGPT data'!$B$3:$B$20000,$A9),IF($B9="LinkedIn Ads",SUMIFS('LinkedIn data'!$I$3:$I$20000,'LinkedIn data'!$A$3:$A$20000,">="&F$3,'LinkedIn data'!$A$3:$A$20000,"<="&F$4,'LinkedIn data'!$B$3:$B$20000,$A9),0))))) -> 0 | G9: =IF($A9="","",IF($B9="Meta",SUMIFS('Meta data'!$I$3:$I$20000,'Meta data'!$A$3:$A$20000,">="&G$3,'Meta data'!$A$3:$A$20000,"<="&G$4,'Meta data'!$B$3:$B$20000,$A9),IF($B9="Google Ads",SUMIFS('Google data'!$I$3:$I$20000,'Google data'!$A$3:$A$20000,">="&G$3,'Google data'!$A$3:$A$20000,"<="&G$4,'Google data'!$B$3:$B$20000,$A9),IF($B9="ChatGPT Ads",SUMIFS('ChatGPT data'!$I$3:$I$20000,'ChatGPT data'!$A$3:$A$20000,">="&G$3,'ChatGPT data'!$A$3:$A$20000,"<="&G$4,'ChatGPT data'!$B$3:$B$20000,$A9),IF($B9="LinkedIn Ads",SUMIFS('LinkedIn data'!$I$3:$I$20000,'LinkedIn data'!$A$3:$A$20000,">="&G$3,'LinkedIn data'!$A$3:$A$20000,"<="&G$4,'LinkedIn data'!$B$3:$B$20000,$A9),0))))) -> 0 | H9: =IF($A9="","",IF($B9="Meta",SUMIFS('Meta data'!$I$3:$I$20000,'Meta data'!$A$3:$A$20000,">="&H$3,'Meta data'!$A$3:$A$20000,"<="&H$4,'Meta data'!$B$3:$B$20000,$A9),IF($B9="Google Ads",SUMIFS('Google data'!$I$3:$I$20000,'Google data'!$A$3:$A$20000,">="&H$3,'Google data'!$A$3:$A$20000,"<="&H$4,'Google data'!$B$3:$B$20000,$A9),IF($B9="ChatGPT Ads",SUMIFS('ChatGPT data'!$I$3:$I$20000,'ChatGPT data'!$A$3:$A$20000,">="&H$3,'ChatGPT data'!$A$3:$A$20000,"<="&H$4,'ChatGPT data'!$B$3:$B$20000,$A9),IF($B9="LinkedIn Ads",SUMIFS('LinkedIn data'!$I$3:$I$20000,'LinkedIn data'!$A$3:$A$20000,">="&H$3,'LinkedIn data'!$A$3:$A$20000,"<="&H$4,'LinkedIn data'!$B$3:$B$20000,$A9),0))))) -> 0 | I9: =IF($A9="","",IF($B9="Meta",SUMIFS('Meta data'!$I$3:$I$20000,'Meta data'!$A$3:$A$20000,">="&I$3,'Meta data'!$A$3:$A$20000,"<="&I$4,'Meta data'!$B$3:$B$20000,$A9),IF($B9="Google Ads",SUMIFS('Google data'!$I$3:$I$20000,'Google data'!$A$3:$A$20000,">="&I$3,'Google data'!$A$3:$A$20000,"<="&I$4,'Google data'!$B$3:$B$20000,$A9),IF($B9="ChatGPT Ads",SUMIFS('ChatGPT data'!$I$3:$I$20000,'ChatGPT data'!$A$3:$A$20000,">="&I$3,'ChatGPT data'!$A$3:$A$20000,"<="&I$4,'ChatGPT data'!$B$3:$B$20000,$A9),IF($B9="LinkedIn Ads",SUMIFS('LinkedIn data'!$I$3:$I$20000,'LinkedIn data'!$A$3:$A$20000,">="&I$3,'LinkedIn data'!$A$3:$A$20000,"<="&I$4,'LinkedIn data'!$B$3:$B$20000,$A9),0))))) -> 5268.88 | J9: =IF($A9="","",IF($B9="Meta",SUMIFS('Meta data'!$I$3:$I$20000,'Meta data'!$A$3:$A$20000,">="&J$3,'Meta data'!$A$3:$A$20000,"<="&J$4,'Meta data'!$B$3:$B$20000,$A9),IF($B9="Google Ads",SUMIFS('Google data'!$I$3:$I$20000,'Google data'!$A$3:$A$20000,">="&J$3,'Google data'!$A$3:$A$20000,"<="&J$4,'Google data'!$B$3:$B$20000,$A9),IF($B9="ChatGPT Ads",SUMIFS('ChatGPT data'!$I$3:$I$20000,'ChatGPT data'!$A$3:$A$20000,">="&J$3,'ChatGPT data'!$A$3:$A$20000,"<="&J$4,'ChatGPT data'!$B$3:$B$20000,$A9),IF($B9="LinkedIn Ads",SUMIFS('LinkedIn data'!$I$3:$I$20000,'LinkedIn data'!$A$3:$A$20000,">="&J$3,'LinkedIn data'!$A$3:$A$20000,"<="&J$4,'LinkedIn data'!$B$3:$B$20000,$A9),0))))) -> 7877.6 | K9: =IF($A9="","",IF($B9="Meta",SUMIFS('Meta data'!$I$3:$I$20000,'Meta data'!$A$3:$A$20000,">="&K$3,'Meta data'!$A$3:$A$20000,"<="&K$4,'Meta data'!$B$3:$B$20000,$A9),IF($B9="Google Ads",SUMIFS('Google data'!$I$3:$I$20000,'Google data'!$A$3:$A$20000,">="&K$3,'Google data'!$A$3:$A$20000,"<="&K$4,'Google data'!$B$3:$B$20000,$A9),IF($B9="ChatGPT Ads",SUMIFS('ChatGPT data'!$I$3:$I$20000,'ChatGPT data'!$A$3:$A$20000,">="&K$3,'ChatGPT data'!$A$3:$A$20000,"<="&K$4,'ChatGPT data'!$B$3:$B$20000,$A9),IF($B9="LinkedIn Ads",SUMIFS('LinkedIn data'!$I$3:$I$20000,'LinkedIn data'!$A$3:$A$20000,">="&K$3,'LinkedIn data'!$A$3:$A$20000,"<="&K$4,'LinkedIn data'!$B$3:$B$20000,$A9),0))))) -> 2560.21 | L9: =IF($A9="","",IF($B9="Meta",SUMIFS('Meta data'!$I$3:$I$20000,'Meta data'!$A$3:$A$20000,">="&L$3,'Meta data'!$A$3:$A$20000,"<="&L$4,'Meta data'!$B$3:$B$20000,$A9),IF($B9="Google Ads",SUMIFS('Google data'!$I$3:$I$20000,'Google data'!$A$3:$A$20000,">="&L$3,'Google data'!$A$3:$A$20000,"<="&L$4,'Google data'!$B$3:$B$20000,$A9),IF($B9="ChatGPT Ads",SUMIFS('ChatGPT data'!$I$3:$I$20000,'ChatGPT data'!$A$3:$A$20000,">="&L$3,'ChatGPT data'!$A$3:$A$20000,"<="&L$4,'ChatGPT data'!$B$3:$B$20000,$A9),IF($B9="LinkedIn Ads",SUMIFS('LinkedIn data'!$I$3:$I$20000,'LinkedIn data'!$A$3:$A$20000,">="&L$3,'LinkedIn data'!$A$3:$A$20000,"<="&L$4,'LinkedIn data'!$B$3:$B$20000,$A9),0))))) -> 0 | M9: =IF($A9="","",IF($B9="Meta",SUMIFS('Meta data'!$I$3:$I$20000,'Meta data'!$A$3:$A$20000,">="&M$3,'Meta data'!$A$3:$A$20000,"<="&M$4,'Meta data'!$B$3:$B$20000,$A9),IF($B9="Google Ads",SUMIFS('Google data'!$I$3:$I$20000,'Google data'!$A$3:$A$20000,">="&M$3,'Google data'!$A$3:$A$20000,"<="&M$4,'Google data'!$B$3:$B$20000,$A9),IF($B9="ChatGPT Ads",SUMIFS('ChatGPT data'!$I$3:$I$20000,'ChatGPT data'!$A$3:$A$20000,">="&M$3,'ChatGPT data'!$A$3:$A$20000,"<="&M$4,'ChatGPT data'!$B$3:$B$20000,$A9),IF($B9="LinkedIn Ads",SUMIFS('LinkedIn data'!$I$3:$I$20000,'LinkedIn data'!$A$3:$A$20000,">="&M$3,'LinkedIn data'!$A$3:$A$20000,"<="&M$4,'LinkedIn data'!$B$3:$B$20000,$A9),0))))) -> 0 | ... Q9: =IF($A9="","",IF($B9="Meta",SUMIFS('Meta data'!$I$3:$I$20000,'Meta data'!$A$3:$A$20000,">="&Q$3,'Meta data'!$A$3:$A$20000,"<="&Q$4,'Meta data'!$B$3:$B$20000,$A9),IF($B9="Google Ads",SUMIFS('Google data'!$I$3:$I$20000,'Google data'!$A$3:$A$20000,">="&Q$3,'Google data'!$A$3:$A$20000,"<="&Q$4,'Google data'!$B$3:$B$20000,$A9),IF($B9="ChatGPT Ads",SUMIFS('ChatGPT data'!$I$3:$I$20000,'ChatGPT data'!$A$3:$A$20000,">="&Q$3,'ChatGPT data'!$A$3:$A$20000,"<="&Q$4,'ChatGPT data'!$B$3:$B$20000,$A9),IF($B9="LinkedIn Ads",SUMIFS('LinkedIn data'!$I$3:$I$20000,'LinkedIn data'!$A$3:$A$20000,">="&Q$3,'LinkedIn data'!$A$3:$A$20000,"<="&Q$4,'LinkedIn data'!$B$3:$B$20000,$A9),0))))) -> 0 | R9: =IF($A9="","",SUM(F9:Q9)) -> 15706.69 | S9: =IF($A9="","",IF($B9="Meta",SUMIFS('Meta data'!$E$3:$E$20000,'Meta data'!$B$3:$B$20000,$A9),IF($B9="Google Ads",SUMIFS('Google data'!$E$3:$E$20000,'Google data'!$B$3:$B$20000,$A9),IF($B9="ChatGPT Ads",SUMIFS('ChatGPT data'!$E$3:$E$20000,'ChatGPT data'!$B$3:$B$20000,$A9),IF($B9="LinkedIn Ads",SUMIFS('LinkedIn data'!$E$3:$E$20000,'LinkedIn data'!$B$3:$B$20000,$A9),0))))) -> 4117 | T9: =IF($A9="","",IF($B9="Meta",SUMIFS('Meta data'!$F$3:$F$20000,'Meta data'!$B$3:$B$20000,$A9),IF($B9="Google Ads",SUMIFS('Google data'!$F$3:$F$20000,'Google data'!$B$3:$B$20000,$A9),IF($B9="ChatGPT Ads",SUMIFS('ChatGPT data'!$F$3:$F$20000,'ChatGPT data'!$B$3:$B$20000,$A9),IF($B9="LinkedIn Ads",SUMIFS('LinkedIn data'!$F$3:$F$20000,'LinkedIn data'!$B$3:$B$20000,$A9),0))))) -> 350 | U9: =IF(OR($A9="",T9=0),"",R9/T9) -> 44.876257
A10: Geo:USCA_Objective:lead_Type:prospecting_Budget:cbo_Date:20251010 | B10: Meta | C10: US & Canada | D10: Americas | E10: Meta – lead ads, prospecting | F10: =IF($A10="","",IF($B10="Meta",SUMIFS('Meta data'!$I$3:$I$20000,'Meta data'!$A$3:$A$20000,">="&F$3,'Meta data'!$A$3:$A$20000,"<="&F$4,'Meta data'!$B$3:$B$20000,$A10),IF($B10="Google Ads",SUMIFS('Google data'!$I$3:$I$20000,'Google data'!$A$3:$A$20000,">="&F$3,'Google data'!$A$3:$A$20000,"<="&F$4,'Google data'!$B$3:$B$20000,$A10),IF($B10="ChatGPT Ads",SUMIFS('ChatGPT data'!$I$3:$I$20000,'ChatGPT data'!$A$3:$A$20000,">="&F$3,'ChatGPT data'!$A$3:$A$20000,"<="&F$4,'ChatGPT data'!$B$3:$B$20000,$A10),IF($B10="LinkedIn Ads",SUMIFS('LinkedIn data'!$I$3:$I$20000,'LinkedIn data'!$A$3:$A$20000,">="&F$3,'LinkedIn data'!$A$3:$A$20000,"<="&F$4,'LinkedIn data'!$B$3:$B$20000,$A10),0))))) -> 2148.71 | G10: =IF($A10="","",IF($B10="Meta",SUMIFS('Meta data'!$I$3:$I$20000,'Meta data'!$A$3:$A$20000,">="&G$3,'Meta data'!$A$3:$A$20000,"<="&G$4,'Meta data'!$B$3:$B$20000,$A10),IF($B10="Google Ads",SUMIFS('Google data'!$I$3:$I$20000,'Google data'!$A$3:$A$20000,">="&G$3,'Google data'!$A$3:$A$20000,"<="&G$4,'Google data'!$B$3:$B$20000,$A10),IF($B10="ChatGPT Ads",SUMIFS('ChatGPT data'!$I$3:$I$20000,'ChatGPT data'!$A$3:$A$20000,">="&G$3,'ChatGPT data'!$A$3:$A$20000,"<="&G$4,'ChatGPT data'!$B$3:$B$20000,$A10),IF($B10="LinkedIn Ads",SUMIFS('LinkedIn data'!$I$3:$I$20000,'LinkedIn data'!$A$3:$A$20000,">="&G$3,'LinkedIn data'!$A$3:$A$20000,"<="&G$4,'LinkedIn data'!$B$3:$B$20000,$A10),0))))) -> 1948.23 | H10: =IF($A10="","",IF($B10="Meta",SUMIFS('Meta data'!$I$3:$I$20000,'Meta data'!$A$3:$A$20000,">="&H$3,'Meta data'!$A$3:$A$20000,"<="&H$4,'Meta data'!$B$3:$B$20000,$A10),IF($B10="Google Ads",SUMIFS('Google data'!$I$3:$I$20000,'Google data'!$A$3:$A$20000,">="&H$3,'Google data'!$A$3:$A$20000,"<="&H$4,'Google data'!$B$3:$B$20000,$A10),IF($B10="ChatGPT Ads",SUMIFS('ChatGPT data'!$I$3:$I$20000,'ChatGPT data'!$A$3:$A$20000,">="&H$3,'ChatGPT data'!$A$3:$A$20000,"<="&H$4,'ChatGPT data'!$B$3:$B$20000,$A10),IF($B10="LinkedIn Ads",SUMIFS('LinkedIn data'!$I$3:$I$20000,'LinkedIn data'!$A$3:$A$20000,">="&H$3,'LinkedIn data'!$A$3:$A$20000,"<="&H$4,'LinkedIn data'!$B$3:$B$20000,$A10),0))))) -> 2200.97 | I10: =IF($A10="","",IF($B10="Meta",SUMIFS('Meta data'!$I$3:$I$20000,'Meta data'!$A$3:$A$20000,">="&I$3,'Meta data'!$A$3:$A$20000,"<="&I$4,'Meta data'!$B$3:$B$20000,$A10),IF($B10="Google Ads",SUMIFS('Google data'!$I$3:$I$20000,'Google data'!$A$3:$A$20000,">="&I$3,'Google data'!$A$3:$A$20000,"<="&I$4,'Google data'!$B$3:$B$20000,$A10),IF($B10="ChatGPT Ads",SUMIFS('ChatGPT data'!$I$3:$I$20000,'ChatGPT data'!$A$3:$A$20000,">="&I$3,'ChatGPT data'!$A$3:$A$20000,"<="&I$4,'ChatGPT data'!$B$3:$B$20000,$A10),IF($B10="LinkedIn Ads",SUMIFS('LinkedIn data'!$I$3:$I$20000,'LinkedIn data'!$A$3:$A$20000,">="&I$3,'LinkedIn data'!$A$3:$A$20000,"<="&I$4,'LinkedIn data'!$B$3:$B$20000,$A10),0))))) -> 2116.08 | J10: =IF($A10="","",IF($B10="Meta",SUMIFS('Meta data'!$I$3:$I$20000,'Meta data'!$A$3:$A$20000,">="&J$3,'Meta data'!$A$3:$A$20000,"<="&J$4,'Meta data'!$B$3:$B$20000,$A10),IF($B10="Google Ads",SUMIFS('Google data'!$I$3:$I$20000,'Google data'!$A$3:$A$20000,">="&J$3,'Google data'!$A$3:$A$20000,"<="&J$4,'Google data'!$B$3:$B$20000,$A10),IF($B10="ChatGPT Ads",SUMIFS('ChatGPT data'!$I$3:$I$20000,'ChatGPT data'!$A$3:$A$20000,">="&J$3,'ChatGPT data'!$A$3:$A$20000,"<="&J$4,'ChatGPT data'!$B$3:$B$20000,$A10),IF($B10="LinkedIn Ads",SUMIFS('LinkedIn data'!$I$3:$I$20000,'LinkedIn data'!$A$3:$A$20000,">="&J$3,'LinkedIn data'!$A$3:$A$20000,"<="&J$4,'LinkedIn data'!$B$3:$B$20000,$A10),0))))) -> 2121.95 | K10: =IF($A10="","",IF($B10="Meta",SUMIFS('Meta data'!$I$3:$I$20000,'Meta data'!$A$3:$A$20000,">="&K$3,'Meta data'!$A$3:$A$20000,"<="&K$4,'Meta data'!$B$3:$B$20000,$A10),IF($B10="Google Ads",SUMIFS('Google data'!$I$3:$I$20000,'Google data'!$A$3:$A$20000,">="&K$3,'Google data'!$A$3:$A$20000,"<="&K$4,'Google data'!$B$3:$B$20000,$A10),IF($B10="ChatGPT Ads",SUMIFS('ChatGPT data'!$I$3:$I$20000,'ChatGPT data'!$A$3:$A$20000,">="&K$3,'ChatGPT data'!$A$3:$A$20000,"<="&K$4,'ChatGPT data'!$B$3:$B$20000,$A10),IF($B10="LinkedIn Ads",SUMIFS('LinkedIn data'!$I$3:$I$20000,'LinkedIn data'!$A$3:$A$20000,">="&K$3,'LinkedIn data'!$A$3:$A$20000,"<="&K$4,'LinkedIn data'!$B$3:$B$20000,$A10),0))))) -> 1152.63 | L10: =IF($A10="","",IF($B10="Meta",SUMIFS('Meta data'!$I$3:$I$20000,'Meta data'!$A$3:$A$20000,">="&L$3,'Meta data'!$A$3:$A$20000,"<="&L$4,'Meta data'!$B$3:$B$20000,$A10),IF($B10="Google Ads",SUMIFS('Google data'!$I$3:$I$20000,'Google data'!$A$3:$A$20000,">="&L$3,'Google data'!$A$3:$A$20000,"<="&L$4,'Google data'!$B$3:$B$20000,$A10),IF($B10="ChatGPT Ads",SUMIFS('ChatGPT data'!$I$3:$I$20000,'ChatGPT data'!$A$3:$A$20000,">="&L$3,'ChatGPT data'!$A$3:$A$20000,"<="&L$4,'ChatGPT data'!$B$3:$B$20000,$A10),IF($B10="LinkedIn Ads",SUMIFS('LinkedIn data'!$I$3:$I$20000,'LinkedIn data'!$A$3:$A$20000,">="&L$3,'LinkedIn data'!$A$3:$A$20000,"<="&L$4,'LinkedIn data'!$B$3:$B$20000,$A10),0))))) -> 0 | M10: =IF($A10="","",IF($B10="Meta",SUMIFS('Meta data'!$I$3:$I$20000,'Meta data'!$A$3:$A$20000,">="&M$3,'Meta data'!$A$3:$A$20000,"<="&M$4,'Meta data'!$B$3:$B$20000,$A10),IF($B10="Google Ads",SUMIFS('Google data'!$I$3:$I$20000,'Google data'!$A$3:$A$20000,">="&M$3,'Google data'!$A$3:$A$20000,"<="&M$4,'Google data'!$B$3:$B$20000,$A10),IF($B10="ChatGPT Ads",SUMIFS('ChatGPT data'!$I$3:$I$20000,'ChatGPT data'!$A$3:$A$20000,">="&M$3,'ChatGPT data'!$A$3:$A$20000,"<="&M$4,'ChatGPT data'!$B$3:$B$20000,$A10),IF($B10="LinkedIn Ads",SUMIFS('LinkedIn data'!$I$3:$I$20000,'LinkedIn data'!$A$3:$A$20000,">="&M$3,'LinkedIn data'!$A$3:$A$20000,"<="&M$4,'LinkedIn data'!$B$3:$B$20000,$A10),0))))) -> 0 | ... Q10: =IF($A10="","",IF($B10="Meta",SUMIFS('Meta data'!$I$3:$I$20000,'Meta data'!$A$3:$A$20000,">="&Q$3,'Meta data'!$A$3:$A$20000,"<="&Q$4,'Meta data'!$B$3:$B$20000,$A10),IF($B10="Google Ads",SUMIFS('Google data'!$I$3:$I$20000,'Google data'!$A$3:$A$20000,">="&Q$3,'Google data'!$A$3:$A$20000,"<="&Q$4,'Google data'!$B$3:$B$20000,$A10),IF($B10="ChatGPT Ads",SUMIFS('ChatGPT data'!$I$3:$I$20000,'ChatGPT data'!$A$3:$A$20000,">="&Q$3,'ChatGPT data'!$A$3:$A$20000,"<="&Q$4,'ChatGPT data'!$B$3:$B$20000,$A10),IF($B10="LinkedIn Ads",SUMIFS('LinkedIn data'!$I$3:$I$20000,'LinkedIn data'!$A$3:$A$20000,">="&Q$3,'LinkedIn data'!$A$3:$A$20000,"<="&Q$4,'LinkedIn data'!$B$3:$B$20000,$A10),0))))) -> 0 | R10: =IF($A10="","",SUM(F10:Q10)) -> 11688.57 | S10: =IF($A10="","",IF($B10="Meta",SUMIFS('Meta data'!$E$3:$E$20000,'Meta data'!$B$3:$B$20000,$A10),IF($B10="Google Ads",SUMIFS('Google data'!$E$3:$E$20000,'Google data'!$B$3:$B$20000,$A10),IF($B10="ChatGPT Ads",SUMIFS('ChatGPT data'!$E$3:$E$20000,'ChatGPT data'!$B$3:$B$20000,$A10),IF($B10="LinkedIn Ads",SUMIFS('LinkedIn data'!$E$3:$E$20000,'LinkedIn data'!$B$3:$B$20000,$A10),0))))) -> 4444 | T10: =IF($A10="","",IF($B10="Meta",SUMIFS('Meta data'!$F$3:$F$20000,'Meta data'!$B$3:$B$20000,$A10),IF($B10="Google Ads",SUMIFS('Google data'!$F$3:$F$20000,'Google data'!$B$3:$B$20000,$A10),IF($B10="ChatGPT Ads",SUMIFS('ChatGPT data'!$F$3:$F$20000,'ChatGPT data'!$B$3:$B$20000,$A10),IF($B10="LinkedIn Ads",SUMIFS('LinkedIn data'!$F$3:$F$20000,'LinkedIn data'!$B$3:$B$20000,$A10),0))))) -> 700 | U10: =IF(OR($A10="",T10=0),"",R10/T10) -> 16.697957
A11: Geo:California_Objective:lead_Type:prospecting-test_Budget:cbo_Date:20260115 | B11: Meta | C11: California | D11: Americas | E11: Meta – lead ads, prospecting | F11: =IF($A11="","",IF($B11="Meta",SUMIFS('Meta data'!$I$3:$I$20000,'Meta data'!$A$3:$A$20000,">="&F$3,'Meta data'!$A$3:$A$20000,"<="&F$4,'Meta data'!$B$3:$B$20000,$A11),IF($B11="Google Ads",SUMIFS('Google data'!$I$3:$I$20000,'Google data'!$A$3:$A$20000,">="&F$3,'Google data'!$A$3:$A$20000,"<="&F$4,'Google data'!$B$3:$B$20000,$A11),IF($B11="ChatGPT Ads",SUMIFS('ChatGPT data'!$I$3:$I$20000,'ChatGPT data'!$A$3:$A$20000,">="&F$3,'ChatGPT data'!$A$3:$A$20000,"<="&F$4,'ChatGPT data'!$B$3:$B$20000,$A11),IF($B11="LinkedIn Ads",SUMIFS('LinkedIn data'!$I$3:$I$20000,'LinkedIn data'!$A$3:$A$20000,">="&F$3,'LinkedIn data'!$A$3:$A$20000,"<="&F$4,'LinkedIn data'!$B$3:$B$20000,$A11),0))))) -> 628.57 | G11: =IF($A11="","",IF($B11="Meta",SUMIFS('Meta data'!$I$3:$I$20000,'Meta data'!$A$3:$A$20000,">="&G$3,'Meta data'!$A$3:$A$20000,"<="&G$4,'Meta data'!$B$3:$B$20000,$A11),IF($B11="Google Ads",SUMIFS('Google data'!$I$3:$I$20000,'Google data'!$A$3:$A$20000,">="&G$3,'Google data'!$A$3:$A$20000,"<="&G$4,'Google data'!$B$3:$B$20000,$A11),IF($B11="ChatGPT Ads",SUMIFS('ChatGPT data'!$I$3:$I$20000,'ChatGPT data'!$A$3:$A$20000,">="&G$3,'ChatGPT data'!$A$3:$A$20000,"<="&G$4,'ChatGPT data'!$B$3:$B$20000,$A11),IF($B11="LinkedIn Ads",SUMIFS('LinkedIn data'!$I$3:$I$20000,'LinkedIn data'!$A$3:$A$20000,">="&G$3,'LinkedIn data'!$A$3:$A$20000,"<="&G$4,'LinkedIn data'!$B$3:$B$20000,$A11),0))))) -> 2516.8 | H11: =IF($A11="","",IF($B11="Meta",SUMIFS('Meta data'!$I$3:$I$20000,'Meta data'!$A$3:$A$20000,">="&H$3,'Meta data'!$A$3:$A$20000,"<="&H$4,'Meta data'!$B$3:$B$20000,$A11),IF($B11="Google Ads",SUMIFS('Google data'!$I$3:$I$20000,'Google data'!$A$3:$A$20000,">="&H$3,'Google data'!$A$3:$A$20000,"<="&H$4,'Google data'!$B$3:$B$20000,$A11),IF($B11="ChatGPT Ads",SUMIFS('ChatGPT data'!$I$3:$I$20000,'ChatGPT data'!$A$3:$A$20000,">="&H$3,'ChatGPT data'!$A$3:$A$20000,"<="&H$4,'ChatGPT data'!$B$3:$B$20000,$A11),IF($B11="LinkedIn Ads",SUMIFS('LinkedIn data'!$I$3:$I$20000,'LinkedIn data'!$A$3:$A$20000,">="&H$3,'LinkedIn data'!$A$3:$A$20000,"<="&H$4,'LinkedIn data'!$B$3:$B$20000,$A11),0))))) -> 2809.01 | I11: =IF($A11="","",IF($B11="Meta",SUMIFS('Meta data'!$I$3:$I$20000,'Meta data'!$A$3:$A$20000,">="&I$3,'Meta data'!$A$3:$A$20000,"<="&I$4,'Meta data'!$B$3:$B$20000,$A11),IF($B11="Google Ads",SUMIFS('Google data'!$I$3:$I$20000,'Google data'!$A$3:$A$20000,">="&I$3,'Google data'!$A$3:$A$20000,"<="&I$4,'Google data'!$B$3:$B$20000,$A11),IF($B11="ChatGPT Ads",SUMIFS('ChatGPT data'!$I$3:$I$20000,'ChatGPT data'!$A$3:$A$20000,">="&I$3,'ChatGPT data'!$A$3:$A$20000,"<="&I$4,'ChatGPT data'!$B$3:$B$20000,$A11),IF($B11="LinkedIn Ads",SUMIFS('LinkedIn data'!$I$3:$I$20000,'LinkedIn data'!$A$3:$A$20000,">="&I$3,'LinkedIn data'!$A$3:$A$20000,"<="&I$4,'LinkedIn data'!$B$3:$B$20000,$A11),0))))) -> 2737.77 | J11: =IF($A11="","",IF($B11="Meta",SUMIFS('Meta data'!$I$3:$I$20000,'Meta data'!$A$3:$A$20000,">="&J$3,'Meta data'!$A$3:$A$20000,"<="&J$4,'Meta data'!$B$3:$B$20000,$A11),IF($B11="Google Ads",SUMIFS('Google data'!$I$3:$I$20000,'Google data'!$A$3:$A$20000,">="&J$3,'Google data'!$A$3:$A$20000,"<="&J$4,'Google data'!$B$3:$B$20000,$A11),IF($B11="ChatGPT Ads",SUMIFS('ChatGPT data'!$I$3:$I$20000,'ChatGPT data'!$A$3:$A$20000,">="&J$3,'ChatGPT data'!$A$3:$A$20000,"<="&J$4,'ChatGPT data'!$B$3:$B$20000,$A11),IF($B11="LinkedIn Ads",SUMIFS('LinkedIn data'!$I$3:$I$20000,'LinkedIn data'!$A$3:$A$20000,">="&J$3,'LinkedIn data'!$A$3:$A$20000,"<="&J$4,'LinkedIn data'!$B$3:$B$20000,$A11),0))))) -> 2733.67 | K11: =IF($A11="","",IF($B11="Meta",SUMIFS('Meta data'!$I$3:$I$20000,'Meta data'!$A$3:$A$20000,">="&K$3,'Meta data'!$A$3:$A$20000,"<="&K$4,'Meta data'!$B$3:$B$20000,$A11),IF($B11="Google Ads",SUMIFS('Google data'!$I$3:$I$20000,'Google data'!$A$3:$A$20000,">="&K$3,'Google data'!$A$3:$A$20000,"<="&K$4,'Google data'!$B$3:$B$20000,$A11),IF($B11="ChatGPT Ads",SUMIFS('ChatGPT data'!$I$3:$I$20000,'ChatGPT data'!$A$3:$A$20000,">="&K$3,'ChatGPT data'!$A$3:$A$20000,"<="&K$4,'ChatGPT data'!$B$3:$B$20000,$A11),IF($B11="LinkedIn Ads",SUMIFS('LinkedIn data'!$I$3:$I$20000,'LinkedIn data'!$A$3:$A$20000,">="&K$3,'LinkedIn data'!$A$3:$A$20000,"<="&K$4,'LinkedIn data'!$B$3:$B$20000,$A11),0))))) -> 144.2 | L11: =IF($A11="","",IF($B11="Meta",SUMIFS('Meta data'!$I$3:$I$20000,'Meta data'!$A$3:$A$20000,">="&L$3,'Meta data'!$A$3:$A$20000,"<="&L$4,'Meta data'!$B$3:$B$20000,$A11),IF($B11="Google Ads",SUMIFS('Google data'!$I$3:$I$20000,'Google data'!$A$3:$A$20000,">="&L$3,'Google data'!$A$3:$A$20000,"<="&L$4,'Google data'!$B$3:$B$20000,$A11),IF($B11="ChatGPT Ads",SUMIFS('ChatGPT data'!$I$3:$I$20000,'ChatGPT data'!$A$3:$A$20000,">="&L$3,'ChatGPT data'!$A$3:$A$20000,"<="&L$4,'ChatGPT data'!$B$3:$B$20000,$A11),IF($B11="LinkedIn Ads",SUMIFS('LinkedIn data'!$I$3:$I$20000,'LinkedIn data'!$A$3:$A$20000,">="&L$3,'LinkedIn data'!$A$3:$A$20000,"<="&L$4,'LinkedIn data'!$B$3:$B$20000,$A11),0))))) -> 0 | M11: =IF($A11="","",IF($B11="Meta",SUMIFS('Meta data'!$I$3:$I$20000,'Meta data'!$A$3:$A$20000,">="&M$3,'Meta data'!$A$3:$A$20000,"<="&M$4,'Meta data'!$B$3:$B$20000,$A11),IF($B11="Google Ads",SUMIFS('Google data'!$I$3:$I$20000,'Google data'!$A$3:$A$20000,">="&M$3,'Google data'!$A$3:$A$20000,"<="&M$4,'Google data'!$B$3:$B$20000,$A11),IF($B11="ChatGPT Ads",SUMIFS('ChatGPT data'!$I$3:$I$20000,'ChatGPT data'!$A$3:$A$20000,">="&M$3,'ChatGPT data'!$A$3:$A$20000,"<="&M$4,'ChatGPT data'!$B$3:$B$20000,$A11),IF($B11="LinkedIn Ads",SUMIFS('LinkedIn data'!$I$3:$I$20000,'LinkedIn data'!$A$3:$A$20000,">="&M$3,'LinkedIn data'!$A$3:$A$20000,"<="&M$4,'LinkedIn data'!$B$3:$B$20000,$A11),0))))) -> 0 | ... Q11: =IF($A11="","",IF($B11="Meta",SUMIFS('Meta data'!$I$3:$I$20000,'Meta data'!$A$3:$A$20000,">="&Q$3,'Meta data'!$A$3:$A$20000,"<="&Q$4,'Meta data'!$B$3:$B$20000,$A11),IF($B11="Google Ads",SUMIFS('Google data'!$I$3:$I$20000,'Google data'!$A$3:$A$20000,">="&Q$3,'Google data'!$A$3:$A$20000,"<="&Q$4,'Google data'!$B$3:$B$20000,$A11),IF($B11="ChatGPT Ads",SUMIFS('ChatGPT data'!$I$3:$I$20000,'ChatGPT data'!$A$3:$A$20000,">="&Q$3,'ChatGPT data'!$A$3:$A$20000,"<="&Q$4,'ChatGPT data'!$B$3:$B$20000,$A11),IF($B11="LinkedIn Ads",SUMIFS('LinkedIn data'!$I$3:$I$20000,'LinkedIn data'!$A$3:$A$20000,">="&Q$3,'LinkedIn data'!$A$3:$A$20000,"<="&Q$4,'LinkedIn data'!$B$3:$B$20000,$A11),0))))) -> 0 | R11: =IF($A11="","",SUM(F11:Q11)) -> 11570.02 | S11: =IF($A11="","",IF($B11="Meta",SUMIFS('Meta data'!$E$3:$E$20000,'Meta data'!$B$3:$B$20000,$A11),IF($B11="Google Ads",SUMIFS('Google data'!$E$3:$E$20000,'Google data'!$B$3:$B$20000,$A11),IF($B11="ChatGPT Ads",SUMIFS('ChatGPT data'!$E$3:$E$20000,'ChatGPT data'!$B$3:$B$20000,$A11),IF($B11="LinkedIn Ads",SUMIFS('LinkedIn data'!$E$3:$E$20000,'LinkedIn data'!$B$3:$B$20000,$A11),0))))) -> 3085 | T11: =IF($A11="","",IF($B11="Meta",SUMIFS('Meta data'!$F$3:$F$20000,'Meta data'!$B$3:$B$20000,$A11),IF($B11="Google Ads",SUMIFS('Google data'!$F$3:$F$20000,'Google data'!$B$3:$B$20000,$A11),IF($B11="ChatGPT Ads",SUMIFS('ChatGPT data'!$F$3:$F$20000,'ChatGPT data'!$B$3:$B$20000,$A11),IF($B11="LinkedIn Ads",SUMIFS('LinkedIn data'!$F$3:$F$20000,'LinkedIn data'!$B$3:$B$20000,$A11),0))))) -> 473 | U11: =IF(OR($A11="",T11=0),"",R11/T11) -> 24.46093
A12: Geo:WW_Objective:lead_Type:retargeting_Budget:cbo_Date:20260612 | B12: Meta | C12: Worldwide | D12: Global | E12: Meta – lead ads, retargeting | F12: =IF($A12="","",IF($B12="Meta",SUMIFS('Meta data'!$I$3:$I$20000,'Meta data'!$A$3:$A$20000,">="&F$3,'Meta data'!$A$3:$A$20000,"<="&F$4,'Meta data'!$B$3:$B$20000,$A12),IF($B12="Google Ads",SUMIFS('Google data'!$I$3:$I$20000,'Google data'!$A$3:$A$20000,">="&F$3,'Google data'!$A$3:$A$20000,"<="&F$4,'Google data'!$B$3:$B$20000,$A12),IF($B12="ChatGPT Ads",SUMIFS('ChatGPT data'!$I$3:$I$20000,'ChatGPT data'!$A$3:$A$20000,">="&F$3,'ChatGPT data'!$A$3:$A$20000,"<="&F$4,'ChatGPT data'!$B$3:$B$20000,$A12),IF($B12="LinkedIn Ads",SUMIFS('LinkedIn data'!$I$3:$I$20000,'LinkedIn data'!$A$3:$A$20000,">="&F$3,'LinkedIn data'!$A$3:$A$20000,"<="&F$4,'LinkedIn data'!$B$3:$B$20000,$A12),0))))) -> 482.04 | G12: =IF($A12="","",IF($B12="Meta",SUMIFS('Meta data'!$I$3:$I$20000,'Meta data'!$A$3:$A$20000,">="&G$3,'Meta data'!$A$3:$A$20000,"<="&G$4,'Meta data'!$B$3:$B$20000,$A12),IF($B12="Google Ads",SUMIFS('Google data'!$I$3:$I$20000,'Google data'!$A$3:$A$20000,">="&G$3,'Google data'!$A$3:$A$20000,"<="&G$4,'Google data'!$B$3:$B$20000,$A12),IF($B12="ChatGPT Ads",SUMIFS('ChatGPT data'!$I$3:$I$20000,'ChatGPT data'!$A$3:$A$20000,">="&G$3,'ChatGPT data'!$A$3:$A$20000,"<="&G$4,'ChatGPT data'!$B$3:$B$20000,$A12),IF($B12="LinkedIn Ads",SUMIFS('LinkedIn data'!$I$3:$I$20000,'LinkedIn data'!$A$3:$A$20000,">="&G$3,'LinkedIn data'!$A$3:$A$20000,"<="&G$4,'LinkedIn data'!$B$3:$B$20000,$A12),0))))) -> 556.5 | H12: =IF($A12="","",IF($B12="Meta",SUMIFS('Meta data'!$I$3:$I$20000,'Meta data'!$A$3:$A$20000,">="&H$3,'Meta data'!$A$3:$A$20000,"<="&H$4,'Meta data'!$B$3:$B$20000,$A12),IF($B12="Google Ads",SUMIFS('Google data'!$I$3:$I$20000,'Google data'!$A$3:$A$20000,">="&H$3,'Google data'!$A$3:$A$20000,"<="&H$4,'Google data'!$B$3:$B$20000,$A12),IF($B12="ChatGPT Ads",SUMIFS('ChatGPT data'!$I$3:$I$20000,'ChatGPT data'!$A$3:$A$20000,">="&H$3,'ChatGPT data'!$A$3:$A$20000,"<="&H$4,'ChatGPT data'!$B$3:$B$20000,$A12),IF($B12="LinkedIn Ads",SUMIFS('LinkedIn data'!$I$3:$I$20000,'LinkedIn data'!$A$3:$A$20000,">="&H$3,'LinkedIn data'!$A$3:$A$20000,"<="&H$4,'LinkedIn data'!$B$3:$B$20000,$A12),0))))) -> 634.17 | I12: =IF($A12="","",IF($B12="Meta",SUMIFS('Meta data'!$I$3:$I$20000,'Meta data'!$A$3:$A$20000,">="&I$3,'Meta data'!$A$3:$A$20000,"<="&I$4,'Meta data'!$B$3:$B$20000,$A12),IF($B12="Google Ads",SUMIFS('Google data'!$I$3:$I$20000,'Google data'!$A$3:$A$20000,">="&I$3,'Google data'!$A$3:$A$20000,"<="&I$4,'Google data'!$B$3:$B$20000,$A12),IF($B12="ChatGPT Ads",SUMIFS('ChatGPT data'!$I$3:$I$20000,'ChatGPT data'!$A$3:$A$20000,">="&I$3,'ChatGPT data'!$A$3:$A$20000,"<="&I$4,'ChatGPT data'!$B$3:$B$20000,$A12),IF($B12="LinkedIn Ads",SUMIFS('LinkedIn data'!$I$3:$I$20000,'LinkedIn data'!$A$3:$A$20000,">="&I$3,'LinkedIn data'!$A$3:$A$20000,"<="&I$4,'LinkedIn data'!$B$3:$B$20000,$A12),0))))) -> 579.09 | J12: =IF($A12="","",IF($B12="Meta",SUMIFS('Meta data'!$I$3:$I$20000,'Meta data'!$A$3:$A$20000,">="&J$3,'Meta data'!$A$3:$A$20000,"<="&J$4,'Meta data'!$B$3:$B$20000,$A12),IF($B12="Google Ads",SUMIFS('Google data'!$I$3:$I$20000,'Google data'!$A$3:$A$20000,">="&J$3,'Google data'!$A$3:$A$20000,"<="&J$4,'Google data'!$B$3:$B$20000,$A12),IF($B12="ChatGPT Ads",SUMIFS('ChatGPT data'!$I$3:$I$20000,'ChatGPT data'!$A$3:$A$20000,">="&J$3,'ChatGPT data'!$A$3:$A$20000,"<="&J$4,'ChatGPT data'!$B$3:$B$20000,$A12),IF($B12="LinkedIn Ads",SUMIFS('LinkedIn data'!$I$3:$I$20000,'LinkedIn data'!$A$3:$A$20000,">="&J$3,'LinkedIn data'!$A$3:$A$20000,"<="&J$4,'LinkedIn data'!$B$3:$B$20000,$A12),0))))) -> 561.84 | K12: =IF($A12="","",IF($B12="Meta",SUMIFS('Meta data'!$I$3:$I$20000,'Meta data'!$A$3:$A$20000,">="&K$3,'Meta data'!$A$3:$A$20000,"<="&K$4,'Meta data'!$B$3:$B$20000,$A12),IF($B12="Google Ads",SUMIFS('Google data'!$I$3:$I$20000,'Google data'!$A$3:$A$20000,">="&K$3,'Google data'!$A$3:$A$20000,"<="&K$4,'Google data'!$B$3:$B$20000,$A12),IF($B12="ChatGPT Ads",SUMIFS('ChatGPT data'!$I$3:$I$20000,'ChatGPT data'!$A$3:$A$20000,">="&K$3,'ChatGPT data'!$A$3:$A$20000,"<="&K$4,'ChatGPT data'!$B$3:$B$20000,$A12),IF($B12="LinkedIn Ads",SUMIFS('LinkedIn data'!$I$3:$I$20000,'LinkedIn data'!$A$3:$A$20000,">="&K$3,'LinkedIn data'!$A$3:$A$20000,"<="&K$4,'LinkedIn data'!$B$3:$B$20000,$A12),0))))) -> 1012.22 | L12: =IF($A12="","",IF($B12="Meta",SUMIFS('Meta data'!$I$3:$I$20000,'Meta data'!$A$3:$A$20000,">="&L$3,'Meta data'!$A$3:$A$20000,"<="&L$4,'Meta data'!$B$3:$B$20000,$A12),IF($B12="Google Ads",SUMIFS('Google data'!$I$3:$I$20000,'Google data'!$A$3:$A$20000,">="&L$3,'Google data'!$A$3:$A$20000,"<="&L$4,'Google data'!$B$3:$B$20000,$A12),IF($B12="ChatGPT Ads",SUMIFS('ChatGPT data'!$I$3:$I$20000,'ChatGPT data'!$A$3:$A$20000,">="&L$3,'ChatGPT data'!$A$3:$A$20000,"<="&L$4,'ChatGPT data'!$B$3:$B$20000,$A12),IF($B12="LinkedIn Ads",SUMIFS('LinkedIn data'!$I$3:$I$20000,'LinkedIn data'!$A$3:$A$20000,">="&L$3,'LinkedIn data'!$A$3:$A$20000,"<="&L$4,'LinkedIn data'!$B$3:$B$20000,$A12),0))))) -> 3047.53 | M12: =IF($A12="","",IF($B12="Meta",SUMIFS('Meta data'!$I$3:$I$20000,'Meta data'!$A$3:$A$20000,">="&M$3,'Meta data'!$A$3:$A$20000,"<="&M$4,'Meta data'!$B$3:$B$20000,$A12),IF($B12="Google Ads",SUMIFS('Google data'!$I$3:$I$20000,'Google data'!$A$3:$A$20000,">="&M$3,'Google data'!$A$3:$A$20000,"<="&M$4,'Google data'!$B$3:$B$20000,$A12),IF($B12="ChatGPT Ads",SUMIFS('ChatGPT data'!$I$3:$I$20000,'ChatGPT data'!$A$3:$A$20000,">="&M$3,'ChatGPT data'!$A$3:$A$20000,"<="&M$4,'ChatGPT data'!$B$3:$B$20000,$A12),IF($B12="LinkedIn Ads",SUMIFS('LinkedIn data'!$I$3:$I$20000,'LinkedIn data'!$A$3:$A$20000,">="&M$3,'LinkedIn data'!$A$3:$A$20000,"<="&M$4,'LinkedIn data'!$B$3:$B$20000,$A12),0))))) -> 2719.28 | ... Q12: =IF($A12="","",IF($B12="Meta",SUMIFS('Meta data'!$I$3:$I$20000,'Meta data'!$A$3:$A$20000,">="&Q$3,'Meta data'!$A$3:$A$20000,"<="&Q$4,'Meta data'!$B$3:$B$20000,$A12),IF($B12="Google Ads",SUMIFS('Google data'!$I$3:$I$20000,'Google data'!$A$3:$A$20000,">="&Q$3,'Google data'!$A$3:$A$20000,"<="&Q$4,'Google data'!$B$3:$B$20000,$A12),IF($B12="ChatGPT Ads",SUMIFS('ChatGPT data'!$I$3:$I$20000,'ChatGPT data'!$A$3:$A$20000,">="&Q$3,'ChatGPT data'!$A$3:$A$20000,"<="&Q$4,'ChatGPT data'!$B$3:$B$20000,$A12),IF($B12="LinkedIn Ads",SUMIFS('LinkedIn data'!$I$3:$I$20000,'LinkedIn data'!$A$3:$A$20000,">="&Q$3,'LinkedIn data'!$A$3:$A$20000,"<="&Q$4,'LinkedIn data'!$B$3:$B$20000,$A12),0))))) -> 0 | R12: =IF($A12="","",SUM(F12:Q12)) -> 11487.77 | S12: =IF($A12="","",IF($B12="Meta",SUMIFS('Meta data'!$E$3:$E$20000,'Meta data'!$B$3:$B$20000,$A12),IF($B12="Google Ads",SUMIFS('Google data'!$E$3:$E$20000,'Google data'!$B$3:$B$20000,$A12),IF($B12="ChatGPT Ads",SUMIFS('ChatGPT data'!$E$3:$E$20000,'ChatGPT data'!$B$3:$B$20000,$A12),IF($B12="LinkedIn Ads",SUMIFS('LinkedIn data'!$E$3:$E$20000,'LinkedIn data'!$B$3:$B$20000,$A12),0))))) -> 5737 | T12: =IF($A12="","",IF($B12="Meta",SUMIFS('Meta data'!$F$3:$F$20000,'Meta data'!$B$3:$B$20000,$A12),IF($B12="Google Ads",SUMIFS('Google data'!$F$3:$F$20000,'Google data'!$B$3:$B$20000,$A12),IF($B12="ChatGPT Ads",SUMIFS('ChatGPT data'!$F$3:$F$20000,'ChatGPT data'!$B$3:$B$20000,$A12),IF($B12="LinkedIn Ads",SUMIFS('LinkedIn data'!$F$3:$F$20000,'LinkedIn data'!$B$3:$B$20000,$A12),0))))) -> 471 | U12: =IF(OR($A12="",T12=0),"",R12/T12) -> 24.39017
A13: Geo:US-California_Objective:lead_Type:prospecting_Budget:cbo_Date:20260602 | B13: Meta | C13: California | D13: Americas | E13: Meta – lead ads, prospecting | F13: =IF($A13="","",IF($B13="Meta",SUMIFS('Meta data'!$I$3:$I$20000,'Meta data'!$A$3:$A$20000,">="&F$3,'Meta data'!$A$3:$A$20000,"<="&F$4,'Meta data'!$B$3:$B$20000,$A13),IF($B13="Google Ads",SUMIFS('Google data'!$I$3:$I$20000,'Google data'!$A$3:$A$20000,">="&F$3,'Google data'!$A$3:$A$20000,"<="&F$4,'Google data'!$B$3:$B$20000,$A13),IF($B13="ChatGPT Ads",SUMIFS('ChatGPT data'!$I$3:$I$20000,'ChatGPT data'!$A$3:$A$20000,">="&F$3,'ChatGPT data'!$A$3:$A$20000,"<="&F$4,'ChatGPT data'!$B$3:$B$20000,$A13),IF($B13="LinkedIn Ads",SUMIFS('LinkedIn data'!$I$3:$I$20000,'LinkedIn data'!$A$3:$A$20000,">="&F$3,'LinkedIn data'!$A$3:$A$20000,"<="&F$4,'LinkedIn data'!$B$3:$B$20000,$A13),0))))) -> 0 | G13: =IF($A13="","",IF($B13="Meta",SUMIFS('Meta data'!$I$3:$I$20000,'Meta data'!$A$3:$A$20000,">="&G$3,'Meta data'!$A$3:$A$20000,"<="&G$4,'Meta data'!$B$3:$B$20000,$A13),IF($B13="Google Ads",SUMIFS('Google data'!$I$3:$I$20000,'Google data'!$A$3:$A$20000,">="&G$3,'Google data'!$A$3:$A$20000,"<="&G$4,'Google data'!$B$3:$B$20000,$A13),IF($B13="ChatGPT Ads",SUMIFS('ChatGPT data'!$I$3:$I$20000,'ChatGPT data'!$A$3:$A$20000,">="&G$3,'ChatGPT data'!$A$3:$A$20000,"<="&G$4,'ChatGPT data'!$B$3:$B$20000,$A13),IF($B13="LinkedIn Ads",SUMIFS('LinkedIn data'!$I$3:$I$20000,'LinkedIn data'!$A$3:$A$20000,">="&G$3,'LinkedIn data'!$A$3:$A$20000,"<="&G$4,'LinkedIn data'!$B$3:$B$20000,$A13),0))))) -> 0 | H13: =IF($A13="","",IF($B13="Meta",SUMIFS('Meta data'!$I$3:$I$20000,'Meta data'!$A$3:$A$20000,">="&H$3,'Meta data'!$A$3:$A$20000,"<="&H$4,'Meta data'!$B$3:$B$20000,$A13),IF($B13="Google Ads",SUMIFS('Google data'!$I$3:$I$20000,'Google data'!$A$3:$A$20000,">="&H$3,'Google data'!$A$3:$A$20000,"<="&H$4,'Google data'!$B$3:$B$20000,$A13),IF($B13="ChatGPT Ads",SUMIFS('ChatGPT data'!$I$3:$I$20000,'ChatGPT data'!$A$3:$A$20000,">="&H$3,'ChatGPT data'!$A$3:$A$20000,"<="&H$4,'ChatGPT data'!$B$3:$B$20000,$A13),IF($B13="LinkedIn Ads",SUMIFS('LinkedIn data'!$I$3:$I$20000,'LinkedIn data'!$A$3:$A$20000,">="&H$3,'LinkedIn data'!$A$3:$A$20000,"<="&H$4,'LinkedIn data'!$B$3:$B$20000,$A13),0))))) -> 0 | I13: =IF($A13="","",IF($B13="Meta",SUMIFS('Meta data'!$I$3:$I$20000,'Meta data'!$A$3:$A$20000,">="&I$3,'Meta data'!$A$3:$A$20000,"<="&I$4,'Meta data'!$B$3:$B$20000,$A13),IF($B13="Google Ads",SUMIFS('Google data'!$I$3:$I$20000,'Google data'!$A$3:$A$20000,">="&I$3,'Google data'!$A$3:$A$20000,"<="&I$4,'Google data'!$B$3:$B$20000,$A13),IF($B13="ChatGPT Ads",SUMIFS('ChatGPT data'!$I$3:$I$20000,'ChatGPT data'!$A$3:$A$20000,">="&I$3,'ChatGPT data'!$A$3:$A$20000,"<="&I$4,'ChatGPT data'!$B$3:$B$20000,$A13),IF($B13="LinkedIn Ads",SUMIFS('LinkedIn data'!$I$3:$I$20000,'LinkedIn data'!$A$3:$A$20000,">="&I$3,'LinkedIn data'!$A$3:$A$20000,"<="&I$4,'LinkedIn data'!$B$3:$B$20000,$A13),0))))) -> 0 | J13: =IF($A13="","",IF($B13="Meta",SUMIFS('Meta data'!$I$3:$I$20000,'Meta data'!$A$3:$A$20000,">="&J$3,'Meta data'!$A$3:$A$20000,"<="&J$4,'Meta data'!$B$3:$B$20000,$A13),IF($B13="Google Ads",SUMIFS('Google data'!$I$3:$I$20000,'Google data'!$A$3:$A$20000,">="&J$3,'Google data'!$A$3:$A$20000,"<="&J$4,'Google data'!$B$3:$B$20000,$A13),IF($B13="ChatGPT Ads",SUMIFS('ChatGPT data'!$I$3:$I$20000,'ChatGPT data'!$A$3:$A$20000,">="&J$3,'ChatGPT data'!$A$3:$A$20000,"<="&J$4,'ChatGPT data'!$B$3:$B$20000,$A13),IF($B13="LinkedIn Ads",SUMIFS('LinkedIn data'!$I$3:$I$20000,'LinkedIn data'!$A$3:$A$20000,">="&J$3,'LinkedIn data'!$A$3:$A$20000,"<="&J$4,'LinkedIn data'!$B$3:$B$20000,$A13),0))))) -> 0 | K13: =IF($A13="","",IF($B13="Meta",SUMIFS('Meta data'!$I$3:$I$20000,'Meta data'!$A$3:$A$20000,">="&K$3,'Meta data'!$A$3:$A$20000,"<="&K$4,'Meta data'!$B$3:$B$20000,$A13),IF($B13="Google Ads",SUMIFS('Google data'!$I$3:$I$20000,'Google data'!$A$3:$A$20000,">="&K$3,'Google data'!$A$3:$A$20000,"<="&K$4,'Google data'!$B$3:$B$20000,$A13),IF($B13="ChatGPT Ads",SUMIFS('ChatGPT data'!$I$3:$I$20000,'ChatGPT data'!$A$3:$A$20000,">="&K$3,'ChatGPT data'!$A$3:$A$20000,"<="&K$4,'ChatGPT data'!$B$3:$B$20000,$A13),IF($B13="LinkedIn Ads",SUMIFS('LinkedIn data'!$I$3:$I$20000,'LinkedIn data'!$A$3:$A$20000,">="&K$3,'LinkedIn data'!$A$3:$A$20000,"<="&K$4,'LinkedIn data'!$B$3:$B$20000,$A13),0))))) -> 2401.95 | L13: =IF($A13="","",IF($B13="Meta",SUMIFS('Meta data'!$I$3:$I$20000,'Meta data'!$A$3:$A$20000,">="&L$3,'Meta data'!$A$3:$A$20000,"<="&L$4,'Meta data'!$B$3:$B$20000,$A13),IF($B13="Google Ads",SUMIFS('Google data'!$I$3:$I$20000,'Google data'!$A$3:$A$20000,">="&L$3,'Google data'!$A$3:$A$20000,"<="&L$4,'Google data'!$B$3:$B$20000,$A13),IF($B13="ChatGPT Ads",SUMIFS('ChatGPT data'!$I$3:$I$20000,'ChatGPT data'!$A$3:$A$20000,">="&L$3,'ChatGPT data'!$A$3:$A$20000,"<="&L$4,'ChatGPT data'!$B$3:$B$20000,$A13),IF($B13="LinkedIn Ads",SUMIFS('LinkedIn data'!$I$3:$I$20000,'LinkedIn data'!$A$3:$A$20000,">="&L$3,'LinkedIn data'!$A$3:$A$20000,"<="&L$4,'LinkedIn data'!$B$3:$B$20000,$A13),0))))) -> 1772.61 | M13: =IF($A13="","",IF($B13="Meta",SUMIFS('Meta data'!$I$3:$I$20000,'Meta data'!$A$3:$A$20000,">="&M$3,'Meta data'!$A$3:$A$20000,"<="&M$4,'Meta data'!$B$3:$B$20000,$A13),IF($B13="Google Ads",SUMIFS('Google data'!$I$3:$I$20000,'Google data'!$A$3:$A$20000,">="&M$3,'Google data'!$A$3:$A$20000,"<="&M$4,'Google data'!$B$3:$B$20000,$A13),IF($B13="ChatGPT Ads",SUMIFS('ChatGPT data'!$I$3:$I$20000,'ChatGPT data'!$A$3:$A$20000,">="&M$3,'ChatGPT data'!$A$3:$A$20000,"<="&M$4,'ChatGPT data'!$B$3:$B$20000,$A13),IF($B13="LinkedIn Ads",SUMIFS('LinkedIn data'!$I$3:$I$20000,'LinkedIn data'!$A$3:$A$20000,">="&M$3,'LinkedIn data'!$A$3:$A$20000,"<="&M$4,'LinkedIn data'!$B$3:$B$20000,$A13),0))))) -> 1184.66 | ... Q13: =IF($A13="","",IF($B13="Meta",SUMIFS('Meta data'!$I$3:$I$20000,'Meta data'!$A$3:$A$20000,">="&Q$3,'Meta data'!$A$3:$A$20000,"<="&Q$4,'Meta data'!$B$3:$B$20000,$A13),IF($B13="Google Ads",SUMIFS('Google data'!$I$3:$I$20000,'Google data'!$A$3:$A$20000,">="&Q$3,'Google data'!$A$3:$A$20000,"<="&Q$4,'Google data'!$B$3:$B$20000,$A13),IF($B13="ChatGPT Ads",SUMIFS('ChatGPT data'!$I$3:$I$20000,'ChatGPT data'!$A$3:$A$20000,">="&Q$3,'ChatGPT data'!$A$3:$A$20000,"<="&Q$4,'ChatGPT data'!$B$3:$B$20000,$A13),IF($B13="LinkedIn Ads",SUMIFS('LinkedIn data'!$I$3:$I$20000,'LinkedIn data'!$A$3:$A$20000,">="&Q$3,'LinkedIn data'!$A$3:$A$20000,"<="&Q$4,'LinkedIn data'!$B$3:$B$20000,$A13),0))))) -> 0 | R13: =IF($A13="","",SUM(F13:Q13)) -> 6326.23 | S13: =IF($A13="","",IF($B13="Meta",SUMIFS('Meta data'!$E$3:$E$20000,'Meta data'!$B$3:$B$20000,$A13),IF($B13="Google Ads",SUMIFS('Google data'!$E$3:$E$20000,'Google data'!$B$3:$B$20000,$A13),IF($B13="ChatGPT Ads",SUMIFS('ChatGPT data'!$E$3:$E$20000,'ChatGPT data'!$B$3:$B$20000,$A13),IF($B13="LinkedIn Ads",SUMIFS('LinkedIn data'!$E$3:$E$20000,'LinkedIn data'!$B$3:$B$20000,$A13),0))))) -> 1561 | T13: =IF($A13="","",IF($B13="Meta",SUMIFS('Meta data'!$F$3:$F$20000,'Meta data'!$B$3:$B$20000,$A13),IF($B13="Google Ads",SUMIFS('Google data'!$F$3:$F$20000,'Google data'!$B$3:$B$20000,$A13),IF($B13="ChatGPT Ads",SUMIFS('ChatGPT data'!$F$3:$F$20000,'ChatGPT data'!$B$3:$B$20000,$A13),IF($B13="LinkedIn Ads",SUMIFS('LinkedIn data'!$F$3:$F$20000,'LinkedIn data'!$B$3:$B$20000,$A13),0))))) -> 202 | U13: =IF(OR($A13="",T13=0),"",R13/T13) -> 31.31797
A14: Geo:US-East-Coast_Objective:lead_Type:prospecting_Budget:cbo_Date:20260617 | B14: Meta | C14: US East Coast | D14: Americas | E14: Meta – lead ads, prospecting | F14: =IF($A14="","",IF($B14="Meta",SUMIFS('Meta data'!$I$3:$I$20000,'Meta data'!$A$3:$A$20000,">="&F$3,'Meta data'!$A$3:$A$20000,"<="&F$4,'Meta data'!$B$3:$B$20000,$A14),IF($B14="Google Ads",SUMIFS('Google data'!$I$3:$I$20000,'Google data'!$A$3:$A$20000,">="&F$3,'Google data'!$A$3:$A$20000,"<="&F$4,'Google data'!$B$3:$B$20000,$A14),IF($B14="ChatGPT Ads",SUMIFS('ChatGPT data'!$I$3:$I$20000,'ChatGPT data'!$A$3:$A$20000,">="&F$3,'ChatGPT data'!$A$3:$A$20000,"<="&F$4,'ChatGPT data'!$B$3:$B$20000,$A14),IF($B14="LinkedIn Ads",SUMIFS('LinkedIn data'!$I$3:$I$20000,'LinkedIn data'!$A$3:$A$20000,">="&F$3,'LinkedIn data'!$A$3:$A$20000,"<="&F$4,'LinkedIn data'!$B$3:$B$20000,$A14),0))))) -> 0 | G14: =IF($A14="","",IF($B14="Meta",SUMIFS('Meta data'!$I$3:$I$20000,'Meta data'!$A$3:$A$20000,">="&G$3,'Meta data'!$A$3:$A$20000,"<="&G$4,'Meta data'!$B$3:$B$20000,$A14),IF($B14="Google Ads",SUMIFS('Google data'!$I$3:$I$20000,'Google data'!$A$3:$A$20000,">="&G$3,'Google data'!$A$3:$A$20000,"<="&G$4,'Google data'!$B$3:$B$20000,$A14),IF($B14="ChatGPT Ads",SUMIFS('ChatGPT data'!$I$3:$I$20000,'ChatGPT data'!$A$3:$A$20000,">="&G$3,'ChatGPT data'!$A$3:$A$20000,"<="&G$4,'ChatGPT data'!$B$3:$B$20000,$A14),IF($B14="LinkedIn Ads",SUMIFS('LinkedIn data'!$I$3:$I$20000,'LinkedIn data'!$A$3:$A$20000,">="&G$3,'LinkedIn data'!$A$3:$A$20000,"<="&G$4,'LinkedIn data'!$B$3:$B$20000,$A14),0))))) -> 0 | H14: =IF($A14="","",IF($B14="Meta",SUMIFS('Meta data'!$I$3:$I$20000,'Meta data'!$A$3:$A$20000,">="&H$3,'Meta data'!$A$3:$A$20000,"<="&H$4,'Meta data'!$B$3:$B$20000,$A14),IF($B14="Google Ads",SUMIFS('Google data'!$I$3:$I$20000,'Google data'!$A$3:$A$20000,">="&H$3,'Google data'!$A$3:$A$20000,"<="&H$4,'Google data'!$B$3:$B$20000,$A14),IF($B14="ChatGPT Ads",SUMIFS('ChatGPT data'!$I$3:$I$20000,'ChatGPT data'!$A$3:$A$20000,">="&H$3,'ChatGPT data'!$A$3:$A$20000,"<="&H$4,'ChatGPT data'!$B$3:$B$20000,$A14),IF($B14="LinkedIn Ads",SUMIFS('LinkedIn data'!$I$3:$I$20000,'LinkedIn data'!$A$3:$A$20000,">="&H$3,'LinkedIn data'!$A$3:$A$20000,"<="&H$4,'LinkedIn data'!$B$3:$B$20000,$A14),0))))) -> 0 | I14: =IF($A14="","",IF($B14="Meta",SUMIFS('Meta data'!$I$3:$I$20000,'Meta data'!$A$3:$A$20000,">="&I$3,'Meta data'!$A$3:$A$20000,"<="&I$4,'Meta data'!$B$3:$B$20000,$A14),IF($B14="Google Ads",SUMIFS('Google data'!$I$3:$I$20000,'Google data'!$A$3:$A$20000,">="&I$3,'Google data'!$A$3:$A$20000,"<="&I$4,'Google data'!$B$3:$B$20000,$A14),IF($B14="ChatGPT Ads",SUMIFS('ChatGPT data'!$I$3:$I$20000,'ChatGPT data'!$A$3:$A$20000,">="&I$3,'ChatGPT data'!$A$3:$A$20000,"<="&I$4,'ChatGPT data'!$B$3:$B$20000,$A14),IF($B14="LinkedIn Ads",SUMIFS('LinkedIn data'!$I$3:$I$20000,'LinkedIn data'!$A$3:$A$20000,">="&I$3,'LinkedIn data'!$A$3:$A$20000,"<="&I$4,'LinkedIn data'!$B$3:$B$20000,$A14),0))))) -> 0 | J14: =IF($A14="","",IF($B14="Meta",SUMIFS('Meta data'!$I$3:$I$20000,'Meta data'!$A$3:$A$20000,">="&J$3,'Meta data'!$A$3:$A$20000,"<="&J$4,'Meta data'!$B$3:$B$20000,$A14),IF($B14="Google Ads",SUMIFS('Google data'!$I$3:$I$20000,'Google data'!$A$3:$A$20000,">="&J$3,'Google data'!$A$3:$A$20000,"<="&J$4,'Google data'!$B$3:$B$20000,$A14),IF($B14="ChatGPT Ads",SUMIFS('ChatGPT data'!$I$3:$I$20000,'ChatGPT data'!$A$3:$A$20000,">="&J$3,'ChatGPT data'!$A$3:$A$20000,"<="&J$4,'ChatGPT data'!$B$3:$B$20000,$A14),IF($B14="LinkedIn Ads",SUMIFS('LinkedIn data'!$I$3:$I$20000,'LinkedIn data'!$A$3:$A$20000,">="&J$3,'LinkedIn data'!$A$3:$A$20000,"<="&J$4,'LinkedIn data'!$B$3:$B$20000,$A14),0))))) -> 0 | K14: =IF($A14="","",IF($B14="Meta",SUMIFS('Meta data'!$I$3:$I$20000,'Meta data'!$A$3:$A$20000,">="&K$3,'Meta data'!$A$3:$A$20000,"<="&K$4,'Meta data'!$B$3:$B$20000,$A14),IF($B14="Google Ads",SUMIFS('Google data'!$I$3:$I$20000,'Google data'!$A$3:$A$20000,">="&K$3,'Google data'!$A$3:$A$20000,"<="&K$4,'Google data'!$B$3:$B$20000,$A14),IF($B14="ChatGPT Ads",SUMIFS('ChatGPT data'!$I$3:$I$20000,'ChatGPT data'!$A$3:$A$20000,">="&K$3,'ChatGPT data'!$A$3:$A$20000,"<="&K$4,'ChatGPT data'!$B$3:$B$20000,$A14),IF($B14="LinkedIn Ads",SUMIFS('LinkedIn data'!$I$3:$I$20000,'LinkedIn data'!$A$3:$A$20000,">="&K$3,'LinkedIn data'!$A$3:$A$20000,"<="&K$4,'LinkedIn data'!$B$3:$B$20000,$A14),0))))) -> 817.03 | L14: =IF($A14="","",IF($B14="Meta",SUMIFS('Meta data'!$I$3:$I$20000,'Meta data'!$A$3:$A$20000,">="&L$3,'Meta data'!$A$3:$A$20000,"<="&L$4,'Meta data'!$B$3:$B$20000,$A14),IF($B14="Google Ads",SUMIFS('Google data'!$I$3:$I$20000,'Google data'!$A$3:$A$20000,">="&L$3,'Google data'!$A$3:$A$20000,"<="&L$4,'Google data'!$B$3:$B$20000,$A14),IF($B14="ChatGPT Ads",SUMIFS('ChatGPT data'!$I$3:$I$20000,'ChatGPT data'!$A$3:$A$20000,">="&L$3,'ChatGPT data'!$A$3:$A$20000,"<="&L$4,'ChatGPT data'!$B$3:$B$20000,$A14),IF($B14="LinkedIn Ads",SUMIFS('LinkedIn data'!$I$3:$I$20000,'LinkedIn data'!$A$3:$A$20000,">="&L$3,'LinkedIn data'!$A$3:$A$20000,"<="&L$4,'LinkedIn data'!$B$3:$B$20000,$A14),0))))) -> 1617.62 | M14: =IF($A14="","",IF($B14="Meta",SUMIFS('Meta data'!$I$3:$I$20000,'Meta data'!$A$3:$A$20000,">="&M$3,'Meta data'!$A$3:$A$20000,"<="&M$4,'Meta data'!$B$3:$B$20000,$A14),IF($B14="Google Ads",SUMIFS('Google data'!$I$3:$I$20000,'Google data'!$A$3:$A$20000,">="&M$3,'Google data'!$A$3:$A$20000,"<="&M$4,'Google data'!$B$3:$B$20000,$A14),IF($B14="ChatGPT Ads",SUMIFS('ChatGPT data'!$I$3:$I$20000,'ChatGPT data'!$A$3:$A$20000,">="&M$3,'ChatGPT data'!$A$3:$A$20000,"<="&M$4,'ChatGPT data'!$B$3:$B$20000,$A14),IF($B14="LinkedIn Ads",SUMIFS('LinkedIn data'!$I$3:$I$20000,'LinkedIn data'!$A$3:$A$20000,">="&M$3,'LinkedIn data'!$A$3:$A$20000,"<="&M$4,'LinkedIn data'!$B$3:$B$20000,$A14),0))))) -> 1557.31 | ... Q14: =IF($A14="","",IF($B14="Meta",SUMIFS('Meta data'!$I$3:$I$20000,'Meta data'!$A$3:$A$20000,">="&Q$3,'Meta data'!$A$3:$A$20000,"<="&Q$4,'Meta data'!$B$3:$B$20000,$A14),IF($B14="Google Ads",SUMIFS('Google data'!$I$3:$I$20000,'Google data'!$A$3:$A$20000,">="&Q$3,'Google data'!$A$3:$A$20000,"<="&Q$4,'Google data'!$B$3:$B$20000,$A14),IF($B14="ChatGPT Ads",SUMIFS('ChatGPT data'!$I$3:$I$20000,'ChatGPT data'!$A$3:$A$20000,">="&Q$3,'ChatGPT data'!$A$3:$A$20000,"<="&Q$4,'ChatGPT data'!$B$3:$B$20000,$A14),IF($B14="LinkedIn Ads",SUMIFS('LinkedIn data'!$I$3:$I$20000,'LinkedIn data'!$A$3:$A$20000,">="&Q$3,'LinkedIn data'!$A$3:$A$20000,"<="&Q$4,'LinkedIn data'!$B$3:$B$20000,$A14),0))))) -> 0 | R14: =IF($A14="","",SUM(F14:Q14)) -> 5170.48 | S14: =IF($A14="","",IF($B14="Meta",SUMIFS('Meta data'!$E$3:$E$20000,'Meta data'!$B$3:$B$20000,$A14),IF($B14="Google Ads",SUMIFS('Google data'!$E$3:$E$20000,'Google data'!$B$3:$B$20000,$A14),IF($B14="ChatGPT Ads",SUMIFS('ChatGPT data'!$E$3:$E$20000,'ChatGPT data'!$B$3:$B$20000,$A14),IF($B14="LinkedIn Ads",SUMIFS('LinkedIn data'!$E$3:$E$20000,'LinkedIn data'!$B$3:$B$20000,$A14),0))))) -> 1686 | T14: =IF($A14="","",IF($B14="Meta",SUMIFS('Meta data'!$F$3:$F$20000,'Meta data'!$B$3:$B$20000,$A14),IF($B14="Google Ads",SUMIFS('Google data'!$F$3:$F$20000,'Google data'!$B$3:$B$20000,$A14),IF($B14="ChatGPT Ads",SUMIFS('ChatGPT data'!$F$3:$F$20000,'ChatGPT data'!$B$3:$B$20000,$A14),IF($B14="LinkedIn Ads",SUMIFS('LinkedIn data'!$F$3:$F$20000,'LinkedIn data'!$B$3:$B$20000,$A14),0))))) -> 231 | U14: =IF(OR($A14="",T14=0),"",R14/T14) -> 22.38303
A15: Geo:USCA_Objective:lead_Type:prospecting_Budget:cbo_Date:20260617 | B15: Meta | C15: US & Canada | D15: Americas | E15: Meta – lead ads, prospecting | F15: =IF($A15="","",IF($B15="Meta",SUMIFS('Meta data'!$I$3:$I$20000,'Meta data'!$A$3:$A$20000,">="&F$3,'Meta data'!$A$3:$A$20000,"<="&F$4,'Meta data'!$B$3:$B$20000,$A15),IF($B15="Google Ads",SUMIFS('Google data'!$I$3:$I$20000,'Google data'!$A$3:$A$20000,">="&F$3,'Google data'!$A$3:$A$20000,"<="&F$4,'Google data'!$B$3:$B$20000,$A15),IF($B15="ChatGPT Ads",SUMIFS('ChatGPT data'!$I$3:$I$20000,'ChatGPT data'!$A$3:$A$20000,">="&F$3,'ChatGPT data'!$A$3:$A$20000,"<="&F$4,'ChatGPT data'!$B$3:$B$20000,$A15),IF($B15="LinkedIn Ads",SUMIFS('LinkedIn data'!$I$3:$I$20000,'LinkedIn data'!$A$3:$A$20000,">="&F$3,'LinkedIn data'!$A$3:$A$20000,"<="&F$4,'LinkedIn data'!$B$3:$B$20000,$A15),0))))) -> 0 | G15: =IF($A15="","",IF($B15="Meta",SUMIFS('Meta data'!$I$3:$I$20000,'Meta data'!$A$3:$A$20000,">="&G$3,'Meta data'!$A$3:$A$20000,"<="&G$4,'Meta data'!$B$3:$B$20000,$A15),IF($B15="Google Ads",SUMIFS('Google data'!$I$3:$I$20000,'Google data'!$A$3:$A$20000,">="&G$3,'Google data'!$A$3:$A$20000,"<="&G$4,'Google data'!$B$3:$B$20000,$A15),IF($B15="ChatGPT Ads",SUMIFS('ChatGPT data'!$I$3:$I$20000,'ChatGPT data'!$A$3:$A$20000,">="&G$3,'ChatGPT data'!$A$3:$A$20000,"<="&G$4,'ChatGPT data'!$B$3:$B$20000,$A15),IF($B15="LinkedIn Ads",SUMIFS('LinkedIn data'!$I$3:$I$20000,'LinkedIn data'!$A$3:$A$20000,">="&G$3,'LinkedIn data'!$A$3:$A$20000,"<="&G$4,'LinkedIn data'!$B$3:$B$20000,$A15),0))))) -> 0 | H15: =IF($A15="","",IF($B15="Meta",SUMIFS('Meta data'!$I$3:$I$20000,'Meta data'!$A$3:$A$20000,">="&H$3,'Meta data'!$A$3:$A$20000,"<="&H$4,'Meta data'!$B$3:$B$20000,$A15),IF($B15="Google Ads",SUMIFS('Google data'!$I$3:$I$20000,'Google data'!$A$3:$A$20000,">="&H$3,'Google data'!$A$3:$A$20000,"<="&H$4,'Google data'!$B$3:$B$20000,$A15),IF($B15="ChatGPT Ads",SUMIFS('ChatGPT data'!$I$3:$I$20000,'ChatGPT data'!$A$3:$A$20000,">="&H$3,'ChatGPT data'!$A$3:$A$20000,"<="&H$4,'ChatGPT data'!$B$3:$B$20000,$A15),IF($B15="LinkedIn Ads",SUMIFS('LinkedIn data'!$I$3:$I$20000,'LinkedIn data'!$A$3:$A$20000,">="&H$3,'LinkedIn data'!$A$3:$A$20000,"<="&H$4,'LinkedIn data'!$B$3:$B$20000,$A15),0))))) -> 0 | I15: =IF($A15="","",IF($B15="Meta",SUMIFS('Meta data'!$I$3:$I$20000,'Meta data'!$A$3:$A$20000,">="&I$3,'Meta data'!$A$3:$A$20000,"<="&I$4,'Meta data'!$B$3:$B$20000,$A15),IF($B15="Google Ads",SUMIFS('Google data'!$I$3:$I$20000,'Google data'!$A$3:$A$20000,">="&I$3,'Google data'!$A$3:$A$20000,"<="&I$4,'Google data'!$B$3:$B$20000,$A15),IF($B15="ChatGPT Ads",SUMIFS('ChatGPT data'!$I$3:$I$20000,'ChatGPT data'!$A$3:$A$20000,">="&I$3,'ChatGPT data'!$A$3:$A$20000,"<="&I$4,'ChatGPT data'!$B$3:$B$20000,$A15),IF($B15="LinkedIn Ads",SUMIFS('LinkedIn data'!$I$3:$I$20000,'LinkedIn data'!$A$3:$A$20000,">="&I$3,'LinkedIn data'!$A$3:$A$20000,"<="&I$4,'LinkedIn data'!$B$3:$B$20000,$A15),0))))) -> 0 | J15: =IF($A15="","",IF($B15="Meta",SUMIFS('Meta data'!$I$3:$I$20000,'Meta data'!$A$3:$A$20000,">="&J$3,'Meta data'!$A$3:$A$20000,"<="&J$4,'Meta data'!$B$3:$B$20000,$A15),IF($B15="Google Ads",SUMIFS('Google data'!$I$3:$I$20000,'Google data'!$A$3:$A$20000,">="&J$3,'Google data'!$A$3:$A$20000,"<="&J$4,'Google data'!$B$3:$B$20000,$A15),IF($B15="ChatGPT Ads",SUMIFS('ChatGPT data'!$I$3:$I$20000,'ChatGPT data'!$A$3:$A$20000,">="&J$3,'ChatGPT data'!$A$3:$A$20000,"<="&J$4,'ChatGPT data'!$B$3:$B$20000,$A15),IF($B15="LinkedIn Ads",SUMIFS('LinkedIn data'!$I$3:$I$20000,'LinkedIn data'!$A$3:$A$20000,">="&J$3,'LinkedIn data'!$A$3:$A$20000,"<="&J$4,'LinkedIn data'!$B$3:$B$20000,$A15),0))))) -> 0 | K15: =IF($A15="","",IF($B15="Meta",SUMIFS('Meta data'!$I$3:$I$20000,'Meta data'!$A$3:$A$20000,">="&K$3,'Meta data'!$A$3:$A$20000,"<="&K$4,'Meta data'!$B$3:$B$20000,$A15),IF($B15="Google Ads",SUMIFS('Google data'!$I$3:$I$20000,'Google data'!$A$3:$A$20000,">="&K$3,'Google data'!$A$3:$A$20000,"<="&K$4,'Google data'!$B$3:$B$20000,$A15),IF($B15="ChatGPT Ads",SUMIFS('ChatGPT data'!$I$3:$I$20000,'ChatGPT data'!$A$3:$A$20000,">="&K$3,'ChatGPT data'!$A$3:$A$20000,"<="&K$4,'ChatGPT data'!$B$3:$B$20000,$A15),IF($B15="LinkedIn Ads",SUMIFS('LinkedIn data'!$I$3:$I$20000,'LinkedIn data'!$A$3:$A$20000,">="&K$3,'LinkedIn data'!$A$3:$A$20000,"<="&K$4,'LinkedIn data'!$B$3:$B$20000,$A15),0))))) -> 952.34 | L15: =IF($A15="","",IF($B15="Meta",SUMIFS('Meta data'!$I$3:$I$20000,'Meta data'!$A$3:$A$20000,">="&L$3,'Meta data'!$A$3:$A$20000,"<="&L$4,'Meta data'!$B$3:$B$20000,$A15),IF($B15="Google Ads",SUMIFS('Google data'!$I$3:$I$20000,'Google data'!$A$3:$A$20000,">="&L$3,'Google data'!$A$3:$A$20000,"<="&L$4,'Google data'!$B$3:$B$20000,$A15),IF($B15="ChatGPT Ads",SUMIFS('ChatGPT data'!$I$3:$I$20000,'ChatGPT data'!$A$3:$A$20000,">="&L$3,'ChatGPT data'!$A$3:$A$20000,"<="&L$4,'ChatGPT data'!$B$3:$B$20000,$A15),IF($B15="LinkedIn Ads",SUMIFS('LinkedIn data'!$I$3:$I$20000,'LinkedIn data'!$A$3:$A$20000,">="&L$3,'LinkedIn data'!$A$3:$A$20000,"<="&L$4,'LinkedIn data'!$B$3:$B$20000,$A15),0))))) -> 1685.84 | M15: =IF($A15="","",IF($B15="Meta",SUMIFS('Meta data'!$I$3:$I$20000,'Meta data'!$A$3:$A$20000,">="&M$3,'Meta data'!$A$3:$A$20000,"<="&M$4,'Meta data'!$B$3:$B$20000,$A15),IF($B15="Google Ads",SUMIFS('Google data'!$I$3:$I$20000,'Google data'!$A$3:$A$20000,">="&M$3,'Google data'!$A$3:$A$20000,"<="&M$4,'Google data'!$B$3:$B$20000,$A15),IF($B15="ChatGPT Ads",SUMIFS('ChatGPT data'!$I$3:$I$20000,'ChatGPT data'!$A$3:$A$20000,">="&M$3,'ChatGPT data'!$A$3:$A$20000,"<="&M$4,'ChatGPT data'!$B$3:$B$20000,$A15),IF($B15="LinkedIn Ads",SUMIFS('LinkedIn data'!$I$3:$I$20000,'LinkedIn data'!$A$3:$A$20000,">="&M$3,'LinkedIn data'!$A$3:$A$20000,"<="&M$4,'LinkedIn data'!$B$3:$B$20000,$A15),0))))) -> 915.04 | ... Q15: =IF($A15="","",IF($B15="Meta",SUMIFS('Meta data'!$I$3:$I$20000,'Meta data'!$A$3:$A$20000,">="&Q$3,'Meta data'!$A$3:$A$20000,"<="&Q$4,'Meta data'!$B$3:$B$20000,$A15),IF($B15="Google Ads",SUMIFS('Google data'!$I$3:$I$20000,'Google data'!$A$3:$A$20000,">="&Q$3,'Google data'!$A$3:$A$20000,"<="&Q$4,'Google data'!$B$3:$B$20000,$A15),IF($B15="ChatGPT Ads",SUMIFS('ChatGPT data'!$I$3:$I$20000,'ChatGPT data'!$A$3:$A$20000,">="&Q$3,'ChatGPT data'!$A$3:$A$20000,"<="&Q$4,'ChatGPT data'!$B$3:$B$20000,$A15),IF($B15="LinkedIn Ads",SUMIFS('LinkedIn data'!$I$3:$I$20000,'LinkedIn data'!$A$3:$A$20000,">="&Q$3,'LinkedIn data'!$A$3:$A$20000,"<="&Q$4,'LinkedIn data'!$B$3:$B$20000,$A15),0))))) -> 0 | R15: =IF($A15="","",SUM(F15:Q15)) -> 4021.91 | S15: =IF($A15="","",IF($B15="Meta",SUMIFS('Meta data'!$E$3:$E$20000,'Meta data'!$B$3:$B$20000,$A15),IF($B15="Google Ads",SUMIFS('Google data'!$E$3:$E$20000,'Google data'!$B$3:$B$20000,$A15),IF($B15="ChatGPT Ads",SUMIFS('ChatGPT data'!$E$3:$E$20000,'ChatGPT data'!$B$3:$B$20000,$A15),IF($B15="LinkedIn Ads",SUMIFS('LinkedIn data'!$E$3:$E$20000,'LinkedIn data'!$B$3:$B$20000,$A15),0))))) -> 1269 | T15: =IF($A15="","",IF($B15="Meta",SUMIFS('Meta data'!$F$3:$F$20000,'Meta data'!$B$3:$B$20000,$A15),IF($B15="Google Ads",SUMIFS('Google data'!$F$3:$F$20000,'Google data'!$B$3:$B$20000,$A15),IF($B15="ChatGPT Ads",SUMIFS('ChatGPT data'!$F$3:$F$20000,'ChatGPT data'!$B$3:$B$20000,$A15),IF($B15="LinkedIn Ads",SUMIFS('LinkedIn data'!$F$3:$F$20000,'LinkedIn data'!$B$3:$B$20000,$A15),0))))) -> 134 | U15: =IF(OR($A15="",T15=0),"",R15/T15) -> 30.014254
A16: FR_Alibaba Campaign | B16: Meta | C16: France | D16: EMEA | E16: Meta – traffic | F16: =IF($A16="","",IF($B16="Meta",SUMIFS('Meta data'!$I$3:$I$20000,'Meta data'!$A$3:$A$20000,">="&F$3,'Meta data'!$A$3:$A$20000,"<="&F$4,'Meta data'!$B$3:$B$20000,$A16),IF($B16="Google Ads",SUMIFS('Google data'!$I$3:$I$20000,'Google data'!$A$3:$A$20000,">="&F$3,'Google data'!$A$3:$A$20000,"<="&F$4,'Google data'!$B$3:$B$20000,$A16),IF($B16="ChatGPT Ads",SUMIFS('ChatGPT data'!$I$3:$I$20000,'ChatGPT data'!$A$3:$A$20000,">="&F$3,'ChatGPT data'!$A$3:$A$20000,"<="&F$4,'ChatGPT data'!$B$3:$B$20000,$A16),IF($B16="LinkedIn Ads",SUMIFS('LinkedIn data'!$I$3:$I$20000,'LinkedIn data'!$A$3:$A$20000,">="&F$3,'LinkedIn data'!$A$3:$A$20000,"<="&F$4,'LinkedIn data'!$B$3:$B$20000,$A16),0))))) -> 0 | G16: =IF($A16="","",IF($B16="Meta",SUMIFS('Meta data'!$I$3:$I$20000,'Meta data'!$A$3:$A$20000,">="&G$3,'Meta data'!$A$3:$A$20000,"<="&G$4,'Meta data'!$B$3:$B$20000,$A16),IF($B16="Google Ads",SUMIFS('Google data'!$I$3:$I$20000,'Google data'!$A$3:$A$20000,">="&G$3,'Google data'!$A$3:$A$20000,"<="&G$4,'Google data'!$B$3:$B$20000,$A16),IF($B16="ChatGPT Ads",SUMIFS('ChatGPT data'!$I$3:$I$20000,'ChatGPT data'!$A$3:$A$20000,">="&G$3,'ChatGPT data'!$A$3:$A$20000,"<="&G$4,'ChatGPT data'!$B$3:$B$20000,$A16),IF($B16="LinkedIn Ads",SUMIFS('LinkedIn data'!$I$3:$I$20000,'LinkedIn data'!$A$3:$A$20000,">="&G$3,'LinkedIn data'!$A$3:$A$20000,"<="&G$4,'LinkedIn data'!$B$3:$B$20000,$A16),0))))) -> 0 | H16: =IF($A16="","",IF($B16="Meta",SUMIFS('Meta data'!$I$3:$I$20000,'Meta data'!$A$3:$A$20000,">="&H$3,'Meta data'!$A$3:$A$20000,"<="&H$4,'Meta data'!$B$3:$B$20000,$A16),IF($B16="Google Ads",SUMIFS('Google data'!$I$3:$I$20000,'Google data'!$A$3:$A$20000,">="&H$3,'Google data'!$A$3:$A$20000,"<="&H$4,'Google data'!$B$3:$B$20000,$A16),IF($B16="ChatGPT Ads",SUMIFS('ChatGPT data'!$I$3:$I$20000,'ChatGPT data'!$A$3:$A$20000,">="&H$3,'ChatGPT data'!$A$3:$A$20000,"<="&H$4,'ChatGPT data'!$B$3:$B$20000,$A16),IF($B16="LinkedIn Ads",SUMIFS('LinkedIn data'!$I$3:$I$20000,'LinkedIn data'!$A$3:$A$20000,">="&H$3,'LinkedIn data'!$A$3:$A$20000,"<="&H$4,'LinkedIn data'!$B$3:$B$20000,$A16),0))))) -> 0 | I16: =IF($A16="","",IF($B16="Meta",SUMIFS('Meta data'!$I$3:$I$20000,'Meta data'!$A$3:$A$20000,">="&I$3,'Meta data'!$A$3:$A$20000,"<="&I$4,'Meta data'!$B$3:$B$20000,$A16),IF($B16="Google Ads",SUMIFS('Google data'!$I$3:$I$20000,'Google data'!$A$3:$A$20000,">="&I$3,'Google data'!$A$3:$A$20000,"<="&I$4,'Google data'!$B$3:$B$20000,$A16),IF($B16="ChatGPT Ads",SUMIFS('ChatGPT data'!$I$3:$I$20000,'ChatGPT data'!$A$3:$A$20000,">="&I$3,'ChatGPT data'!$A$3:$A$20000,"<="&I$4,'ChatGPT data'!$B$3:$B$20000,$A16),IF($B16="LinkedIn Ads",SUMIFS('LinkedIn data'!$I$3:$I$20000,'LinkedIn data'!$A$3:$A$20000,">="&I$3,'LinkedIn data'!$A$3:$A$20000,"<="&I$4,'LinkedIn data'!$B$3:$B$20000,$A16),0))))) -> 0 | J16: =IF($A16="","",IF($B16="Meta",SUMIFS('Meta data'!$I$3:$I$20000,'Meta data'!$A$3:$A$20000,">="&J$3,'Meta data'!$A$3:$A$20000,"<="&J$4,'Meta data'!$B$3:$B$20000,$A16),IF($B16="Google Ads",SUMIFS('Google data'!$I$3:$I$20000,'Google data'!$A$3:$A$20000,">="&J$3,'Google data'!$A$3:$A$20000,"<="&J$4,'Google data'!$B$3:$B$20000,$A16),IF($B16="ChatGPT Ads",SUMIFS('ChatGPT data'!$I$3:$I$20000,'ChatGPT data'!$A$3:$A$20000,">="&J$3,'ChatGPT data'!$A$3:$A$20000,"<="&J$4,'ChatGPT data'!$B$3:$B$20000,$A16),IF($B16="LinkedIn Ads",SUMIFS('LinkedIn data'!$I$3:$I$20000,'LinkedIn data'!$A$3:$A$20000,">="&J$3,'LinkedIn data'!$A$3:$A$20000,"<="&J$4,'LinkedIn data'!$B$3:$B$20000,$A16),0))))) -> 0 | K16: =IF($A16="","",IF($B16="Meta",SUMIFS('Meta data'!$I$3:$I$20000,'Meta data'!$A$3:$A$20000,">="&K$3,'Meta data'!$A$3:$A$20000,"<="&K$4,'Meta data'!$B$3:$B$20000,$A16),IF($B16="Google Ads",SUMIFS('Google data'!$I$3:$I$20000,'Google data'!$A$3:$A$20000,">="&K$3,'Google data'!$A$3:$A$20000,"<="&K$4,'Google data'!$B$3:$B$20000,$A16),IF($B16="ChatGPT Ads",SUMIFS('ChatGPT data'!$I$3:$I$20000,'ChatGPT data'!$A$3:$A$20000,">="&K$3,'ChatGPT data'!$A$3:$A$20000,"<="&K$4,'ChatGPT data'!$B$3:$B$20000,$A16),IF($B16="LinkedIn Ads",SUMIFS('LinkedIn data'!$I$3:$I$20000,'LinkedIn data'!$A$3:$A$20000,">="&K$3,'LinkedIn data'!$A$3:$A$20000,"<="&K$4,'LinkedIn data'!$B$3:$B$20000,$A16),0))))) -> 0 | L16: =IF($A16="","",IF($B16="Meta",SUMIFS('Meta data'!$I$3:$I$20000,'Meta data'!$A$3:$A$20000,">="&L$3,'Meta data'!$A$3:$A$20000,"<="&L$4,'Meta data'!$B$3:$B$20000,$A16),IF($B16="Google Ads",SUMIFS('Google data'!$I$3:$I$20000,'Google data'!$A$3:$A$20000,">="&L$3,'Google data'!$A$3:$A$20000,"<="&L$4,'Google data'!$B$3:$B$20000,$A16),IF($B16="ChatGPT Ads",SUMIFS('ChatGPT data'!$I$3:$I$20000,'ChatGPT data'!$A$3:$A$20000,">="&L$3,'ChatGPT data'!$A$3:$A$20000,"<="&L$4,'ChatGPT data'!$B$3:$B$20000,$A16),IF($B16="LinkedIn Ads",SUMIFS('LinkedIn data'!$I$3:$I$20000,'LinkedIn data'!$A$3:$A$20000,">="&L$3,'LinkedIn data'!$A$3:$A$20000,"<="&L$4,'LinkedIn data'!$B$3:$B$20000,$A16),0))))) -> 0 | M16: =IF($A16="","",IF($B16="Meta",SUMIFS('Meta data'!$I$3:$I$20000,'Meta data'!$A$3:$A$20000,">="&M$3,'Meta data'!$A$3:$A$20000,"<="&M$4,'Meta data'!$B$3:$B$20000,$A16),IF($B16="Google Ads",SUMIFS('Google data'!$I$3:$I$20000,'Google data'!$A$3:$A$20000,">="&M$3,'Google data'!$A$3:$A$20000,"<="&M$4,'Google data'!$B$3:$B$20000,$A16),IF($B16="ChatGPT Ads",SUMIFS('ChatGPT data'!$I$3:$I$20000,'ChatGPT data'!$A$3:$A$20000,">="&M$3,'ChatGPT data'!$A$3:$A$20000,"<="&M$4,'ChatGPT data'!$B$3:$B$20000,$A16),IF($B16="LinkedIn Ads",SUMIFS('LinkedIn data'!$I$3:$I$20000,'LinkedIn data'!$A$3:$A$20000,">="&M$3,'LinkedIn data'!$A$3:$A$20000,"<="&M$4,'LinkedIn data'!$B$3:$B$20000,$A16),0))))) -> 0 | ... Q16: =IF($A16="","",IF($B16="Meta",SUMIFS('Meta data'!$I$3:$I$20000,'Meta data'!$A$3:$A$20000,">="&Q$3,'Meta data'!$A$3:$A$20000,"<="&Q$4,'Meta data'!$B$3:$B$20000,$A16),IF($B16="Google Ads",SUMIFS('Google data'!$I$3:$I$20000,'Google data'!$A$3:$A$20000,">="&Q$3,'Google data'!$A$3:$A$20000,"<="&Q$4,'Google data'!$B$3:$B$20000,$A16),IF($B16="ChatGPT Ads",SUMIFS('ChatGPT data'!$I$3:$I$20000,'ChatGPT data'!$A$3:$A$20000,">="&Q$3,'ChatGPT data'!$A$3:$A$20000,"<="&Q$4,'ChatGPT data'!$B$3:$B$20000,$A16),IF($B16="LinkedIn Ads",SUMIFS('LinkedIn data'!$I$3:$I$20000,'LinkedIn data'!$A$3:$A$20000,">="&Q$3,'LinkedIn data'!$A$3:$A$20000,"<="&Q$4,'LinkedIn data'!$B$3:$B$20000,$A16),0))))) -> 0 | R16: =IF($A16="","",SUM(F16:Q16)) -> 3692.72 | S16: =IF($A16="","",IF($B16="Meta",SUMIFS('Meta data'!$E$3:$E$20000,'Meta data'!$B$3:$B$20000,$A16),IF($B16="Google Ads",SUMIFS('Google data'!$E$3:$E$20000,'Google data'!$B$3:$B$20000,$A16),IF($B16="ChatGPT Ads",SUMIFS('ChatGPT data'!$E$3:$E$20000,'ChatGPT data'!$B$3:$B$20000,$A16),IF($B16="LinkedIn Ads",SUMIFS('LinkedIn data'!$E$3:$E$20000,'LinkedIn data'!$B$3:$B$20000,$A16),0))))) -> 83839 | T16: =IF($A16="","",IF($B16="Meta",SUMIFS('Meta data'!$F$3:$F$20000,'Meta data'!$B$3:$B$20000,$A16),IF($B16="Google Ads",SUMIFS('Google data'!$F$3:$F$20000,'Google data'!$B$3:$B$20000,$A16),IF($B16="ChatGPT Ads",SUMIFS('ChatGPT data'!$F$3:$F$20000,'ChatGPT data'!$B$3:$B$20000,$A16),IF($B16="LinkedIn Ads",SUMIFS('LinkedIn data'!$F$3:$F$20000,'LinkedIn data'!$B$3:$B$20000,$A16),0))))) -> 7 | U16: =IF(OR($A16="",T16=0),"",R16/T16) -> 527.53143
